Workbook
Name analysis_start: #REF!
Name market_rent: #REF!

Sheet Summary
B2: Land Residual Valuation
B3: Required Return | D3: 0.1
B4: Efficiency | D4: 0.7
B5: Vacancy | D5: 0.05
B6: Maximum Land Cost | D6: 0.01
B8: Market Rent | C8: / rsf | D8: 11
B9: Effective Rent | C9: / rsf | D9: =D8*(1-D5) -> 10.45
B10: Operating Costs | C10: / gsf | D10: =SUM('[2]Torrance Inputs'!H3:H6)/'[2]Torrance Inputs'!D9 -> 0.37501655
B11: Soft Costs | C11: / gsf | D11: =('[2]Torrance Inputs'!I36+'[2]Torrance Inputs'!I40)/'[2]Torrance Inputs'!D9 -> 5.0971356
B12: Hard Costs | C12: / gsf | D12: =SUM('[2]Torrance Inputs'!I37:I39)/'[2]Torrance Inputs'!D9 -> 23.677017
B14: Rental Revenue | C14: / gsf | D14: =D9*(D4) -> 7.315
B15: NOI | C15: / gsf | D15: =D14-D10 -> 6.9399835
B17: Maximum Land Cost | C17: / gsf | D17: =(D15-(SUM(D11:D12)*$D$3))/D3 -> 40.625682
B18: Maximum To Pay | C18: $ | D18: =D17*'[2]Torrance Inputs'!D9 -> 24707919

Sheet Rent Table
A1: Street Address | B1: City | C1: State | D1: Zip Code | E1: Market | F1: Sector | G1: Date As Of | H1: Zip Code Grade | I1: Size | J1: Size Type | K1: Effective Rent* ($/Size Type) | L1: Avg. Transaction Size | M1: Avg. Lease Terms (Months) | N1: Avg. Work Value ($/Size Type) | O1: Avg. Free Months | P1: Floors | Q1: Year Built | R1: Year Renovated | S1: Size (SF)
A2: 1000 Francisco Street | B2: Torrance | C2: CA | D2: 90502 | E2: Los Angeles | F2: Industrial | G2: 45566 | H2: A++ | I2: 298000 | J2: SF | K2: 25.5206 | L2: 298000 | M2: 63 | N2: 2.5 | O2: 3 | P2: 1 | Q2: 1975 | R2: - | S2: {=_xlfn.IFS(AND('Rent Table'!$I2>0,'Rent Table'!$I2<=50000),"0-50,000", AND('Rent Table'!$I2 > 50000, 'Rent Table'!$I2 <= 150000), "50,001-150,000", AND('Rent Table'!$I2 > 150000, 'Rent Table'!$I2 <= 250000), "150,001-250,000", AND('Rent Table'!$I2 > 250000, 'Rent Table'!$I2 <= 350000), "250,001-350,000", AND('Rent Table'!$I2 > 350000, 'Rent Table'!$I2 <= 450000), "350,001-450,000", AND('Rent Table'!$I2 > 450000, 'Rent Table'!$I2 <= 600000), "450,001-600,000", AND('Rent Table'!$I2 > 600000, 'Rent Table'!$I2 <= 750000), "600,001-750,000",'Rent Table'!$I2 > 750000, "750,000+", TRUE, "Undefined" )} -> 250,001-350,000
A3: 1000 West 190th Street | B3: Torrance | C3: CA | D3: 90502 | E3: Los Angeles | F3: Industrial | G3: 45566 | H3: A++ | I3: 129556 | J3: SF | K3: 22.0341 | L3: 129256 | M3: 120 | N3: - | O3: - | P3: 1 | Q3: 2000 | R3: - | S3: {=_xlfn.IFS(AND('Rent Table'!$I3>0,'Rent Table'!$I3<=50000),"0-50,000", AND('Rent Table'!$I3 > 50000, 'Rent Table'!$I3 <= 150000), "50,001-150,000", AND('Rent Table'!$I3 > 150000, 'Rent Table'!$I3 <= 250000), "150,001-250,000", AND('Rent Table'!$I3 > 250000, 'Rent Table'!$I3 <= 350000), "250,001-350,000", AND('Rent Table'!$I3 > 350000, 'Rent Table'!$I3 <= 450000), "350,001-450,000", AND('Rent Table'!$I3 > 450000, 'Rent Table'!$I3 <= 600000), "450,001-600,000", AND('Rent Table'!$I3 > 600000, 'Rent Table'!$I3 <= 750000), "600,001-750,000",'Rent Table'!$I3 > 750000, "750,000+", TRUE, "Undefined" )} -> 50,001-150,000
A4: 1001 Knox Street | B4: Torrance | C4: CA | D4: 90502 | E4: Los Angeles | F4: Industrial | G4: 45566 | H4: A++ | I4: 49112 | J4: SF | K4: 30.2333 | L4: 49112 | M4: 123 | N4: 20 | O4: 3 | P4: 1 | Q4: 1981 | R4: - | S4: {=_xlfn.IFS(AND('Rent Table'!$I4>0,'Rent Table'!$I4<=50000),"0-50,000", AND('Rent Table'!$I4 > 50000, 'Rent Table'!$I4 <= 150000), "50,001-150,000", AND('Rent Table'!$I4 > 150000, 'Rent Table'!$I4 <= 250000), "150,001-250,000", AND('Rent Table'!$I4 > 250000, 'Rent Table'!$I4 <= 350000), "250,001-350,000", AND('Rent Table'!$I4 > 350000, 'Rent Table'!$I4 <= 450000), "350,001-450,000", AND('Rent Table'!$I4 > 450000, 'Rent Table'!$I4 <= 600000), "450,001-600,000", AND('Rent Table'!$I4 > 600000, 'Rent Table'!$I4 <= 750000), "600,001-750,000",'Rent Table'!$I4 > 750000, "750,000+", TRUE, "Undefined" )} -> 0-50,000
A5: 1011 Francisco Street | B5: Torrance | C5: CA | D5: 90502 | E5: Los Angeles | F5: Industrial | G5: 45566 | H5: A++ | I5: 45550 | J5: SF | K5: 18.1314 | L5: 45550 | M5: 85 | N5: - | O5: 1 | P5: 1 | Q5: 1979 | R5: - | S5: {=_xlfn.IFS(AND('Rent Table'!$I5>0,'Rent Table'!$I5<=50000),"0-50,000", AND('Rent Table'!$I5 > 50000, 'Rent Table'!$I5 <= 150000), "50,001-150,000", AND('Rent Table'!$I5 > 150000, 'Rent Table'!$I5 <= 250000), "150,001-250,000", AND('Rent Table'!$I5 > 250000, 'Rent Table'!$I5 <= 350000), "250,001-350,000", AND('Rent Table'!$I5 > 350000, 'Rent Table'!$I5 <= 450000), "350,001-450,000", AND('Rent Table'!$I5 > 450000, 'Rent Table'!$I5 <= 600000), "450,001-600,000", AND('Rent Table'!$I5 > 600000, 'Rent Table'!$I5 <= 750000), "600,001-750,000",'Rent Table'!$I5 > 750000, "750,000+", TRUE, "Undefined" )} -> 0-50,000
A6: 1024 East Del Amo Boulevard | B6: Carson | C6: CA | D6: 90746 | E6: Los Angeles | F6: Industrial | G6: 45566 | H6: A+ | I6: 36580 | J6: SF | K6: 18.473 | L6: 18301 | M6: 62 | N6: - | O6: - | P6: 1 | Q6: 1977 | R6: - | S6: {=_xlfn.IFS(AND('Rent Table'!$I6>0,'Rent Table'!$I6<=50000),"0-50,000", AND('Rent Table'!$I6 > 50000, 'Rent Table'!$I6 <= 150000), "50,001-150,000", AND('Rent Table'!$I6 > 150000, 'Rent Table'!$I6 <= 250000), "150,001-250,000", AND('Rent Table'!$I6 > 250000, 'Rent Table'!$I6 <= 350000), "250,001-350,000", AND('Rent Table'!$I6 > 350000, 'Rent Table'!$I6 <= 450000), "350,001-450,000", AND('Rent Table'!$I6 > 450000, 'Rent Table'!$I6 <= 600000), "450,001-600,000", AND('Rent Table'!$I6 > 600000, 'Rent Table'!$I6 <= 750000), "600,001-750,000",'Rent Table'!$I6 > 750000, "750,000+", TRUE, "Undefined" )} -> 0-50,000
A7: 1048 East Burgrove Street | B7: Carson | C7: CA | D7: 90746 | E7: Los Angeles | F7: Industrial | G7: 45566 | H7: A+ | I7: 75194 | J7: SF | K7: 19.1764 | L7: 53474 | M7: 36 | N7: - | O7: - | P7: 1 | Q7: 1972 | R7: 1973 | S7: {=_xlfn.IFS(AND('Rent Table'!$I7>0,'Rent Table'!$I7<=50000),"0-50,000", AND('Rent Table'!$I7 > 50000, 'Rent Table'!$I7 <= 150000), "50,001-150,000", AND('Rent Table'!$I7 > 150000, 'Rent Table'!$I7 <= 250000), "150,001-250,000", AND('Rent Table'!$I7 > 250000, 'Rent Table'!$I7 <= 350000), "250,001-350,000", AND('Rent Table'!$I7 > 350000, 'Rent Table'!$I7 <= 450000), "350,001-450,000", AND('Rent Table'!$I7 > 450000, 'Rent Table'!$I7 <= 600000), "450,001-600,000", AND('Rent Table'!$I7 > 600000, 'Rent Table'!$I7 <= 750000), "600,001-750,000",'Rent Table'!$I7 > 750000, "750,000+", TRUE, "Undefined" )} -> 50,001-150,000
A8: 1062 East Del Amo Boulevard | B8: Carson | C8: CA | D8: 90746 | E8: Los Angeles | F8: Industrial | G8: 45566 | H8: A+ | I8: 121551 | J8: SF | K8: 14.9052 | L8: 33855 | M8: 61.5 | N8: 0.5 | O8: 2 | P8: 1 | Q8: 1972 | R8: - | S8: {=_xlfn.IFS(AND('Rent Table'!$I8>0,'Rent Table'!$I8<=50000),"0-50,000", AND('Rent Table'!$I8 > 50000, 'Rent Table'!$I8 <= 150000), "50,001-150,000", AND('Rent Table'!$I8 > 150000, 'Rent Table'!$I8 <= 250000), "150,001-250,000", AND('Rent Table'!$I8 > 250000, 'Rent Table'!$I8 <= 350000), "250,001-350,000", AND('Rent Table'!$I8 > 350000, 'Rent Table'!$I8 <= 450000), "350,001-450,000", AND('Rent Table'!$I8 > 450000, 'Rent Table'!$I8 <= 600000), "450,001-600,000", AND('Rent Table'!$I8 > 600000, 'Rent Table'!$I8 <= 750000), "600,001-750,000",'Rent Table'!$I8 > 750000, "750,000+", TRUE, "Undefined" )} -> 50,001-150,000
A9: 1227 Knox Street | B9: Torrance | C9: CA | D9: 90502 | E9: Los Angeles | F9: Industrial | G9: 45566 | H9: A++ | I9: 16000 | J9: SF | K9: 12.102 | L9: 16000 | M9: 36 | N9: - | O9: 1 | P9: 1 | Q9: 1974 | R9: - | S9: {=_xlfn.IFS(AND('Rent Table'!$I9>0,'Rent Table'!$I9<=50000),"0-50,000", AND('Rent Table'!$I9 > 50000, 'Rent Table'!$I9 <= 150000), "50,001-150,000", AND('Rent Table'!$I9 > 150000, 'Rent Table'!$I9 <= 250000), "150,001-250,000", AND('Rent Table'!$I9 > 250000, 'Rent Table'!$I9 <= 350000), "250,001-350,000", AND('Rent Table'!$I9 > 350000, 'Rent Table'!$I9 <= 450000), "350,001-450,000", AND('Rent Table'!$I9 > 450000, 'Rent Table'!$I9 <= 600000), "450,001-600,000", AND('Rent Table'!$I9 > 600000, 'Rent Table'!$I9 <= 750000), "600,001-750,000",'Rent Table'!$I9 > 750000, "750,000+", TRUE, "Undefined" )} -> 0-50,000
A10: 1234 Francisco Street | B10: Torrance | C10: CA | D10: 90502 | E10: Los Angeles | F10: Industrial | G10: 45566 | H10: A++ | I10: 14950 | J10: SF | K10: 15.3947 | L10: 14950 | M10: 61.5 | N10: - | O10: 3 | P10: 1 | Q10: 1964 | R10: - | S10: {=_xlfn.IFS(AND('Rent Table'!$I10>0,'Rent Table'!$I10<=50000),"0-50,000", AND('Rent Table'!$I10 > 50000, 'Rent Table'!$I10 <= 150000), "50,001-150,000", AND('Rent Table'!$I10 > 150000, 'Rent Table'!$I10 <= 250000), "150,001-250,000", AND('Rent Table'!$I10 > 250000, 'Rent Table'!$I10 <= 350000), "250,001-350,000", AND('Rent Table'!$I10 > 350000, 'Rent Table'!$I10 <= 450000), "350,001-450,000", AND('Rent Table'!$I10 > 450000, 'Rent Table'!$I10 <= 600000), "450,001-600,000", AND('Rent Table'!$I10 > 600000, 'Rent Table'!$I10 <= 750000), "600,001-750,000",'Rent Table'!$I10 > 750000, "750,000+", TRUE, "Undefined" )} -> 0-50,000
A11: 1380-1400 Charles Willard Street | B11: Carson | C11: CA | D11: 90746 | E11: Los Angeles | F11: Industrial | G11: 45566 | H11: A+ | I11: 250272 | J11: SF | K11: 20.28085 | L11: 148706 | M11: 36.75 | N11: - | O11: - | P11: 1 | Q11: 2003 | R11: - | S11: {=_xlfn.IFS(AND('Rent Table'!$I11>0,'Rent Table'!$I11<=50000),"0-50,000", AND('Rent Table'!$I11 > 50000, 'Rent Table'!$I11 <= 150000), "50,001-150,000", AND('Rent Table'!$I11 > 150000, 'Rent Table'!$I11 <= 250000), "150,001-250,000", AND('Rent Table'!$I11 > 250000, 'Rent Table'!$I11 <= 350000), "250,001-350,000", AND('Rent Table'!$I11 > 350000, 'Rent Table'!$I11 <= 450000), "350,001-450,000", AND('Rent Table'!$I11 > 450000, 'Rent Table'!$I11 <= 600000), "450,001-600,000", AND('Rent Table'!$I11 > 600000, 'Rent Table'!$I11 <= 750000), "600,001-750,000",'Rent Table'!$I11 > 750000, "750,000+", TRUE, "Undefined" )} -> 250,001-350,000
A12: 1450 Glenn Curtiss Street | B12: Carson | C12: CA | D12: 90746 | E12: Los Angeles | F12: Industrial | G12: 45566 | H12: A+ | I12: 182554 | J12: SF | K12: 19.0129 | L12: 182554 | M12: 60 | N12: 1.1 | O12: - | P12: 1 | Q12: 2005 | R12: - | S12: {=_xlfn.IFS(AND('Rent Table'!$I12>0,'Rent Table'!$I12<=50000),"0-50,000", AND('Rent Table'!$I12 > 50000, 'Rent Table'!$I12 <= 150000), "50,001-150,000", AND('Rent Table'!$I12 > 150000, 'Rent Table'!$I12 <= 250000), "150,001-250,000", AND('Rent Table'!$I12 > 250000, 'Rent Table'!$I12 <= 350000), "250,001-350,000", AND('Rent Table'!$I12 > 350000, 'Rent Table'!$I12 <= 450000), "350,001-450,000", AND('Rent Table'!$I12 > 450000, 'Rent Table'!$I12 <= 600000), "450,001-600,000", AND('Rent Table'!$I12 > 600000, 'Rent Table'!$I12 <= 750000), "600,001-750,000",'Rent Table'!$I12 > 750000, "750,000+", TRUE, "Undefined" )} -> 150,001-250,000
A13: 1450-1480 Charles Willard Street | B13: Carson | C13: CA | D13: 90746 | E13: Los Angeles | F13: Industrial | G13: 45566 | H13: A+ | I13: 81893 | J13: SF | K13: 19.08 | L13: 81532 | M13: 59 | N13: - | O13: 1 | P13: 1 | Q13: 2007 | R13: - | S13: {=_xlfn.IFS(AND('Rent Table'!$I13>0,'Rent Table'!$I13<=50000),"0-50,000", AND('Rent Table'!$I13 > 50000, 'Rent Table'!$I13 <= 150000), "50,001-150,000", AND('Rent Table'!$I13 > 150000, 'Rent Table'!$I13 <= 250000), "150,001-250,000", AND('Rent Table'!$I13 > 250000, 'Rent Table'!$I13 <= 350000), "250,001-350,000", AND('Rent Table'!$I13 > 350000, 'Rent Table'!$I13 <= 450000), "350,001-450,000", AND('Rent Table'!$I13 > 450000, 'Rent Table'!$I13 <= 600000), "450,001-600,000", AND('Rent Table'!$I13 > 600000, 'Rent Table'!$I13 <= 750000), "600,001-750,000",'Rent Table'!$I13 > 750000, "750,000+", TRUE, "Undefined" )} -> 50,001-150,000
A14: 1451 West Knox Street | B14: Torrance | C14: CA | D14: 90501 | E14: Los Angeles | F14: Industrial | G14: 45566 | H14: A++ | I14: 153000 | J14: SF | K14: 27.9826 | L14: 152790 | M14: 65 | N14: 1 | O14: - | P14: 1 | Q14: 2005 | R14: - | S14: {=_xlfn.IFS(AND('Rent Table'!$I14>0,'Rent Table'!$I14<=50000),"0-50,000", AND('Rent Table'!$I14 > 50000, 'Rent Table'!$I14 <= 150000), "50,001-150,000", AND('Rent Table'!$I14 > 150000, 'Rent Table'!$I14 <= 250000), "150,001-250,000", AND('Rent Table'!$I14 > 250000, 'Rent Table'!$I14 <= 350000), "250,001-350,000", AND('Rent Table'!$I14 > 350000, 'Rent Table'!$I14 <= 450000), "350,001-450,000", AND('Rent Table'!$I14 > 450000, 'Rent Table'!$I14 <= 600000), "450,001-600,000", AND('Rent Table'!$I14 > 600000, 'Rent Table'!$I14 <= 750000), "600,001-750,000",'Rent Table'!$I14 > 750000, "750,000+", TRUE, "Undefined" )} -> 150,001-250,000
A15: 1452 West Knox Street | B15: Torrance | C15: CA | D15: 90501 | E15: Los Angeles | F15: Industrial | G15: 45566 | H15: A++ | I15: 442550 | J15: SF | K15: 18.5248 | L15: 442550 | M15: 65 | N15: 2.82 | O15: 5.5 | P15: - | Q15: 2003 | R15: 2004 | S15: {=_xlfn.IFS(AND('Rent Table'!$I15>0,'Rent Table'!$I15<=50000),"0-50,000", AND('Rent Table'!$I15 > 50000, 'Rent Table'!$I15 <= 150000), "50,001-150,000", AND('Rent Table'!$I15 > 150000, 'Rent Table'!$I15 <= 250000), "150,001-250,000", AND('Rent Table'!$I15 > 250000, 'Rent Table'!$I15 <= 350000), "250,001-350,000", AND('Rent Table'!$I15 > 350000, 'Rent Table'!$I15 <= 450000), "350,001-450,000", AND('Rent Table'!$I15 > 450000, 'Rent Table'!$I15 <= 600000), "450,001-600,000", AND('Rent Table'!$I15 > 600000, 'Rent Table'!$I15 <= 750000), "600,001-750,000",'Rent Table'!$I15 > 750000, "750,000+", TRUE, "Undefined" )} -> 350,001-450,000
A16: 1457 Glenn Curtiss Street | B16: Carson | C16: CA | D16: 90746 | E16: Los Angeles | F16: Industrial | G16: 45566 | H16: A+ | I16: 76028 | J16: SF | K16: 16.8732 | L16: 76028 | M16: 48 | N16: 0.53 | O16: 1 | P16: 1 | Q16: 2006 | R16: - | S16: {=_xlfn.IFS(AND('Rent Table'!$I16>0,'Rent Table'!$I16<=50000),"0-50,000", AND('Rent Table'!$I16 > 50000, 'Rent Table'!$I16 <= 150000), "50,001-150,000", AND('Rent Table'!$I16 > 150000, 'Rent Table'!$I16 <= 250000), "150,001-250,000", AND('Rent Table'!$I16 > 250000, 'Rent Table'!$I16 <= 350000), "250,001-350,000", AND('Rent Table'!$I16 > 350000, 'Rent Table'!$I16 <= 450000), "350,001-450,000", AND('Rent Table'!$I16 > 450000, 'Rent Table'!$I16 <= 600000), "450,001-600,000", AND('Rent Table'!$I16 > 600000, 'Rent Table'!$I16 <= 750000), "600,001-750,000",'Rent Table'!$I16 > 750000, "750,000+", TRUE, "Undefined" )} -> 50,001-150,000
A17: 1460-1490 Beachey Place | B17: Carson | C17: CA | D17: 90746 | E17: Los Angeles | F17: Industrial | G17: 45566 | H17: A+ | I17: 185375 | J17: SF | K17: 18.03055 | L17: 40905 | M17: 61.5 | N17: 1 | O17: 1.5 | P17: 1 | Q17: 2005 | R17: - | S17: {=_xlfn.IFS(AND('Rent Table'!$I17>0,'Rent Table'!$I17<=50000),"0-50,000", AND('Rent Table'!$I17 > 50000, 'Rent Table'!$I17 <= 150000), "50,001-150,000", AND('Rent Table'!$I17 > 150000, 'Rent Table'!$I17 <= 250000), "150,001-250,000", AND('Rent Table'!$I17 > 250000, 'Rent Table'!$I17 <= 350000), "250,001-350,000", AND('Rent Table'!$I17 > 350000, 'Rent Table'!$I17 <= 450000), "350,001-450,000", AND('Rent Table'!$I17 > 450000, 'Rent Table'!$I17 <= 600000), "450,001-600,000", AND('Rent Table'!$I17 > 600000, 'Rent Table'!$I17 <= 750000), "600,001-750,000",'Rent Table'!$I17 > 750000, "750,000+", TRUE, "Undefined" )} -> 150,001-250,000
A18: 1500 Glenn Curtiss Street | B18: Carson | C18: CA | D18: 90746 | E18: Los Angeles | F18: Industrial | G18: 45566 | H18: A+ | I18: 242143 | J18: SF | K18: 21.1519 | L18: 48330 | M18: 64 | N18: - | O18: 4 | P18: 1 | Q18: 2002 | R18: - | S18: {=_xlfn.IFS(AND('Rent Table'!$I18>0,'Rent Table'!$I18<=50000),"0-50,000", AND('Rent Table'!$I18 > 50000, 'Rent Table'!$I18 <= 150000), "50,001-150,000", AND('Rent Table'!$I18 > 150000, 'Rent Table'!$I18 <= 250000), "150,001-250,000", AND('Rent Table'!$I18 > 250000, 'Rent Table'!$I18 <= 350000), "250,001-350,000", AND('Rent Table'!$I18 > 350000, 'Rent Table'!$I18 <= 450000), "350,001-450,000", AND('Rent Table'!$I18 > 450000, 'Rent Table'!$I18 <= 600000), "450,001-600,000", AND('Rent Table'!$I18 > 600000, 'Rent Table'!$I18 <= 750000), "600,001-750,000",'Rent Table'!$I18 > 750000, "750,000+", TRUE, "Undefined" )} -> 150,001-250,000
A19: 1521 Francisco Street | B19: Torrance | C19: CA | D19: 90501 | E19: Los Angeles | F19: Industrial | G19: 45566 | H19: A++ | I19: 46479 | J19: SF | K19: 20.3035 | L19: 23949 | M19: 35 | N19: - | O19: 1 | P19: - | Q19: 2011 | R19: 2012 | S19: {=_xlfn.IFS(AND('Rent Table'!$I19>0,'Rent Table'!$I19<=50000),"0-50,000", AND('Rent Table'!$I19 > 50000, 'Rent Table'!$I19 <= 150000), "50,001-150,000", AND('Rent Table'!$I19 > 150000, 'Rent Table'!$I19 <= 250000), "150,001-250,000", AND('Rent Table'!$I19 > 250000, 'Rent Table'!$I19 <= 350000), "250,001-350,000", AND('Rent Table'!$I19 > 350000, 'Rent Table'!$I19 <= 450000), "350,001-450,000", AND('Rent Table'!$I19 > 450000, 'Rent Table'!$I19 <= 600000), "450,001-600,000", AND('Rent Table'!$I19 > 600000, 'Rent Table'!$I19 <= 750000), "600,001-750,000",'Rent Table'!$I19 > 750000, "750,000+", TRUE, "Undefined" )} -> 0-50,000
A20: 1533-1543 East Del Amo Boulevard | B20: Carson | C20: CA | D20: 90746 | E20: Los Angeles | F20: Industrial | G20: 45566 | H20: A+ | I20: 35186 | J20: SF | K20: 12.4838 | L20: 17666 | M20: 36 | N20: - | O20: 0.5 | P20: 1 | Q20: 1971 | R20: - | S20: {=_xlfn.IFS(AND('Rent Table'!$I20>0,'Rent Table'!$I20<=50000),"0-50,000", AND('Rent Table'!$I20 > 50000, 'Rent Table'!$I20 <= 150000), "50,001-150,000", AND('Rent Table'!$I20 > 150000, 'Rent Table'!$I20 <= 250000), "150,001-250,000", AND('Rent Table'!$I20 > 250000, 'Rent Table'!$I20 <= 350000), "250,001-350,000", AND('Rent Table'!$I20 > 350000, 'Rent Table'!$I20 <= 450000), "350,001-450,000", AND('Rent Table'!$I20 > 450000, 'Rent Table'!$I20 <= 600000), "450,001-600,000", AND('Rent Table'!$I20 > 600000, 'Rent Table'!$I20 <= 750000), "600,001-750,000",'Rent Table'!$I20 > 750000, "750,000+", TRUE, "Undefined" )} -> 0-50,000
A21: 1540-1560 West 190th Street | B21: Torrance | C21: CA | D21: 90501 | E21: Los Angeles | F21: Industrial | G21: 45566 | H21: A++ | I21: 117460 | J21: SF | K21: 25.9481 | L21: 90133 | M21: 60 | N21: - | O21: - | P21: 1 | Q21: 2000 | R21: - | S21: {=_xlfn.IFS(AND('Rent Table'!$I21>0,'Rent Table'!$I21<=50000),"0-50,000", AND('Rent Table'!$I21 > 50000, 'Rent Table'!$I21 <= 150000), "50,001-150,000", AND('Rent Table'!$I21 > 150000, 'Rent Table'!$I21 <= 250000), "150,001-250,000", AND('Rent Table'!$I21 > 250000, 'Rent Table'!$I21 <= 350000), "250,001-350,000", AND('Rent Table'!$I21 > 350000, 'Rent Table'!$I21 <= 450000), "350,001-450,000", AND('Rent Table'!$I21 > 450000, 'Rent Table'!$I21 <= 600000), "450,001-600,000", AND('Rent Table'!$I21 > 600000, 'Rent Table'!$I21 <= 750000), "600,001-750,000",'Rent Table'!$I21 > 750000, "750,000+", TRUE, "Undefined" )} -> 50,001-150,000
A22: 1545 Francisco Street | B22: Torrance | C22: CA | D22: 90501 | E22: Los Angeles | F22: Industrial | G22: 45566 | H22: A++ | I22: 277000 | J22: SF | K22: 16.2203 | L22: 106898 | M22: 61 | N22: 1 | O22: 1 | P22: 2 | Q22: 2012 | R22: 2013 | S22: {=_xlfn.IFS(AND('Rent Table'!$I22>0,'Rent Table'!$I22<=50000),"0-50,000", AND('Rent Table'!$I22 > 50000, 'Rent Table'!$I22 <= 150000), "50,001-150,000", AND('Rent Table'!$I22 > 150000, 'Rent Table'!$I22 <= 250000), "150,001-250,000", AND('Rent Table'!$I22 > 250000, 'Rent Table'!$I22 <= 350000), "250,001-350,000", AND('Rent Table'!$I22 > 350000, 'Rent Table'!$I22 <= 450000), "350,001-450,000", AND('Rent Table'!$I22 > 450000, 'Rent Table'!$I22 <= 600000), "450,001-600,000", AND('Rent Table'!$I22 > 600000, 'Rent Table'!$I22 <= 750000), "600,001-750,000",'Rent Table'!$I22 > 750000, "750,000+", TRUE, "Undefined" )} -> 250,001-350,000
A23: 1550-1650 Charles Willard Street | B23: Carson | C23: CA | D23: 90746 | E23: Los Angeles | F23: Industrial | G23: 45566 | H23: A+ | I23: 210938 | J23: SF | K23: 21.9904 | L23: 107753 | M23: 64 | N23: 1.5 | O23: 1 | P23: 1 | Q23: 2000 | R23: 2005 | S23: {=_xlfn.IFS(AND('Rent Table'!$I23>0,'Rent Table'!$I23<=50000),"0-50,000", AND('Rent Table'!$I23 > 50000, 'Rent Table'!$I23 <= 150000), "50,001-150,000", AND('Rent Table'!$I23 > 150000, 'Rent Table'!$I23 <= 250000), "150,001-250,000", AND('Rent Table'!$I23 > 250000, 'Rent Table'!$I23 <= 350000), "250,001-350,000", AND('Rent Table'!$I23 > 350000, 'Rent Table'!$I23 <= 450000), "350,001-450,000", AND('Rent Table'!$I23 > 450000, 'Rent Table'!$I23 <= 600000), "450,001-600,000", AND('Rent Table'!$I23 > 600000, 'Rent Table'!$I23 <= 750000), "600,001-750,000",'Rent Table'!$I23 > 750000, "750,000+", TRUE, "Undefined" )} -> 150,001-250,000
A24: 1561 Beachey Place | B24: Carson | C24: CA | D24: 90746 | E24: Los Angeles | F24: Industrial | G24: 45566 | H24: A+ | I24: 108873 | J24: SF | K24: 21.6977 | L24: 107603 | M24: 60 | N24: - | O24: 2 | P24: 2 | Q24: 2004 | R24: 2005 | S24: {=_xlfn.IFS(AND('Rent Table'!$I24>0,'Rent Table'!$I24<=50000),"0-50,000", AND('Rent Table'!$I24 > 50000, 'Rent Table'!$I24 <= 150000), "50,001-150,000", AND('Rent Table'!$I24 > 150000, 'Rent Table'!$I24 <= 250000), "150,001-250,000", AND('Rent Table'!$I24 > 250000, 'Rent Table'!$I24 <= 350000), "250,001-350,000", AND('Rent Table'!$I24 > 350000, 'Rent Table'!$I24 <= 450000), "350,001-450,000", AND('Rent Table'!$I24 > 450000, 'Rent Table'!$I24 <= 600000), "450,001-600,000", AND('Rent Table'!$I24 > 600000, 'Rent Table'!$I24 <= 750000), "600,001-750,000",'Rent Table'!$I24 > 750000, "750,000+", TRUE, "Undefined" )} -> 50,001-150,000
A25: 1640 West 190th Street | B25: Torrance | C25: CA | D25: 90501 | E25: Los Angeles | F25: Industrial | G25: 45566 | H25: A++ | I25: 123345 | J25: SF | K25: 28.9685 | L25: 123345 | M25: 120 | N25: - | O25: 1.5 | P25: 1 | Q25: 2000 | R25: - | S25: {=_xlfn.IFS(AND('Rent Table'!$I25>0,'Rent Table'!$I25<=50000),"0-50,000", AND('Rent Table'!$I25 > 50000, 'Rent Table'!$I25 <= 150000), "50,001-150,000", AND('Rent Table'!$I25 > 150000, 'Rent Table'!$I25 <= 250000), "150,001-250,000", AND('Rent Table'!$I25 > 250000, 'Rent Table'!$I25 <= 350000), "250,001-350,000", AND('Rent Table'!$I25 > 350000, 'Rent Table'!$I25 <= 450000), "350,001-450,000", AND('Rent Table'!$I25 > 450000, 'Rent Table'!$I25 <= 600000), "450,001-600,000", AND('Rent Table'!$I25 > 600000, 'Rent Table'!$I25 <= 750000), "600,001-750,000",'Rent Table'!$I25 > 750000, "750,000+", TRUE, "Undefined" )} -> 50,001-150,000
A26: 1667 East Del Amo Boulevard | B26: Carson | C26: CA | D26: 90746 | E26: Los Angeles | F26: Industrial | G26: 45566 | H26: A+ | I26: 16863 | J26: SF | K26: 11.3567 | L26: 1752 | M26: 24 | N26: - | O26: - | P26: 1 | Q26: 1970 | R26: - | S26: {=_xlfn.IFS(AND('Rent Table'!$I26>0,'Rent Table'!$I26<=50000),"0-50,000", AND('Rent Table'!$I26 > 50000, 'Rent Table'!$I26 <= 150000), "50,001-150,000", AND('Rent Table'!$I26 > 150000, 'Rent Table'!$I26 <= 250000), "150,001-250,000", AND('Rent Table'!$I26 > 250000, 'Rent Table'!$I26 <= 350000), "250,001-350,000", AND('Rent Table'!$I26 > 350000, 'Rent Table'!$I26 <= 450000), "350,001-450,000", AND('Rent Table'!$I26 > 450000, 'Rent Table'!$I26 <= 600000), "450,001-600,000", AND('Rent Table'!$I26 > 600000, 'Rent Table'!$I26 <= 750000), "600,001-750,000",'Rent Table'!$I26 > 750000, "750,000+", TRUE, "Undefined" )} -> 0-50,000
A27: 1681 East Del Amo Boulevard | B27: Carson | C27: CA | D27: 90746 | E27: Los Angeles | F27: Industrial | G27: 45566 | H27: A+ | I27: 16862 | J27: SF | K27: 10.7525 | L27: 2592 | M27: 36 | N27: - | O27: - | P27: 1 | Q27: 1970 | R27: - | S27: {=_xlfn.IFS(AND('Rent Table'!$I27>0,'Rent Table'!$I27<=50000),"0-50,000", AND('Rent Table'!$I27 > 50000, 'Rent Table'!$I27 <= 150000), "50,001-150,000", AND('Rent Table'!$I27 > 150000, 'Rent Table'!$I27 <= 250000), "150,001-250,000", AND('Rent Table'!$I27 > 250000, 'Rent Table'!$I27 <= 350000), "250,001-350,000", AND('Rent Table'!$I27 > 350000, 'Rent Table'!$I27 <= 450000), "350,001-450,000", AND('Rent Table'!$I27 > 450000, 'Rent Table'!$I27 <= 600000), "450,001-600,000", AND('Rent Table'!$I27 > 600000, 'Rent Table'!$I27 <= 750000), "600,001-750,000",'Rent Table'!$I27 > 750000, "750,000+", TRUE, "Undefined" )} -> 0-50,000
A28: 1683 East Del Amo Boulevard | B28: Carson | C28: CA | D28: 90746 | E28: Los Angeles | F28: Industrial | G28: 45566 | H28: A+ | I28: 16882 | J28: SF | K28: 12.214405 | L28: 2555 | M28: 48.5 | N28: - | O28: 1 | P28: 1 | Q28: 1970 | R28: - | S28: {=_xlfn.IFS(AND('Rent Table'!$I28>0,'Rent Table'!$I28<=50000),"0-50,000", AND('Rent Table'!$I28 > 50000, 'Rent Table'!$I28 <= 150000), "50,001-150,000", AND('Rent Table'!$I28 > 150000, 'Rent Table'!$I28 <= 250000), "150,001-250,000", AND('Rent Table'!$I28 > 250000, 'Rent Table'!$I28 <= 350000), "250,001-350,000", AND('Rent Table'!$I28 > 350000, 'Rent Table'!$I28 <= 450000), "350,001-450,000", AND('Rent Table'!$I28 > 450000, 'Rent Table'!$I28 <= 600000), "450,001-600,000", AND('Rent Table'!$I28 > 600000, 'Rent Table'!$I28 <= 750000), "600,001-750,000",'Rent Table'!$I28 > 750000, "750,000+", TRUE, "Undefined" )} -> 0-50,000
A29: 1685 East Del Amo Boulevard | B29: Carson | C29: CA | D29: 90746 | E29: Los Angeles | F29: Industrial | G29: 45566 | H29: A+ | I29: 16862 | J29: SF | K29: 12.9391 | L29: 1752 | M29: 36 | N29: - | O29: - | P29: 1 | Q29: 1970 | R29: - | S29: {=_xlfn.IFS(AND('Rent Table'!$I29>0,'Rent Table'!$I29<=50000),"0-50,000", AND('Rent Table'!$I29 > 50000, 'Rent Table'!$I29 <= 150000), "50,001-150,000", AND('Rent Table'!$I29 > 150000, 'Rent Table'!$I29 <= 250000), "150,001-250,000", AND('Rent Table'!$I29 > 250000, 'Rent Table'!$I29 <= 350000), "250,001-350,000", AND('Rent Table'!$I29 > 350000, 'Rent Table'!$I29 <= 450000), "350,001-450,000", AND('Rent Table'!$I29 > 450000, 'Rent Table'!$I29 <= 600000), "450,001-600,000", AND('Rent Table'!$I29 > 600000, 'Rent Table'!$I29 <= 750000), "600,001-750,000",'Rent Table'!$I29 > 750000, "750,000+", TRUE, "Undefined" )} -> 0-50,000
A30: 1689 East Del Amo Boulevard | B30: Carson | C30: CA | D30: 90746 | E30: Los Angeles | F30: Industrial | G30: 45566 | H30: A+ | I30: 40332 | J30: SF | K30: 12.4644 | L30: 1752 | M30: 36 | N30: - | O30: - | P30: 1 | Q30: 1970 | R30: - | S30: {=_xlfn.IFS(AND('Rent Table'!$I30>0,'Rent Table'!$I30<=50000),"0-50,000", AND('Rent Table'!$I30 > 50000, 'Rent Table'!$I30 <= 150000), "50,001-150,000", AND('Rent Table'!$I30 > 150000, 'Rent Table'!$I30 <= 250000), "150,001-250,000", AND('Rent Table'!$I30 > 250000, 'Rent Table'!$I30 <= 350000), "250,001-350,000", AND('Rent Table'!$I30 > 350000, 'Rent Table'!$I30 <= 450000), "350,001-450,000", AND('Rent Table'!$I30 > 450000, 'Rent Table'!$I30 <= 600000), "450,001-600,000", AND('Rent Table'!$I30 > 600000, 'Rent Table'!$I30 <= 750000), "600,001-750,000",'Rent Table'!$I30 > 750000, "750,000+", TRUE, "Undefined" )} -> 0-50,000
A31: 1693 East Del Amo Boulevard | B31: Carson | C31: CA | D31: 90746 | E31: Los Angeles | F31: Industrial | G31: 45566 | H31: A+ | I31: 16863 | J31: SF | K31: 13.0156 | L31: 2336 | M31: 24 | N31: - | O31: - | P31: 1 | Q31: 1970 | R31: - | S31: {=_xlfn.IFS(AND('Rent Table'!$I31>0,'Rent Table'!$I31<=50000),"0-50,000", AND('Rent Table'!$I31 > 50000, 'Rent Table'!$I31 <= 150000), "50,001-150,000", AND('Rent Table'!$I31 > 150000, 'Rent Table'!$I31 <= 250000), "150,001-250,000", AND('Rent Table'!$I31 > 250000, 'Rent Table'!$I31 <= 350000), "250,001-350,000", AND('Rent Table'!$I31 > 350000, 'Rent Table'!$I31 <= 450000), "350,001-450,000", AND('Rent Table'!$I31 > 450000, 'Rent Table'!$I31 <= 600000), "450,001-600,000", AND('Rent Table'!$I31 > 600000, 'Rent Table'!$I31 <= 750000), "600,001-750,000",'Rent Table'!$I31 > 750000, "750,000+", TRUE, "Undefined" )} -> 0-50,000
A32: 1810 195th Street | B32: Torrance | C32: CA | D32: 90501 | E32: Los Angeles | F32: Industrial | G32: 45566 | H32: A++ | I32: 107140 | J32: SF | K32: 19.7753 | L32: 107140 | M32: 123 | N32: 3 | O32: 3 | P32: - | Q32: 2022 | R32: - | S32: {=_xlfn.IFS(AND('Rent Table'!$I32>0,'Rent Table'!$I32<=50000),"0-50,000", AND('Rent Table'!$I32 > 50000, 'Rent Table'!$I32 <= 150000), "50,001-150,000", AND('Rent Table'!$I32 > 150000, 'Rent Table'!$I32 <= 250000), "150,001-250,000", AND('Rent Table'!$I32 > 250000, 'Rent Table'!$I32 <= 350000), "250,001-350,000", AND('Rent Table'!$I32 > 350000, 'Rent Table'!$I32 <= 450000), "350,001-450,000", AND('Rent Table'!$I32 > 450000, 'Rent Table'!$I32 <= 600000), "450,001-600,000", AND('Rent Table'!$I32 > 600000, 'Rent Table'!$I32 <= 750000), "600,001-750,000",'Rent Table'!$I32 > 750000, "750,000+", TRUE, "Undefined" )} -> 50,001-150,000
A33: 1820 195th Street | B33: Torrance | C33: CA | D33: 90501 | E33: Los Angeles | F33: Industrial | G33: 45566 | H33: A++ | I33: 104544 | J33: SF | K33: 20.2742 | L33: 104544 | M33: 123 | N33: 3 | O33: 3 | P33: - | Q33: 2022 | R33: - | S33: {=_xlfn.IFS(AND('Rent Table'!$I33>0,'Rent Table'!$I33<=50000),"0-50,000", AND('Rent Table'!$I33 > 50000, 'Rent Table'!$I33 <= 150000), "50,001-150,000", AND('Rent Table'!$I33 > 150000, 'Rent Table'!$I33 <= 250000), "150,001-250,000", AND('Rent Table'!$I33 > 250000, 'Rent Table'!$I33 <= 350000), "250,001-350,000", AND('Rent Table'!$I33 > 350000, 'Rent Table'!$I33 <= 450000), "350,001-450,000", AND('Rent Table'!$I33 > 450000, 'Rent Table'!$I33 <= 600000), "450,001-600,000", AND('Rent Table'!$I33 > 600000, 'Rent Table'!$I33 <= 750000), "600,001-750,000",'Rent Table'!$I33 > 750000, "750,000+", TRUE, "Undefined" )} -> 50,001-150,000
A34: 1830 West 205th Street | B34: Torrance | C34: CA | D34: 90501 | E34: Los Angeles | F34: Industrial | G34: 45566 | H34: A++ | I34: 31505 | J34: SF | K34: 24.8275 | L34: 31505 | M34: 84 | N34: 7.94 | O34: 3 | P34: 1 | Q34: 1978 | R34: 1993 | S34: {=_xlfn.IFS(AND('Rent Table'!$I34>0,'Rent Table'!$I34<=50000),"0-50,000", AND('Rent Table'!$I34 > 50000, 'Rent Table'!$I34 <= 150000), "50,001-150,000", AND('Rent Table'!$I34 > 150000, 'Rent Table'!$I34 <= 250000), "150,001-250,000", AND('Rent Table'!$I34 > 250000, 'Rent Table'!$I34 <= 350000), "250,001-350,000", AND('Rent Table'!$I34 > 350000, 'Rent Table'!$I34 <= 450000), "350,001-450,000", AND('Rent Table'!$I34 > 450000, 'Rent Table'!$I34 <= 600000), "450,001-600,000", AND('Rent Table'!$I34 > 600000, 'Rent Table'!$I34 <= 750000), "600,001-750,000",'Rent Table'!$I34 > 750000, "750,000+", TRUE, "Undefined" )} -> 0-50,000
A35: 18300 Central Avenue | B35: Carson | C35: CA | D35: 90746 | E35: Los Angeles | F35: Industrial | G35: 45566 | H35: A+ | I35: 183473 | J35: SF | K35: 18.754 | L35: 183473 | M35: 120 | N35: - | O35: 1 | P35: 1 | Q35: 2000 | R35: - | S35: {=_xlfn.IFS(AND('Rent Table'!$I35>0,'Rent Table'!$I35<=50000),"0-50,000", AND('Rent Table'!$I35 > 50000, 'Rent Table'!$I35 <= 150000), "50,001-150,000", AND('Rent Table'!$I35 > 150000, 'Rent Table'!$I35 <= 250000), "150,001-250,000", AND('Rent Table'!$I35 > 250000, 'Rent Table'!$I35 <= 350000), "250,001-350,000", AND('Rent Table'!$I35 > 350000, 'Rent Table'!$I35 <= 450000), "350,001-450,000", AND('Rent Table'!$I35 > 450000, 'Rent Table'!$I35 <= 600000), "450,001-600,000", AND('Rent Table'!$I35 > 600000, 'Rent Table'!$I35 <= 750000), "600,001-750,000",'Rent Table'!$I35 > 750000, "750,000+", TRUE, "Undefined" )} -> 150,001-250,000
A36: 1845 West 205th Street | B36: Torrance | C36: CA | D36: 90501 | E36: Los Angeles | F36: Industrial | G36: 45566 | H36: A++ | I36: 34505 | J36: SF | K36: 24.277 | L36: 25301 | M36: 89 | N36: - | O36: 4.34 | P36: 1 | Q36: 1978 | R36: - | S36: {=_xlfn.IFS(AND('Rent Table'!$I36>0,'Rent Table'!$I36<=50000),"0-50,000", AND('Rent Table'!$I36 > 50000, 'Rent Table'!$I36 <= 150000), "50,001-150,000", AND('Rent Table'!$I36 > 150000, 'Rent Table'!$I36 <= 250000), "150,001-250,000", AND('Rent Table'!$I36 > 250000, 'Rent Table'!$I36 <= 350000), "250,001-350,000", AND('Rent Table'!$I36 > 350000, 'Rent Table'!$I36 <= 450000), "350,001-450,000", AND('Rent Table'!$I36 > 450000, 'Rent Table'!$I36 <= 600000), "450,001-600,000", AND('Rent Table'!$I36 > 600000, 'Rent Table'!$I36 <= 750000), "600,001-750,000",'Rent Table'!$I36 > 750000, "750,000+", TRUE, "Undefined" )} -> 0-50,000
A37: 18600 Crenshaw Boulevard | B37: Torrance | C37: CA | D37: 90504 | E37: Los Angeles | F37: Industrial | G37: 45566 | H37: A++ | I37: 77843 | J37: SF | K37: 16.7513 | L37: 29978 | M37: 120 | N37: - | O37: 4 | P37: 1 | Q37: 1974 | R37: - | S37: {=_xlfn.IFS(AND('Rent Table'!$I37>0,'Rent Table'!$I37<=50000),"0-50,000", AND('Rent Table'!$I37 > 50000, 'Rent Table'!$I37 <= 150000), "50,001-150,000", AND('Rent Table'!$I37 > 150000, 'Rent Table'!$I37 <= 250000), "150,001-250,000", AND('Rent Table'!$I37 > 250000, 'Rent Table'!$I37 <= 350000), "250,001-350,000", AND('Rent Table'!$I37 > 350000, 'Rent Table'!$I37 <= 450000), "350,001-450,000", AND('Rent Table'!$I37 > 450000, 'Rent Table'!$I37 <= 600000), "450,001-600,000", AND('Rent Table'!$I37 > 600000, 'Rent Table'!$I37 <= 750000), "600,001-750,000",'Rent Table'!$I37 > 750000, "750,000+", TRUE, "Undefined" )} -> 50,001-150,000
A38: 19000-19010 South Vermont Avenue | B38: Gardena | C38: CA | D38: 90248 | E38: Los Angeles | F38: Industrial | G38: 45505 | H38: A++ | I38: 45585 | J38: SF | K38: 25.7664 | L38: 20497 | M38: 120 | N38: - | O38: - | P38: 1 | Q38: 1970 | R38: 1982 | S38: {=_xlfn.IFS(AND('Rent Table'!$I38>0,'Rent Table'!$I38<=50000),"0-50,000", AND('Rent Table'!$I38 > 50000, 'Rent Table'!$I38 <= 150000), "50,001-150,000", AND('Rent Table'!$I38 > 150000, 'Rent Table'!$I38 <= 250000), "150,001-250,000", AND('Rent Table'!$I38 > 250000, 'Rent Table'!$I38 <= 350000), "250,001-350,000", AND('Rent Table'!$I38 > 350000, 'Rent Table'!$I38 <= 450000), "350,001-450,000", AND('Rent Table'!$I38 > 450000, 'Rent Table'!$I38 <= 600000), "450,001-600,000", AND('Rent Table'!$I38 > 600000, 'Rent Table'!$I38 <= 750000), "600,001-750,000",'Rent Table'!$I38 > 750000, "750,000+", TRUE, "Undefined" )} -> 0-50,000
A39: 19032 South Vermont Avenue | B39: Gardena | C39: CA | D39: 90248 | E39: Los Angeles | F39: Industrial | G39: 45566 | H39: A++ | I39: 100080 | J39: SF | K39: 11.7541 | L39: 33850 | M39: 24 | N39: - | O39: - | P39: 1 | Q39: 1970 | R39: 1972 | S39: {=_xlfn.IFS(AND('Rent Table'!$I39>0,'Rent Table'!$I39<=50000),"0-50,000", AND('Rent Table'!$I39 > 50000, 'Rent Table'!$I39 <= 150000), "50,001-150,000", AND('Rent Table'!$I39 > 150000, 'Rent Table'!$I39 <= 250000), "150,001-250,000", AND('Rent Table'!$I39 > 250000, 'Rent Table'!$I39 <= 350000), "250,001-350,000", AND('Rent Table'!$I39 > 350000, 'Rent Table'!$I39 <= 450000), "350,001-450,000", AND('Rent Table'!$I39 > 450000, 'Rent Table'!$I39 <= 600000), "450,001-600,000", AND('Rent Table'!$I39 > 600000, 'Rent Table'!$I39 <= 750000), "600,001-750,000",'Rent Table'!$I39 > 750000, "750,000+", TRUE, "Undefined" )} -> 50,001-150,000
A40: 19038 South Vermont Avenue | B40: Gardena | C40: CA | D40: 90248 | E40: Los Angeles | F40: Industrial | G40: 45566 | H40: A++ | I40: 100080 | J40: SF | K40: 22.5784 | L40: 49690 | M40: 120.5 | N40: - | O40: - | P40: 1 | Q40: 1970 | R40: 1972 | S40: {=_xlfn.IFS(AND('Rent Table'!$I40>0,'Rent Table'!$I40<=50000),"0-50,000", AND('Rent Table'!$I40 > 50000, 'Rent Table'!$I40 <= 150000), "50,001-150,000", AND('Rent Table'!$I40 > 150000, 'Rent Table'!$I40 <= 250000), "150,001-250,000", AND('Rent Table'!$I40 > 250000, 'Rent Table'!$I40 <= 350000), "250,001-350,000", AND('Rent Table'!$I40 > 350000, 'Rent Table'!$I40 <= 450000), "350,001-450,000", AND('Rent Table'!$I40 > 450000, 'Rent Table'!$I40 <= 600000), "450,001-600,000", AND('Rent Table'!$I40 > 600000, 'Rent Table'!$I40 <= 750000), "600,001-750,000",'Rent Table'!$I40 > 750000, "750,000+", TRUE, "Undefined" )} -> 50,001-150,000
A41: 19145 Gramercy Place | B41: Torrance | C41: CA | D41: 90501 | E41: Los Angeles | F41: Industrial | G41: 45566 | H41: A++ | I41: 102279 | J41: SF | K41: 22.426 | L41: 102143 | M41: 120 | N41: 10 | O41: 2 | P41: 1 | Q41: 1982 | R41: 1983 | S41: {=_xlfn.IFS(AND('Rent Table'!$I41>0,'Rent Table'!$I41<=50000),"0-50,000", AND('Rent Table'!$I41 > 50000, 'Rent Table'!$I41 <= 150000), "50,001-150,000", AND('Rent Table'!$I41 > 150000, 'Rent Table'!$I41 <= 250000), "150,001-250,000", AND('Rent Table'!$I41 > 250000, 'Rent Table'!$I41 <= 350000), "250,001-350,000", AND('Rent Table'!$I41 > 350000, 'Rent Table'!$I41 <= 450000), "350,001-450,000", AND('Rent Table'!$I41 > 450000, 'Rent Table'!$I41 <= 600000), "450,001-600,000", AND('Rent Table'!$I41 > 600000, 'Rent Table'!$I41 <= 750000), "600,001-750,000",'Rent Table'!$I41 > 750000, "750,000+", TRUE, "Undefined" )} -> 50,001-150,000
A42: 19200-19270 South Western Avenue | B42: Torrance | C42: CA | D42: 90501 | E42: Los Angeles | F42: Industrial | G42: 45566 | H42: A++ | I42: 684900 | J42: SF | K42: 16.1212 | L42: 342450 | M42: 91 | N42: 1 | O42: 2.5 | P42: 1 | Q42: 1998 | R42: - | S42: {=_xlfn.IFS(AND('Rent Table'!$I42>0,'Rent Table'!$I42<=50000),"0-50,000", AND('Rent Table'!$I42 > 50000, 'Rent Table'!$I42 <= 150000), "50,001-150,000", AND('Rent Table'!$I42 > 150000, 'Rent Table'!$I42 <= 250000), "150,001-250,000", AND('Rent Table'!$I42 > 250000, 'Rent Table'!$I42 <= 350000), "250,001-350,000", AND('Rent Table'!$I42 > 350000, 'Rent Table'!$I42 <= 450000), "350,001-450,000", AND('Rent Table'!$I42 > 450000, 'Rent Table'!$I42 <= 600000), "450,001-600,000", AND('Rent Table'!$I42 > 600000, 'Rent Table'!$I42 <= 750000), "600,001-750,000",'Rent Table'!$I42 > 750000, "750,000+", TRUE, "Undefined" )} -> 600,001-750,000
A43: 19301 Prairie Avenue | B43: Torrance | C43: CA | D43: 90503 | E43: Los Angeles | F43: Industrial | G43: 45566 | H43: A++ | I43: 108320 | J43: SF | K43: 25.8251 | L43: 108320 | M43: 89 | N43: 6 | O43: 5 | P43: - | Q43: 2023 | R43: - | S43: {=_xlfn.IFS(AND('Rent Table'!$I43>0,'Rent Table'!$I43<=50000),"0-50,000", AND('Rent Table'!$I43 > 50000, 'Rent Table'!$I43 <= 150000), "50,001-150,000", AND('Rent Table'!$I43 > 150000, 'Rent Table'!$I43 <= 250000), "150,001-250,000", AND('Rent Table'!$I43 > 250000, 'Rent Table'!$I43 <= 350000), "250,001-350,000", AND('Rent Table'!$I43 > 350000, 'Rent Table'!$I43 <= 450000), "350,001-450,000", AND('Rent Table'!$I43 > 450000, 'Rent Table'!$I43 <= 600000), "450,001-600,000", AND('Rent Table'!$I43 > 600000, 'Rent Table'!$I43 <= 750000), "600,001-750,000",'Rent Table'!$I43 > 750000, "750,000+", TRUE, "Undefined" )} -> 50,001-150,000
A44: 19340-19370 Van Ness Avenue | B44: Torrance | C44: CA | D44: 90501 | E44: Los Angeles | F44: Industrial | G44: 45505 | H44: A++ | I44: 43133 | J44: SF | K44: 18.75135 | L44: 24393 | M44: 48 | N44: - | O44: 3.5 | P44: 1 | Q44: 1977 | R44: - | S44: {=_xlfn.IFS(AND('Rent Table'!$I44>0,'Rent Table'!$I44<=50000),"0-50,000", AND('Rent Table'!$I44 > 50000, 'Rent Table'!$I44 <= 150000), "50,001-150,000", AND('Rent Table'!$I44 > 150000, 'Rent Table'!$I44 <= 250000), "150,001-250,000", AND('Rent Table'!$I44 > 250000, 'Rent Table'!$I44 <= 350000), "250,001-350,000", AND('Rent Table'!$I44 > 350000, 'Rent Table'!$I44 <= 450000), "350,001-450,000", AND('Rent Table'!$I44 > 450000, 'Rent Table'!$I44 <= 600000), "450,001-600,000", AND('Rent Table'!$I44 > 600000, 'Rent Table'!$I44 <= 750000), "600,001-750,000",'Rent Table'!$I44 > 750000, "750,000+", TRUE, "Undefined" )} -> 0-50,000
A45: 19400 Harborgate Way | B45: Torrance | C45: CA | D45: 90501 | E45: Los Angeles | F45: Industrial | G45: 45566 | H45: A++ | I45: 860000 | J45: SF | K45: 17.2818 | L45: 127608 | M45: 130 | N45: - | O45: - | P45: - | Q45: 2003 | R45: 2004 | S45: {=_xlfn.IFS(AND('Rent Table'!$I45>0,'Rent Table'!$I45<=50000),"0-50,000", AND('Rent Table'!$I45 > 50000, 'Rent Table'!$I45 <= 150000), "50,001-150,000", AND('Rent Table'!$I45 > 150000, 'Rent Table'!$I45 <= 250000), "150,001-250,000", AND('Rent Table'!$I45 > 250000, 'Rent Table'!$I45 <= 350000), "250,001-350,000", AND('Rent Table'!$I45 > 350000, 'Rent Table'!$I45 <= 450000), "350,001-450,000", AND('Rent Table'!$I45 > 450000, 'Rent Table'!$I45 <= 600000), "450,001-600,000", AND('Rent Table'!$I45 > 600000, 'Rent Table'!$I45 <= 750000), "600,001-750,000",'Rent Table'!$I45 > 750000, "750,000+", TRUE, "Undefined" )} -> 750,000+
A46: 19400 South Western Avenue | B46: Torrance | C46: CA | D46: 90501 | E46: Los Angeles | F46: Industrial | G46: 45566 | H46: A++ | I46: 259327 | J46: SF | K46: 17.7651 | L46: 259327 | M46: 62 | N46: 1.75 | O46: 1 | P46: 1 | Q46: 1998 | R46: - | S46: {=_xlfn.IFS(AND('Rent Table'!$I46>0,'Rent Table'!$I46<=50000),"0-50,000", AND('Rent Table'!$I46 > 50000, 'Rent Table'!$I46 <= 150000), "50,001-150,000", AND('Rent Table'!$I46 > 150000, 'Rent Table'!$I46 <= 250000), "150,001-250,000", AND('Rent Table'!$I46 > 250000, 'Rent Table'!$I46 <= 350000), "250,001-350,000", AND('Rent Table'!$I46 > 350000, 'Rent Table'!$I46 <= 450000), "350,001-450,000", AND('Rent Table'!$I46 > 450000, 'Rent Table'!$I46 <= 600000), "450,001-600,000", AND('Rent Table'!$I46 > 600000, 'Rent Table'!$I46 <= 750000), "600,001-750,000",'Rent Table'!$I46 > 750000, "750,000+", TRUE, "Undefined" )} -> 250,001-350,000
A47: 19500-19600 South Vermont Avenue | B47: Torrance | C47: CA | D47: 90502 | E47: Los Angeles | F47: Industrial | G47: 45566 | H47: A++ | I47: 208896 | J47: SF | K47: 20.37695 | L47: 101767 | M47: 69 | N47: 2 | O47: 3 | P47: 1 | Q47: 1980 | R47: - | S47: {=_xlfn.IFS(AND('Rent Table'!$I47>0,'Rent Table'!$I47<=50000),"0-50,000", AND('Rent Table'!$I47 > 50000, 'Rent Table'!$I47 <= 150000), "50,001-150,000", AND('Rent Table'!$I47 > 150000, 'Rent Table'!$I47 <= 250000), "150,001-250,000", AND('Rent Table'!$I47 > 250000, 'Rent Table'!$I47 <= 350000), "250,001-350,000", AND('Rent Table'!$I47 > 350000, 'Rent Table'!$I47 <= 450000), "350,001-450,000", AND('Rent Table'!$I47 > 450000, 'Rent Table'!$I47 <= 600000), "450,001-600,000", AND('Rent Table'!$I47 > 600000, 'Rent Table'!$I47 <= 750000), "600,001-750,000",'Rent Table'!$I47 > 750000, "750,000+", TRUE, "Undefined" )} -> 150,001-250,000
A48: 19600 South Western Avenue | B48: Torrance | C48: CA | D48: 90501 | E48: Los Angeles | F48: Industrial | G48: 45566 | H48: A++ | I48: 314559 | J48: SF | K48: 17.5816 | L48: 314559 | M48: 95.5 | N48: 3.25 | O48: 2 | P48: 1 | Q48: 1998 | R48: - | S48: {=_xlfn.IFS(AND('Rent Table'!$I48>0,'Rent Table'!$I48<=50000),"0-50,000", AND('Rent Table'!$I48 > 50000, 'Rent Table'!$I48 <= 150000), "50,001-150,000", AND('Rent Table'!$I48 > 150000, 'Rent Table'!$I48 <= 250000), "150,001-250,000", AND('Rent Table'!$I48 > 250000, 'Rent Table'!$I48 <= 350000), "250,001-350,000", AND('Rent Table'!$I48 > 350000, 'Rent Table'!$I48 <= 450000), "350,001-450,000", AND('Rent Table'!$I48 > 450000, 'Rent Table'!$I48 <= 600000), "450,001-600,000", AND('Rent Table'!$I48 > 600000, 'Rent Table'!$I48 <= 750000), "600,001-750,000",'Rent Table'!$I48 > 750000, "750,000+", TRUE, "Undefined" )} -> 250,001-350,000
A49: 19600-19688 Van Ness Avenue | B49: Torrance | C49: CA | D49: 90501 | E49: Los Angeles | F49: Industrial | G49: 45566 | H49: A++ | I49: 177372 | J49: SF | K49: 19.51805 | L49: 88660 | M49: 96.5 | N49: - | O49: 2 | P49: 1 | Q49: 2001 | R49: - | S49: {=_xlfn.IFS(AND('Rent Table'!$I49>0,'Rent Table'!$I49<=50000),"0-50,000", AND('Rent Table'!$I49 > 50000, 'Rent Table'!$I49 <= 150000), "50,001-150,000", AND('Rent Table'!$I49 > 150000, 'Rent Table'!$I49 <= 250000), "150,001-250,000", AND('Rent Table'!$I49 > 250000, 'Rent Table'!$I49 <= 350000), "250,001-350,000", AND('Rent Table'!$I49 > 350000, 'Rent Table'!$I49 <= 450000), "350,001-450,000", AND('Rent Table'!$I49 > 450000, 'Rent Table'!$I49 <= 600000), "450,001-600,000", AND('Rent Table'!$I49 > 600000, 'Rent Table'!$I49 <= 750000), "600,001-750,000",'Rent Table'!$I49 > 750000, "750,000+", TRUE, "Undefined" )} -> 150,001-250,000
A50: 19601 Hamilton Avenue | B50: Torrance | C50: CA | D50: 90502 | E50: Los Angeles | F50: Industrial | G50: 45566 | H50: A++ | I50: 72808 | J50: SF | K50: 17.342 | L50: 72808 | M50: 61 | N50: 6.5 | O50: 1 | P50: 2 | Q50: 1985 | R50: 2005 | S50: {=_xlfn.IFS(AND('Rent Table'!$I50>0,'Rent Table'!$I50<=50000),"0-50,000", AND('Rent Table'!$I50 > 50000, 'Rent Table'!$I50 <= 150000), "50,001-150,000", AND('Rent Table'!$I50 > 150000, 'Rent Table'!$I50 <= 250000), "150,001-250,000", AND('Rent Table'!$I50 > 250000, 'Rent Table'!$I50 <= 350000), "250,001-350,000", AND('Rent Table'!$I50 > 350000, 'Rent Table'!$I50 <= 450000), "350,001-450,000", AND('Rent Table'!$I50 > 450000, 'Rent Table'!$I50 <= 600000), "450,001-600,000", AND('Rent Table'!$I50 > 600000, 'Rent Table'!$I50 <= 750000), "600,001-750,000",'Rent Table'!$I50 > 750000, "750,000+", TRUE, "Undefined" )} -> 50,001-150,000
A51: 19681 Pacific Gateway Drive | B51: Torrance | C51: CA | D51: 90502 | E51: Los Angeles | F51: Industrial | G51: 45566 | H51: A++ | I51: 251606 | J51: SF | K51: 18.353 | L51: 251606 | M51: 124 | N51: 10 | O51: 4 | P51: 1 | Q51: 2021 | R51: - | S51: {=_xlfn.IFS(AND('Rent Table'!$I51>0,'Rent Table'!$I51<=50000),"0-50,000", AND('Rent Table'!$I51 > 50000, 'Rent Table'!$I51 <= 150000), "50,001-150,000", AND('Rent Table'!$I51 > 150000, 'Rent Table'!$I51 <= 250000), "150,001-250,000", AND('Rent Table'!$I51 > 250000, 'Rent Table'!$I51 <= 350000), "250,001-350,000", AND('Rent Table'!$I51 > 350000, 'Rent Table'!$I51 <= 450000), "350,001-450,000", AND('Rent Table'!$I51 > 450000, 'Rent Table'!$I51 <= 600000), "450,001-600,000", AND('Rent Table'!$I51 > 600000, 'Rent Table'!$I51 <= 750000), "600,001-750,000",'Rent Table'!$I51 > 750000, "750,000+", TRUE, "Undefined" )} -> 250,001-350,000
A52: 1603 East Steel Road | B52: Colton | C52: CA | D52: 92324 | E52: Inland Empire | F52: Industrial | G52: 45566 | H52: A- | I52: 331000 | J52: SF | K52: 10.2039 | L52: 169143 | M52: 60 | N52: 0.59 | O52: 1 | P52: 2 | Q52: 2014 | R52: 2015 | S52: {=_xlfn.IFS(AND('Rent Table'!$I52>0,'Rent Table'!$I52<=50000),"0-50,000", AND('Rent Table'!$I52 > 50000, 'Rent Table'!$I52 <= 150000), "50,001-150,000", AND('Rent Table'!$I52 > 150000, 'Rent Table'!$I52 <= 250000), "150,001-250,000", AND('Rent Table'!$I52 > 250000, 'Rent Table'!$I52 <= 350000), "250,001-350,000", AND('Rent Table'!$I52 > 350000, 'Rent Table'!$I52 <= 450000), "350,001-450,000", AND('Rent Table'!$I52 > 450000, 'Rent Table'!$I52 <= 600000), "450,001-600,000", AND('Rent Table'!$I52 > 600000, 'Rent Table'!$I52 <= 750000), "600,001-750,000",'Rent Table'!$I52 > 750000, "750,000+", TRUE, "Undefined" )} -> 250,001-350,000
A53: 1861 Mountain View Avenue | B53: Loma Linda | C53: CA | D53: 92354 | E53: Inland Empire | F53: Industrial | G53: 45566 | H53: A- | I53: 114057 | J53: SF | K53: 14.1289 | L53: 114057 | M53: 62 | N53: 2 | O53: 2 | P53: 1 | Q53: 2022 | R53: 2023 | S53: {=_xlfn.IFS(AND('Rent Table'!$I53>0,'Rent Table'!$I53<=50000),"0-50,000", AND('Rent Table'!$I53 > 50000, 'Rent Table'!$I53 <= 150000), "50,001-150,000", AND('Rent Table'!$I53 > 150000, 'Rent Table'!$I53 <= 250000), "150,001-250,000", AND('Rent Table'!$I53 > 250000, 'Rent Table'!$I53 <= 350000), "250,001-350,000", AND('Rent Table'!$I53 > 350000, 'Rent Table'!$I53 <= 450000), "350,001-450,000", AND('Rent Table'!$I53 > 450000, 'Rent Table'!$I53 <= 600000), "450,001-600,000", AND('Rent Table'!$I53 > 600000, 'Rent Table'!$I53 <= 750000), "600,001-750,000",'Rent Table'!$I53 > 750000, "750,000+", TRUE, "Undefined" )} -> 50,001-150,000
A54: 1865 Mountain View Avenue | B54: Loma Linda | C54: CA | D54: 92354 | E54: Inland Empire | F54: Industrial | G54: 45566 | H54: A- | I54: 304262 | J54: SF | K54: 13.7359 | L54: 304262 | M54: 123 | N54: 6 | O54: 3 | P54: 1 | Q54: 2022 | R54: 2023 | S54: {=_xlfn.IFS(AND('Rent Table'!$I54>0,'Rent Table'!$I54<=50000),"0-50,000", AND('Rent Table'!$I54 > 50000, 'Rent Table'!$I54 <= 150000), "50,001-150,000", AND('Rent Table'!$I54 > 150000, 'Rent Table'!$I54 <= 250000), "150,001-250,000", AND('Rent Table'!$I54 > 250000, 'Rent Table'!$I54 <= 350000), "250,001-350,000", AND('Rent Table'!$I54 > 350000, 'Rent Table'!$I54 <= 450000), "350,001-450,000", AND('Rent Table'!$I54 > 450000, 'Rent Table'!$I54 <= 600000), "450,001-600,000", AND('Rent Table'!$I54 > 600000, 'Rent Table'!$I54 <= 750000), "600,001-750,000",'Rent Table'!$I54 > 750000, "750,000+", TRUE, "Undefined" )} -> 250,001-350,000
A55: 25525 Redlands Boulevard | B55: Loma Linda | C55: CA | D55: 92354 | E55: Inland Empire | F55: Industrial | G55: 45566 | H55: A- | I55: 80000 | J55: SF | K55: 13.0548 | L55: 80000 | M55: 122 | N55: - | O55: 2 | P55: - | Q55: 1944 | R55: - | S55: {=_xlfn.IFS(AND('Rent Table'!$I55>0,'Rent Table'!$I55<=50000),"0-50,000", AND('Rent Table'!$I55 > 50000, 'Rent Table'!$I55 <= 150000), "50,001-150,000", AND('Rent Table'!$I55 > 150000, 'Rent Table'!$I55 <= 250000), "150,001-250,000", AND('Rent Table'!$I55 > 250000, 'Rent Table'!$I55 <= 350000), "250,001-350,000", AND('Rent Table'!$I55 > 350000, 'Rent Table'!$I55 <= 450000), "350,001-450,000", AND('Rent Table'!$I55 > 450000, 'Rent Table'!$I55 <= 600000), "450,001-600,000", AND('Rent Table'!$I55 > 600000, 'Rent Table'!$I55 <= 750000), "600,001-750,000",'Rent Table'!$I55 > 750000, "750,000+", TRUE, "Undefined" )} -> 50,001-150,000
A56: 10421 Corporate Drive | B56: Redlands | C56: CA | D56: 92374 | E56: Inland Empire | F56: Industrial | G56: 45566 | H56: A- | I56: 23120 | J56: SF | K56: 9.07241 | L56: 23120 | M56: 72 | N56: - | O56: 2 | P56: - | Q56: 1987 | R56: - | S56: {=_xlfn.IFS(AND('Rent Table'!$I56>0,'Rent Table'!$I56<=50000),"0-50,000", AND('Rent Table'!$I56 > 50000, 'Rent Table'!$I56 <= 150000), "50,001-150,000", AND('Rent Table'!$I56 > 150000, 'Rent Table'!$I56 <= 250000), "150,001-250,000", AND('Rent Table'!$I56 > 250000, 'Rent Table'!$I56 <= 350000), "250,001-350,000", AND('Rent Table'!$I56 > 350000, 'Rent Table'!$I56 <= 450000), "350,001-450,000", AND('Rent Table'!$I56 > 450000, 'Rent Table'!$I56 <= 600000), "450,001-600,000", AND('Rent Table'!$I56 > 600000, 'Rent Table'!$I56 <= 750000), "600,001-750,000",'Rent Table'!$I56 > 750000, "750,000+", TRUE, "Undefined" )} -> 0-50,000
A57: 10446 Enterprise Drive | B57: Redlands | C57: CA | D57: 92374 | E57: Inland Empire | F57: Industrial | G57: 45566 | H57: A- | I57: 9670 | J57: SF | K57: 9.85711 | L57: 9670 | M57: 36 | N57: - | O57: 1 | P57: 1 | Q57: 1991 | R57: - | S57: {=_xlfn.IFS(AND('Rent Table'!$I57>0,'Rent Table'!$I57<=50000),"0-50,000", AND('Rent Table'!$I57 > 50000, 'Rent Table'!$I57 <= 150000), "50,001-150,000", AND('Rent Table'!$I57 > 150000, 'Rent Table'!$I57 <= 250000), "150,001-250,000", AND('Rent Table'!$I57 > 250000, 'Rent Table'!$I57 <= 350000), "250,001-350,000", AND('Rent Table'!$I57 > 350000, 'Rent Table'!$I57 <= 450000), "350,001-450,000", AND('Rent Table'!$I57 > 450000, 'Rent Table'!$I57 <= 600000), "450,001-600,000", AND('Rent Table'!$I57 > 600000, 'Rent Table'!$I57 <= 750000), "600,001-750,000",'Rent Table'!$I57 > 750000, "750,000+", TRUE, "Undefined" )} -> 0-50,000
A58: 1115 Research Drive | B58: Redlands | C58: CA | D58: 92374 | E58: Inland Empire | F58: Industrial | G58: 45566 | H58: A- | I58: 31000 | J58: SF | K58: 12.7346 | L58: 8946 | M58: 64 | N58: - | O58: - | P58: 1 | Q58: 1991 | R58: - | S58: {=_xlfn.IFS(AND('Rent Table'!$I58>0,'Rent Table'!$I58<=50000),"0-50,000", AND('Rent Table'!$I58 > 50000, 'Rent Table'!$I58 <= 150000), "50,001-150,000", AND('Rent Table'!$I58 > 150000, 'Rent Table'!$I58 <= 250000), "150,001-250,000", AND('Rent Table'!$I58 > 250000, 'Rent Table'!$I58 <= 350000), "250,001-350,000", AND('Rent Table'!$I58 > 350000, 'Rent Table'!$I58 <= 450000), "350,001-450,000", AND('Rent Table'!$I58 > 450000, 'Rent Table'!$I58 <= 600000), "450,001-600,000", AND('Rent Table'!$I58 > 600000, 'Rent Table'!$I58 <= 750000), "600,001-750,000",'Rent Table'!$I58 > 750000, "750,000+", TRUE, "Undefined" )} -> 0-50,000
A59: 1125 Research Drive | B59: Redlands | C59: CA | D59: 92374 | E59: Inland Empire | F59: Industrial | G59: 45566 | H59: A- | I59: 32135 | J59: SF | K59: 12.3047 | L59: 15643 | M59: 63 | N59: - | O59: 3 | P59: 1 | Q59: 1991 | R59: - | S59: {=_xlfn.IFS(AND('Rent Table'!$I59>0,'Rent Table'!$I59<=50000),"0-50,000", AND('Rent Table'!$I59 > 50000, 'Rent Table'!$I59 <= 150000), "50,001-150,000", AND('Rent Table'!$I59 > 150000, 'Rent Table'!$I59 <= 250000), "150,001-250,000", AND('Rent Table'!$I59 > 250000, 'Rent Table'!$I59 <= 350000), "250,001-350,000", AND('Rent Table'!$I59 > 350000, 'Rent Table'!$I59 <= 450000), "350,001-450,000", AND('Rent Table'!$I59 > 450000, 'Rent Table'!$I59 <= 600000), "450,001-600,000", AND('Rent Table'!$I59 > 600000, 'Rent Table'!$I59 <= 750000), "600,001-750,000",'Rent Table'!$I59 > 750000, "750,000+", TRUE, "Undefined" )} -> 0-50,000
A60: 1235 Indiana Court | B60: Redlands | C60: CA | D60: 92374 | E60: Inland Empire | F60: Industrial | G60: 45566 | H60: A- | I60: 27516 | J60: SF | K60: 20.4175 | L60: 1207 | M60: 60 | N60: - | O60: - | P60: - | Q60: 1990 | R60: - | S60: {=_xlfn.IFS(AND('Rent Table'!$I60>0,'Rent Table'!$I60<=50000),"0-50,000", AND('Rent Table'!$I60 > 50000, 'Rent Table'!$I60 <= 150000), "50,001-150,000", AND('Rent Table'!$I60 > 150000, 'Rent Table'!$I60 <= 250000), "150,001-250,000", AND('Rent Table'!$I60 > 250000, 'Rent Table'!$I60 <= 350000), "250,001-350,000", AND('Rent Table'!$I60 > 350000, 'Rent Table'!$I60 <= 450000), "350,001-450,000", AND('Rent Table'!$I60 > 450000, 'Rent Table'!$I60 <= 600000), "450,001-600,000", AND('Rent Table'!$I60 > 600000, 'Rent Table'!$I60 <= 750000), "600,001-750,000",'Rent Table'!$I60 > 750000, "750,000+", TRUE, "Undefined" )} -> 0-50,000
A61: 1419 West State Street | B61: Redlands | C61: CA | D61: 92373 | E61: Inland Empire | F61: Industrial | G61: 45566 | H61: A- | I61: 17659 | J61: SF | K61: 10.5063 | L61: 17659 | M61: 62 | N61: - | O61: 2 | P61: 1 | Q61: 1987 | R61: 1988 | S61: {=_xlfn.IFS(AND('Rent Table'!$I61>0,'Rent Table'!$I61<=50000),"0-50,000", AND('Rent Table'!$I61 > 50000, 'Rent Table'!$I61 <= 150000), "50,001-150,000", AND('Rent Table'!$I61 > 150000, 'Rent Table'!$I61 <= 250000), "150,001-250,000", AND('Rent Table'!$I61 > 250000, 'Rent Table'!$I61 <= 350000), "250,001-350,000", AND('Rent Table'!$I61 > 350000, 'Rent Table'!$I61 <= 450000), "350,001-450,000", AND('Rent Table'!$I61 > 450000, 'Rent Table'!$I61 <= 600000), "450,001-600,000", AND('Rent Table'!$I61 > 600000, 'Rent Table'!$I61 <= 750000), "600,001-750,000",'Rent Table'!$I61 > 750000, "750,000+", TRUE, "Undefined" )} -> 0-50,000
A62: 1645 West Park Avenue | B62: Redlands | C62: CA | D62: 92373 | E62: Inland Empire | F62: Industrial | G62: 45566 | H62: A- | I62: 40800 | J62: SF | K62: 12.3778 | L62: 20400 | M62: 61 | N62: - | O62: - | P62: 1 | Q62: 2017 | R62: - | S62: {=_xlfn.IFS(AND('Rent Table'!$I62>0,'Rent Table'!$I62<=50000),"0-50,000", AND('Rent Table'!$I62 > 50000, 'Rent Table'!$I62 <= 150000), "50,001-150,000", AND('Rent Table'!$I62 > 150000, 'Rent Table'!$I62 <= 250000), "150,001-250,000", AND('Rent Table'!$I62 > 250000, 'Rent Table'!$I62 <= 350000), "250,001-350,000", AND('Rent Table'!$I62 > 350000, 'Rent Table'!$I62 <= 450000), "350,001-450,000", AND('Rent Table'!$I62 > 450000, 'Rent Table'!$I62 <= 600000), "450,001-600,000", AND('Rent Table'!$I62 > 600000, 'Rent Table'!$I62 <= 750000), "600,001-750,000",'Rent Table'!$I62 > 750000, "750,000+", TRUE, "Undefined" )} -> 0-50,000
A63: 1670 West Park Avenue | B63: Redlands | C63: CA | D63: 92373 | E63: Inland Empire | F63: Industrial | G63: 45566 | H63: A- | I63: 29000 | J63: SF | K63: 13.4695 | L63: 29000 | M63: 48 | N63: - | O63: - | P63: - | Q63: 2017 | R63: 2018 | S63: {=_xlfn.IFS(AND('Rent Table'!$I63>0,'Rent Table'!$I63<=50000),"0-50,000", AND('Rent Table'!$I63 > 50000, 'Rent Table'!$I63 <= 150000), "50,001-150,000", AND('Rent Table'!$I63 > 150000, 'Rent Table'!$I63 <= 250000), "150,001-250,000", AND('Rent Table'!$I63 > 250000, 'Rent Table'!$I63 <= 350000), "250,001-350,000", AND('Rent Table'!$I63 > 350000, 'Rent Table'!$I63 <= 450000), "350,001-450,000", AND('Rent Table'!$I63 > 450000, 'Rent Table'!$I63 <= 600000), "450,001-600,000", AND('Rent Table'!$I63 > 600000, 'Rent Table'!$I63 <= 750000), "600,001-750,000",'Rent Table'!$I63 > 750000, "750,000+", TRUE, "Undefined" )} -> 0-50,000
A64: 1939 West Park Avenue | B64: Redlands | C64: CA | D64: 92373 | E64: Inland Empire | F64: Industrial | G64: 45566 | H64: A- | I64: 21612 | J64: SF | K64: 11.7579 | L64: 21612 | M64: 48 | N64: - | O64: - | P64: 1 | Q64: 2007 | R64: - | S64: {=_xlfn.IFS(AND('Rent Table'!$I64>0,'Rent Table'!$I64<=50000),"0-50,000", AND('Rent Table'!$I64 > 50000, 'Rent Table'!$I64 <= 150000), "50,001-150,000", AND('Rent Table'!$I64 > 150000, 'Rent Table'!$I64 <= 250000), "150,001-250,000", AND('Rent Table'!$I64 > 250000, 'Rent Table'!$I64 <= 350000), "250,001-350,000", AND('Rent Table'!$I64 > 350000, 'Rent Table'!$I64 <= 450000), "350,001-450,000", AND('Rent Table'!$I64 > 450000, 'Rent Table'!$I64 <= 600000), "450,001-600,000", AND('Rent Table'!$I64 > 600000, 'Rent Table'!$I64 <= 750000), "600,001-750,000",'Rent Table'!$I64 > 750000, "750,000+", TRUE, "Undefined" )} -> 0-50,000
A65: 1941 West Park Avenue | B65: Redlands | C65: CA | D65: 92373 | E65: Inland Empire | F65: Industrial | G65: 45566 | H65: A- | I65: 19370 | J65: SF | K65: 14.149 | L65: 19370 | M65: 61 | N65: 1.17 | O65: 1 | P65: 1 | Q65: 2023 | R65: - | S65: {=_xlfn.IFS(AND('Rent Table'!$I65>0,'Rent Table'!$I65<=50000),"0-50,000", AND('Rent Table'!$I65 > 50000, 'Rent Table'!$I65 <= 150000), "50,001-150,000", AND('Rent Table'!$I65 > 150000, 'Rent Table'!$I65 <= 250000), "150,001-250,000", AND('Rent Table'!$I65 > 250000, 'Rent Table'!$I65 <= 350000), "250,001-350,000", AND('Rent Table'!$I65 > 350000, 'Rent Table'!$I65 <= 450000), "350,001-450,000", AND('Rent Table'!$I65 > 450000, 'Rent Table'!$I65 <= 600000), "450,001-600,000", AND('Rent Table'!$I65 > 600000, 'Rent Table'!$I65 <= 750000), "600,001-750,000",'Rent Table'!$I65 > 750000, "750,000+", TRUE, "Undefined" )} -> 0-50,000
A66: 1972 Essex Court | B66: Redlands | C66: CA | D66: 92373 | E66: Inland Empire | F66: Industrial | G66: 45566 | H66: A- | I66: 15636 | J66: SF | K66: 12.5485 | L66: 15636 | M66: 60 | N66: - | O66: - | P66: 1 | Q66: 2002 | R66: - | S66: {=_xlfn.IFS(AND('Rent Table'!$I66>0,'Rent Table'!$I66<=50000),"0-50,000", AND('Rent Table'!$I66 > 50000, 'Rent Table'!$I66 <= 150000), "50,001-150,000", AND('Rent Table'!$I66 > 150000, 'Rent Table'!$I66 <= 250000), "150,001-250,000", AND('Rent Table'!$I66 > 250000, 'Rent Table'!$I66 <= 350000), "250,001-350,000", AND('Rent Table'!$I66 > 350000, 'Rent Table'!$I66 <= 450000), "350,001-450,000", AND('Rent Table'!$I66 > 450000, 'Rent Table'!$I66 <= 600000), "450,001-600,000", AND('Rent Table'!$I66 > 600000, 'Rent Table'!$I66 <= 750000), "600,001-750,000",'Rent Table'!$I66 > 750000, "750,000+", TRUE, "Undefined" )} -> 0-50,000
A67: 2351 West Lugonia Avenue | B67: Redlands | C67: CA | D67: 92374 | E67: Inland Empire | F67: Industrial | G67: 45566 | H67: A- | I67: 28681 | J67: SF | K67: 9.65636 | L67: 28181 | M67: 45 | N67: - | O67: - | P67: 1 | Q67: 2003 | R67: - | S67: {=_xlfn.IFS(AND('Rent Table'!$I67>0,'Rent Table'!$I67<=50000),"0-50,000", AND('Rent Table'!$I67 > 50000, 'Rent Table'!$I67 <= 150000), "50,001-150,000", AND('Rent Table'!$I67 > 150000, 'Rent Table'!$I67 <= 250000), "150,001-250,000", AND('Rent Table'!$I67 > 250000, 'Rent Table'!$I67 <= 350000), "250,001-350,000", AND('Rent Table'!$I67 > 350000, 'Rent Table'!$I67 <= 450000), "350,001-450,000", AND('Rent Table'!$I67 > 450000, 'Rent Table'!$I67 <= 600000), "450,001-600,000", AND('Rent Table'!$I67 > 600000, 'Rent Table'!$I67 <= 750000), "600,001-750,000",'Rent Table'!$I67 > 750000, "750,000+", TRUE, "Undefined" )} -> 0-50,000
A68: 1251 Research Drive | B68: Redlands | C68: CA | D68: 92374 | E68: Inland Empire | F68: Industrial | G68: 45566 | H68: A- | I68: 118000 | J68: SF | K68: 9.983765 | L68: 70318 | M68: 92.5 | N68: 1 | O68: 2.5 | P68: 1 | Q68: 1990 | R68: - | S68: {=_xlfn.IFS(AND('Rent Table'!$I68>0,'Rent Table'!$I68<=50000),"0-50,000", AND('Rent Table'!$I68 > 50000, 'Rent Table'!$I68 <= 150000), "50,001-150,000", AND('Rent Table'!$I68 > 150000, 'Rent Table'!$I68 <= 250000), "150,001-250,000", AND('Rent Table'!$I68 > 250000, 'Rent Table'!$I68 <= 350000), "250,001-350,000", AND('Rent Table'!$I68 > 350000, 'Rent Table'!$I68 <= 450000), "350,001-450,000", AND('Rent Table'!$I68 > 450000, 'Rent Table'!$I68 <= 600000), "450,001-600,000", AND('Rent Table'!$I68 > 600000, 'Rent Table'!$I68 <= 750000), "600,001-750,000",'Rent Table'!$I68 > 750000, "750,000+", TRUE, "Undefined" )} -> 50,001-150,000
A69: 1455 Research Drive | B69: Redlands | C69: CA | D69: 92374 | E69: Inland Empire | F69: Industrial | G69: 45566 | H69: A- | I69: 147677 | J69: SF | K69: 14.7399 | L69: 73838 | M69: 62 | N69: - | O69: 2 | P69: 1 | Q69: 2006 | R69: - | S69: {=_xlfn.IFS(AND('Rent Table'!$I69>0,'Rent Table'!$I69<=50000),"0-50,000", AND('Rent Table'!$I69 > 50000, 'Rent Table'!$I69 <= 150000), "50,001-150,000", AND('Rent Table'!$I69 > 150000, 'Rent Table'!$I69 <= 250000), "150,001-250,000", AND('Rent Table'!$I69 > 250000, 'Rent Table'!$I69 <= 350000), "250,001-350,000", AND('Rent Table'!$I69 > 350000, 'Rent Table'!$I69 <= 450000), "350,001-450,000", AND('Rent Table'!$I69 > 450000, 'Rent Table'!$I69 <= 600000), "450,001-600,000", AND('Rent Table'!$I69 > 600000, 'Rent Table'!$I69 <= 750000), "600,001-750,000",'Rent Table'!$I69 > 750000, "750,000+", TRUE, "Undefined" )} -> 50,001-150,000
A70: 2456 West Lugonia Avenue | B70: Redlands | C70: CA | D70: 92374 | E70: Inland Empire | F70: Industrial | G70: 45566 | H70: A- | I70: 128141 | J70: SF | K70: 9.0859 | L70: 128141 | M70: 123 | N70: - | O70: 3 | P70: 1 | Q70: 2008 | R70: - | S70: {=_xlfn.IFS(AND('Rent Table'!$I70>0,'Rent Table'!$I70<=50000),"0-50,000", AND('Rent Table'!$I70 > 50000, 'Rent Table'!$I70 <= 150000), "50,001-150,000", AND('Rent Table'!$I70 > 150000, 'Rent Table'!$I70 <= 250000), "150,001-250,000", AND('Rent Table'!$I70 > 250000, 'Rent Table'!$I70 <= 350000), "250,001-350,000", AND('Rent Table'!$I70 > 350000, 'Rent Table'!$I70 <= 450000), "350,001-450,000", AND('Rent Table'!$I70 > 450000, 'Rent Table'!$I70 <= 600000), "450,001-600,000", AND('Rent Table'!$I70 > 600000, 'Rent Table'!$I70 <= 750000), "600,001-750,000",'Rent Table'!$I70 > 750000, "750,000+", TRUE, "Undefined" )} -> 50,001-150,000
A71: 2459 Almond Avenue | B71: Redlands | C71: CA | D71: 92374 | E71: Inland Empire | F71: Industrial | G71: 45566 | H71: A- | I71: 149275 | J71: SF | K71: 9.89598 | L71: 149275 | M71: 62 | N71: 1 | O71: 2 | P71: 2 | Q71: 2008 | R71: - | S71: {=_xlfn.IFS(AND('Rent Table'!$I71>0,'Rent Table'!$I71<=50000),"0-50,000", AND('Rent Table'!$I71 > 50000, 'Rent Table'!$I71 <= 150000), "50,001-150,000", AND('Rent Table'!$I71 > 150000, 'Rent Table'!$I71 <= 250000), "150,001-250,000", AND('Rent Table'!$I71 > 250000, 'Rent Table'!$I71 <= 350000), "250,001-350,000", AND('Rent Table'!$I71 > 350000, 'Rent Table'!$I71 <= 450000), "350,001-450,000", AND('Rent Table'!$I71 > 450000, 'Rent Table'!$I71 <= 600000), "450,001-600,000", AND('Rent Table'!$I71 > 600000, 'Rent Table'!$I71 <= 750000), "600,001-750,000",'Rent Table'!$I71 > 750000, "750,000+", TRUE, "Undefined" )} -> 50,001-150,000
A72: 2470 West Lugonia Avenue | B72: Redlands | C72: CA | D72: 92374 | E72: Inland Empire | F72: Industrial | G72: 45566 | H72: A- | I72: 104072 | J72: SF | K72: 14.5142 | L72: 104072 | M72: 61 | N72: - | O72: 1 | P72: 1 | Q72: 2008 | R72: - | S72: {=_xlfn.IFS(AND('Rent Table'!$I72>0,'Rent Table'!$I72<=50000),"0-50,000", AND('Rent Table'!$I72 > 50000, 'Rent Table'!$I72 <= 150000), "50,001-150,000", AND('Rent Table'!$I72 > 150000, 'Rent Table'!$I72 <= 250000), "150,001-250,000", AND('Rent Table'!$I72 > 250000, 'Rent Table'!$I72 <= 350000), "250,001-350,000", AND('Rent Table'!$I72 > 350000, 'Rent Table'!$I72 <= 450000), "350,001-450,000", AND('Rent Table'!$I72 > 450000, 'Rent Table'!$I72 <= 600000), "450,001-600,000", AND('Rent Table'!$I72 > 600000, 'Rent Table'!$I72 <= 750000), "600,001-750,000",'Rent Table'!$I72 > 750000, "750,000+", TRUE, "Undefined" )} -> 50,001-150,000
A73: 10843 New Jersey Street | B73: Redlands | C73: CA | D73: 92373 | E73: Inland Empire | F73: Industrial | G73: 45566 | H73: A- | I73: 179400 | J73: SF | K73: 14.9824 | L73: 179400 | M73: 86 | N73: 12 | O73: 2 | P73: - | Q73: 2022 | R73: - | S73: {=_xlfn.IFS(AND('Rent Table'!$I73>0,'Rent Table'!$I73<=50000),"0-50,000", AND('Rent Table'!$I73 > 50000, 'Rent Table'!$I73 <= 150000), "50,001-150,000", AND('Rent Table'!$I73 > 150000, 'Rent Table'!$I73 <= 250000), "150,001-250,000", AND('Rent Table'!$I73 > 250000, 'Rent Table'!$I73 <= 350000), "250,001-350,000", AND('Rent Table'!$I73 > 350000, 'Rent Table'!$I73 <= 450000), "350,001-450,000", AND('Rent Table'!$I73 > 450000, 'Rent Table'!$I73 <= 600000), "450,001-600,000", AND('Rent Table'!$I73 > 600000, 'Rent Table'!$I73 <= 750000), "600,001-750,000",'Rent Table'!$I73 > 750000, "750,000+", TRUE, "Undefined" )} -> 150,001-250,000
A74: 1675 West Park Avenue | B74: Redlands | C74: CA | D74: 92373 | E74: Inland Empire | F74: Industrial | G74: 45566 | H74: A- | I74: 156694 | J74: SF | K74: 9.18398 | L74: 156694 | M74: 88 | N74: 6.75 | O74: 4 | P74: 1 | Q74: 2019 | R74: - | S74: {=_xlfn.IFS(AND('Rent Table'!$I74>0,'Rent Table'!$I74<=50000),"0-50,000", AND('Rent Table'!$I74 > 50000, 'Rent Table'!$I74 <= 150000), "50,001-150,000", AND('Rent Table'!$I74 > 150000, 'Rent Table'!$I74 <= 250000), "150,001-250,000", AND('Rent Table'!$I74 > 250000, 'Rent Table'!$I74 <= 350000), "250,001-350,000", AND('Rent Table'!$I74 > 350000, 'Rent Table'!$I74 <= 450000), "350,001-450,000", AND('Rent Table'!$I74 > 450000, 'Rent Table'!$I74 <= 600000), "450,001-600,000", AND('Rent Table'!$I74 > 600000, 'Rent Table'!$I74 <= 750000), "600,001-750,000",'Rent Table'!$I74 > 750000, "750,000+", TRUE, "Undefined" )} -> 150,001-250,000
A75: 1300 California Street | B75: Redlands | C75: CA | D75: 92374 | E75: Inland Empire | F75: Industrial | G75: 45566 | H75: A- | I75: 771839 | J75: SF | K75: 6.89242 | L75: 771839 | M75: 84 | N75: 4 | O75: 7.25 | P75: 1 | Q75: 2015 | R75: - | S75: {=_xlfn.IFS(AND('Rent Table'!$I75>0,'Rent Table'!$I75<=50000),"0-50,000", AND('Rent Table'!$I75 > 50000, 'Rent Table'!$I75 <= 150000), "50,001-150,000", AND('Rent Table'!$I75 > 150000, 'Rent Table'!$I75 <= 250000), "150,001-250,000", AND('Rent Table'!$I75 > 250000, 'Rent Table'!$I75 <= 350000), "250,001-350,000", AND('Rent Table'!$I75 > 350000, 'Rent Table'!$I75 <= 450000), "350,001-450,000", AND('Rent Table'!$I75 > 450000, 'Rent Table'!$I75 <= 600000), "450,001-600,000", AND('Rent Table'!$I75 > 600000, 'Rent Table'!$I75 <= 750000), "600,001-750,000",'Rent Table'!$I75 > 750000, "750,000+", TRUE, "Undefined" )} -> 750,000+
A76: 1730 Marigold Avenue | B76: Redlands | C76: CA | D76: 92374 | E76: Inland Empire | F76: Industrial | G76: 45566 | H76: A- | I76: 328000 | J76: SF | K76: 12.901 | L76: 327790 | M76: 64 | N76: 2.5 | O76: 2 | P76: 1 | Q76: 2008 | R76: - | S76: {=_xlfn.IFS(AND('Rent Table'!$I76>0,'Rent Table'!$I76<=50000),"0-50,000", AND('Rent Table'!$I76 > 50000, 'Rent Table'!$I76 <= 150000), "50,001-150,000", AND('Rent Table'!$I76 > 150000, 'Rent Table'!$I76 <= 250000), "150,001-250,000", AND('Rent Table'!$I76 > 250000, 'Rent Table'!$I76 <= 350000), "250,001-350,000", AND('Rent Table'!$I76 > 350000, 'Rent Table'!$I76 <= 450000), "350,001-450,000", AND('Rent Table'!$I76 > 450000, 'Rent Table'!$I76 <= 600000), "450,001-600,000", AND('Rent Table'!$I76 > 600000, 'Rent Table'!$I76 <= 750000), "600,001-750,000",'Rent Table'!$I76 > 750000, "750,000+", TRUE, "Undefined" )} -> 250,001-350,000
A77: 2185 West Lugonia Avenue | B77: Redlands | C77: CA | D77: 92374 | E77: Inland Empire | F77: Industrial | G77: 45566 | H77: A- | I77: 500602 | J77: SF | K77: 13.67495 | L77: 500602 | M77: 55.25 | N77: - | O77: - | P77: 2 | Q77: 2016 | R77: - | S77: {=_xlfn.IFS(AND('Rent Table'!$I77>0,'Rent Table'!$I77<=50000),"0-50,000", AND('Rent Table'!$I77 > 50000, 'Rent Table'!$I77 <= 150000), "50,001-150,000", AND('Rent Table'!$I77 > 150000, 'Rent Table'!$I77 <= 250000), "150,001-250,000", AND('Rent Table'!$I77 > 250000, 'Rent Table'!$I77 <= 350000), "250,001-350,000", AND('Rent Table'!$I77 > 350000, 'Rent Table'!$I77 <= 450000), "350,001-450,000", AND('Rent Table'!$I77 > 450000, 'Rent Table'!$I77 <= 600000), "450,001-600,000", AND('Rent Table'!$I77 > 600000, 'Rent Table'!$I77 <= 750000), "600,001-750,000",'Rent Table'!$I77 > 750000, "750,000+", TRUE, "Undefined" )} -> 450,001-600,000
A78: 2220 Almond Avenue | B78: Redlands | C78: CA | D78: 92374 | E78: Inland Empire | F78: Industrial | G78: 45566 | H78: A- | I78: 412000 | J78: SF | K78: 10.0171 | L78: 411879 | M78: 122 | N78: 0.55 | O78: 2 | P78: 1 | Q78: 2007 | R78: - | S78: {=_xlfn.IFS(AND('Rent Table'!$I78>0,'Rent Table'!$I78<=50000),"0-50,000", AND('Rent Table'!$I78 > 50000, 'Rent Table'!$I78 <= 150000), "50,001-150,000", AND('Rent Table'!$I78 > 150000, 'Rent Table'!$I78 <= 250000), "150,001-250,000", AND('Rent Table'!$I78 > 250000, 'Rent Table'!$I78 <= 350000), "250,001-350,000", AND('Rent Table'!$I78 > 350000, 'Rent Table'!$I78 <= 450000), "350,001-450,000", AND('Rent Table'!$I78 > 450000, 'Rent Table'!$I78 <= 600000), "450,001-600,000", AND('Rent Table'!$I78 > 600000, 'Rent Table'!$I78 <= 750000), "600,001-750,000",'Rent Table'!$I78 > 750000, "750,000+", TRUE, "Undefined" )} -> 350,001-450,000
A79: 2301 West San Bernardino Avenue | B79: Redlands | C79: CA | D79: 92374 | E79: Inland Empire | F79: Industrial | G79: 45566 | H79: A- | I79: 983986 | J79: SF | K79: 10.09254 | L79: 896662 | M79: 63.5 | N79: 0.875 | O79: 2 | P79: 1 | Q79: 2004 | R79: - | S79: {=_xlfn.IFS(AND('Rent Table'!$I79>0,'Rent Table'!$I79<=50000),"0-50,000", AND('Rent Table'!$I79 > 50000, 'Rent Table'!$I79 <= 150000), "50,001-150,000", AND('Rent Table'!$I79 > 150000, 'Rent Table'!$I79 <= 250000), "150,001-250,000", AND('Rent Table'!$I79 > 250000, 'Rent Table'!$I79 <= 350000), "250,001-350,000", AND('Rent Table'!$I79 > 350000, 'Rent Table'!$I79 <= 450000), "350,001-450,000", AND('Rent Table'!$I79 > 450000, 'Rent Table'!$I79 <= 600000), "450,001-600,000", AND('Rent Table'!$I79 > 600000, 'Rent Table'!$I79 <= 750000), "600,001-750,000",'Rent Table'!$I79 > 750000, "750,000+", TRUE, "Undefined" )} -> 750,000+
A80: 2501 West San Bernardino Avenue | B80: Redlands | C80: CA | D80: 92374 | E80: Inland Empire | F80: Industrial | G80: 45566 | H80: A- | I80: 683269 | J80: SF | K80: 8.70586 | L80: 683269 | M80: 120 | N80: 2 | O80: 3 | P80: 1 | Q80: 2005 | R80: - | S80: {=_xlfn.IFS(AND('Rent Table'!$I80>0,'Rent Table'!$I80<=50000),"0-50,000", AND('Rent Table'!$I80 > 50000, 'Rent Table'!$I80 <= 150000), "50,001-150,000", AND('Rent Table'!$I80 > 150000, 'Rent Table'!$I80 <= 250000), "150,001-250,000", AND('Rent Table'!$I80 > 250000, 'Rent Table'!$I80 <= 350000), "250,001-350,000", AND('Rent Table'!$I80 > 350000, 'Rent Table'!$I80 <= 450000), "350,001-450,000", AND('Rent Table'!$I80 > 450000, 'Rent Table'!$I80 <= 600000), "450,001-600,000", AND('Rent Table'!$I80 > 600000, 'Rent Table'!$I80 <= 750000), "600,001-750,000",'Rent Table'!$I80 > 750000, "750,000+", TRUE, "Undefined" )} -> 600,001-750,000
A81: 26525 Pioneer Avenue | B81: Redlands | C81: CA | D81: 92374 | E81: Inland Empire | F81: Industrial | G81: 45566 | H81: A- | I81: 375839 | J81: SF | K81: 13.1526 | L81: 375839 | M81: 60 | N81: - | O81: - | P81: 1 | Q81: 2014 | R81: - | S81: {=_xlfn.IFS(AND('Rent Table'!$I81>0,'Rent Table'!$I81<=50000),"0-50,000", AND('Rent Table'!$I81 > 50000, 'Rent Table'!$I81 <= 150000), "50,001-150,000", AND('Rent Table'!$I81 > 150000, 'Rent Table'!$I81 <= 250000), "150,001-250,000", AND('Rent Table'!$I81 > 250000, 'Rent Table'!$I81 <= 350000), "250,001-350,000", AND('Rent Table'!$I81 > 350000, 'Rent Table'!$I81 <= 450000), "350,001-450,000", AND('Rent Table'!$I81 > 450000, 'Rent Table'!$I81 <= 600000), "450,001-600,000", AND('Rent Table'!$I81 > 600000, 'Rent Table'!$I81 <= 750000), "600,001-750,000",'Rent Table'!$I81 > 750000, "750,000+", TRUE, "Undefined" )} -> 350,001-450,000
A82: 26597 San Bernardino Avenue | B82: Redlands | C82: CA | D82: 92374 | E82: Inland Empire | F82: Industrial | G82: 45566 | H82: A- | I82: 557213 | J82: SF | K82: 10.0691 | L82: 557213 | M82: 60 | N82: - | O82: - | P82: 1 | Q82: 2012 | R82: - | S82: {=_xlfn.IFS(AND('Rent Table'!$I82>0,'Rent Table'!$I82<=50000),"0-50,000", AND('Rent Table'!$I82 > 50000, 'Rent Table'!$I82 <= 150000), "50,001-150,000", AND('Rent Table'!$I82 > 150000, 'Rent Table'!$I82 <= 250000), "150,001-250,000", AND('Rent Table'!$I82 > 250000, 'Rent Table'!$I82 <= 350000), "250,001-350,000", AND('Rent Table'!$I82 > 350000, 'Rent Table'!$I82 <= 450000), "350,001-450,000", AND('Rent Table'!$I82 > 450000, 'Rent Table'!$I82 <= 600000), "450,001-600,000", AND('Rent Table'!$I82 > 600000, 'Rent Table'!$I82 <= 750000), "600,001-750,000",'Rent Table'!$I82 > 750000, "750,000+", TRUE, "Undefined" )} -> 450,001-600,000
A83: 26635 Pioneer Avenue | B83: Redlands | C83: CA | D83: 92374 | E83: Inland Empire | F83: Industrial | G83: 45566 | H83: A- | I83: 616542 | J83: SF | K83: 8.74871 | L83: 616542 | M83: 61 | N83: 1 | O83: 1 | P83: 1 | Q83: 2011 | R83: - | S83: {=_xlfn.IFS(AND('Rent Table'!$I83>0,'Rent Table'!$I83<=50000),"0-50,000", AND('Rent Table'!$I83 > 50000, 'Rent Table'!$I83 <= 150000), "50,001-150,000", AND('Rent Table'!$I83 > 150000, 'Rent Table'!$I83 <= 250000), "150,001-250,000", AND('Rent Table'!$I83 > 250000, 'Rent Table'!$I83 <= 350000), "250,001-350,000", AND('Rent Table'!$I83 > 350000, 'Rent Table'!$I83 <= 450000), "350,001-450,000", AND('Rent Table'!$I83 > 450000, 'Rent Table'!$I83 <= 600000), "450,001-600,000", AND('Rent Table'!$I83 > 600000, 'Rent Table'!$I83 <= 750000), "600,001-750,000",'Rent Table'!$I83 > 750000, "750,000+", TRUE, "Undefined" )} -> 600,001-750,000
A84: 10756 Nevada Street | B84: Redlands | C84: CA | D84: 92373 | E84: Inland Empire | F84: Industrial | G84: 45566 | H84: A- | I84: 88967 | J84: SF | K84: 13.6725 | L84: 88967 | M84: 63 | N84: - | O84: 4 | P84: 1 | Q84: 2023 | R84: - | S84: {=_xlfn.IFS(AND('Rent Table'!$I84>0,'Rent Table'!$I84<=50000),"0-50,000", AND('Rent Table'!$I84 > 50000, 'Rent Table'!$I84 <= 150000), "50,001-150,000", AND('Rent Table'!$I84 > 150000, 'Rent Table'!$I84 <= 250000), "150,001-250,000", AND('Rent Table'!$I84 > 250000, 'Rent Table'!$I84 <= 350000), "250,001-350,000", AND('Rent Table'!$I84 > 350000, 'Rent Table'!$I84 <= 450000), "350,001-450,000", AND('Rent Table'!$I84 > 450000, 'Rent Table'!$I84 <= 600000), "450,001-600,000", AND('Rent Table'!$I84 > 600000, 'Rent Table'!$I84 <= 750000), "600,001-750,000",'Rent Table'!$I84 > 750000, "750,000+", TRUE, "Undefined" )} -> 50,001-150,000
A85: 1351 West Park Avenue | B85: Redlands | C85: CA | D85: 92373 | E85: Inland Empire | F85: Industrial | G85: 45566 | H85: A- | I85: 83451 | J85: SF | K85: 12.642233 | L85: 19145 | M85: 84 | N85: 2 | O85: - | P85: 1 | Q85: 2007 | R85: - | S85: {=_xlfn.IFS(AND('Rent Table'!$I85>0,'Rent Table'!$I85<=50000),"0-50,000", AND('Rent Table'!$I85 > 50000, 'Rent Table'!$I85 <= 150000), "50,001-150,000", AND('Rent Table'!$I85 > 150000, 'Rent Table'!$I85 <= 250000), "150,001-250,000", AND('Rent Table'!$I85 > 250000, 'Rent Table'!$I85 <= 350000), "250,001-350,000", AND('Rent Table'!$I85 > 350000, 'Rent Table'!$I85 <= 450000), "350,001-450,000", AND('Rent Table'!$I85 > 450000, 'Rent Table'!$I85 <= 600000), "450,001-600,000", AND('Rent Table'!$I85 > 600000, 'Rent Table'!$I85 <= 750000), "600,001-750,000",'Rent Table'!$I85 > 750000, "750,000+", TRUE, "Undefined" )} -> 50,001-150,000
A86: 1450 Mountain View Avenue | B86: Redlands | C86: CA | D86: 92374 | E86: Inland Empire | F86: Industrial | G86: 45566 | H86: A- | I86: 99582 | J86: SF | K86: 11.6535 | L86: 99580 | M86: 124 | N86: 1.6 | O86: 4 | P86: 1 | Q86: 2008 | R86: - | S86: {=_xlfn.IFS(AND('Rent Table'!$I86>0,'Rent Table'!$I86<=50000),"0-50,000", AND('Rent Table'!$I86 > 50000, 'Rent Table'!$I86 <= 150000), "50,001-150,000", AND('Rent Table'!$I86 > 150000, 'Rent Table'!$I86 <= 250000), "150,001-250,000", AND('Rent Table'!$I86 > 250000, 'Rent Table'!$I86 <= 350000), "250,001-350,000", AND('Rent Table'!$I86 > 350000, 'Rent Table'!$I86 <= 450000), "350,001-450,000", AND('Rent Table'!$I86 > 450000, 'Rent Table'!$I86 <= 600000), "450,001-600,000", AND('Rent Table'!$I86 > 600000, 'Rent Table'!$I86 <= 750000), "600,001-750,000",'Rent Table'!$I86 > 750000, "750,000+", TRUE, "Undefined" )} -> 50,001-150,000
A87: 2466 West Lugonia Avenue | B87: Redlands | C87: CA | D87: 92374 | E87: Inland Empire | F87: Industrial | G87: 45566 | H87: A- | I87: 99363 | J87: SF | K87: 10.0447 | L87: 99363 | M87: 61 | N87: - | O87: 1 | P87: 1 | Q87: 2008 | R87: - | S87: {=_xlfn.IFS(AND('Rent Table'!$I87>0,'Rent Table'!$I87<=50000),"0-50,000", AND('Rent Table'!$I87 > 50000, 'Rent Table'!$I87 <= 150000), "50,001-150,000", AND('Rent Table'!$I87 > 150000, 'Rent Table'!$I87 <= 250000), "150,001-250,000", AND('Rent Table'!$I87 > 250000, 'Rent Table'!$I87 <= 350000), "250,001-350,000", AND('Rent Table'!$I87 > 350000, 'Rent Table'!$I87 <= 450000), "350,001-450,000", AND('Rent Table'!$I87 > 450000, 'Rent Table'!$I87 <= 600000), "450,001-600,000", AND('Rent Table'!$I87 > 600000, 'Rent Table'!$I87 <= 750000), "600,001-750,000",'Rent Table'!$I87 > 750000, "750,000+", TRUE, "Undefined" )} -> 50,001-150,000
A88: 1055 East Cooley Avenue | B88: San Bernardino | C88: CA | D88: 92408 | E88: Inland Empire | F88: Industrial | G88: 45566 | H88: A- | I88: 72000 | J88: SF | K88: 12.2991 | L88: 72000 | M88: 89 | N88: 2.33 | O88: 2 | P88: - | Q88: 1986 | R88: - | S88: {=_xlfn.IFS(AND('Rent Table'!$I88>0,'Rent Table'!$I88<=50000),"0-50,000", AND('Rent Table'!$I88 > 50000, 'Rent Table'!$I88 <= 150000), "50,001-150,000", AND('Rent Table'!$I88 > 150000, 'Rent Table'!$I88 <= 250000), "150,001-250,000", AND('Rent Table'!$I88 > 250000, 'Rent Table'!$I88 <= 350000), "250,001-350,000", AND('Rent Table'!$I88 > 350000, 'Rent Table'!$I88 <= 450000), "350,001-450,000", AND('Rent Table'!$I88 > 450000, 'Rent Table'!$I88 <= 600000), "450,001-600,000", AND('Rent Table'!$I88 > 600000, 'Rent Table'!$I88 <= 750000), "600,001-750,000",'Rent Table'!$I88 > 750000, "750,000+", TRUE, "Undefined" )} -> 50,001-150,000
A89: 1335 Riverview Drive | B89: San Bernardino | C89: CA | D89: 92408 | E89: Inland Empire | F89: Industrial | G89: 45566 | H89: A- | I89: 19142 | J89: SF | K89: 11.8502 | L89: 19142 | M89: 120 | N89: - | O89: 4 | P89: 1 | Q89: 2008 | R89: - | S89: {=_xlfn.IFS(AND('Rent Table'!$I89>0,'Rent Table'!$I89<=50000),"0-50,000", AND('Rent Table'!$I89 > 50000, 'Rent Table'!$I89 <= 150000), "50,001-150,000", AND('Rent Table'!$I89 > 150000, 'Rent Table'!$I89 <= 250000), "150,001-250,000", AND('Rent Table'!$I89 > 250000, 'Rent Table'!$I89 <= 350000), "250,001-350,000", AND('Rent Table'!$I89 > 350000, 'Rent Table'!$I89 <= 450000), "350,001-450,000", AND('Rent Table'!$I89 > 450000, 'Rent Table'!$I89 <= 600000), "450,001-600,000", AND('Rent Table'!$I89 > 600000, 'Rent Table'!$I89 <= 750000), "600,001-750,000",'Rent Table'!$I89 > 750000, "750,000+", TRUE, "Undefined" )} -> 0-50,000
A90: 1350 South Waterman Avenue | B90: San Bernardino | C90: CA | D90: 92408 | E90: Inland Empire | F90: Industrial | G90: 45566 | H90: A- | I90: 553592 | J90: SF | K90: 7.35182 | L90: 553592 | M90: 88 | N90: 7 | O90: 4 | P90: 1 | Q90: 2018 | R90: - | S90: {=_xlfn.IFS(AND('Rent Table'!$I90>0,'Rent Table'!$I90<=50000),"0-50,000", AND('Rent Table'!$I90 > 50000, 'Rent Table'!$I90 <= 150000), "50,001-150,000", AND('Rent Table'!$I90 > 150000, 'Rent Table'!$I90 <= 250000), "150,001-250,000", AND('Rent Table'!$I90 > 250000, 'Rent Table'!$I90 <= 350000), "250,001-350,000", AND('Rent Table'!$I90 > 350000, 'Rent Table'!$I90 <= 450000), "350,001-450,000", AND('Rent Table'!$I90 > 450000, 'Rent Table'!$I90 <= 600000), "450,001-600,000", AND('Rent Table'!$I90 > 600000, 'Rent Table'!$I90 <= 750000), "600,001-750,000",'Rent Table'!$I90 > 750000, "750,000+", TRUE, "Undefined" )} -> 450,001-600,000
A91: 1385 South Tippecanoe Avenue | B91: San Bernardino | C91: CA | D91: 92408 | E91: Inland Empire | F91: Industrial | G91: 45566 | H91: A- | I91: 81286 | J91: SF | K91: 14.355 | L91: 81286 | M91: 37 | N91: - | O91: 1 | P91: 2 | Q91: 2018 | R91: - | S91: {=_xlfn.IFS(AND('Rent Table'!$I91>0,'Rent Table'!$I91<=50000),"0-50,000", AND('Rent Table'!$I91 > 50000, 'Rent Table'!$I91 <= 150000), "50,001-150,000", AND('Rent Table'!$I91 > 150000, 'Rent Table'!$I91 <= 250000), "150,001-250,000", AND('Rent Table'!$I91 > 250000, 'Rent Table'!$I91 <= 350000), "250,001-350,000", AND('Rent Table'!$I91 > 350000, 'Rent Table'!$I91 <= 450000), "350,001-450,000", AND('Rent Table'!$I91 > 450000, 'Rent Table'!$I91 <= 600000), "450,001-600,000", AND('Rent Table'!$I91 > 600000, 'Rent Table'!$I91 <= 750000), "600,001-750,000",'Rent Table'!$I91 > 750000, "750,000+", TRUE, "Undefined" )} -> 50,001-150,000
A92: 1390 South Tippecanoe Avenue | B92: San Bernardino | C92: CA | D92: 92408 | E92: Inland Empire | F92: Industrial | G92: 45566 | H92: A- | I92: 65360 | J92: SF | K92: 11.1859 | L92: 43600 | M92: 89 | N92: - | O92: 4 | P92: - | Q92: 1989 | R92: - | S92: {=_xlfn.IFS(AND('Rent Table'!$I92>0,'Rent Table'!$I92<=50000),"0-50,000", AND('Rent Table'!$I92 > 50000, 'Rent Table'!$I92 <= 150000), "50,001-150,000", AND('Rent Table'!$I92 > 150000, 'Rent Table'!$I92 <= 250000), "150,001-250,000", AND('Rent Table'!$I92 > 250000, 'Rent Table'!$I92 <= 350000), "250,001-350,000", AND('Rent Table'!$I92 > 350000, 'Rent Table'!$I92 <= 450000), "350,001-450,000", AND('Rent Table'!$I92 > 450000, 'Rent Table'!$I92 <= 600000), "450,001-600,000", AND('Rent Table'!$I92 > 600000, 'Rent Table'!$I92 <= 750000), "600,001-750,000",'Rent Table'!$I92 > 750000, "750,000+", TRUE, "Undefined" )} -> 50,001-150,000
A93: 1425 Victoria Court | B93: San Bernardino | C93: CA | D93: 92408 | E93: Inland Empire | F93: Industrial | G93: 45566 | H93: A- | I93: 23748 | J93: SF | K93: 11.743167 | L93: 8246.667 | M93: 61 | N93: - | O93: 2.3333333 | P93: - | Q93: 1988 | R93: - | S93: {=_xlfn.IFS(AND('Rent Table'!$I93>0,'Rent Table'!$I93<=50000),"0-50,000", AND('Rent Table'!$I93 > 50000, 'Rent Table'!$I93 <= 150000), "50,001-150,000", AND('Rent Table'!$I93 > 150000, 'Rent Table'!$I93 <= 250000), "150,001-250,000", AND('Rent Table'!$I93 > 250000, 'Rent Table'!$I93 <= 350000), "250,001-350,000", AND('Rent Table'!$I93 > 350000, 'Rent Table'!$I93 <= 450000), "350,001-450,000", AND('Rent Table'!$I93 > 450000, 'Rent Table'!$I93 <= 600000), "450,001-600,000", AND('Rent Table'!$I93 > 600000, 'Rent Table'!$I93 <= 750000), "600,001-750,000",'Rent Table'!$I93 > 750000, "750,000+", TRUE, "Undefined" )} -> 0-50,000
A94: 1442 South Gage Street | B94: San Bernardino | C94: CA | D94: 92408 | E94: Inland Empire | F94: Industrial | G94: 45566 | H94: A- | I94: 6600 | J94: SF | K94: 10.9107 | L94: 6600 | M94: 36 | N94: - | O94: - | P94: 1 | Q94: 1989 | R94: - | S94: {=_xlfn.IFS(AND('Rent Table'!$I94>0,'Rent Table'!$I94<=50000),"0-50,000", AND('Rent Table'!$I94 > 50000, 'Rent Table'!$I94 <= 150000), "50,001-150,000", AND('Rent Table'!$I94 > 150000, 'Rent Table'!$I94 <= 250000), "150,001-250,000", AND('Rent Table'!$I94 > 250000, 'Rent Table'!$I94 <= 350000), "250,001-350,000", AND('Rent Table'!$I94 > 350000, 'Rent Table'!$I94 <= 450000), "350,001-450,000", AND('Rent Table'!$I94 > 450000, 'Rent Table'!$I94 <= 600000), "450,001-600,000", AND('Rent Table'!$I94 > 600000, 'Rent Table'!$I94 <= 750000), "600,001-750,000",'Rent Table'!$I94 > 750000, "750,000+", TRUE, "Undefined" )} -> 0-50,000
A95: 1445 South Tippecanoe Avenue | B95: San Bernardino | C95: CA | D95: 92408 | E95: Inland Empire | F95: Industrial | G95: 45566 | H95: A- | I95: 344000 | J95: SF | K95: 8.39927 | L95: 205398 | M95: 126 | N95: 5 | O95: 6 | P95: 1 | Q95: 2018 | R95: - | S95: {=_xlfn.IFS(AND('Rent Table'!$I95>0,'Rent Table'!$I95<=50000),"0-50,000", AND('Rent Table'!$I95 > 50000, 'Rent Table'!$I95 <= 150000), "50,001-150,000", AND('Rent Table'!$I95 > 150000, 'Rent Table'!$I95 <= 250000), "150,001-250,000", AND('Rent Table'!$I95 > 250000, 'Rent Table'!$I95 <= 350000), "250,001-350,000", AND('Rent Table'!$I95 > 350000, 'Rent Table'!$I95 <= 450000), "350,001-450,000", AND('Rent Table'!$I95 > 450000, 'Rent Table'!$I95 <= 600000), "450,001-600,000", AND('Rent Table'!$I95 > 600000, 'Rent Table'!$I95 <= 750000), "600,001-750,000",'Rent Table'!$I95 > 750000, "750,000+", TRUE, "Undefined" )} -> 250,001-350,000
A96: 1445-1455 Riverview Drive | B96: San Bernardino | C96: CA | D96: 92408 | E96: Inland Empire | F96: Industrial | G96: 45566 | H96: A- | I96: 116645 | J96: SF | K96: 16.583 | L96: 116645 | M96: 36 | N96: - | O96: - | P96: 1 | Q96: 1980 | R96: - | S96: {=_xlfn.IFS(AND('Rent Table'!$I96>0,'Rent Table'!$I96<=50000),"0-50,000", AND('Rent Table'!$I96 > 50000, 'Rent Table'!$I96 <= 150000), "50,001-150,000", AND('Rent Table'!$I96 > 150000, 'Rent Table'!$I96 <= 250000), "150,001-250,000", AND('Rent Table'!$I96 > 250000, 'Rent Table'!$I96 <= 350000), "250,001-350,000", AND('Rent Table'!$I96 > 350000, 'Rent Table'!$I96 <= 450000), "350,001-450,000", AND('Rent Table'!$I96 > 450000, 'Rent Table'!$I96 <= 600000), "450,001-600,000", AND('Rent Table'!$I96 > 600000, 'Rent Table'!$I96 <= 750000), "600,001-750,000",'Rent Table'!$I96 > 750000, "750,000+", TRUE, "Undefined" )} -> 50,001-150,000
A97: 1615 Riverview Drive | B97: San Bernardino | C97: CA | D97: 92408 | E97: Inland Empire | F97: Industrial | G97: 45566 | H97: A- | I97: 18710 | J97: SF | K97: 10.7996 | L97: 8160 | M97: 36 | N97: - | O97: - | P97: 1 | Q97: 1982 | R97: - | S97: {=_xlfn.IFS(AND('Rent Table'!$I97>0,'Rent Table'!$I97<=50000),"0-50,000", AND('Rent Table'!$I97 > 50000, 'Rent Table'!$I97 <= 150000), "50,001-150,000", AND('Rent Table'!$I97 > 150000, 'Rent Table'!$I97 <= 250000), "150,001-250,000", AND('Rent Table'!$I97 > 250000, 'Rent Table'!$I97 <= 350000), "250,001-350,000", AND('Rent Table'!$I97 > 350000, 'Rent Table'!$I97 <= 450000), "350,001-450,000", AND('Rent Table'!$I97 > 450000, 'Rent Table'!$I97 <= 600000), "450,001-600,000", AND('Rent Table'!$I97 > 600000, 'Rent Table'!$I97 <= 750000), "600,001-750,000",'Rent Table'!$I97 > 750000, "750,000+", TRUE, "Undefined" )} -> 0-50,000
A98: 1655 Riverview Drive | B98: San Bernardino | C98: CA | D98: 92408 | E98: Inland Empire | F98: Industrial | G98: 45566 | H98: A- | I98: 8000 | J98: SF | K98: 15.5779 | L98: 8000 | M98: 59.75 | N98: - | O98: 1 | P98: 1 | Q98: 1980 | R98: - | S98: {=_xlfn.IFS(AND('Rent Table'!$I98>0,'Rent Table'!$I98<=50000),"0-50,000", AND('Rent Table'!$I98 > 50000, 'Rent Table'!$I98 <= 150000), "50,001-150,000", AND('Rent Table'!$I98 > 150000, 'Rent Table'!$I98 <= 250000), "150,001-250,000", AND('Rent Table'!$I98 > 250000, 'Rent Table'!$I98 <= 350000), "250,001-350,000", AND('Rent Table'!$I98 > 350000, 'Rent Table'!$I98 <= 450000), "350,001-450,000", AND('Rent Table'!$I98 > 450000, 'Rent Table'!$I98 <= 600000), "450,001-600,000", AND('Rent Table'!$I98 > 600000, 'Rent Table'!$I98 <= 750000), "600,001-750,000",'Rent Table'!$I98 > 750000, "750,000+", TRUE, "Undefined" )} -> 0-50,000
A99: 1811-1833 Riverview Drive | B99: San Bernardino | C99: CA | D99: 92408 | E99: Inland Empire | F99: Industrial | G99: 45566 | H99: A- | I99: 44000 | J99: SF | K99: 10.4113 | L99: 8800 | M99: 61 | N99: - | O99: 1 | P99: 1 | Q99: 1984 | R99: - | S99: {=_xlfn.IFS(AND('Rent Table'!$I99>0,'Rent Table'!$I99<=50000),"0-50,000", AND('Rent Table'!$I99 > 50000, 'Rent Table'!$I99 <= 150000), "50,001-150,000", AND('Rent Table'!$I99 > 150000, 'Rent Table'!$I99 <= 250000), "150,001-250,000", AND('Rent Table'!$I99 > 250000, 'Rent Table'!$I99 <= 350000), "250,001-350,000", AND('Rent Table'!$I99 > 350000, 'Rent Table'!$I99 <= 450000), "350,001-450,000", AND('Rent Table'!$I99 > 450000, 'Rent Table'!$I99 <= 600000), "450,001-600,000", AND('Rent Table'!$I99 > 600000, 'Rent Table'!$I99 <= 750000), "600,001-750,000",'Rent Table'!$I99 > 750000, "750,000+", TRUE, "Undefined" )} -> 0-50,000
A100: 1833 Riverview Drive | B100: San Bernardino | C100: CA | D100: 92408 | E100: Inland Empire | F100: Industrial | G100: 45566 | H100: A- | I100: 44000 | J100: SF | K100: 8.32503 | L100: 8800 | M100: 39 | N100: - | O100: 4 | P100: 1 | Q100: 1981 | R100: - | S100: {=_xlfn.IFS(AND('Rent Table'!$I100>0,'Rent Table'!$I100<=50000),"0-50,000", AND('Rent Table'!$I100 > 50000, 'Rent Table'!$I100 <= 150000), "50,001-150,000", AND('Rent Table'!$I100 > 150000, 'Rent Table'!$I100 <= 250000), "150,001-250,000", AND('Rent Table'!$I100 > 250000, 'Rent Table'!$I100 <= 350000), "250,001-350,000", AND('Rent Table'!$I100 > 350000, 'Rent Table'!$I100 <= 450000), "350,001-450,000", AND('Rent Table'!$I100 > 450000, 'Rent Table'!$I100 <= 600000), "450,001-600,000", AND('Rent Table'!$I100 > 600000, 'Rent Table'!$I100 <= 750000), "600,001-750,000",'Rent Table'!$I100 > 750000, "750,000+", TRUE, "Undefined" )} -> 0-50,000
...

Sheet Rent Summary
B2: Effective Rent Market Summary
E3: Count | F3: Min | G3: Max | H3: SD | I3: Average Effective Rent
B4: Inland Empire | E4: 50 | F4: 6.89242 | G4: 20.4175 | H4: 2.5608557 | I4: 11.74845
C5: Colton | E5: 1 | F5: 10.2039 | G5: 10.2039 | I5: 10.2039
D6: 250,001-350,000 | E6: 1 | F6: 10.2039 | G6: 10.2039 | I6: 10.2039
C7: Loma Linda | E7: 3 | F7: 13.0548 | G7: 14.1289 | H7: 0.54345147 | I7: 13.639867
D8: 250,001-350,000 | E8: 1 | F8: 13.7359 | G8: 13.7359 | I8: 13.7359
D9: 50,001-150,000 | E9: 2 | F9: 13.0548 | G9: 14.1289 | H9: 0.75950339 | I9: 13.59185
C10: Redlands | E10: 32 | F10: 6.89242 | G10: 20.4175 | H10: 2.6320308 | I10: 11.672032
D11: 0-50,000 | E11: 12 | F11: 9.07241 | G11: 20.4175 | H11: 2.9801098 | I11: 12.404307
D12: 150,001-250,000 | E12: 2 | F12: 9.18398 | G12: 14.9824 | H12: 4.1001021 | I12: 12.08319
D13: 250,001-350,000 | E13: 1 | F13: 12.901 | G13: 12.901 | I13: 12.901
D14: 350,001-450,000 | E14: 2 | F14: 10.0171 | G14: 13.1526 | H14: 2.2171333 | I14: 11.58485
D15: 450,001-600,000 | E15: 2 | F15: 10.0691 | G15: 13.67495 | H15: 2.549721 | I15: 11.872025
D16: 50,001-150,000 | E16: 9 | F16: 9.0859 | G16: 14.7399 | H16: 2.1684749 | I16: 11.803631
D17: 600,001-750,000 | E17: 2 | F17: 8.70586 | G17: 8.74871 | H17: 0.030299526 | I17: 8.727285
D18: 750,000+ | E18: 2 | F18: 6.89242 | G18: 10.09254 | H18: 2.2628266 | I18: 8.49248
C19: San Bernardino | E19: 14 | F19: 7.35182 | G19: 16.583 | H19: 2.6672912 | I19: 11.628142
D20: 0-50,000 | E20: 8 | F20: 8.32503 | G20: 15.5779 | H20: 2.1085725 | I20: 11.577487
D21: 250,001-350,000 | E21: 1 | F21: 8.39927 | G21: 8.39927 | I21: 8.39927
D22: 450,001-600,000 | E22: 1 | F22: 7.35182 | G22: 7.35182 | I22: 7.35182
D23: 50,001-150,000 | E23: 4 | F23: 11.1859 | G23: 16.583 | H23: 2.3796639 | I23: 13.60575
B24: Los Angeles | E24: 50 | F24: 10.7525 | G24: 30.2333 | H24: 4.7616267 | I24: 19.067257
C25: Carson | E25: 19 | F25: 10.7525 | G25: 21.9904 | H25: 3.8169864 | I25: 16.560663
D26: 0-50,000 | E26: 8 | F26: 10.7525 | G26: 18.473 | H26: 2.3564069 | I26: 12.962438
D27: 150,001-250,000 | E27: 5 | F27: 18.03055 | G27: 21.9904 | H27: 1.6933218 | I27: 19.78795
D28: 250,001-350,000 | E28: 1 | F28: 20.28085 | G28: 20.28085 | I28: 20.28085
D29: 50,001-150,000 | E29: 5 | F29: 14.9052 | G29: 21.6977 | H29: 2.5724724 | I29: 18.3465
C30: Gardena | E30: 3 | F30: 11.7541 | G30: 25.7664 | H30: 7.3447642 | I30: 20.032967
D31: 0-50,000 | E31: 1 | F31: 25.7664 | G31: 25.7664 | I31: 25.7664
D32: 50,001-150,000 | E32: 2 | F32: 11.7541 | G32: 22.5784 | H32: 7.6539359 | I32: 17.16625
C33: Torrance | E33: 28 | F33: 12.102 | G33: 30.2333 | H33: 4.5019173 | I33: 20.664691
D34: 0-50,000 | E34: 8 | F34: 12.102 | G34: 30.2333 | H34: 5.7697141 | I34: 20.502594
D35: 150,001-250,000 | E35: 3 | F35: 19.51805 | G35: 27.9826 | H35: 4.6589024 | I35: 22.625867
D36: 250,001-350,000 | E36: 5 | F36: 16.2203 | G36: 25.5206 | H36: 3.6797274 | I36: 19.08812
D37: 350,001-450,000 | E37: 1 | F37: 18.5248 | G37: 18.5248 | I37: 18.5248
D38: 50,001-150,000 | E38: 9 | F38: 16.7513 | G38: 28.9685 | H38: 4.1221069 | I38: 22.1494
D39: 600,001-750,000 | E39: 1 | F39: 16.1212 | G39: 16.1212 | I39: 16.1212
D40: 750,000+ | E40: 1 | F40: 17.2818 | G40: 17.2818 | I40: 17.2818

Sheet Sales Comp Summary
A2: City | B2: Sum of Sale Price Per (in Local Currency)
A3: Torrance | B3: 7180.68
A4: Redlands | B4: 2616.45
A5: Gardena | B5: 2320.64
A6: San Bernardino | B6: 1485.3
A7: Carson | B7: 894.51
A8: Colton | B8: 451.08
A9: Oxnard | B9: 161.66
A10: Grand Total | B10: 15110.32

Sheet Sales Table
A1: Appended Table
B4: Portfolio / Property Name | C4: Street Address | D4: City | E4: State | F4: Country | G4: Zip Code | H4: Sector | I4: Subsector | J4: Sector Attribute | K4: Part of Mixed Use Development | L4: Market | M4: Submarket | N4: Size | O4: Size Type | P4: Sale Date | Q4: Stake Sold | R4: Local Currency Sale Price (M) | S4: Local Currency Symbol | T4: Sale Price Per (in Local Currency) | U4: Selected Currency Sale Price ($) (M) | V4: Submarket Grade | W4: Property Cap Rate | X4: Property Cap Rate Type | Y4: Part of a Portfolio? | Z4: Buyer | AA4: Seller | AB4: Buyer Objective | AC4: To be demolished | AD4: Buyer Broker | AE4: Seller Broker | AF4: Land Area (acres) | AG4: Stories | AH4: Parking | AI4: Buildings | AJ4: Year Built | AK4: Year Renovated | AL4: Occupancy | AM4: Green Street Market Cap Rate | AN4: Submarket Cap Rate | AO4: Zip Code Cap Rate | AP4: Lender | AQ4: 1st Mortgage | AR4: Verified?
B5: 1971 Essex Court | C5: 1971 Essex Court, Redlands, CA 92373 | D5: Redlands | E5: CA | F5: United States | G5: 92373 | H5: Industrial | I5: Flex Industrial | K5: No | L5: Inland Empire | M5: IE-East Redlands | N5: 21228 | O5: SF | P5: 45295 | Q5: 1 | R5: 5.1 | S5: $ | T5: 240.25 | V5: A- | W5: 0.04052253 | X5: Green Street Market Estimate | Y5: No | Z5: CMJ Brother's Corp. | AC5: No | AF5: 1.183 | AG5: 1 | AI5: 1 | AJ5: 2001 | AM5: 0.047 | AN5: 0.0481871 | AO5: 0.04791285 | AP5: Rediger Investments | AQ5: 2550000 | AR5: Yes
B6: 1425 Cooley Court | C6: 1425 Cooley Court, San Bernardino, CA 92408 | D6: San Bernardino | E6: CA | F6: United States | G6: 92408 | H6: Industrial | I6: Warehouse | J6: Light Industrial | K6: No | L6: Inland Empire | M6: IE-East Redlands | N6: 78012 | O6: SF | P6: 45205 | Q6: 1 | R6: 11.1 | S6: $ | T6: 142.29 | V6: A- | W6: 0.0424211 | X6: Green Street Market Estimate | Y6: No | AC6: No | AF6: 2.81 | AG6: 2 | AI6: 1 | AJ6: 1988 | AM6: 0.047 | AN6: 0.0481871 | AO6: 0.04791285 | AP6: Symetra Financial | AQ6: 6400000 | AR6: Yes
B7: 1320 Riverview Drive | C7: 1320 Riverview Drive, San Bernardino, CA 92408 | D7: San Bernardino | E7: CA | F7: United States | G7: 92408 | H7: Industrial | I7: Warehouse | J7: Light Industrial | K7: No | L7: Inland Empire | M7: IE-East Redlands | N7: 23397 | O7: SF | P7: 45201 | Q7: 1 | R7: 5.62 | S7: $ | T7: 240.01 | V7: A- | W7: 0.0424211 | X7: Green Street Market Estimate | Y7: No | AA7: Rogina Family Living Trust | AC7: No | AF7: 1.24 | AG7: 2 | AI7: 1 | AJ7: 2004 | AM7: 0.047 | AN7: 0.0481871 | AO7: 0.04791285 | AP7: Wells Fargo Bank | AQ7: 3369200 | AR7: Yes
B8: 401 Alabama Street | C8: 401 Alabama Street, Redlands, CA 92373 | D8: Redlands | E8: CA | F8: United States | G8: 92373 | H8: Industrial | I8: Warehouse | J8: Light Industrial | K8: No | L8: Inland Empire | M8: IE-East Redlands | N8: 95500 | O8: SF | P8: 45051 | Q8: 1 | R8: 27.25 | S8: $ | T8: 285.34 | V8: A- | W8: 0.043 | X8: As Reported | Y8: No | Z8: General Investment & Development Cos. | AA8: Investment Building Group | AC8: No | AE8: CBRE Group | AF8: 4.526 | AG8: 1 | AI8: 1 | AJ8: 2017 | AL8: 1 | AM8: 0.047 | AN8: 0.0481871 | AO8: 0.04791285 | AR8: Yes
B9: Carnegie Business Center | C9: 720 East Carnegie Drive, San Bernardino, CA 92408 | D9: San Bernardino | E9: CA | F9: United States | G9: 92408 | H9: Industrial | I9: Warehouse | J9: Light Industrial | K9: No | L9: Inland Empire | M9: IE-East Redlands | N9: 51438 | O9: SF | P9: 44715 | Q9: 1 | R9: 11.02 | S9: $ | T9: 214.19 | V9: A- | W9: 0.0577 | X9: As Reported | Y9: No | AA9: Entrada Partners | AC9: No | AD9: CBRE Group | AE9: CBRE Group | AH9: 0 | AI9: 1 | AJ9: 1987 | AL9: 0.95 | AM9: 0.047 | AN9: 0.0481871 | AO9: 0.04791285 | AR9: Yes
B10: 1990 Riverview Drive | C10: 1990 Riverview Drive, San Bernardino, CA 92408 | D10: San Bernardino | E10: CA | F10: United States | G10: 92408 | H10: Industrial | I10: Warehouse | K10: No | L10: Inland Empire | M10: IE-East Redlands | N10: 20473 | O10: SF | P10: 44704 | Q10: 1 | R10: 24 | S10: $ | T10: 1,172.28 | V10: A- | W10: 0.03667045 | X10: Green Street Market Estimate | Y10: No | AC10: No | AD10: CBRE Group | AH10: 0 | AJ10: 1980 | AM10: 0.047 | AN10: 0.0481871 | AO10: 0.04791285 | AR10: Yes
B11: 1393 East San Bernardino Avenue | C11: 1393 East San Bernardino Avenue, San Bernardino, CA 92408 | D11: San Bernardino | E11: CA | F11: United States | G11: 92408 | H11: Industrial | I11: Warehouse | J11: Light Industrial | K11: No | L11: Inland Empire | M11: IE-East Redlands | N11: 117125 | O11: SF | P11: 44696 | Q11: 1 | R11: 20 | S11: $ | T11: 170.76 | V11: A- | W11: 0.03667045 | X11: Green Street Market Estimate | Y11: No | Z11: First Industrial Realty Trust (FR) | AC11: No | AM11: 0.047 | AN11: 0.0481871 | AO11: 0.04791285 | AR11: Yes
B12: 301 Tennessee Street | C12: 301 Tennessee Street, Redlands, CA 92373 | D12: Redlands | E12: CA | F12: United States | G12: 92373 | H12: Industrial | I12: Warehouse | J12: Manufacturing / Heavy Industrial | K12: No | L12: Inland Empire | M12: IE-East Redlands | N12: 193469 | O12: SF | P12: 44665 | Q12: 1 | R12: 18.25 | S12: $ | T12: 94.33 | V12: A- | W12: 0.03412073 | X12: Green Street Market Estimate | Y12: No | Z12: Stos Partners | AA12: ESRI | AC12: No | AE12: Savills | AH12: 0 | AM12: 0.047 | AN12: 0.0481871 | AO12: 0.04791285 | AR12: Yes
B13: 1939 West Park Avenue | C13: 1939 West Park Avenue, Redlands, CA 92373 | D13: Redlands | E13: CA | F13: United States | G13: 92373 | H13: Industrial | I13: Warehouse | K13: No | L13: Inland Empire | M13: IE-East Redlands | N13: 21612 | O13: SF | P13: 44651 | Q13: 1 | R13: 5.96 | S13: $ | T13: 275.77 | V13: A- | W13: 0.03162073 | X13: Green Street Market Estimate | Y13: No | Z13: Scott Barnes | AA13: John C. Steinmann | AC13: No | AD13: CBRE Group | AE13: CBRE Group | AG13: 1 | AH13: 0 | AJ13: 2007 | AM13: 0.047 | AN13: 0.0481871 | AO13: 0.04791285 | AR13: Yes
B14: I-215 Commerce Center | C14: 1648 Ashley Way, Colton, CA 92324 | D14: Colton | E14: CA | F14: United States | G14: 92324 | H14: Industrial | I14: Warehouse | K14: No | L14: Inland Empire | M14: IE-East Redlands | N14: 225353 | O14: SF | P14: 44439 | Q14: 1 | R14: 57.5 | S14: $ | T14: 255.16 | V14: A- | W14: 0.028 | X14: As Reported | Y14: No | Z14: Zurich Alternative Asset Management | AA14: Transwestern Development Company | AC14: No | AE14: CBRE Group | AH14: 0 | AJ14: 2021 | AL14: 1 | AM14: 0.047 | AN14: 0.0481871 | AO14: 0.04791285 | AR14: Yes
B15: Washington Commerce Center | C15: 998 South Washington Avenue, San Bernardino, CA 92408 | D15: San Bernardino | E15: CA | F15: United States | G15: 92408 | H15: Industrial | I15: Warehouse | K15: No | L15: Inland Empire | M15: IE-East Redlands | N15: 574984 | O15: SF | P15: 44423 | Q15: 1 | S15: $ | T15: 164.53 | V15: A- | Y15: Yes | Z15: PGIM | AA15: Crow Holdings | AC15: No | AE15: Eastdil Secured | AH15: 0 | AM15: 0.047 | AN15: 0.0481871 | AO15: 0.04791285 | AR15: Yes
B16: Washington Commerce Center, Building 3 | C16: 998 South Washington Avenue, San Bernardino, CA 92408 | D16: San Bernardino | E16: CA | F16: United States | G16: 92408 | H16: Industrial | I16: Warehouse | K16: No | L16: Inland Empire | M16: IE-East Redlands | N16: 146800 | O16: SF | P16: 44423 | Q16: 1 | V16: A- | Y16: Yes | Z16: PGIM | AA16: Crow Holdings | AC16: No | AE16: Eastdil Secured | AH16: 0 | AM16: 0.047 | AN16: 0.0481871 | AO16: 0.04791285 | AR16: Yes
B17: Washington Commerce Center, Building 2 | C17: 975 South Washington Avenue, San Bernardino, CA 92408 | D17: San Bernardino | E17: CA | F17: United States | G17: 92408 | H17: Industrial | I17: Warehouse | K17: No | L17: Inland Empire | M17: IE-East Redlands | N17: 179584 | O17: SF | P17: 44423 | Q17: 1 | V17: A- | Y17: Yes | Z17: PGIM | AA17: Crow Holdings | AC17: No | AE17: Eastdil Secured | AH17: 0 | AM17: 0.047 | AN17: 0.0481871 | AO17: 0.04791285 | AR17: Yes
B18: Dedeaux Business Park Redlands | C18: 509 Alabama Street, Redlands, CA 92373 | D18: Redlands | E18: CA | F18: United States | G18: 92373 | H18: Industrial | I18: Warehouse | K18: No | L18: Inland Empire | M18: IE-East Redlands | N18: 74000 | O18: SF | P18: 44320 | Q18: 1 | R18: 16.9 | S18: $ | T18: 228.38 | V18: A- | W18: 0.0371 | X18: As Reported | Y18: No | Z18: LBA Realty | AA18: Brasa Capital; Dedeaux Properties | AC18: No | AD18: Cushman & Wakefield | AE18: Cushman & Wakefield; Lee & Associates | AH18: 0 | AM18: 0.047 | AN18: 0.0481871 | AO18: 0.04791285 | AR18: Yes
B19: 1255 Research Drive | C19: 1255 Research Drive, Redlands, CA 92374 | D19: Redlands | E19: CA | F19: United States | G19: 92374 | H19: Industrial | I19: Warehouse | K19: No | L19: Inland Empire | M19: IE-East Redlands | N19: 118000 | O19: SF | P19: 44295 | Q19: 1 | R19: 18.38 | S19: $ | T19: 155.72 | V19: A- | W19: 0.03612073 | X19: Green Street Market Estimate | Y19: No | Z19: EQT Exeter | AA19: Garner Holt Productions Inc. | AC19: No | AE19: Colliers | AH19: 0 | AM19: 0.047 | AN19: 0.0481871 | AO19: 0.04791285 | AR19: Yes
B20: Crow Holdings Los Angeles Area Industrial Portfolio | C20: 1070 South Waterman Avenue, San Bernardino, CA 92408 | D20: San Bernardino | E20: CA | F20: United States | G20: 92408 | H20: Industrial | I20: Warehouse | K20: No | L20: Inland Empire | M20: IE-East Redlands | N20: 591000 | O20: SF | P20: 44276 | Q20: 1 | S20: $ | T20: 155.77 | V20: A- | Y20: Yes | Z20: Principal Real Estate Investors | AA20: Crow Holdings | AC20: No | AE20: CBRE Group; Eastdil Secured | AH20: 0 | AM20: 0.047 | AN20: 0.0481871 | AO20: 0.04791285 | AR20: Yes
B21: 1070 South Waterman Avenue | C21: 1070 South Waterman Avenue, San Bernardino, CA 92408 | D21: San Bernardino | E21: CA | F21: United States | G21: 92408 | H21: Industrial | I21: Warehouse | K21: No | L21: Inland Empire | M21: IE-East Redlands | N21: 392000 | O21: SF | P21: 44276 | Q21: 1 | V21: A- | Y21: Yes | Z21: Principal Real Estate Investors | AA21: Crow Holdings | AC21: No | AE21: CBRE Group; Eastdil Secured | AH21: 0 | AM21: 0.047 | AN21: 0.0481871 | AO21: 0.04791285 | AR21: Yes
B22: Redlands Corporate Center 1&2 | C22: 1289 Bryn Mawr Avenue, Redlands, CA 92374 | D22: Redlands | E22: CA | F22: United States | G22: 92374 | H22: Office | I22: Warehouse | K22: No | L22: Inland Empire | M22: IE-East Redlands | N22: 287000 | O22: SF | P22: 44215 | Q22: 1 | S22: $ | T22: 141.46 | V22: A- | Y22: Yes | Z22: Penwood Real Estate Investment Management | AA22: Stockbridge Capital Group | AC22: No | AE22: CBRE Group | AH22: 0 | AJ22: 2003 | AM22: 0.047 | AN22: 0.0481871 | AO22: 0.04791285 | AR22: Yes
B23: Redlands Corporate Center 2 | C23: 1289 Bryn Mawr Avenue, Redlands, CA 92374 | D23: Redlands | E23: CA | F23: United States | G23: 92374 | H23: Industrial | I23: Warehouse | K23: No | L23: Inland Empire | M23: IE-East Redlands | N23: 39000 | O23: SF | P23: 44215 | Q23: 1 | V23: A- | Y23: Yes | Z23: Penwood Real Estate Investment Management | AA23: Stockbridge Capital Group | AC23: No | AE23: CBRE Group | AH23: 0 | AJ23: 2003 | AM23: 0.047 | AN23: 0.0481871 | AO23: 0.04791285 | AR23: Yes
B24: Redlands Corporate Center 1 | C24: 1115 Research Drive, Redlands, CA 92374 | D24: Redlands | E24: CA | F24: United States | G24: 92374 | H24: Industrial | I24: Warehouse | K24: No | L24: Inland Empire | M24: IE-East Redlands | N24: 31000 | O24: SF | P24: 44215 | Q24: 1 | V24: A- | Y24: Yes | Z24: Penwood Real Estate Investment Management | AA24: Stockbridge Capital Group | AC24: No | AE24: CBRE Group | AH24: 0 | AJ24: 1991 | AM24: 0.047 | AN24: 0.0481871 | AO24: 0.04791285 | AR24: Yes
B25: Hillwood Development Multi-state Industrial Portfolio (B) | C25: 1494 South Waterman Avenue, San Bernardino, CA 92408 | F25: United States | G25: 92408 | H25: Industrial | I25: Warehouse | K25: No | L25: Inland Empire | M25: IE-East Redlands | N25: 4287000 | O25: SF | P25: 44167 | Q25: 1 | S25: $ | T25: 107.89 | V25: A- | Y25: Yes | Z25: Stockbridge Capital Group | AA25: Hillwood Investment Properties | AC25: No | AE25: CBRE Group | AH25: 0 | AJ25: 2019 | AM25: 0.047 | AN25: 0.0481871 | AO25: 0.04791285 | AR25: Yes
B26: 1494 South Waterman Avenue | C26: 1494 South Waterman Avenue, San Bernardino, CA 92408 | D26: San Bernardino | E26: CA | F26: United States | G26: 92408 | H26: Industrial | I26: Warehouse | K26: No | L26: Inland Empire | M26: IE-East Redlands | N26: 1066000 | O26: SF | P26: 44167 | Q26: 1 | R26: 132.81 | S26: $ | T26: 124.58 | V26: A- | Y26: Yes | Z26: Stockbridge Capital Group | AA26: Hillwood Investment Properties | AC26: No | AE26: CBRE Group | AH26: 0 | AJ26: 2019 | AM26: 0.047 | AN26: 0.0481871 | AO26: 0.04791285 | AR26: Yes
B27: 1601&1603 Steel Road | C27: 1603 East Steel Road, Colton, CA 92324 | D27: Colton | E27: CA | F27: United States | G27: 92324 | H27: Industrial | I27: Warehouse | K27: No | L27: Inland Empire | M27: IE-East Redlands | N27: 331000 | O27: SF | P27: 44152 | Q27: 1 | R27: 46 | S27: $ | T27: 138.97 | V27: A- | W27: 0.04067045 | X27: Green Street Market Estimate | Y27: No | Z27: Brookfield Property Group | AC27: No | AD27: CBRE Group | AF27: 8.99 | AH27: 0 | AI27: 1 | AM27: 0.047 | AN27: 0.0481871 | AO27: 0.04791285 | AR27: Yes
B28: Redlands Corporate Center | C28: 1251 Research Drive, Redlands, CA 92374 | D28: Redlands | E28: CA | F28: United States | G28: 92374 | H28: Industrial | I28: Warehouse | K28: No | L28: Inland Empire | M28: IE-East Redlands | N28: 118000 | O28: SF | P28: 43899 | Q28: 1 | R28: 10.5 | S28: $ | T28: 88.98 | V28: A- | W28: 0.03912073 | X28: Green Street Market Estimate | Y28: No | Z28: Garner Holt Productions Inc. | AA28: Stockbridge Real Estate | AC28: No | AE28: Cushman & Wakefield | AH28: 0 | AM28: 0.047 | AN28: 0.0481871 | AO28: 0.04791285 | AR28: Yes
B29: 301 Tennessee Street | C29: 301 Tennessee Street, Redlands, CA 92373 | D29: Redlands | E29: CA | F29: United States | G29: 92373 | H29: Industrial | I29: Warehouse | K29: No | L29: Inland Empire | M29: IE-East Redlands | N29: 193000 | O29: SF | P29: 43861 | Q29: 1 | R29: 11.5 | S29: $ | T29: 59.59 | V29: A- | W29: 0.03912073 | X29: Green Street Market Estimate | Y29: No | AA29: La-Z-Boy Inc. | AC29: No | AE29: Savills | AH29: 0 | AM29: 0.047 | AN29: 0.0481871 | AO29: 0.04791285 | AR29: Yes
B30: 1730 Marigold Avenue | C30: 1730 Marigold Avenue, Redlands, CA 92374 | D30: Redlands | E30: CA | F30: United States | G30: 92374 | H30: Industrial | I30: Warehouse | K30: No | L30: Inland Empire | M30: IE-East Redlands | N30: 328000 | O30: SF | P30: 43830 | Q30: 1 | R30: 39.7 | S30: $ | T30: 121.04 | V30: A- | W30: 0.04062073 | X30: Green Street Market Estimate | Y30: No | Z30: Black Creek Group | AA30: Kensington Realty Advisors | AC30: No | AE30: Cushman & Wakefield | AF30: 15.368 | AH30: 0 | AI30: 1 | AM30: 0.047 | AN30: 0.0481871 | AO30: 0.04791285 | AR30: Yes
B31: Los Angeles Area Industrial Portfolio | C31: Redlands, CA | D31: Redlands | E31: CA | F31: United States | H31: Industrial | I31: Warehouse | J31: Park | K31: No | L31: Other | N31: 257000 | O31: SF | P31: 43818 | Q31: 1 | R31: 24.8 | S31: $ | T31: 96.5 | Y31: Yes | AC31: No | AE31: CBRE Group | AH31: 0 | AR31: Yes
B32: 1445 South Tippacanoe Avenue | C32: 1445 South Tippecanoe Avenue, San Bernardino, CA 92408 | D32: San Bernardino | E32: CA | F32: United States | G32: 92408 | H32: Industrial | I32: Warehouse | K32: No | L32: Inland Empire | M32: IE-East Redlands | N32: 344000 | O32: SF | P32: 43663 | Q32: 1 | R32: 43.1 | S32: $ | T32: 125.29 | V32: A- | W32: 0.04317045 | X32: Green Street Market Estimate | Y32: No | Z32: Nuveen Real Estate | AA32: Rockefeller Group | AC32: No | AE32: Cushman & Wakefield | AF32: 14.886 | AH32: 0 | AI32: 1 | AM32: 0.047 | AN32: 0.0481871 | AO32: 0.04791285 | AR32: Yes
B33: 1898 Marigold Avenue | C33: 1898 Marigold Avenue, Redlands, CA 92374 | D33: Redlands | E33: CA | F33: United States | G33: 92374 | H33: Industrial | I33: Warehouse | K33: No | L33: Inland Empire | M33: IE-East Redlands | N33: 290000 | O33: SF | P33: 43508 | Q33: 1 | R33: 31.29 | S33: $ | T33: 107.88 | V33: A- | W33: 0.04212073 | X33: Green Street Market Estimate | Y33: No | Z33: Liberty Property Trust | AC33: No | AE33: CBRE Group | AF33: 16 | AH33: 0 | AI33: 1 | AM33: 0.047 | AN33: 0.0481871 | AO33: 0.04791285 | AR33: Yes
B34: Cabot Properties National Industrial Portfolio | C34: 1833 Riverview Drive, San Bernardino, CA 92408 | F34: United States | G34: 92408 | H34: Industrial | I34: Warehouse | K34: No | L34: Inland Empire | M34: IE-East Redlands | N34: 21719000 | O34: SF | P34: 43172 | Q34: 1 | S34: $ | T34: 83.11 | V34: A- | Y34: Yes | Z34: Blackstone Real Estate Income Trust | AA34: Cabot Properties | AC34: No | AE34: CBRE Group; Eastdil Secured | AH34: 0 | AM34: 0.047 | AN34: 0.0481871 | AO34: 0.04791285 | AR34: Yes
B35: 1833 Riverview Dr | C35: 1833 Riverview Drive, San Bernardino, CA 92408 | D35: San Bernardino | E35: CA | F35: United States | G35: 92408 | H35: Industrial | I35: Warehouse | K35: No | L35: Inland Empire | M35: IE-East Redlands | N35: 44000 | O35: SF | P35: 43172 | Q35: 1 | V35: A- | Y35: Yes | Z35: Blackstone Real Estate Income Trust | AA35: Cabot Properties | AC35: No | AE35: CBRE Group; Eastdil Secured | AH35: 0 | AM35: 0.047 | AN35: 0.0481871 | AO35: 0.04791285 | AR35: Yes
B36: 1817 Riverview Dr | C36: 1817 Riverview Drive, San Bernardino, CA 92408 | D36: San Bernardino | E36: CA | F36: United States | G36: 92408 | H36: Industrial | I36: Warehouse | K36: No | L36: Inland Empire | M36: IE-East Redlands | N36: 40000 | O36: SF | P36: 43172 | Q36: 1 | V36: A- | Y36: Yes | Z36: Blackstone Real Estate Income Trust | AA36: Cabot Properties | AC36: No | AE36: CBRE Group; Eastdil Secured | AH36: 0 | AM36: 0.047 | AN36: 0.0481871 | AO36: 0.04791285 | AR36: Yes
B37: 1811 Riverview Dr | C37: 1811 Riverview Drive, San Bernardino, CA 92408 | D37: San Bernardino | E37: CA | F37: United States | G37: 92408 | H37: Industrial | I37: Warehouse | K37: No | L37: Inland Empire | M37: IE-East Redlands | N37: 60000 | O37: SF | P37: 43172 | Q37: 1 | V37: A- | Y37: Yes | Z37: Blackstone Real Estate Income Trust | AA37: Cabot Properties | AC37: No | AE37: CBRE Group; Eastdil Secured | AH37: 0 | AM37: 0.047 | AN37: 0.0481871 | AO37: 0.04791285 | AR37: Yes
B38: 1445-1455 E Riverview Dr | C38: 1445 Riverview Drive, San Bernardino, CA 92408 | D38: San Bernardino | E38: CA | F38: United States | G38: 92408 | H38: Industrial | I38: Warehouse | K38: No | L38: Inland Empire | M38: IE-East Redlands | N38: 117000 | O38: SF | P38: 43172 | Q38: 1 | V38: A- | Y38: Yes | Z38: Blackstone Real Estate Income Trust | AA38: Cabot Properties | AC38: No | AE38: CBRE Group; Eastdil Secured | AH38: 0 | AM38: 0.047 | AN38: 0.0481871 | AO38: 0.04791285 | AR38: Yes
B39: Redlands Gateway Logistics Center | C39: 9712 Alabama Street, Redlands, CA 92374 | D39: Redlands | E39: CA | F39: United States | G39: 92374 | H39: Industrial | I39: Warehouse | K39: No | L39: Inland Empire | M39: IE-East Redlands | N39: 928000 | O39: SF | P39: 43158 | Q39: 1 | R39: 100.5 | S39: $ | T39: 108.3 | V39: A- | W39: 0.04362073 | X39: Green Street Market Estimate | Y39: No | Z39: Alere Property Group | AA39: Crow Holdings | AC39: No | AE39: CBRE Group | AH39: 0 | AM39: 0.047 | AN39: 0.0481871 | AO39: 0.04791285 | AR39: Yes
B40: Hillwood Investment National Industrial Portfolio | C40: 555 East Orange Show Road, San Bernardino, CA 92408 | F40: United States | G40: 92408 | H40: Industrial | I40: Warehouse | K40: No | L40: Inland Empire | M40: IE-East Redlands | N40: 9116000 | O40: SF | P40: 42723 | Q40: 1 | S40: $ | T40: 73.68 | V40: A- | Y40: Yes | Z40: GLP | AA40: Hillwood Investment Properties | AC40: No | AE40: CBRE Group; Eastdil Secured | AH40: 0 | AM40: 0.047 | AN40: 0.0481871 | AO40: 0.04791285 | AR40: Yes
B41: 555 Orange Show Road | C41: 555 East Orange Show Road, San Bernardino, CA 92408 | D41: San Bernardino | E41: CA | F41: United States | G41: 92408 | H41: Industrial | I41: Warehouse | K41: No | L41: Inland Empire | M41: IE-East Redlands | N41: 1103000 | O41: SF | P41: 42723 | Q41: 1 | R41: 98.9 | S41: $ | T41: 89.66 | V41: A- | Y41: Yes | Z41: GLP | AA41: Hillwood Investment Properties | AC41: No | AE41: CBRE Group; Eastdil Secured | AH41: 0 | AM41: 0.047 | AN41: 0.0481871 | AO41: 0.04791285 | AR41: Yes
B42: AREA Property Multi-State Industrial Portfolio | C42: 2200 West San Bernardino Avenue, Redlands, CA 92374 | F42: United States | G42: 92374 | H42: Industrial | I42: Warehouse | K42: No | L42: Inland Empire | M42: IE-East Redlands | N42: 2858000 | O42: SF | P42: 42528 | Q42: 1 | S42: $ | T42: 65.61 | V42: A- | Y42: Yes | Z42: Industrial Property Trust | AA42: AREA Property Partners | AC42: No | AH42: 0 | AI42: 1 | AM42: 0.047 | AN42: 0.0481871 | AO42: 0.04791285 | AR42: Yes
B43: 2200 West San Bernardino Avenue | C43: 2200 West San Bernardino Avenue, Redlands, CA 92374 | D43: Redlands | E43: CA | F43: United States | G43: 92374 | H43: Industrial | I43: Warehouse | K43: No | L43: Inland Empire | M43: IE-East Redlands | N43: 425000 | O43: SF | P43: 42528 | Q43: 1 | R43: 37.5 | S43: $ | T43: 88.24 | V43: A- | Y43: Yes | Z43: Industrial Property Trust | AA43: AREA Property Partners | AC43: No | AF43: 24 | AH43: 0 | AI43: 1 | AM43: 0.047 | AN43: 0.0481871 | AO43: 0.04791285 | AR43: Yes
B44: CT Realty Southern California Industrial Portfolio | C44: 1333 South Tippecanoe Avenue, San Bernardino, CA 92408 | E44: CA | F44: United States | G44: 92408 | H44: Industrial | I44: Warehouse | K44: No | L44: Inland Empire | M44: IE-East Redlands | N44: 1427000 | O44: SF | P44: 42479 | Q44: 1 | S44: $ | T44: 143.1 | V44: A- | Y44: Yes | Z44: Rexford Industrial Realty (REXR) | AA44: CT Realty Investors | AC44: No | AE44: CBRE Group; Eastdil Secured | AH44: 0 | AM44: 0.047 | AN44: 0.0481871 | AO44: 0.04791285 | AR44: Yes
B45: 1333 South Tippecanoe Avenue | C45: 1333 South Tippecanoe Avenue, San Bernardino, CA 92408 | D45: San Bernardino | E45: CA | F45: United States | G45: 92408 | H45: Industrial | I45: Warehouse | K45: No | L45: Inland Empire | M45: IE-East Redlands | N45: 225000 | O45: SF | P45: 42479 | Q45: 1 | R45: 13.1 | S45: $ | T45: 58.22 | V45: A- | Y45: Yes | Z45: Rexford Industrial Realty (REXR) | AA45: CT Realty Investors | AC45: No | AE45: CBRE Group; Eastdil Secured | AF45: 19 | AH45: 0 | AM45: 0.047 | AN45: 0.0481871 | AO45: 0.04791285 | AR45: Yes
B46: 10444 Corporate Drive | C46: 10444 Corporate Drive, Redlands, CA 92374 | D46: Redlands | E46: CA | F46: United States | G46: 92374 | H46: Industrial | I46: Warehouse | K46: No | L46: Inland Empire | M46: IE-East Redlands | N46: 527000 | O46: SF | P46: 42361 | Q46: 1 | R46: 46.2 | S46: $ | T46: 87.67 | V46: A- | W46: 0.04662073 | X46: Green Street Market Estimate | Y46: No | Z46: TIAA | AA46: Oakmont Industrial Group | AC46: No | AE46: CBRE Group | AH46: 0 | AM46: 0.047 | AN46: 0.0481871 | AO46: 0.04791285 | AR46: Yes
B47: Redlands Business Center | C47: 2220 Almond Avenue, Redlands, CA 92374 | D47: Redlands | E47: CA | F47: United States | G47: 92374 | H47: Industrial | I47: Warehouse | K47: No | L47: Inland Empire | M47: IE-East Redlands | N47: 412000 | O47: SF | P47: 42353 | Q47: 1 | R47: 33.3 | S47: $ | T47: 80.83 | V47: A- | W47: 0.04662073 | X47: Green Street Market Estimate | Y47: No | Z47: Clarion Partners | AA47: Bixby Land Co. | AC47: No | AE47: JLL | AF47: 21 | AH47: 0 | AI47: 1 | AM47: 0.047 | AN47: 0.0481871 | AO47: 0.04791285 | AR47: Yes
B48: Hillwood Properties National Industrial Portfolio | C48: 5631 South Waterman Avenue, San Bernardino, CA 92408 | F48: United States | G48: 92408 | H48: Industrial | I48: Warehouse | K48: No | L48: Inland Empire | M48: IE-East Redlands | N48: 5933000 | O48: SF | P48: 41981 | Q48: 1 | S48: $ | T48: 56.35 | V48: A- | Y48: Yes | Z48: Clarion Partners | AA48: Hillwood Properties | AC48: No | AE48: CBRE Group | AH48: 0 | AM48: 0.047 | AN48: 0.0481871 | AO48: 0.04791285 | AR48: Yes
B49: AC Westgate | C49: 5631 South Waterman Avenue, San Bernardino, CA 92408 | D49: San Bernardino | E49: CA | F49: United States | G49: 92408 | H49: Industrial | I49: Warehouse | K49: No | L49: Inland Empire | M49: IE-East Redlands | N49: 346000 | O49: SF | P49: 41981 | Q49: 1 | V49: A- | Y49: Yes | Z49: Clarion Partners | AA49: Hillwood Properties | AC49: No | AE49: CBRE Group | AH49: 0 | AM49: 0.047 | AN49: 0.0481871 | AO49: 0.04791285 | AR49: Yes
B50: Redlands Corporate Center 1-3 | C50: 1251 Research Drive, Redlands, CA 92374 | D50: Redlands | E50: CA | F50: United States | G50: 92374 | H50: Industrial | I50: Warehouse | K50: No | L50: Inland Empire | M50: IE-East Redlands | N50: 404000 | O50: SF | P50: 41884 | Q50: 1 | R50: 27.5 | S50: $ | T50: 68.07 | V50: A- | W50: 0.04812073 | X50: Green Street Market Estimate | Y50: No | Z50: Stockbridge Capital Group | AA50: Pacific Coast Capital Partners | AC50: No | AE50: CBRE Group | AH50: 0 | AM50: 0.047 | AN50: 0.0481871 | AO50: 0.04791285 | AR50: Yes
B51: Redlands Industrial Centre | C51: East San Bernardino Avenue, Redlands, CA 92408 | D51: Redlands | E51: CA | F51: United States | G51: 92408 | H51: Industrial | I51: Warehouse | K51: No | L51: Inland Empire | M51: IE-East Redlands | N51: 586000 | O51: SF | P51: 41613 | Q51: 1 | R51: 39.3 | S51: $ | T51: 67.06 | V51: A- | W51: 0.05236506 | X51: Green Street Market Estimate | Y51: No | AA51: Kearny Real Estate | AC51: No | AE51: Colliers | AH51: 0 | AM51: 0.047 | AN51: 0.0481871 | AO51: 0.04791285 | AR51: Yes
B52: USAA Industrial Portfolio | C52: 2300 West San Bernardino Avenue, Redlands, CA 92374 | F52: United States | G52: 92374 | H52: Industrial | I52: Warehouse | K52: No | L52: Inland Empire | M52: IE-East Redlands | N52: 4839000 | O52: SF | P52: 41443 | Q52: 1 | S52: $ | T52: 64.27 | V52: A- | Y52: Yes | Z52: Duke Realty | AA52: USAA Real Estate | AC52: No | AE52: CBRE Group | AH52: 0 | AI52: 1 | AM52: 0.047 | AN52: 0.0481871 | AO52: 0.04791285 | AR52: Yes
B53: 2300 West San Bernardino Avenue | C53: 2300 West San Bernardino Avenue, Redlands, CA 92374 | D53: Redlands | E53: CA | F53: United States | G53: 92374 | H53: Industrial | I53: Warehouse | K53: No | L53: Inland Empire | M53: IE-East Redlands | N53: 575000 | O53: SF | P53: 41443 | Q53: 1 | V53: A- | Y53: Yes | Z53: Duke Realty | AA53: USAA Real Estate | AC53: No | AE53: CBRE Group | AF53: 36.894 | AH53: 0 | AI53: 1 | AM53: 0.047 | AN53: 0.0481871 | AO53: 0.04791285 | AR53: Yes
B54: 1601&1801 East Cooley Drive | C54: 1801 East Cooley Drive, Colton, CA 92324 | D54: Colton | E54: CA | F54: United States | G54: 92324 | H54: Industrial | I54: Warehouse | K54: No | L54: Inland Empire | M54: IE-East Redlands | N54: 439000 | O54: SF | P54: 39455 | Q54: 1 | R54: 25 | S54: $ | T54: 56.95 | V54: A- | W54: 0.05591191 | X54: Green Street Market Estimate | Y54: No | Z54: Overton Moore Properties | AC54: No | AE54: CBRE Group | AH54: 0 | AM54: 0.047 | AN54: 0.0481871 | AO54: 0.04791285 | AR54: Yes
B55: Silagi Development Los Angeles/Phoenix Area portfolio | C55: 1220 Research Drive, Redlands, CA 92374 | D55: Oxnard | E55: CA | F55: United States | G55: 92374 | H55: Office | I55: Warehouse | K55: No | L55: Inland Empire | M55: IE-East Redlands | N55: 2444000 | O55: SF | P55: 39322 | Q55: 1 | S55: $ | T55: 161.66 | V55: A- | Y55: Yes | Z55: Muller Co. | AA55: Silagi Development & Management | AC55: No | AE55: CBRE Group | AH55: 0 | AM55: 0.047 | AN55: 0.0481871 | AO55: 0.04791285 | AR55: Yes
B56: 1110-1135 | C56: 1220 Research Drive, Redlands, CA 92374 | D56: Redlands | E56: CA | F56: United States | G56: 92374 | H56: Industrial | I56: Warehouse | K56: No | L56: Inland Empire | M56: IE-East Redlands | N56: 400000 | O56: SF | P56: 39322 | Q56: 1 | V56: A- | Y56: Yes | Z56: Muller Co. | AA56: Silagi Development & Management | AC56: No | AE56: CBRE Group | AH56: 0 | AM56: 0.047 | AN56: 0.0481871 | AO56: 0.04791285 | AR56: Yes
B57: 9425 California Avenue | C57: 9425 California Street, Redlands, CA 92374 | D57: Redlands | E57: CA | F57: United States | G57: 92374 | H57: Industrial | I57: Warehouse | K57: No | L57: Inland Empire | M57: IE-East Redlands | N57: 784000 | O57: SF | P57: 39079 | Q57: 1 | R57: 54 | S57: $ | T57: 68.88 | V57: A- | W57: 0.05571152 | X57: Green Street Market Estimate | Y57: No | Z57: Lamps Plus | AA57: Trammell Crow Company | AC57: No | AE57: CBRE Group | AH57: 0 | AM57: 0.047 | AN57: 0.0481871 | AO57: 0.04791285 | AR57: Yes
B58: Redlands Industrial Centre | C58: 26682 Almond Avenue, Redlands, CA 92374 | D58: Redlands | E58: CA | F58: United States | G58: 92374 | H58: Industrial | I58: Warehouse | K58: No | L58: Inland Empire | M58: IE-East Redlands | N58: 584000 | O58: SF | P58: 39022 | Q58: 1 | R58: 39.5 | S58: $ | T58: 67.64 | V58: A- | W58: 0.05571152 | X58: Green Street Market Estimate | Y58: No | Z58: Kearny Street | AA58: Borstein Enterprises | AC58: No | AE58: CBRE Group | AH58: 0 | AM58: 0.047 | AN58: 0.0481871 | AO58: 0.04791285 | AR58: Yes
B59: 2300 West San Bernardino Avenue | C59: 2300 West San Bernardino Avenue, Redlands, CA 92374 | D59: Redlands | E59: CA | F59: United States | G59: 92374 | H59: Industrial | I59: Warehouse | K59: No | L59: Inland Empire | M59: IE-East Redlands | N59: 575000 | O59: SF | P59: 38508 | Q59: 1 | R59: 48.6 | S59: $ | T59: 84.52 | V59: A- | W59: 0.06236279 | X59: Green Street Market Estimate | Y59: No | Z59: CBRE Investment Management | AA59: USAA Real Estate | AC59: No | AE59: CBRE Group | AH59: 0 | AM59: 0.047 | AN59: 0.0481871 | AO59: 0.04791285 | AR59: Yes
B60: 1826 West 205th Street | C60: 1826 West 205th Street, Torrance, CA 90501 | D60: Torrance | E60: CA | F60: United States | G60: 90501 | H60: Industrial | I60: Warehouse | J60: Light Industrial | K60: No | L60: Los Angeles | M60: South Bay | N60: 29158 | O60: SF | P60: 45545 | Q60: 1 | R60: 12.85 | S60: $ | T60: 440.7 | V60: A++ | W60: 0.04042914 | X60: Green Street Market Estimate | Y60: No | Z60: Proficiency Capital | AC60: No | AF60: 1.48 | AG60: 1 | AI60: 1 | AJ60: 1978 | AM60: 0.042 | AN60: 0.04155327 | AO60: 0.04123507 | AR60: Yes
B61: 19020 Anelo Avenue | C61: 19020 Anelo Avenue, Gardena, CA 90248 | D61: Gardena | E61: CA | F61: United States | G61: 90248 | H61: Industrial | I61: Warehouse | J61: Light Industrial | K61: No | L61: Los Angeles | M61: South Bay | N61: 71407.9 | O61: SF | P61: 45478 | Q61: 1 | R61: 19.71 | S61: $ | T61: 276.03 | V61: A++ | W61: 0.04111685 | X61: Green Street Market Estimate | Y61: No | Z61: ABC Supply Co. Inc. | AA61: Carroll H. Shelby | AC61: No | AF61: 2.6982 | AG61: 1 | AI61: 1 | AJ61: 1959 | AM61: 0.042 | AN61: 0.04155327 | AO61: 0.04123507 | AR61: Yes
B62: 690-760 West 190th Street | C62: 690 West 190th Street, Gardena, CA 90248 | D62: Gardena | E62: CA | F62: United States | G62: 90248 | H62: Industrial | I62: Warehouse | J62: Park | K62: No | L62: Los Angeles | M62: South Bay | N62: 126015 | O62: SF | P62: 45251 | Q62: 1 | R62: 55 | S62: $ | T62: 436.46 | V62: A++ | W62: 0.03961462 | X62: Green Street Market Estimate | Y62: No | Z62: Evergen Equity; Harbor Associates | AA62: Gary Campbell | AC62: No | AE62: CBRE Group | AF62: 7.5 | AG62: 1 | AI62: 4 | AJ62: 1969 | AK62: 1974 | AM62: 0.042 | AN62: 0.04155327 | AO62: 0.04123507 | AR62: Yes
B63: 206 West 196th Street | C63: 206 West 196th Street, Torrance, CA 90502 | D63: Torrance | E63: CA | F63: United States | G63: 90502 | H63: Industrial | I63: Warehouse | J63: Light Industrial | K63: No | L63: Los Angeles | M63: South Bay | N63: 100254 | O63: SF | P63: 45245 | Q63: 1 | R63: 12.02 | S63: $ | T63: 119.92 | V63: A++ | W63: 0.03961462 | X63: Green Street Market Estimate | Y63: No | AA63: PACCAR Inc. | AC63: No | AE63: JLL | AF63: 2.3003 | AG63: 1 | AJ63: 1953 | AM63: 0.042 | AN63: 0.04155327 | AO63: 0.04123507 | AR63: Yes
B64: 21160 South Figueroa Street | C64: 21160 South Figueroa Street, Carson, CA 90745 | D64: Carson | E64: CA | F64: United States | G64: 90745 | H64: Industrial | I64: Warehouse | J64: Light Industrial | K64: No | L64: Los Angeles | M64: South Bay | N64: 27388 | O64: SF | P64: 45230 | Q64: 1 | R64: 11.55 | S64: $ | T64: 421.72 | V64: A++ | W64: 0.03826464 | X64: Green Street Market Estimate | Y64: No | AA64: Grace Lin | AC64: No | AF64: 0.8549 | AG64: 2 | AI64: 1 | AJ64: 2002 | AM64: 0.042 | AN64: 0.04155327 | AO64: 0.04123507 | AR64: Yes
B65: 18421 South Main Street | C65: 18421 South Main Street, Gardena, CA 90248 | D65: Gardena | E65: CA | F65: United States | G65: 90248 | H65: Industrial | I65: Warehouse | J65: Light Industrial | K65: No | L65: Los Angeles | M65: South Bay | N65: 53978 | O65: SF | P65: 45208 | Q65: 1 | R65: 20 | S65: $ | T65: 370.52 | V65: A++ | W65: 0.03826464 | X65: Green Street Market Estimate | Y65: No | Z65: AIDS Healthcare Foundation (AHF) | AA65: Shultz Properties | AC65: No | AD65: BRC Advisors | AE65: Kidder Mathews | AF65: 2.47 | AG65: 1 | AI65: 1 | AJ65: 2002 | AK65: 2020 | AM65: 0.042 | AN65: 0.04155327 | AO65: 0.04123507 | AR65: Yes
B66: 1580 Francisco Street | C66: 1580 Francisco Street, Torrance, CA 90501 | D66: Torrance | E66: CA | F66: United States | G66: 90501 | H66: Industrial | I66: Warehouse | J66: Light Industrial | K66: No | L66: Los Angeles | M66: South Bay | N66: 116433 | O66: SF | P66: 45147 | Q66: 1 | R66: 88 | S66: $ | T66: 755.8 | V66: A++ | W66: 0.02843792 | X66: Green Street Market Estimate | Y66: No | Z66: Prologis (PLD) | AA66: Blackstone Real Estate | AC66: No | AF66: 8.1352 | AG66: 2 | AJ66: 2000 | AM66: 0.042 | AN66: 0.04155327 | AO66: 0.04123507 | AR66: Yes
B67: 1115-1117 West 190th Street | C67: 1115 West 190th Street, Gardena, CA 90248 | D67: Gardena | E67: CA | F67: United States | G67: 90248 | H67: Industrial | I67: Flex Industrial | J67: Park | K67: No | L67: Los Angeles | M67: South Bay | N67: 11746 | O67: SF | P67: 45009 | Q67: 1 | R67: 5.5 | S67: $ | T67: 468.24 | V67: A++ | W67: 0.062 | X67: As Reported | Y67: No | AA67: Seppi Esfandi | AC67: No | AE67: CBRE Group | AF67: 0.4183 | AG67: 2 | AI67: 2 | AJ67: 1982 | AM67: 0.042 | AN67: 0.04155327 | AO67: 0.04123507 | AR67: Yes
B68: 555 West 189th Street | C68: 555 West 189th Street, Gardena, CA 90248 | D68: Gardena | E68: CA | F68: United States | G68: 90248 | H68: Industrial | I68: Warehouse | J68: Light Industrial | K68: No | L68: Los Angeles | M68: South Bay | N68: 34900 | O68: SF | P68: 45008 | Q68: 1 | R68: 18.3 | S68: $ | T68: 524.36 | V68: A++ | W68: 0.02943792 | X68: Green Street Market Estimate | Y68: No | Z68: Turnbridge Equities | AA68: Burke Real Estate Group | AC68: No | AF68: 2.49 | AJ68: 1959 | AM68: 0.042 | AN68: 0.04155327 | AO68: 0.04123507 | AR68: Yes
B69: 1210 Knox Street | C69: 1210 Knox Street, Torrance, CA 90502 | D69: Torrance | E69: CA | F69: United States | G69: 90502 | H69: Industrial | I69: Warehouse | J69: Light Industrial | K69: No | L69: Los Angeles | M69: South Bay | N69: 12000 | O69: SF | P69: 44958 | Q69: 1 | R69: 5.65 | S69: $ | T69: 471 | V69: A++ | W69: 0.02943792 | X69: Green Street Market Estimate | Y69: No | Z69: Premier Infusion Care | AA69: Universal Projects, Inc. | AC69: No | AF69: 0.681 | AG69: 1 | AI69: 1 | AJ69: 1973 | AM69: 0.042 | AN69: 0.04155327 | AO69: 0.04123507 | AR69: Yes
B70: 1355-1361 West 190th Street | C70: 1355 West 190th Street, Gardena, CA 90248 | D70: Gardena | E70: CA | F70: United States | G70: 90248 | H70: Industrial | I70: Warehouse | J70: Park | K70: No | L70: Los Angeles | M70: South Bay | N70: 92640 | O70: SF | P70: 44949 | Q70: 1 | R70: 22.7 | S70: $ | T70: 245.03 | V70: A++ | W70: 0.0428 | X70: As Reported | Y70: No | Z70: Dunbar Real Estate Investment Management | AA70: Altemus Company | AC70: No | AD70: DAUM Commercial | AF70: 3.7 | AG70: 1 | AI70: 2 | AJ70: 1971 | AM70: 0.042 | AN70: 0.04155327 | AO70: 0.04123507 | AP70: EquiTrust Life Insurance Company | AQ70: 10000000 | AR70: Yes
B71: IDI Logistics CA Industrial Portfolio | C71: 19145 Gramercy Place, Torrance, CA 90501 | E71: CA | F71: United States | G71: 90501 | H71: Industrial | I71: Warehouse | J71: Bulk Distribution | K71: No | L71: Los Angeles | M71: South Bay | N71: 511379 | O71: SF | P71: 44922 | Q71: 1 | S71: $ | T71: 387.29 | V71: A++ | W71: 0.051 | X71: As Reported | Y71: Yes | Z71: Rexford Industrial Realty (REXR) | AA71: IDI Logistics | AC71: No | AE71: CBRE Group | AJ71: 1982 | AK71: 1983 | AL71: 1 | AM71: 0.042 | AN71: 0.04155327 | AO71: 0.04123507 | AR71: Yes
B72: 19145 Gramercy Place | C72: 19145 Gramercy Place, Torrance, CA 90501 | D72: Torrance | E72: CA | F72: United States | G72: 90501 | H72: Industrial | I72: Warehouse | J72: Bulk Distribution | K72: No | L72: Los Angeles | M72: South Bay | N72: 102143 | O72: SF | P72: 44922 | Q72: 1 | R72: 37 | S72: $ | T72: 362.24 | V72: A++ | W72: 0.051 | X72: As Reported | Y72: Yes | Z72: Rexford Industrial Realty (REXR) | AA72: IDI Logistics | AC72: No | AE72: CBRE Group | AJ72: 1982 | AK72: 1983 | AL72: 1 | AM72: 0.042 | AN72: 0.04155327 | AO72: 0.04123507 | AR72: Yes
B73: 21022-21034 South Figueroa Street | C73: 21022 South Figueroa Street, Carson, CA 90745 | D73: Carson | E73: CA | F73: United States | G73: 90745 | H73: Industrial | I73: Warehouse | K73: No | L73: Los Angeles | M73: South Bay | N73: 51185 | O73: SF | P73: 44812 | Q73: 1 | R73: 24.2 | S73: $ | T73: 472.79 | V73: A++ | W73: 0.02743792 | X73: Green Street Market Estimate | Y73: No | Z73: Rexford Industrial Realty (REXR) | AA73: Jobar International, Inc. | AC73: No | AJ73: 2002 | AM73: 0.042 | AN73: 0.04155327 | AO73: 0.04123507 | AR73: Yes
B74: 20900 Normandie Avenue | C74: 20900 South Normandie Avenue, Torrance, CA 90502 | D74: Torrance | E74: CA | F74: United States | G74: 90502 | H74: Industrial | I74: Warehouse | K74: No | L74: Los Angeles | M74: South Bay | N74: 74038 | O74: SF | P74: 44714 | Q74: 1 | R74: 39.98 | S74: $ | T74: 539.99 | V74: A++ | W74: 0.02843792 | X74: Green Street Market Estimate | Y74: No | Z74: Rexford Industrial Realty (REXR) | AA74: Marcus Adams Properties LLC | AC74: No | AE74: Newmark Group | AH74: 0 | AJ74: 2001 | AL74: 1 | AM74: 0.042 | AN74: 0.04155327 | AO74: 0.04123507 | AR74: Yes
B75: 19475 Gramercy Place | C75: 19475 Gramercy Place, Torrance, CA 90501 | D75: Torrance | E75: CA | F75: United States | G75: 90501 | H75: Industrial | I75: Warehouse | K75: No | L75: Los Angeles | M75: South Bay | N75: 47712 | O75: SF | P75: 44601 | Q75: 1 | R75: 11.3 | S75: $ | T75: 236.84 | V75: A++ | W75: 0.02593792 | X75: Green Street Market Estimate | Y75: No | Z75: Rexford Industrial Realty (REXR) | AC75: No | AH75: 0 | AJ75: 1982 | AM75: 0.042 | AN75: 0.04155327 | AO75: 0.04123507 | AR75: Yes
B76: 19875 Pacific Gateway Drive | C76: 19875 Pacific Gateway Drive, Torrance, CA 90502 | D76: Torrance | E76: CA | F76: United States | G76: 90502 | H76: Industrial | I76: Warehouse | K76: No | L76: Los Angeles | M76: South Bay | N76: 65998 | O76: SF | P76: 44537 | Q76: 1 | R76: 51.53 | S76: $ | T76: 780.71 | V76: A++ | W76: 0.02493792 | X76: Green Street Market Estimate | Y76: No | Z76: CenterPoint Properties | AC76: No | AH76: 0 | AJ76: 1990 | AM76: 0.042 | AN76: 0.04155327 | AO76: 0.04123507 | AR76: Yes
B77: 1972 Del Amo Boulevard | C77: 1972 Del Amo Boulevard, Torrance, CA 90501 | D77: Torrance | E77: CA | F77: United States | G77: 90501 | H77: Industrial | I77: Warehouse | K77: No | L77: Los Angeles | M77: South Bay | N77: 20000 | O77: SF | P77: 44433 | Q77: 1 | R77: 5.93 | S77: $ | T77: 296.56 | V77: A++ | W77: 0.02593792 | X77: Green Street Market Estimate | Y77: No | AC77: No | AD77: Newmark Group | AE77: Newmark Group | AH77: 0 | AM77: 0.042 | AN77: 0.04155327 | AO77: 0.04123507 | AR77: Yes
B78: 2700 California Street | C78: 2700 California Street, Torrance, CA 90503 | D78: Torrance | E78: CA | F78: United States | G78: 90503 | H78: Industrial | I78: Warehouse | K78: No | L78: Los Angeles | M78: South Bay | N78: 135000 | O78: SF | P78: 44376 | Q78: 1 | R78: 34.5 | S78: $ | T78: 255.56 | V78: A++ | W78: 0.045 | X78: As Reported | Y78: No | Z78: Bain Capital Real Estate; Staley Point Capital | AA78: Edelbrock LLC | AC78: No | AE78: CBRE Group | AH78: 0 | AM78: 0.042 | AN78: 0.04155327 | AO78: 0.04123507 | AR78: Yes
B79: 20405 Gramercy Place | C79: 20405 Gramercy Place, Torrance, CA 90501 | D79: Torrance | E79: CA | F79: United States | G79: 90501 | H79: Industrial | I79: Warehouse | J79: Light Industrial | K79: No | L79: Los Angeles | M79: South Bay | N79: 16899 | O79: SF | P79: 44328 | Q79: 1 | R79: 6.29 | S79: $ | T79: 372.21 | V79: A++ | W79: 0.047 | X79: As Reported | Y79: No | Z79: Terreno Realty Corp. (TRNO) | AC79: No | AE79: Newmark Group | AF79: 1.21 | AG79: 2 | AH79: 0 | AJ79: 1980 | AM79: 0.042 | AN79: 0.04155327 | AO79: 0.04123507 | AR79: Yes
B80: Dedeaux Los Angeles Area Industrial Portfolio | C80: 711 Knox Street, Gardena, CA 90248 | E80: CA | F80: United States | G80: 90248 | H80: Industrial | I80: Warehouse | K80: No | L80: Los Angeles | M80: South Bay | N80: 1335436 | O80: SF | P80: 44119 | Q80: 0.95 | S80: $ | T80: 177.43 | V80: A++ | Y80: Yes | Z80: Stockbridge Capital Group | AA80: Dedeaux Properties | AC80: No | AE80: Eastdil Secured | AH80: 0 | AM80: 0.042 | AN80: 0.04155327 | AO80: 0.04123507 | AR80: Yes
B81: 711 Knox Street | C81: 711 Knox Street, Gardena, CA 90248 | D81: Gardena | E81: CA | F81: United States | G81: 90248 | H81: Industrial | I81: Warehouse | K81: No | L81: Los Angeles | M81: South Bay | N81: 40000 | O81: SF | P81: 44119 | Q81: 0.95 | V81: A++ | Y81: Yes | Z81: Stockbridge Capital Group | AA81: Dedeaux Properties | AC81: No | AE81: Eastdil Secured | AH81: 0 | AM81: 0.042 | AN81: 0.04155327 | AO81: 0.04123507 | AR81: Yes
B82: 1451 Knox Street | C82: 1451 West Knox Street, Torrance, CA 90501 | D82: Torrance | E82: CA | F82: United States | G82: 90501 | H82: Industrial | I82: Warehouse | K82: No | L82: Los Angeles | M82: South Bay | N82: 153000 | O82: SF | P82: 44042 | Q82: 1 | R82: 44.23 | S82: $ | T82: 289.08 | V82: A++ | W82: 0.03443792 | X82: Green Street Market Estimate | Y82: No | AA82: Boeing Co. | AC82: No | AE82: Cushman & Wakefield | AH82: 0 | AM82: 0.042 | AN82: 0.04155327 | AO82: 0.04123507 | AR82: Yes
B83: Gateway Logistics Center | C83: 538 Crenshaw Boulevard, Torrance, CA 90503 | D83: Torrance | E83: CA | F83: United States | G83: 90503 | H83: Industrial | I83: Warehouse | K83: No | L83: Los Angeles | M83: South Bay | N83: 174000 | O83: SF | P83: 43962 | Q83: 1 | R83: 49.5 | S83: $ | T83: 284.48 | V83: A++ | W83: 0.03643792 | X83: Green Street Market Estimate | Y83: No | Z83: Black Creek Group | AC83: No | AE83: Lee & Associates | AH83: 0 | AM83: 0.042 | AN83: 0.04155327 | AO83: 0.04123507 | AR83: Yes
B84: 2665 Columbia Street | C84: 2665 Columbia Street, Torrance, CA 90503 | D84: Torrance | E84: CA | F84: United States | G84: 90503 | H84: Industrial | I84: Warehouse | K84: No | L84: Los Angeles | M84: South Bay | N84: 61000 | O84: SF | P84: 43776 | Q84: 1 | R84: 10.2 | S84: $ | T84: 167.21 | V84: A++ | W84: 0.03443792 | X84: Green Street Market Estimate | Y84: No | Z84: CenterPoint Properties | AC84: No | AE84: CBRE Group | AH84: 0 | AJ84: 1965 | AM84: 0.042 | AN84: 0.04155327 | AO84: 0.04123507 | AR84: Yes
B85: 20917 Higgins Court | C85: 20917 Higgins Court, Torrance, CA 90501 | D85: Torrance | E85: CA | F85: United States | G85: 90501 | H85: Industrial | I85: Warehouse | K85: No | L85: Los Angeles | M85: South Bay | N85: 31000 | O85: SF | P85: 43709 | Q85: 1 | R85: 8.5 | S85: $ | T85: 274.19 | V85: A++ | W85: 0.03593792 | X85: Green Street Market Estimate | Y85: No | AC85: No | AD85: Newmark Group | AE85: (None) | AG85: 1 | AH85: 0 | AJ85: 1998 | AM85: 0.042 | AN85: 0.04155327 | AO85: 0.04123507 | AR85: Yes
B86: 20210 South Normandie Avenue | C86: 20210 Normandie Avenue, Torrance, CA 90502 | D86: Torrance | E86: CA | F86: United States | G86: 90502 | H86: Industrial | I86: Warehouse | K86: No | L86: Los Angeles | M86: South Bay | N86: 79000 | O86: SF | P86: 43544 | Q86: 1 | R86: 16.65 | S86: $ | T86: 210.76 | V86: A++ | W86: 0.03743792 | X86: Green Street Market Estimate | Y86: No | Z86: Gramercy Property Trust | AA86: Pacifica Capital Group | AC86: No | AE86: Colliers | AH86: 0 | AM86: 0.042 | AN86: 0.04155327 | AO86: 0.04123507 | AR86: Yes
B87: Bridge Point South Bay | C87: 20333 Normandie Avenue, Torrance, CA 90502 | D87: Torrance | E87: CA | F87: United States | G87: 90502 | H87: Industrial | I87: Warehouse | K87: No | L87: Los Angeles | M87: South Bay | N87: 512000 | O87: SF | P87: 43213 | Q87: 1 | R87: 102.5 | S87: $ | T87: 200.2 | V87: A++ | W87: 0.03743792 | X87: Green Street Market Estimate | Y87: No | Z87: Morgan Stanley Real Estate | AA87: Bridge Development Partners | AC87: No | AE87: Cushman & Wakefield | AH87: 0 | AM87: 0.042 | AN87: 0.04155327 | AO87: 0.04123507 | AR87: Yes
B88: 19801 South Vermont Avenue | C88: 19801 South Vermont Avenue, Torrance, CA 90502 | D88: Torrance | E88: CA | F88: United States | G88: 90502 | H88: Industrial | I88: Warehouse | K88: No | L88: Los Angeles | M88: South Bay | N88: 98660 | O88: SF | P88: 43131 | Q88: 1 | R88: 17.5 | S88: $ | T88: 177.38 | V88: A++ | W88: 0.03893792 | X88: Green Street Market Estimate | Y88: No | Z88: Terreno Realty Corp. (TRNO) | AC88: No | AH88: 0 | AJ88: 1978 | AM88: 0.042 | AN88: 0.04155327 | AO88: 0.04123507 | AR88: Yes
B89: 20333 South Normandie Avenue | C89: 20333 Normandie Avenue, Torrance, CA 90502 | D89: Torrance | E89: CA | F89: United States | G89: 90502 | H89: Industrial | I89: Warehouse | K89: No | L89: Los Angeles | M89: South Bay | N89: 665000 | O89: SF | P89: 42566 | Q89: 1 | R89: 43 | S89: $ | T89: 64.66 | V89: A++ | W89: 0.04193792 | X89: Green Street Market Estimate | Y89: No | Z89: Bridge Development Partners | AC89: No | AE89: Cushman & Wakefield | AH89: 0 | AM89: 0.042 | AN89: 0.04155327 | AO89: 0.04123507 | AR89: Yes
B90: 588 Crenshaw Boulevard | C90: 588 Crenshaw Boulevard, Torrance, CA 90503 | D90: Torrance | E90: CA | F90: United States | G90: 90503 | H90: Industrial | I90: Warehouse | K90: No | L90: Los Angeles | M90: South Bay | N90: 133000 | O90: SF | P90: 41520 | Q90: 1 | R90: 33.6 | S90: $ | T90: 252.63 | V90: A++ | W90: 0.04426229 | X90: Green Street Market Estimate | Y90: No | Z90: IIT Acquisitions | AC90: No | AE90: CBRE Group | AH90: 0 | AM90: 0.042 | AN90: 0.04155327 | AO90: 0.04123507 | AR90: Yes
B91: 4000-4100 West 190th Street | C91: 4000 West 190th Street, Torrance, CA 90504 | D91: Torrance | E91: CA | F91: United States | G91: 90504 | H91: Industrial | I91: Warehouse | K91: No | L91: Los Angeles | M91: South Bay | N91: 363000 | O91: SF | P91: 40801 | Q91: 1 | R91: 44.4 | S91: $ | T91: 122.31 | V91: A++ | W91: 0.05009619 | X91: Green Street Market Estimate | Y91: No | Z91: California Public Employees' Retirement System | AA91: HDG Mansur | AC91: No | AE91: JLL | AH91: 0 | AM91: 0.042 | AN91: 0.04155327 | AO91: 0.04123507 | AR91: Yes
B92: 20000 South Western Avenue | C92: 20000 South Western Avenue, Torrance, CA 90501 | D92: Torrance | E92: CA | F92: United States | G92: 90501 | H92: Industrial | I92: Warehouse | K92: No | L92: Los Angeles | M92: South Bay | N92: 434000 | O92: SF | P92: 39142 | Q92: 1 | R92: 81.82 | S92: $ | T92: 188.52 | V92: A++ | W92: 0.04773711 | X92: Green Street Market Estimate | Y92: No | Z92: AMB Property Corp. | AA92: Danat Investment Co. | AC92: No | AH92: 0 | AM92: 0.042 | AN92: 0.04155327 | AO92: 0.04123507 | AR92: Yes
B93: Prentiss Properties portfolio | C93: 19780 Pacific Gateway Drive, Torrance, CA 90502 | D93: Torrance | E93: CA | F93: United States | G93: 90502 | H93: Industrial | I93: Warehouse | K93: No | L93: Los Angeles | M93: South Bay | N93: 4324000 | O93: SF | P93: 38718 | Q93: 1 | S93: $ | T93: 172.92 | V93: A++ | Y93: Yes | Z93: PGIM Real Estate | AA93: Prentiss Properties Trust | AC93: No | AE93: Lazard Freres | AH93: 0 | AM93: 0.042 | AN93: 0.04155327 | AO93: 0.04123507 | AR93: Yes
B94: Pacific Gateway Center | C94: 19780 Pacific Gateway Drive, Torrance, CA 90502 | D94: Torrance | E94: CA | F94: United States | G94: 90502 | H94: Industrial | I94: Warehouse | K94: No | L94: Los Angeles | M94: South Bay | N94: 1253000 | O94: SF | P94: 38718 | Q94: 1 | V94: A++ | Y94: Yes | Z94: PGIM Real Estate | AA94: Prentiss Properties Trust | AC94: No | AE94: Lazard Freres | AH94: 0 | AM94: 0.042 | AN94: 0.04155327 | AO94: 0.04123507 | AR94: Yes
B95: Starboard Distribution Center | C95: 2027 Harpers Way, Torrance, CA 90501 | D95: Torrance | E95: CA | F95: United States | G95: 90501 | H95: Industrial | I95: Warehouse | K95: No | L95: Los Angeles | M95: South Bay | N95: 559000 | O95: SF | P95: 38508 | Q95: 1 | R95: 38.7 | S95: $ | T95: 69.23 | V95: A++ | W95: 0.05351834 | X95: Green Street Market Estimate | Y95: No | Z95: AMB Property Corp. | AA95: FHL Group | AC95: No | AH95: 0 | AM95: 0.042 | AN95: 0.04155327 | AO95: 0.04123507 | AR95: Yes
B96: Harbor Gateway Industrial Center | C96: 19400 Harborgate Way, Torrance, CA 90501 | D96: Torrance | E96: CA | F96: United States | G96: 90501 | H96: Industrial | I96: Warehouse | K96: No | L96: Los Angeles | M96: South Bay | N96: 860000 | O96: SF | P96: 38231 | Q96: 1 | R96: 65 | S96: $ | T96: 75.58 | V96: A++ | Y96: No | Z96: Sunrider International | AA96: Deutsche Asset Management; Fremont Development | AC96: No | AE96: CBRE Group | AH96: 0 | AJ96: 2000 | AM96: 0.042 | AN96: 0.04155327 | AO96: 0.04123507 | AR96: Yes
