Workbook
Name analysis_start: #REF!
Name analysis_start: 'Redlands Inputs'!$D$14
Name market_rent: #REF!
Name market_rent: 'Redlands Inputs'!$D$25

Sheet Annual Projections
C1: year 1-5 | D1: year 6-10
A2: Market Rent Inflation | C2: 0.03 | D2: 0.022
A3: Expense Inflation | C3: 0.025
A4: Cash Flow Projections
A5: Redlands Industrial Property
B7: Actuals | C7: Forecast | D7: Forecast | E7: Forecast | F7: Forecast | G7: Forecast | H7: Forecast | I7: Forecast | J7: Forecast | K7: Forecast | L7: Forecast | M7: Forecast
B8: =ROUNDUP(B$9/12,0) -> 0 | C8: 1 | D8: =C8+1 -> 2 | E8: =D8+1 -> 3 | F8: =E8+1 -> 4 | G8: =F8+1 -> 5 | H8: =G8+1 -> 6 | I8: =H8+1 -> 7 | J8: =I8+1 -> 8 | K8: =J8+1 -> 9 | ... M8: =L8+1 -> 11
A10: Months | B10: =EOMONTH(C10,-12) -> 45322 | C10: =EOMONTH('Redlands Inputs'!D14,0) -> 45688 | D10: =EOMONTH(C10,12) -> 46053 | E10: =EOMONTH(D10,12) -> 46418 | F10: =EOMONTH(E10,12) -> 46783 | G10: =EOMONTH(F10,12) -> 47149 | H10: =EOMONTH(G10,12) -> 47514 | I10: =EOMONTH(H10,12) -> 47879 | J10: =EOMONTH(I10,12) -> 48244 | K10: =EOMONTH(J10,12) -> 48610 | ... M10: =EOMONTH(L10,12) -> 49340
A12: Rental Revenue
A13: Base Rent / SF | B13: =SUMIF('Redlands Pro Forma'!$B$8:$ED$8,'Annual Projections'!B$8,'Redlands Pro Forma'!$B13:$ED13) -> 0 | C13: =SUMIF('Redlands Pro Forma'!$B$8:$ED$8,'Annual Projections'!C$8,'Redlands Pro Forma'!$B13:$ED13) -> 77.997314 | D13: =SUMIF('Redlands Pro Forma'!$B$8:$ED$8,'Annual Projections'!D$8,'Redlands Pro Forma'!$B13:$ED13) -> 79.55726 | E13: =SUMIF('Redlands Pro Forma'!$B$8:$ED$8,'Annual Projections'!E$8,'Redlands Pro Forma'!$B13:$ED13) -> 81.148406 | F13: =SUMIF('Redlands Pro Forma'!$B$8:$ED$8,'Annual Projections'!F$8,'Redlands Pro Forma'!$B13:$ED13) -> 82.771374 | G13: =SUMIF('Redlands Pro Forma'!$B$8:$ED$8,'Annual Projections'!G$8,'Redlands Pro Forma'!$B13:$ED13) -> 84.426801 | H13: =SUMIF('Redlands Pro Forma'!$B$8:$ED$8,'Annual Projections'!H$8,'Redlands Pro Forma'!$B13:$ED13) -> 86.115337 | I13: =SUMIF('Redlands Pro Forma'!$B$8:$ED$8,'Annual Projections'!I$8,'Redlands Pro Forma'!$B13:$ED13) -> 87.837644 | ... M13: =SUMIF('Redlands Pro Forma'!$B$8:$ED$8,'Annual Projections'!M$8,'Redlands Pro Forma'!$B13:$ED13) -> 138.24913
A14: Potential Base Rent | B14: =SUMIF('Redlands Pro Forma'!$B$8:$ED$8,'Annual Projections'!B$8,'Redlands Pro Forma'!$B14:$ED14) -> 0 | C14: =SUMIF('Redlands Pro Forma'!$B$8:$ED$8,'Annual Projections'!C$8,'Redlands Pro Forma'!$B14:$ED14) -> 3899865.7 | D14: =SUMIF('Redlands Pro Forma'!$B$8:$ED$8,'Annual Projections'!D$8,'Redlands Pro Forma'!$B14:$ED14) -> 3977863 | E14: =SUMIF('Redlands Pro Forma'!$B$8:$ED$8,'Annual Projections'!E$8,'Redlands Pro Forma'!$B14:$ED14) -> 4057420.3 | F14: =SUMIF('Redlands Pro Forma'!$B$8:$ED$8,'Annual Projections'!F$8,'Redlands Pro Forma'!$B14:$ED14) -> 4138568.7 | G14: =SUMIF('Redlands Pro Forma'!$B$8:$ED$8,'Annual Projections'!G$8,'Redlands Pro Forma'!$B14:$ED14) -> 4221340.1 | H14: =SUMIF('Redlands Pro Forma'!$B$8:$ED$8,'Annual Projections'!H$8,'Redlands Pro Forma'!$B14:$ED14) -> 4305766.9 | I14: =SUMIF('Redlands Pro Forma'!$B$8:$ED$8,'Annual Projections'!I$8,'Redlands Pro Forma'!$B14:$ED14) -> 4391882.2 | ... M14: =SUMIF('Redlands Pro Forma'!$B$8:$ED$8,'Annual Projections'!M$8,'Redlands Pro Forma'!$B14:$ED14) -> 6912456.5
A15: Vacancy & Turnover | C15: =SUMIF('Redlands Pro Forma'!$B$8:$ED$8,'Annual Projections'!C$8,'Redlands Pro Forma'!$B15:$ED15) -> 0 | D15: =SUMIF('Redlands Pro Forma'!$B$8:$ED$8,'Annual Projections'!D$8,'Redlands Pro Forma'!$B15:$ED15) -> 0 | E15: =SUMIF('Redlands Pro Forma'!$B$8:$ED$8,'Annual Projections'!E$8,'Redlands Pro Forma'!$B15:$ED15) -> 0 | F15: =SUMIF('Redlands Pro Forma'!$B$8:$ED$8,'Annual Projections'!F$8,'Redlands Pro Forma'!$B15:$ED15) -> 0 | G15: =SUMIF('Redlands Pro Forma'!$B$8:$ED$8,'Annual Projections'!G$8,'Redlands Pro Forma'!$B15:$ED15) -> 0 | H15: =SUMIF('Redlands Pro Forma'!$B$8:$ED$8,'Annual Projections'!H$8,'Redlands Pro Forma'!$B15:$ED15) -> 0 | I15: =SUMIF('Redlands Pro Forma'!$B$8:$ED$8,'Annual Projections'!I$8,'Redlands Pro Forma'!$B15:$ED15) -> 0 | J15: =SUMIF('Redlands Pro Forma'!$B$8:$ED$8,'Annual Projections'!J$8,'Redlands Pro Forma'!$B15:$ED15) -> 0 | ... M15: =SUMIF('Redlands Pro Forma'!$B$8:$ED$8,'Annual Projections'!M$8,'Redlands Pro Forma'!$B15:$ED15) -> 0
A16: Free Rent / Concessions | C16: =SUMIF('Redlands Pro Forma'!$B$8:$ED$8,'Annual Projections'!C$8,'Redlands Pro Forma'!$B16:$ED16) -> 0 | D16: =SUMIF('Redlands Pro Forma'!$B$8:$ED$8,'Annual Projections'!D$8,'Redlands Pro Forma'!$B16:$ED16) -> 0 | E16: =SUMIF('Redlands Pro Forma'!$B$8:$ED$8,'Annual Projections'!E$8,'Redlands Pro Forma'!$B16:$ED16) -> 0 | F16: =SUMIF('Redlands Pro Forma'!$B$8:$ED$8,'Annual Projections'!F$8,'Redlands Pro Forma'!$B16:$ED16) -> 0 | G16: =SUMIF('Redlands Pro Forma'!$B$8:$ED$8,'Annual Projections'!G$8,'Redlands Pro Forma'!$B16:$ED16) -> 0 | H16: =SUMIF('Redlands Pro Forma'!$B$8:$ED$8,'Annual Projections'!H$8,'Redlands Pro Forma'!$B16:$ED16) -> 0 | I16: =SUMIF('Redlands Pro Forma'!$B$8:$ED$8,'Annual Projections'!I$8,'Redlands Pro Forma'!$B16:$ED16) -> 0 | J16: =SUMIF('Redlands Pro Forma'!$B$8:$ED$8,'Annual Projections'!J$8,'Redlands Pro Forma'!$B16:$ED16) -> 0 | ... M16: =SUMIF('Redlands Pro Forma'!$B$8:$ED$8,'Annual Projections'!M$8,'Redlands Pro Forma'!$B16:$ED16) -> 0
A17: Total Base Rent | C17: =SUMIF('Redlands Pro Forma'!$B$8:$ED$8,'Annual Projections'!C$8,'Redlands Pro Forma'!$B17:$ED17) -> 3899865.7 | D17: =SUMIF('Redlands Pro Forma'!$B$8:$ED$8,'Annual Projections'!D$8,'Redlands Pro Forma'!$B17:$ED17) -> 3977863 | E17: =SUMIF('Redlands Pro Forma'!$B$8:$ED$8,'Annual Projections'!E$8,'Redlands Pro Forma'!$B17:$ED17) -> 4057420.3 | F17: =SUMIF('Redlands Pro Forma'!$B$8:$ED$8,'Annual Projections'!F$8,'Redlands Pro Forma'!$B17:$ED17) -> 4138568.7 | G17: =SUMIF('Redlands Pro Forma'!$B$8:$ED$8,'Annual Projections'!G$8,'Redlands Pro Forma'!$B17:$ED17) -> 4221340.1 | H17: =SUMIF('Redlands Pro Forma'!$B$8:$ED$8,'Annual Projections'!H$8,'Redlands Pro Forma'!$B17:$ED17) -> 4305766.9 | I17: =SUMIF('Redlands Pro Forma'!$B$8:$ED$8,'Annual Projections'!I$8,'Redlands Pro Forma'!$B17:$ED17) -> 4391882.2 | J17: =SUMIF('Redlands Pro Forma'!$B$8:$ED$8,'Annual Projections'!J$8,'Redlands Pro Forma'!$B17:$ED17) -> 6257304.5 | ... M17: =SUMIF('Redlands Pro Forma'!$B$8:$ED$8,'Annual Projections'!M$8,'Redlands Pro Forma'!$B17:$ED17) -> 6912456.5
A18: Total Rental Revenue | C18: =SUMIF('Redlands Pro Forma'!$B$8:$ED$8,'Annual Projections'!C$8,'Redlands Pro Forma'!$B18:$ED18) -> 3899865.7 | D18: =SUMIF('Redlands Pro Forma'!$B$8:$ED$8,'Annual Projections'!D$8,'Redlands Pro Forma'!$B18:$ED18) -> 3977863 | E18: =SUMIF('Redlands Pro Forma'!$B$8:$ED$8,'Annual Projections'!E$8,'Redlands Pro Forma'!$B18:$ED18) -> 4057420.3 | F18: =SUMIF('Redlands Pro Forma'!$B$8:$ED$8,'Annual Projections'!F$8,'Redlands Pro Forma'!$B18:$ED18) -> 4138568.7 | G18: =SUMIF('Redlands Pro Forma'!$B$8:$ED$8,'Annual Projections'!G$8,'Redlands Pro Forma'!$B18:$ED18) -> 4221340.1 | H18: =SUMIF('Redlands Pro Forma'!$B$8:$ED$8,'Annual Projections'!H$8,'Redlands Pro Forma'!$B18:$ED18) -> 4305766.9 | I18: =SUMIF('Redlands Pro Forma'!$B$8:$ED$8,'Annual Projections'!I$8,'Redlands Pro Forma'!$B18:$ED18) -> 4391882.2 | J18: =SUMIF('Redlands Pro Forma'!$B$8:$ED$8,'Annual Projections'!J$8,'Redlands Pro Forma'!$B18:$ED18) -> 6257304.5 | ... M18: =SUMIF('Redlands Pro Forma'!$B$8:$ED$8,'Annual Projections'!M$8,'Redlands Pro Forma'!$B18:$ED18) -> 6912456.5
A20: Other Tenant Revenue
A21: Utilities | C21: =SUMIF('Redlands Pro Forma'!$B$8:$ED$8,'Annual Projections'!C$8,'Redlands Pro Forma'!$B21:$ED21) -> 45000 | D21: =SUMIF('Redlands Pro Forma'!$B$8:$ED$8,'Annual Projections'!D$8,'Redlands Pro Forma'!$B21:$ED21) -> 45000 | E21: =SUMIF('Redlands Pro Forma'!$B$8:$ED$8,'Annual Projections'!E$8,'Redlands Pro Forma'!$B21:$ED21) -> 45000 | F21: =SUMIF('Redlands Pro Forma'!$B$8:$ED$8,'Annual Projections'!F$8,'Redlands Pro Forma'!$B21:$ED21) -> 45000 | G21: =SUMIF('Redlands Pro Forma'!$B$8:$ED$8,'Annual Projections'!G$8,'Redlands Pro Forma'!$B21:$ED21) -> 45000 | H21: =SUMIF('Redlands Pro Forma'!$B$8:$ED$8,'Annual Projections'!H$8,'Redlands Pro Forma'!$B21:$ED21) -> 45000 | I21: =SUMIF('Redlands Pro Forma'!$B$8:$ED$8,'Annual Projections'!I$8,'Redlands Pro Forma'!$B21:$ED21) -> 45000 | J21: =SUMIF('Redlands Pro Forma'!$B$8:$ED$8,'Annual Projections'!J$8,'Redlands Pro Forma'!$B21:$ED21) -> 45000 | ... M21: =SUMIF('Redlands Pro Forma'!$B$8:$ED$8,'Annual Projections'!M$8,'Redlands Pro Forma'!$B21:$ED21) -> 45000
A22: Repairs & Maintenance | C22: =SUMIF('Redlands Pro Forma'!$B$8:$ED$8,'Annual Projections'!C$8,'Redlands Pro Forma'!$B22:$ED22) -> 45000 | D22: =SUMIF('Redlands Pro Forma'!$B$8:$ED$8,'Annual Projections'!D$8,'Redlands Pro Forma'!$B22:$ED22) -> 45000 | E22: =SUMIF('Redlands Pro Forma'!$B$8:$ED$8,'Annual Projections'!E$8,'Redlands Pro Forma'!$B22:$ED22) -> 45000 | F22: =SUMIF('Redlands Pro Forma'!$B$8:$ED$8,'Annual Projections'!F$8,'Redlands Pro Forma'!$B22:$ED22) -> 45000 | G22: =SUMIF('Redlands Pro Forma'!$B$8:$ED$8,'Annual Projections'!G$8,'Redlands Pro Forma'!$B22:$ED22) -> 45000 | H22: =SUMIF('Redlands Pro Forma'!$B$8:$ED$8,'Annual Projections'!H$8,'Redlands Pro Forma'!$B22:$ED22) -> 45000 | I22: =SUMIF('Redlands Pro Forma'!$B$8:$ED$8,'Annual Projections'!I$8,'Redlands Pro Forma'!$B22:$ED22) -> 45000 | J22: =SUMIF('Redlands Pro Forma'!$B$8:$ED$8,'Annual Projections'!J$8,'Redlands Pro Forma'!$B22:$ED22) -> 45000 | ... M22: =SUMIF('Redlands Pro Forma'!$B$8:$ED$8,'Annual Projections'!M$8,'Redlands Pro Forma'!$B22:$ED22) -> 45000
A23: Insurance | C23: =SUMIF('Redlands Pro Forma'!$B$8:$ED$8,'Annual Projections'!C$8,'Redlands Pro Forma'!$B23:$ED23) -> 20000 | D23: =SUMIF('Redlands Pro Forma'!$B$8:$ED$8,'Annual Projections'!D$8,'Redlands Pro Forma'!$B23:$ED23) -> 20000 | E23: =SUMIF('Redlands Pro Forma'!$B$8:$ED$8,'Annual Projections'!E$8,'Redlands Pro Forma'!$B23:$ED23) -> 20000 | F23: =SUMIF('Redlands Pro Forma'!$B$8:$ED$8,'Annual Projections'!F$8,'Redlands Pro Forma'!$B23:$ED23) -> 20000 | G23: =SUMIF('Redlands Pro Forma'!$B$8:$ED$8,'Annual Projections'!G$8,'Redlands Pro Forma'!$B23:$ED23) -> 20000 | H23: =SUMIF('Redlands Pro Forma'!$B$8:$ED$8,'Annual Projections'!H$8,'Redlands Pro Forma'!$B23:$ED23) -> 20000 | I23: =SUMIF('Redlands Pro Forma'!$B$8:$ED$8,'Annual Projections'!I$8,'Redlands Pro Forma'!$B23:$ED23) -> 20000 | J23: =SUMIF('Redlands Pro Forma'!$B$8:$ED$8,'Annual Projections'!J$8,'Redlands Pro Forma'!$B23:$ED23) -> 20000 | ... M23: =SUMIF('Redlands Pro Forma'!$B$8:$ED$8,'Annual Projections'!M$8,'Redlands Pro Forma'!$B23:$ED23) -> 20000
A24: Property Taxes | C24: =SUMIF('Redlands Pro Forma'!$B$8:$ED$8,'Annual Projections'!C$8,'Redlands Pro Forma'!$B24:$ED24) -> 150000 | D24: =SUMIF('Redlands Pro Forma'!$B$8:$ED$8,'Annual Projections'!D$8,'Redlands Pro Forma'!$B24:$ED24) -> 153000 | E24: =SUMIF('Redlands Pro Forma'!$B$8:$ED$8,'Annual Projections'!E$8,'Redlands Pro Forma'!$B24:$ED24) -> 156060 | F24: =SUMIF('Redlands Pro Forma'!$B$8:$ED$8,'Annual Projections'!F$8,'Redlands Pro Forma'!$B24:$ED24) -> 159181.2 | G24: =SUMIF('Redlands Pro Forma'!$B$8:$ED$8,'Annual Projections'!G$8,'Redlands Pro Forma'!$B24:$ED24) -> 162364.82 | H24: =SUMIF('Redlands Pro Forma'!$B$8:$ED$8,'Annual Projections'!H$8,'Redlands Pro Forma'!$B24:$ED24) -> 165612.12 | I24: =SUMIF('Redlands Pro Forma'!$B$8:$ED$8,'Annual Projections'!I$8,'Redlands Pro Forma'!$B24:$ED24) -> 168924.36 | J24: =SUMIF('Redlands Pro Forma'!$B$8:$ED$8,'Annual Projections'!J$8,'Redlands Pro Forma'!$B24:$ED24) -> 850119.29 | ... M24: =SUMIF('Redlands Pro Forma'!$B$8:$ED$8,'Annual Projections'!M$8,'Redlands Pro Forma'!$B24:$ED24) -> 902153.39
A25: Total Expense Recoveries | C25: =SUMIF('Redlands Pro Forma'!$B$8:$ED$8,'Annual Projections'!C$8,'Redlands Pro Forma'!$B25:$ED25) -> 260000 | D25: =SUMIF('Redlands Pro Forma'!$B$8:$ED$8,'Annual Projections'!D$8,'Redlands Pro Forma'!$B25:$ED25) -> 263000 | E25: =SUMIF('Redlands Pro Forma'!$B$8:$ED$8,'Annual Projections'!E$8,'Redlands Pro Forma'!$B25:$ED25) -> 266060 | F25: =SUMIF('Redlands Pro Forma'!$B$8:$ED$8,'Annual Projections'!F$8,'Redlands Pro Forma'!$B25:$ED25) -> 269181.2 | G25: =SUMIF('Redlands Pro Forma'!$B$8:$ED$8,'Annual Projections'!G$8,'Redlands Pro Forma'!$B25:$ED25) -> 272364.82 | H25: =SUMIF('Redlands Pro Forma'!$B$8:$ED$8,'Annual Projections'!H$8,'Redlands Pro Forma'!$B25:$ED25) -> 275612.12 | I25: =SUMIF('Redlands Pro Forma'!$B$8:$ED$8,'Annual Projections'!I$8,'Redlands Pro Forma'!$B25:$ED25) -> 278924.36 | J25: =SUMIF('Redlands Pro Forma'!$B$8:$ED$8,'Annual Projections'!J$8,'Redlands Pro Forma'!$B25:$ED25) -> 960119.29 | ... M25: =SUMIF('Redlands Pro Forma'!$B$8:$ED$8,'Annual Projections'!M$8,'Redlands Pro Forma'!$B25:$ED25) -> 1012153.4
A26: Total Other Tenant Revenue | C26: =SUMIF('Redlands Pro Forma'!$B$8:$ED$8,'Annual Projections'!C$8,'Redlands Pro Forma'!$B26:$ED26) -> 260000 | D26: =SUMIF('Redlands Pro Forma'!$B$8:$ED$8,'Annual Projections'!D$8,'Redlands Pro Forma'!$B26:$ED26) -> 263000 | E26: =SUMIF('Redlands Pro Forma'!$B$8:$ED$8,'Annual Projections'!E$8,'Redlands Pro Forma'!$B26:$ED26) -> 266060 | F26: =SUMIF('Redlands Pro Forma'!$B$8:$ED$8,'Annual Projections'!F$8,'Redlands Pro Forma'!$B26:$ED26) -> 269181.2 | G26: =SUMIF('Redlands Pro Forma'!$B$8:$ED$8,'Annual Projections'!G$8,'Redlands Pro Forma'!$B26:$ED26) -> 272364.82 | H26: =SUMIF('Redlands Pro Forma'!$B$8:$ED$8,'Annual Projections'!H$8,'Redlands Pro Forma'!$B26:$ED26) -> 275612.12 | I26: =SUMIF('Redlands Pro Forma'!$B$8:$ED$8,'Annual Projections'!I$8,'Redlands Pro Forma'!$B26:$ED26) -> 278924.36 | J26: =SUMIF('Redlands Pro Forma'!$B$8:$ED$8,'Annual Projections'!J$8,'Redlands Pro Forma'!$B26:$ED26) -> 960119.29 | ... M26: =SUMIF('Redlands Pro Forma'!$B$8:$ED$8,'Annual Projections'!M$8,'Redlands Pro Forma'!$B26:$ED26) -> 1012153.4
C27: =SUMIF('Redlands Pro Forma'!$B$8:$ED$8,'Annual Projections'!C$8,'Redlands Pro Forma'!$B27:$ED27) -> 0 | D27: =SUMIF('Redlands Pro Forma'!$B$8:$ED$8,'Annual Projections'!D$8,'Redlands Pro Forma'!$B27:$ED27) -> 0 | E27: =SUMIF('Redlands Pro Forma'!$B$8:$ED$8,'Annual Projections'!E$8,'Redlands Pro Forma'!$B27:$ED27) -> 0 | F27: =SUMIF('Redlands Pro Forma'!$B$8:$ED$8,'Annual Projections'!F$8,'Redlands Pro Forma'!$B27:$ED27) -> 0 | G27: =SUMIF('Redlands Pro Forma'!$B$8:$ED$8,'Annual Projections'!G$8,'Redlands Pro Forma'!$B27:$ED27) -> 0 | H27: =SUMIF('Redlands Pro Forma'!$B$8:$ED$8,'Annual Projections'!H$8,'Redlands Pro Forma'!$B27:$ED27) -> 0 | I27: =SUMIF('Redlands Pro Forma'!$B$8:$ED$8,'Annual Projections'!I$8,'Redlands Pro Forma'!$B27:$ED27) -> 0 | J27: =SUMIF('Redlands Pro Forma'!$B$8:$ED$8,'Annual Projections'!J$8,'Redlands Pro Forma'!$B27:$ED27) -> 0 | ... M27: =SUMIF('Redlands Pro Forma'!$B$8:$ED$8,'Annual Projections'!M$8,'Redlands Pro Forma'!$B27:$ED27) -> 0
A28: Total Tenant Revenue | C28: =SUMIF('Redlands Pro Forma'!$B$8:$ED$8,'Annual Projections'!C$8,'Redlands Pro Forma'!$B28:$ED28) -> 4159865.7 | D28: =SUMIF('Redlands Pro Forma'!$B$8:$ED$8,'Annual Projections'!D$8,'Redlands Pro Forma'!$B28:$ED28) -> 4240863 | E28: =SUMIF('Redlands Pro Forma'!$B$8:$ED$8,'Annual Projections'!E$8,'Redlands Pro Forma'!$B28:$ED28) -> 4323480.3 | F28: =SUMIF('Redlands Pro Forma'!$B$8:$ED$8,'Annual Projections'!F$8,'Redlands Pro Forma'!$B28:$ED28) -> 4407749.9 | G28: =SUMIF('Redlands Pro Forma'!$B$8:$ED$8,'Annual Projections'!G$8,'Redlands Pro Forma'!$B28:$ED28) -> 4493704.9 | H28: =SUMIF('Redlands Pro Forma'!$B$8:$ED$8,'Annual Projections'!H$8,'Redlands Pro Forma'!$B28:$ED28) -> 4581379 | I28: =SUMIF('Redlands Pro Forma'!$B$8:$ED$8,'Annual Projections'!I$8,'Redlands Pro Forma'!$B28:$ED28) -> 4670806.6 | J28: =SUMIF('Redlands Pro Forma'!$B$8:$ED$8,'Annual Projections'!J$8,'Redlands Pro Forma'!$B28:$ED28) -> 7217423.8 | ... M28: =SUMIF('Redlands Pro Forma'!$B$8:$ED$8,'Annual Projections'!M$8,'Redlands Pro Forma'!$B28:$ED28) -> 7924609.9
A30: Potential Gross Revenue | C30: =SUMIF('Redlands Pro Forma'!$B$8:$ED$8,'Annual Projections'!C$8,'Redlands Pro Forma'!$B30:$ED30) -> 4159865.7 | D30: =SUMIF('Redlands Pro Forma'!$B$8:$ED$8,'Annual Projections'!D$8,'Redlands Pro Forma'!$B30:$ED30) -> 4240863 | E30: =SUMIF('Redlands Pro Forma'!$B$8:$ED$8,'Annual Projections'!E$8,'Redlands Pro Forma'!$B30:$ED30) -> 4323480.3 | F30: =SUMIF('Redlands Pro Forma'!$B$8:$ED$8,'Annual Projections'!F$8,'Redlands Pro Forma'!$B30:$ED30) -> 4407749.9 | G30: =SUMIF('Redlands Pro Forma'!$B$8:$ED$8,'Annual Projections'!G$8,'Redlands Pro Forma'!$B30:$ED30) -> 4493704.9 | H30: =SUMIF('Redlands Pro Forma'!$B$8:$ED$8,'Annual Projections'!H$8,'Redlands Pro Forma'!$B30:$ED30) -> 4581379 | I30: =SUMIF('Redlands Pro Forma'!$B$8:$ED$8,'Annual Projections'!I$8,'Redlands Pro Forma'!$B30:$ED30) -> 4670806.6 | J30: =SUMIF('Redlands Pro Forma'!$B$8:$ED$8,'Annual Projections'!J$8,'Redlands Pro Forma'!$B30:$ED30) -> 7217423.8 | ... M30: =SUMIF('Redlands Pro Forma'!$B$8:$ED$8,'Annual Projections'!M$8,'Redlands Pro Forma'!$B30:$ED30) -> 7924609.9
C31: =SUMIF('Redlands Pro Forma'!$B$8:$ED$8,'Annual Projections'!C$8,'Redlands Pro Forma'!$B31:$ED31) -> 0 | D31: =SUMIF('Redlands Pro Forma'!$B$8:$ED$8,'Annual Projections'!D$8,'Redlands Pro Forma'!$B31:$ED31) -> 0 | E31: =SUMIF('Redlands Pro Forma'!$B$8:$ED$8,'Annual Projections'!E$8,'Redlands Pro Forma'!$B31:$ED31) -> 0 | F31: =SUMIF('Redlands Pro Forma'!$B$8:$ED$8,'Annual Projections'!F$8,'Redlands Pro Forma'!$B31:$ED31) -> 0 | G31: =SUMIF('Redlands Pro Forma'!$B$8:$ED$8,'Annual Projections'!G$8,'Redlands Pro Forma'!$B31:$ED31) -> 0 | H31: =SUMIF('Redlands Pro Forma'!$B$8:$ED$8,'Annual Projections'!H$8,'Redlands Pro Forma'!$B31:$ED31) -> 0 | I31: =SUMIF('Redlands Pro Forma'!$B$8:$ED$8,'Annual Projections'!I$8,'Redlands Pro Forma'!$B31:$ED31) -> 0 | J31: =SUMIF('Redlands Pro Forma'!$B$8:$ED$8,'Annual Projections'!J$8,'Redlands Pro Forma'!$B31:$ED31) -> 0 | ... M31: =SUMIF('Redlands Pro Forma'!$B$8:$ED$8,'Annual Projections'!M$8,'Redlands Pro Forma'!$B31:$ED31) -> 0
A32: Vacancy & Loss to Lease | C32: =SUMIF('Redlands Pro Forma'!$B$8:$ED$8,'Annual Projections'!C$8,'Redlands Pro Forma'!$B32:$ED32) -> 0 | D32: =SUMIF('Redlands Pro Forma'!$B$8:$ED$8,'Annual Projections'!D$8,'Redlands Pro Forma'!$B32:$ED32) -> 0 | E32: =SUMIF('Redlands Pro Forma'!$B$8:$ED$8,'Annual Projections'!E$8,'Redlands Pro Forma'!$B32:$ED32) -> 0 | F32: =SUMIF('Redlands Pro Forma'!$B$8:$ED$8,'Annual Projections'!F$8,'Redlands Pro Forma'!$B32:$ED32) -> 0 | G32: =SUMIF('Redlands Pro Forma'!$B$8:$ED$8,'Annual Projections'!G$8,'Redlands Pro Forma'!$B32:$ED32) -> 0 | H32: =SUMIF('Redlands Pro Forma'!$B$8:$ED$8,'Annual Projections'!H$8,'Redlands Pro Forma'!$B32:$ED32) -> 0 | I32: =SUMIF('Redlands Pro Forma'!$B$8:$ED$8,'Annual Projections'!I$8,'Redlands Pro Forma'!$B32:$ED32) -> 0 | J32: =SUMIF('Redlands Pro Forma'!$B$8:$ED$8,'Annual Projections'!J$8,'Redlands Pro Forma'!$B32:$ED32) -> 0 | ... M32: =SUMIF('Redlands Pro Forma'!$B$8:$ED$8,'Annual Projections'!M$8,'Redlands Pro Forma'!$B32:$ED32) -> 0
A33: Vacancy & L2L | C33: =SUMIF('Redlands Pro Forma'!$B$8:$ED$8,'Annual Projections'!C$8,'Redlands Pro Forma'!$B33:$ED33) -> -415986.57 | D33: =SUMIF('Redlands Pro Forma'!$B$8:$ED$8,'Annual Projections'!D$8,'Redlands Pro Forma'!$B33:$ED33) -> -424086.3 | E33: =SUMIF('Redlands Pro Forma'!$B$8:$ED$8,'Annual Projections'!E$8,'Redlands Pro Forma'!$B33:$ED33) -> -432348.03 | F33: =SUMIF('Redlands Pro Forma'!$B$8:$ED$8,'Annual Projections'!F$8,'Redlands Pro Forma'!$B33:$ED33) -> -440774.99 | G33: =SUMIF('Redlands Pro Forma'!$B$8:$ED$8,'Annual Projections'!G$8,'Redlands Pro Forma'!$B33:$ED33) -> -449370.49 | H33: =SUMIF('Redlands Pro Forma'!$B$8:$ED$8,'Annual Projections'!H$8,'Redlands Pro Forma'!$B33:$ED33) -> -458137.9 | I33: =SUMIF('Redlands Pro Forma'!$B$8:$ED$8,'Annual Projections'!I$8,'Redlands Pro Forma'!$B33:$ED33) -> -467080.66 | J33: =SUMIF('Redlands Pro Forma'!$B$8:$ED$8,'Annual Projections'!J$8,'Redlands Pro Forma'!$B33:$ED33) -> -721742.38 | ... M33: =SUMIF('Redlands Pro Forma'!$B$8:$ED$8,'Annual Projections'!M$8,'Redlands Pro Forma'!$B33:$ED33) -> -792460.99
A34: Total Vacancy & Credit Loss | C34: =SUMIF('Redlands Pro Forma'!$B$8:$ED$8,'Annual Projections'!C$8,'Redlands Pro Forma'!$B34:$ED34) -> -415986.57 | D34: =SUMIF('Redlands Pro Forma'!$B$8:$ED$8,'Annual Projections'!D$8,'Redlands Pro Forma'!$B34:$ED34) -> -424086.3 | E34: =SUMIF('Redlands Pro Forma'!$B$8:$ED$8,'Annual Projections'!E$8,'Redlands Pro Forma'!$B34:$ED34) -> -432348.03 | F34: =SUMIF('Redlands Pro Forma'!$B$8:$ED$8,'Annual Projections'!F$8,'Redlands Pro Forma'!$B34:$ED34) -> -440774.99 | G34: =SUMIF('Redlands Pro Forma'!$B$8:$ED$8,'Annual Projections'!G$8,'Redlands Pro Forma'!$B34:$ED34) -> -449370.49 | H34: =SUMIF('Redlands Pro Forma'!$B$8:$ED$8,'Annual Projections'!H$8,'Redlands Pro Forma'!$B34:$ED34) -> -458137.9 | I34: =SUMIF('Redlands Pro Forma'!$B$8:$ED$8,'Annual Projections'!I$8,'Redlands Pro Forma'!$B34:$ED34) -> -467080.66 | J34: =SUMIF('Redlands Pro Forma'!$B$8:$ED$8,'Annual Projections'!J$8,'Redlands Pro Forma'!$B34:$ED34) -> -721742.38 | ... M34: =SUMIF('Redlands Pro Forma'!$B$8:$ED$8,'Annual Projections'!M$8,'Redlands Pro Forma'!$B34:$ED34) -> -792460.99
A36: Effective Gross Revenue | C36: =SUMIF('Redlands Pro Forma'!$B$8:$ED$8,'Annual Projections'!C$8,'Redlands Pro Forma'!$B36:$ED36) -> 3743879.1 | D36: =SUMIF('Redlands Pro Forma'!$B$8:$ED$8,'Annual Projections'!D$8,'Redlands Pro Forma'!$B36:$ED36) -> 3816776.7 | E36: =SUMIF('Redlands Pro Forma'!$B$8:$ED$8,'Annual Projections'!E$8,'Redlands Pro Forma'!$B36:$ED36) -> 3891132.2 | F36: =SUMIF('Redlands Pro Forma'!$B$8:$ED$8,'Annual Projections'!F$8,'Redlands Pro Forma'!$B36:$ED36) -> 3966974.9 | G36: =SUMIF('Redlands Pro Forma'!$B$8:$ED$8,'Annual Projections'!G$8,'Redlands Pro Forma'!$B36:$ED36) -> 4044334.4 | H36: =SUMIF('Redlands Pro Forma'!$B$8:$ED$8,'Annual Projections'!H$8,'Redlands Pro Forma'!$B36:$ED36) -> 4123241.1 | I36: =SUMIF('Redlands Pro Forma'!$B$8:$ED$8,'Annual Projections'!I$8,'Redlands Pro Forma'!$B36:$ED36) -> 4203725.9 | J36: =SUMIF('Redlands Pro Forma'!$B$8:$ED$8,'Annual Projections'!J$8,'Redlands Pro Forma'!$B36:$ED36) -> 6495681.4 | ... M36: =SUMIF('Redlands Pro Forma'!$B$8:$ED$8,'Annual Projections'!M$8,'Redlands Pro Forma'!$B36:$ED36) -> 7132148.9
A38: Operating Expenses
A39: Utilities | B39: ='Redlands Pro Forma'!$C39*12 -> 45000 | C39: =SUMIF('Redlands Pro Forma'!$B$8:$ED$8,'Annual Projections'!C$8,'Redlands Pro Forma'!$B39:$ED39) -> 45000 | D39: =SUMIF('Redlands Pro Forma'!$B$8:$ED$8,'Annual Projections'!D$8,'Redlands Pro Forma'!$B39:$ED39) -> 46125 | E39: =SUMIF('Redlands Pro Forma'!$B$8:$ED$8,'Annual Projections'!E$8,'Redlands Pro Forma'!$B39:$ED39) -> 47278.125 | F39: =SUMIF('Redlands Pro Forma'!$B$8:$ED$8,'Annual Projections'!F$8,'Redlands Pro Forma'!$B39:$ED39) -> 48460.078 | G39: =SUMIF('Redlands Pro Forma'!$B$8:$ED$8,'Annual Projections'!G$8,'Redlands Pro Forma'!$B39:$ED39) -> 49671.58 | H39: =SUMIF('Redlands Pro Forma'!$B$8:$ED$8,'Annual Projections'!H$8,'Redlands Pro Forma'!$B39:$ED39) -> 50913.37 | I39: =SUMIF('Redlands Pro Forma'!$B$8:$ED$8,'Annual Projections'!I$8,'Redlands Pro Forma'!$B39:$ED39) -> 52186.204 | J39: =SUMIF('Redlands Pro Forma'!$B$8:$ED$8,'Annual Projections'!J$8,'Redlands Pro Forma'!$B39:$ED39) -> 53490.859 | ... M39: =SUMIF('Redlands Pro Forma'!$B$8:$ED$8,'Annual Projections'!M$8,'Redlands Pro Forma'!$B39:$ED39) -> 57603.804
A40: Repairs & Maintenance | B40: ='Redlands Pro Forma'!$C40*12 -> 45000 | C40: =SUMIF('Redlands Pro Forma'!$B$8:$ED$8,'Annual Projections'!C$8,'Redlands Pro Forma'!$B40:$ED40) -> 45000 | D40: =SUMIF('Redlands Pro Forma'!$B$8:$ED$8,'Annual Projections'!D$8,'Redlands Pro Forma'!$B40:$ED40) -> 46125 | E40: =SUMIF('Redlands Pro Forma'!$B$8:$ED$8,'Annual Projections'!E$8,'Redlands Pro Forma'!$B40:$ED40) -> 47278.125 | F40: =SUMIF('Redlands Pro Forma'!$B$8:$ED$8,'Annual Projections'!F$8,'Redlands Pro Forma'!$B40:$ED40) -> 48460.078 | G40: =SUMIF('Redlands Pro Forma'!$B$8:$ED$8,'Annual Projections'!G$8,'Redlands Pro Forma'!$B40:$ED40) -> 49671.58 | H40: =SUMIF('Redlands Pro Forma'!$B$8:$ED$8,'Annual Projections'!H$8,'Redlands Pro Forma'!$B40:$ED40) -> 50913.37 | I40: =SUMIF('Redlands Pro Forma'!$B$8:$ED$8,'Annual Projections'!I$8,'Redlands Pro Forma'!$B40:$ED40) -> 52186.204 | J40: =SUMIF('Redlands Pro Forma'!$B$8:$ED$8,'Annual Projections'!J$8,'Redlands Pro Forma'!$B40:$ED40) -> 53490.859 | ... M40: =SUMIF('Redlands Pro Forma'!$B$8:$ED$8,'Annual Projections'!M$8,'Redlands Pro Forma'!$B40:$ED40) -> 57603.804
A41: Insurance | B41: ='Redlands Pro Forma'!$C41*12 -> 20000 | C41: =SUMIF('Redlands Pro Forma'!$B$8:$ED$8,'Annual Projections'!C$8,'Redlands Pro Forma'!$B41:$ED41) -> 20000 | D41: =SUMIF('Redlands Pro Forma'!$B$8:$ED$8,'Annual Projections'!D$8,'Redlands Pro Forma'!$B41:$ED41) -> 20500 | E41: =SUMIF('Redlands Pro Forma'!$B$8:$ED$8,'Annual Projections'!E$8,'Redlands Pro Forma'!$B41:$ED41) -> 21012.5 | F41: =SUMIF('Redlands Pro Forma'!$B$8:$ED$8,'Annual Projections'!F$8,'Redlands Pro Forma'!$B41:$ED41) -> 21537.812 | G41: =SUMIF('Redlands Pro Forma'!$B$8:$ED$8,'Annual Projections'!G$8,'Redlands Pro Forma'!$B41:$ED41) -> 22076.258 | H41: =SUMIF('Redlands Pro Forma'!$B$8:$ED$8,'Annual Projections'!H$8,'Redlands Pro Forma'!$B41:$ED41) -> 22628.164 | I41: =SUMIF('Redlands Pro Forma'!$B$8:$ED$8,'Annual Projections'!I$8,'Redlands Pro Forma'!$B41:$ED41) -> 23193.868 | J41: =SUMIF('Redlands Pro Forma'!$B$8:$ED$8,'Annual Projections'!J$8,'Redlands Pro Forma'!$B41:$ED41) -> 23773.715 | ... M41: =SUMIF('Redlands Pro Forma'!$B$8:$ED$8,'Annual Projections'!M$8,'Redlands Pro Forma'!$B41:$ED41) -> 25601.691
A42: Property Taxes | B42: ='Redlands Pro Forma'!$C42*12 -> 740080 | C42: =SUMIF('Redlands Pro Forma'!$B$8:$ED$8,'Annual Projections'!C$8,'Redlands Pro Forma'!$B42:$ED42) -> 740080 | D42: =SUMIF('Redlands Pro Forma'!$B$8:$ED$8,'Annual Projections'!D$8,'Redlands Pro Forma'!$B42:$ED42) -> 754881.6 | E42: =SUMIF('Redlands Pro Forma'!$B$8:$ED$8,'Annual Projections'!E$8,'Redlands Pro Forma'!$B42:$ED42) -> 769979.23 | F42: =SUMIF('Redlands Pro Forma'!$B$8:$ED$8,'Annual Projections'!F$8,'Redlands Pro Forma'!$B42:$ED42) -> 785378.82 | G42: =SUMIF('Redlands Pro Forma'!$B$8:$ED$8,'Annual Projections'!G$8,'Redlands Pro Forma'!$B42:$ED42) -> 801086.39 | H42: =SUMIF('Redlands Pro Forma'!$B$8:$ED$8,'Annual Projections'!H$8,'Redlands Pro Forma'!$B42:$ED42) -> 817108.12 | I42: =SUMIF('Redlands Pro Forma'!$B$8:$ED$8,'Annual Projections'!I$8,'Redlands Pro Forma'!$B42:$ED42) -> 833450.28 | J42: =SUMIF('Redlands Pro Forma'!$B$8:$ED$8,'Annual Projections'!J$8,'Redlands Pro Forma'!$B42:$ED42) -> 850119.29 | ... M42: =SUMIF('Redlands Pro Forma'!$B$8:$ED$8,'Annual Projections'!M$8,'Redlands Pro Forma'!$B42:$ED42) -> 902153.39
A43: Management Fee | C43: =SUMIF('Redlands Pro Forma'!$B$8:$ED$8,'Annual Projections'!C$8,'Redlands Pro Forma'!$B43:$ED43) -> 112316.37 | D43: =SUMIF('Redlands Pro Forma'!$B$8:$ED$8,'Annual Projections'!D$8,'Redlands Pro Forma'!$B43:$ED43) -> 114503.3 | E43: =SUMIF('Redlands Pro Forma'!$B$8:$ED$8,'Annual Projections'!E$8,'Redlands Pro Forma'!$B43:$ED43) -> 116733.97 | F43: =SUMIF('Redlands Pro Forma'!$B$8:$ED$8,'Annual Projections'!F$8,'Redlands Pro Forma'!$B43:$ED43) -> 119009.25 | G43: =SUMIF('Redlands Pro Forma'!$B$8:$ED$8,'Annual Projections'!G$8,'Redlands Pro Forma'!$B43:$ED43) -> 121330.03 | H43: =SUMIF('Redlands Pro Forma'!$B$8:$ED$8,'Annual Projections'!H$8,'Redlands Pro Forma'!$B43:$ED43) -> 123697.23 | I43: =SUMIF('Redlands Pro Forma'!$B$8:$ED$8,'Annual Projections'!I$8,'Redlands Pro Forma'!$B43:$ED43) -> 126111.78 | J43: =SUMIF('Redlands Pro Forma'!$B$8:$ED$8,'Annual Projections'!J$8,'Redlands Pro Forma'!$B43:$ED43) -> 194870.44 | ... M43: =SUMIF('Redlands Pro Forma'!$B$8:$ED$8,'Annual Projections'!M$8,'Redlands Pro Forma'!$B43:$ED43) -> 213964.47
A44: Total Operating Expenses | C44: =SUMIF('Redlands Pro Forma'!$B$8:$ED$8,'Annual Projections'!C$8,'Redlands Pro Forma'!$B44:$ED44) -> 962396.37 | D44: =SUMIF('Redlands Pro Forma'!$B$8:$ED$8,'Annual Projections'!D$8,'Redlands Pro Forma'!$B44:$ED44) -> 982134.9 | E44: =SUMIF('Redlands Pro Forma'!$B$8:$ED$8,'Annual Projections'!E$8,'Redlands Pro Forma'!$B44:$ED44) -> 1002281.9 | F44: =SUMIF('Redlands Pro Forma'!$B$8:$ED$8,'Annual Projections'!F$8,'Redlands Pro Forma'!$B44:$ED44) -> 1022846 | G44: =SUMIF('Redlands Pro Forma'!$B$8:$ED$8,'Annual Projections'!G$8,'Redlands Pro Forma'!$B44:$ED44) -> 1043835.8 | H44: =SUMIF('Redlands Pro Forma'!$B$8:$ED$8,'Annual Projections'!H$8,'Redlands Pro Forma'!$B44:$ED44) -> 1065260.3 | I44: =SUMIF('Redlands Pro Forma'!$B$8:$ED$8,'Annual Projections'!I$8,'Redlands Pro Forma'!$B44:$ED44) -> 1087128.3 | J44: =SUMIF('Redlands Pro Forma'!$B$8:$ED$8,'Annual Projections'!J$8,'Redlands Pro Forma'!$B44:$ED44) -> 1175745.2 | ... M44: =SUMIF('Redlands Pro Forma'!$B$8:$ED$8,'Annual Projections'!M$8,'Redlands Pro Forma'!$B44:$ED44) -> 1256927.2
A46: Net Operating Income | C46: =SUMIF('Redlands Pro Forma'!$B$8:$ED$8,'Annual Projections'!C$8,'Redlands Pro Forma'!$B46:$ED46) -> 2959535 | D46: =SUMIF('Redlands Pro Forma'!$B$8:$ED$8,'Annual Projections'!D$8,'Redlands Pro Forma'!$B46:$ED46) -> 3035756 | E46: =SUMIF('Redlands Pro Forma'!$B$8:$ED$8,'Annual Projections'!E$8,'Redlands Pro Forma'!$B46:$ED46) -> 3113933 | F46: =SUMIF('Redlands Pro Forma'!$B$8:$ED$8,'Annual Projections'!F$8,'Redlands Pro Forma'!$B46:$ED46) -> 3194113 | G46: =SUMIF('Redlands Pro Forma'!$B$8:$ED$8,'Annual Projections'!G$8,'Redlands Pro Forma'!$B46:$ED46) -> 3276334 | H46: =SUMIF('Redlands Pro Forma'!$B$8:$ED$8,'Annual Projections'!H$8,'Redlands Pro Forma'!$B46:$ED46) -> 3360666 | I46: =SUMIF('Redlands Pro Forma'!$B$8:$ED$8,'Annual Projections'!I$8,'Redlands Pro Forma'!$B46:$ED46) -> 3446217 | J46: =SUMIF('Redlands Pro Forma'!$B$8:$ED$8,'Annual Projections'!J$8,'Redlands Pro Forma'!$B46:$ED46) -> 4766999 | ... M46: =SUMIF('Redlands Pro Forma'!$B$8:$ED$8,'Annual Projections'!M$8,'Redlands Pro Forma'!$B46:$ED46) -> 6135193
A48: Leasing Costs
A49: Tenant Improvements | C49: =SUMIF('Redlands Pro Forma'!$B$8:$ED$8,'Annual Projections'!C$8,'Redlands Pro Forma'!$B49:$ED49) -> 0 | D49: =SUMIF('Redlands Pro Forma'!$B$8:$ED$8,'Annual Projections'!D$8,'Redlands Pro Forma'!$B49:$ED49) -> 0 | E49: =SUMIF('Redlands Pro Forma'!$B$8:$ED$8,'Annual Projections'!E$8,'Redlands Pro Forma'!$B49:$ED49) -> 0 | F49: =SUMIF('Redlands Pro Forma'!$B$8:$ED$8,'Annual Projections'!F$8,'Redlands Pro Forma'!$B49:$ED49) -> 0 | G49: =SUMIF('Redlands Pro Forma'!$B$8:$ED$8,'Annual Projections'!G$8,'Redlands Pro Forma'!$B49:$ED49) -> 0 | H49: =SUMIF('Redlands Pro Forma'!$B$8:$ED$8,'Annual Projections'!H$8,'Redlands Pro Forma'!$B49:$ED49) -> 0 | I49: =SUMIF('Redlands Pro Forma'!$B$8:$ED$8,'Annual Projections'!I$8,'Redlands Pro Forma'!$B49:$ED49) -> 0 | J49: =SUMIF('Redlands Pro Forma'!$B$8:$ED$8,'Annual Projections'!J$8,'Redlands Pro Forma'!$B49:$ED49) -> 2400000 | ... M49: =SUMIF('Redlands Pro Forma'!$B$8:$ED$8,'Annual Projections'!M$8,'Redlands Pro Forma'!$B49:$ED49) -> 0
A50: Leasing Commissions | C50: =SUMIF('Redlands Pro Forma'!$B$8:$ED$8,'Annual Projections'!C$8,'Redlands Pro Forma'!$B50:$ED50) -> 0 | D50: =SUMIF('Redlands Pro Forma'!$B$8:$ED$8,'Annual Projections'!D$8,'Redlands Pro Forma'!$B50:$ED50) -> 0 | E50: =SUMIF('Redlands Pro Forma'!$B$8:$ED$8,'Annual Projections'!E$8,'Redlands Pro Forma'!$B50:$ED50) -> 0 | F50: =SUMIF('Redlands Pro Forma'!$B$8:$ED$8,'Annual Projections'!F$8,'Redlands Pro Forma'!$B50:$ED50) -> 0 | G50: =SUMIF('Redlands Pro Forma'!$B$8:$ED$8,'Annual Projections'!G$8,'Redlands Pro Forma'!$B50:$ED50) -> 0 | H50: =SUMIF('Redlands Pro Forma'!$B$8:$ED$8,'Annual Projections'!H$8,'Redlands Pro Forma'!$B50:$ED50) -> 0 | I50: =SUMIF('Redlands Pro Forma'!$B$8:$ED$8,'Annual Projections'!I$8,'Redlands Pro Forma'!$B50:$ED50) -> 0 | J50: =SUMIF('Redlands Pro Forma'!$B$8:$ED$8,'Annual Projections'!J$8,'Redlands Pro Forma'!$B50:$ED50) -> 1134000 | ... M50: =SUMIF('Redlands Pro Forma'!$B$8:$ED$8,'Annual Projections'!M$8,'Redlands Pro Forma'!$B50:$ED50) -> 0
A51: Security Deposits | C51: =SUMIF('Redlands Pro Forma'!$B$8:$ED$8,'Annual Projections'!C$8,'Redlands Pro Forma'!$B51:$ED51) -> 0 | D51: =SUMIF('Redlands Pro Forma'!$B$8:$ED$8,'Annual Projections'!D$8,'Redlands Pro Forma'!$B51:$ED51) -> 0 | E51: =SUMIF('Redlands Pro Forma'!$B$8:$ED$8,'Annual Projections'!E$8,'Redlands Pro Forma'!$B51:$ED51) -> 0 | F51: =SUMIF('Redlands Pro Forma'!$B$8:$ED$8,'Annual Projections'!F$8,'Redlands Pro Forma'!$B51:$ED51) -> 0 | G51: =SUMIF('Redlands Pro Forma'!$B$8:$ED$8,'Annual Projections'!G$8,'Redlands Pro Forma'!$B51:$ED51) -> 0 | H51: =SUMIF('Redlands Pro Forma'!$B$8:$ED$8,'Annual Projections'!H$8,'Redlands Pro Forma'!$B51:$ED51) -> 0 | I51: =SUMIF('Redlands Pro Forma'!$B$8:$ED$8,'Annual Projections'!I$8,'Redlands Pro Forma'!$B51:$ED51) -> 0 | J51: =SUMIF('Redlands Pro Forma'!$B$8:$ED$8,'Annual Projections'!J$8,'Redlands Pro Forma'!$B51:$ED51) -> -1800000 | ... M51: =SUMIF('Redlands Pro Forma'!$B$8:$ED$8,'Annual Projections'!M$8,'Redlands Pro Forma'!$B51:$ED51) -> 0
A52: Total Leasing Costs | C52: =SUMIF('Redlands Pro Forma'!$B$8:$ED$8,'Annual Projections'!C$8,'Redlands Pro Forma'!$B52:$ED52) -> 0 | D52: =SUMIF('Redlands Pro Forma'!$B$8:$ED$8,'Annual Projections'!D$8,'Redlands Pro Forma'!$B52:$ED52) -> 0 | E52: =SUMIF('Redlands Pro Forma'!$B$8:$ED$8,'Annual Projections'!E$8,'Redlands Pro Forma'!$B52:$ED52) -> 0 | F52: =SUMIF('Redlands Pro Forma'!$B$8:$ED$8,'Annual Projections'!F$8,'Redlands Pro Forma'!$B52:$ED52) -> 0 | G52: =SUMIF('Redlands Pro Forma'!$B$8:$ED$8,'Annual Projections'!G$8,'Redlands Pro Forma'!$B52:$ED52) -> 0 | H52: =SUMIF('Redlands Pro Forma'!$B$8:$ED$8,'Annual Projections'!H$8,'Redlands Pro Forma'!$B52:$ED52) -> 0 | I52: =SUMIF('Redlands Pro Forma'!$B$8:$ED$8,'Annual Projections'!I$8,'Redlands Pro Forma'!$B52:$ED52) -> 0 | J52: =SUMIF('Redlands Pro Forma'!$B$8:$ED$8,'Annual Projections'!J$8,'Redlands Pro Forma'!$B52:$ED52) -> 1734000 | ... M52: =SUMIF('Redlands Pro Forma'!$B$8:$ED$8,'Annual Projections'!M$8,'Redlands Pro Forma'!$B52:$ED52) -> 0
A54: Capital Expenditures
A55: Replacement Reserve | C55: =SUMIF('Redlands Pro Forma'!$B$8:$ED$8,'Annual Projections'!C$8,'Redlands Pro Forma'!$B55:$ED55) -> 600000 | D55: =SUMIF('Redlands Pro Forma'!$B$8:$ED$8,'Annual Projections'!D$8,'Redlands Pro Forma'!$B55:$ED55) -> 612000 | E55: =SUMIF('Redlands Pro Forma'!$B$8:$ED$8,'Annual Projections'!E$8,'Redlands Pro Forma'!$B55:$ED55) -> 624240 | F55: =SUMIF('Redlands Pro Forma'!$B$8:$ED$8,'Annual Projections'!F$8,'Redlands Pro Forma'!$B55:$ED55) -> 636724.8 | G55: =SUMIF('Redlands Pro Forma'!$B$8:$ED$8,'Annual Projections'!G$8,'Redlands Pro Forma'!$B55:$ED55) -> 649459.3 | H55: =SUMIF('Redlands Pro Forma'!$B$8:$ED$8,'Annual Projections'!H$8,'Redlands Pro Forma'!$B55:$ED55) -> 662448.48 | I55: =SUMIF('Redlands Pro Forma'!$B$8:$ED$8,'Annual Projections'!I$8,'Redlands Pro Forma'!$B55:$ED55) -> 675697.45 | J55: =SUMIF('Redlands Pro Forma'!$B$8:$ED$8,'Annual Projections'!J$8,'Redlands Pro Forma'!$B55:$ED55) -> 689211.4 | ... M55: =SUMIF('Redlands Pro Forma'!$B$8:$ED$8,'Annual Projections'!M$8,'Redlands Pro Forma'!$B55:$ED55) -> 731396.65
A56: Total Capital Expenditures | C56: =SUMIF('Redlands Pro Forma'!$B$8:$ED$8,'Annual Projections'!C$8,'Redlands Pro Forma'!$B56:$ED56) -> 600000 | D56: =SUMIF('Redlands Pro Forma'!$B$8:$ED$8,'Annual Projections'!D$8,'Redlands Pro Forma'!$B56:$ED56) -> 612000 | E56: =SUMIF('Redlands Pro Forma'!$B$8:$ED$8,'Annual Projections'!E$8,'Redlands Pro Forma'!$B56:$ED56) -> 624240 | F56: =SUMIF('Redlands Pro Forma'!$B$8:$ED$8,'Annual Projections'!F$8,'Redlands Pro Forma'!$B56:$ED56) -> 636724.8 | G56: =SUMIF('Redlands Pro Forma'!$B$8:$ED$8,'Annual Projections'!G$8,'Redlands Pro Forma'!$B56:$ED56) -> 649459.3 | H56: =SUMIF('Redlands Pro Forma'!$B$8:$ED$8,'Annual Projections'!H$8,'Redlands Pro Forma'!$B56:$ED56) -> 662448.48 | I56: =SUMIF('Redlands Pro Forma'!$B$8:$ED$8,'Annual Projections'!I$8,'Redlands Pro Forma'!$B56:$ED56) -> 675697.45 | J56: =SUMIF('Redlands Pro Forma'!$B$8:$ED$8,'Annual Projections'!J$8,'Redlands Pro Forma'!$B56:$ED56) -> 689211.4 | ... M56: =SUMIF('Redlands Pro Forma'!$B$8:$ED$8,'Annual Projections'!M$8,'Redlands Pro Forma'!$B56:$ED56) -> 731396.65
A58: Total Leasing & Capital Costs | C58: =SUMIF('Redlands Pro Forma'!$B$8:$ED$8,'Annual Projections'!C$8,'Redlands Pro Forma'!$B58:$ED58) -> 600000 | D58: =SUMIF('Redlands Pro Forma'!$B$8:$ED$8,'Annual Projections'!D$8,'Redlands Pro Forma'!$B58:$ED58) -> 612000 | E58: =SUMIF('Redlands Pro Forma'!$B$8:$ED$8,'Annual Projections'!E$8,'Redlands Pro Forma'!$B58:$ED58) -> 624240 | F58: =SUMIF('Redlands Pro Forma'!$B$8:$ED$8,'Annual Projections'!F$8,'Redlands Pro Forma'!$B58:$ED58) -> 636724.8 | G58: =SUMIF('Redlands Pro Forma'!$B$8:$ED$8,'Annual Projections'!G$8,'Redlands Pro Forma'!$B58:$ED58) -> 649459.3 | H58: =SUMIF('Redlands Pro Forma'!$B$8:$ED$8,'Annual Projections'!H$8,'Redlands Pro Forma'!$B58:$ED58) -> 662448.48 | I58: =SUMIF('Redlands Pro Forma'!$B$8:$ED$8,'Annual Projections'!I$8,'Redlands Pro Forma'!$B58:$ED58) -> 675697.45 | J58: =SUMIF('Redlands Pro Forma'!$B$8:$ED$8,'Annual Projections'!J$8,'Redlands Pro Forma'!$B58:$ED58) -> 2423211.4 | ... M58: =SUMIF('Redlands Pro Forma'!$B$8:$ED$8,'Annual Projections'!M$8,'Redlands Pro Forma'!$B58:$ED58) -> 731396.65
A60: Cash Flow Before Debt Service | C60: =SUMIF('Redlands Pro Forma'!$B$8:$ED$8,'Annual Projections'!C$8,'Redlands Pro Forma'!$B60:$ED60) -> 2359535 | D60: =SUMIF('Redlands Pro Forma'!$B$8:$ED$8,'Annual Projections'!D$8,'Redlands Pro Forma'!$B60:$ED60) -> 2423756 | E60: =SUMIF('Redlands Pro Forma'!$B$8:$ED$8,'Annual Projections'!E$8,'Redlands Pro Forma'!$B60:$ED60) -> 2489693 | F60: =SUMIF('Redlands Pro Forma'!$B$8:$ED$8,'Annual Projections'!F$8,'Redlands Pro Forma'!$B60:$ED60) -> 2557388.2 | G60: =SUMIF('Redlands Pro Forma'!$B$8:$ED$8,'Annual Projections'!G$8,'Redlands Pro Forma'!$B60:$ED60) -> 2626874.7 | H60: =SUMIF('Redlands Pro Forma'!$B$8:$ED$8,'Annual Projections'!H$8,'Redlands Pro Forma'!$B60:$ED60) -> 2698217.5 | I60: =SUMIF('Redlands Pro Forma'!$B$8:$ED$8,'Annual Projections'!I$8,'Redlands Pro Forma'!$B60:$ED60) -> 2770519.5 | J60: =SUMIF('Redlands Pro Forma'!$B$8:$ED$8,'Annual Projections'!J$8,'Redlands Pro Forma'!$B60:$ED60) -> 2343787.6 | ... M60: =SUMIF('Redlands Pro Forma'!$B$8:$ED$8,'Annual Projections'!M$8,'Redlands Pro Forma'!$B60:$ED60) -> 5403796.3
A62: Acquisition
A63: Purchase Price | B63: =SUMIF('Redlands Pro Forma'!$B$8:$ED$8,'Annual Projections'!B$8,'Redlands Pro Forma'!$B63:$ED63) -> -67280000 | C63: =SUMIF('Redlands Pro Forma'!$B$8:$ED$8,'Annual Projections'!C$8,'Redlands Pro Forma'!$B63:$ED63) -> 0 | D63: =SUMIF('Redlands Pro Forma'!$B$8:$ED$8,'Annual Projections'!D$8,'Redlands Pro Forma'!$B63:$ED63) -> 0 | E63: =SUMIF('Redlands Pro Forma'!$B$8:$ED$8,'Annual Projections'!E$8,'Redlands Pro Forma'!$B63:$ED63) -> 0 | F63: =SUMIF('Redlands Pro Forma'!$B$8:$ED$8,'Annual Projections'!F$8,'Redlands Pro Forma'!$B63:$ED63) -> 0 | G63: =SUMIF('Redlands Pro Forma'!$B$8:$ED$8,'Annual Projections'!G$8,'Redlands Pro Forma'!$B63:$ED63) -> 0 | H63: =SUMIF('Redlands Pro Forma'!$B$8:$ED$8,'Annual Projections'!H$8,'Redlands Pro Forma'!$B63:$ED63) -> 0 | I63: =SUMIF('Redlands Pro Forma'!$B$8:$ED$8,'Annual Projections'!I$8,'Redlands Pro Forma'!$B63:$ED63) -> 0 | ... M63: =SUMIF('Redlands Pro Forma'!$B$8:$ED$8,'Annual Projections'!M$8,'Redlands Pro Forma'!$B63:$ED63) -> 0
A64: Cost of Sales | B64: =SUMIF('Redlands Pro Forma'!$B$8:$ED$8,'Annual Projections'!B$8,'Redlands Pro Forma'!$B64:$ED64) -> -1345600 | C64: =SUMIF('Redlands Pro Forma'!$B$8:$ED$8,'Annual Projections'!C$8,'Redlands Pro Forma'!$B64:$ED64) -> 0 | D64: =SUMIF('Redlands Pro Forma'!$B$8:$ED$8,'Annual Projections'!D$8,'Redlands Pro Forma'!$B64:$ED64) -> 0 | E64: =SUMIF('Redlands Pro Forma'!$B$8:$ED$8,'Annual Projections'!E$8,'Redlands Pro Forma'!$B64:$ED64) -> 0 | F64: =SUMIF('Redlands Pro Forma'!$B$8:$ED$8,'Annual Projections'!F$8,'Redlands Pro Forma'!$B64:$ED64) -> 0 | G64: =SUMIF('Redlands Pro Forma'!$B$8:$ED$8,'Annual Projections'!G$8,'Redlands Pro Forma'!$B64:$ED64) -> 0 | H64: =SUMIF('Redlands Pro Forma'!$B$8:$ED$8,'Annual Projections'!H$8,'Redlands Pro Forma'!$B64:$ED64) -> 0 | I64: =SUMIF('Redlands Pro Forma'!$B$8:$ED$8,'Annual Projections'!I$8,'Redlands Pro Forma'!$B64:$ED64) -> 0 | ... M64: =SUMIF('Redlands Pro Forma'!$B$8:$ED$8,'Annual Projections'!M$8,'Redlands Pro Forma'!$B64:$ED64) -> 0
A65: Total Acquisition Cost | B65: =SUMIF('Redlands Pro Forma'!$B$8:$ED$8,'Annual Projections'!B$8,'Redlands Pro Forma'!$B65:$ED65) -> -68625600 | C65: =SUMIF('Redlands Pro Forma'!$B$8:$ED$8,'Annual Projections'!C$8,'Redlands Pro Forma'!$B65:$ED65) -> 0 | D65: =SUMIF('Redlands Pro Forma'!$B$8:$ED$8,'Annual Projections'!D$8,'Redlands Pro Forma'!$B65:$ED65) -> 0 | E65: =SUMIF('Redlands Pro Forma'!$B$8:$ED$8,'Annual Projections'!E$8,'Redlands Pro Forma'!$B65:$ED65) -> 0 | F65: =SUMIF('Redlands Pro Forma'!$B$8:$ED$8,'Annual Projections'!F$8,'Redlands Pro Forma'!$B65:$ED65) -> 0 | G65: =SUMIF('Redlands Pro Forma'!$B$8:$ED$8,'Annual Projections'!G$8,'Redlands Pro Forma'!$B65:$ED65) -> 0 | H65: =SUMIF('Redlands Pro Forma'!$B$8:$ED$8,'Annual Projections'!H$8,'Redlands Pro Forma'!$B65:$ED65) -> 0 | I65: =SUMIF('Redlands Pro Forma'!$B$8:$ED$8,'Annual Projections'!I$8,'Redlands Pro Forma'!$B65:$ED65) -> 0 | ... M65: =SUMIF('Redlands Pro Forma'!$B$8:$ED$8,'Annual Projections'!M$8,'Redlands Pro Forma'!$B65:$ED65) -> 0
B66: =SUMIF('Redlands Pro Forma'!$B$8:$ED$8,'Annual Projections'!B$8,'Redlands Pro Forma'!$B66:$ED66) -> 0 | C66: =SUMIF('Redlands Pro Forma'!$B$8:$ED$8,'Annual Projections'!C$8,'Redlands Pro Forma'!$B66:$ED66) -> 0 | D66: =SUMIF('Redlands Pro Forma'!$B$8:$ED$8,'Annual Projections'!D$8,'Redlands Pro Forma'!$B66:$ED66) -> 0 | E66: =SUMIF('Redlands Pro Forma'!$B$8:$ED$8,'Annual Projections'!E$8,'Redlands Pro Forma'!$B66:$ED66) -> 0 | F66: =SUMIF('Redlands Pro Forma'!$B$8:$ED$8,'Annual Projections'!F$8,'Redlands Pro Forma'!$B66:$ED66) -> 0 | G66: =SUMIF('Redlands Pro Forma'!$B$8:$ED$8,'Annual Projections'!G$8,'Redlands Pro Forma'!$B66:$ED66) -> 0 | H66: =SUMIF('Redlands Pro Forma'!$B$8:$ED$8,'Annual Projections'!H$8,'Redlands Pro Forma'!$B66:$ED66) -> 0 | I66: =SUMIF('Redlands Pro Forma'!$B$8:$ED$8,'Annual Projections'!I$8,'Redlands Pro Forma'!$B66:$ED66) -> 0 | ... M66: =SUMIF('Redlands Pro Forma'!$B$8:$ED$8,'Annual Projections'!M$8,'Redlands Pro Forma'!$B66:$ED66) -> 0
A67: Disposition | C67: =SUMIF('Redlands Pro Forma'!$B$8:$ED$8,'Annual Projections'!C$8,'Redlands Pro Forma'!$B67:$ED67) -> 0 | D67: =SUMIF('Redlands Pro Forma'!$B$8:$ED$8,'Annual Projections'!D$8,'Redlands Pro Forma'!$B67:$ED67) -> 0 | E67: =SUMIF('Redlands Pro Forma'!$B$8:$ED$8,'Annual Projections'!E$8,'Redlands Pro Forma'!$B67:$ED67) -> 0 | F67: =SUMIF('Redlands Pro Forma'!$B$8:$ED$8,'Annual Projections'!F$8,'Redlands Pro Forma'!$B67:$ED67) -> 0 | G67: =SUMIF('Redlands Pro Forma'!$B$8:$ED$8,'Annual Projections'!G$8,'Redlands Pro Forma'!$B67:$ED67) -> 0 | H67: =SUMIF('Redlands Pro Forma'!$B$8:$ED$8,'Annual Projections'!H$8,'Redlands Pro Forma'!$B67:$ED67) -> 0 | I67: =SUMIF('Redlands Pro Forma'!$B$8:$ED$8,'Annual Projections'!I$8,'Redlands Pro Forma'!$B67:$ED67) -> 0 | J67: =SUMIF('Redlands Pro Forma'!$B$8:$ED$8,'Annual Projections'!J$8,'Redlands Pro Forma'!$B67:$ED67) -> 0 | ... M67: =SUMIF('Redlands Pro Forma'!$B$8:$ED$8,'Annual Projections'!M$8,'Redlands Pro Forma'!$B67:$ED67) -> 0
A68: Sale Price | B68: =SUMIF('Redlands Pro Forma'!$B$8:$ED$8,'Annual Projections'!B$8,'Redlands Pro Forma'!$B68:$ED68) -> 0 | C68: =SUMIF('Redlands Pro Forma'!$B$8:$ED$8,'Annual Projections'!C$8,'Redlands Pro Forma'!$B68:$ED68) -> 0 | D68: =SUMIF('Redlands Pro Forma'!$B$8:$ED$8,'Annual Projections'!D$8,'Redlands Pro Forma'!$B68:$ED68) -> 0 | E68: =SUMIF('Redlands Pro Forma'!$B$8:$ED$8,'Annual Projections'!E$8,'Redlands Pro Forma'!$B68:$ED68) -> 0 | F68: =SUMIF('Redlands Pro Forma'!$B$8:$ED$8,'Annual Projections'!F$8,'Redlands Pro Forma'!$B68:$ED68) -> 0 | G68: =SUMIF('Redlands Pro Forma'!$B$8:$ED$8,'Annual Projections'!G$8,'Redlands Pro Forma'!$B68:$ED68) -> 0 | H68: =SUMIF('Redlands Pro Forma'!$B$8:$ED$8,'Annual Projections'!H$8,'Redlands Pro Forma'!$B68:$ED68) -> 0 | I68: =SUMIF('Redlands Pro Forma'!$B$8:$ED$8,'Annual Projections'!I$8,'Redlands Pro Forma'!$B68:$ED68) -> 0 | ... M68: =SUMIF('Redlands Pro Forma'!$B$8:$ED$8,'Annual Projections'!M$8,'Redlands Pro Forma'!$B68:$ED68) -> 0
A69: Cost of Sales | B69: =SUMIF('Redlands Pro Forma'!$B$8:$ED$8,'Annual Projections'!B$8,'Redlands Pro Forma'!$B69:$ED69) -> 0 | C69: =SUMIF('Redlands Pro Forma'!$B$8:$ED$8,'Annual Projections'!C$8,'Redlands Pro Forma'!$B69:$ED69) -> 0 | D69: =SUMIF('Redlands Pro Forma'!$B$8:$ED$8,'Annual Projections'!D$8,'Redlands Pro Forma'!$B69:$ED69) -> 0 | E69: =SUMIF('Redlands Pro Forma'!$B$8:$ED$8,'Annual Projections'!E$8,'Redlands Pro Forma'!$B69:$ED69) -> 0 | F69: =SUMIF('Redlands Pro Forma'!$B$8:$ED$8,'Annual Projections'!F$8,'Redlands Pro Forma'!$B69:$ED69) -> 0 | G69: =SUMIF('Redlands Pro Forma'!$B$8:$ED$8,'Annual Projections'!G$8,'Redlands Pro Forma'!$B69:$ED69) -> 0 | H69: =SUMIF('Redlands Pro Forma'!$B$8:$ED$8,'Annual Projections'!H$8,'Redlands Pro Forma'!$B69:$ED69) -> 0 | I69: =SUMIF('Redlands Pro Forma'!$B$8:$ED$8,'Annual Projections'!I$8,'Redlands Pro Forma'!$B69:$ED69) -> 0 | ... M69: =SUMIF('Redlands Pro Forma'!$B$8:$ED$8,'Annual Projections'!M$8,'Redlands Pro Forma'!$B69:$ED69) -> 0
A70: Total Sale Proceeds | B70: =SUMIF('Redlands Pro Forma'!$B$8:$ED$8,'Annual Projections'!B$8,'Redlands Pro Forma'!$B70:$ED70) -> 0 | C70: =SUMIF('Redlands Pro Forma'!$B$8:$ED$8,'Annual Projections'!C$8,'Redlands Pro Forma'!$B70:$ED70) -> 0 | D70: =SUMIF('Redlands Pro Forma'!$B$8:$ED$8,'Annual Projections'!D$8,'Redlands Pro Forma'!$B70:$ED70) -> 0 | E70: =SUMIF('Redlands Pro Forma'!$B$8:$ED$8,'Annual Projections'!E$8,'Redlands Pro Forma'!$B70:$ED70) -> 0 | F70: =SUMIF('Redlands Pro Forma'!$B$8:$ED$8,'Annual Projections'!F$8,'Redlands Pro Forma'!$B70:$ED70) -> 0 | G70: =SUMIF('Redlands Pro Forma'!$B$8:$ED$8,'Annual Projections'!G$8,'Redlands Pro Forma'!$B70:$ED70) -> 0 | H70: =SUMIF('Redlands Pro Forma'!$B$8:$ED$8,'Annual Projections'!H$8,'Redlands Pro Forma'!$B70:$ED70) -> 0 | I70: =SUMIF('Redlands Pro Forma'!$B$8:$ED$8,'Annual Projections'!I$8,'Redlands Pro Forma'!$B70:$ED70) -> 0 | ... M70: =SUMIF('Redlands Pro Forma'!$B$8:$ED$8,'Annual Projections'!M$8,'Redlands Pro Forma'!$B70:$ED70) -> 0
B71: =SUMIF('Redlands Pro Forma'!$B$8:$ED$8,'Annual Projections'!B$8,'Redlands Pro Forma'!$B71:$ED71) -> 0 | C71: =SUMIF('Redlands Pro Forma'!$B$8:$ED$8,'Annual Projections'!C$8,'Redlands Pro Forma'!$B71:$ED71) -> 0 | D71: =SUMIF('Redlands Pro Forma'!$B$8:$ED$8,'Annual Projections'!D$8,'Redlands Pro Forma'!$B71:$ED71) -> 0 | E71: =SUMIF('Redlands Pro Forma'!$B$8:$ED$8,'Annual Projections'!E$8,'Redlands Pro Forma'!$B71:$ED71) -> 0 | F71: =SUMIF('Redlands Pro Forma'!$B$8:$ED$8,'Annual Projections'!F$8,'Redlands Pro Forma'!$B71:$ED71) -> 0 | G71: =SUMIF('Redlands Pro Forma'!$B$8:$ED$8,'Annual Projections'!G$8,'Redlands Pro Forma'!$B71:$ED71) -> 0 | H71: =SUMIF('Redlands Pro Forma'!$B$8:$ED$8,'Annual Projections'!H$8,'Redlands Pro Forma'!$B71:$ED71) -> 0 | I71: =SUMIF('Redlands Pro Forma'!$B$8:$ED$8,'Annual Projections'!I$8,'Redlands Pro Forma'!$B71:$ED71) -> 0 | ... M71: =SUMIF('Redlands Pro Forma'!$B$8:$ED$8,'Annual Projections'!M$8,'Redlands Pro Forma'!$B71:$ED71) -> 0
A72: Asset Cash Flow | B72: =SUMIF('Redlands Pro Forma'!$B$8:$ED$8,'Annual Projections'!B$8,'Redlands Pro Forma'!$B72:$ED72) -> -68625600 | C72: =SUMIF('Redlands Pro Forma'!$B$8:$ED$8,'Annual Projections'!C$8,'Redlands Pro Forma'!$B72:$ED72) -> 2359535 | D72: =SUMIF('Redlands Pro Forma'!$B$8:$ED$8,'Annual Projections'!D$8,'Redlands Pro Forma'!$B72:$ED72) -> 2423756 | E72: =SUMIF('Redlands Pro Forma'!$B$8:$ED$8,'Annual Projections'!E$8,'Redlands Pro Forma'!$B72:$ED72) -> 2489693 | F72: =SUMIF('Redlands Pro Forma'!$B$8:$ED$8,'Annual Projections'!F$8,'Redlands Pro Forma'!$B72:$ED72) -> 2557388.2 | G72: =SUMIF('Redlands Pro Forma'!$B$8:$ED$8,'Annual Projections'!G$8,'Redlands Pro Forma'!$B72:$ED72) -> 2626874.7 | H72: =SUMIF('Redlands Pro Forma'!$B$8:$ED$8,'Annual Projections'!H$8,'Redlands Pro Forma'!$B72:$ED72) -> 2698217.5 | I72: =SUMIF('Redlands Pro Forma'!$B$8:$ED$8,'Annual Projections'!I$8,'Redlands Pro Forma'!$B72:$ED72) -> 2770519.5 | ... M72: =SUMIF('Redlands Pro Forma'!$B$8:$ED$8,'Annual Projections'!M$8,'Redlands Pro Forma'!$B72:$ED72) -> 0
A74: Asset IRR | B74: =IRR(B72:L72) -> 0.082707284
A75: Asset MOIC | B75: =SUMIF(B72:M72,">0")/-SUMIF(B72:M72,"<0") -> 2.0395921

Sheet Redlands Pro Forma
C1: year 1-5 | D1: year 6-10
A2: Market Rent Inflation | C2: 0.03 | D2: 0.022
A3: Expense Inflation | C3: 0.025
A4: Cash Flow Projections
A5: Redlands Industrial Property
B7: Actuals | C7: Forecast | D7: Forecast | E7: Forecast | F7: Forecast | G7: Forecast | H7: Forecast | I7: Forecast | J7: Forecast | K7: Forecast | L7: Forecast | M7: Forecast | N7: Forecast | O7: Forecast | P7: Forecast | Q7: Forecast | R7: Forecast | S7: Forecast | T7: Forecast | U7: Forecast | V7: Forecast | W7: Forecast | X7: Forecast | Y7: Forecast | Z7: Forecast | AA7: Forecast | AB7: Forecast | AC7: Forecast | AD7: Forecast | AE7: Forecast | AF7: Forecast | AG7: Forecast | AH7: Forecast | AI7: Forecast | AJ7: Forecast | AK7: Forecast | AL7: Forecast | AM7: Forecast | AN7: Forecast | AO7: Forecast | AP7: Forecast | AQ7: Forecast | AR7: Forecast | AS7: Forecast | AT7: Forecast | AU7: Forecast | AV7: Forecast | AW7: Forecast | AX7: Forecast | AY7: Forecast | AZ7: Forecast | BA7: Forecast | BB7: Forecast | BC7: Forecast | BD7: Forecast | BE7: Forecast | BF7: Forecast | BG7: Forecast | BH7: Forecast | BI7: Forecast | BJ7: Forecast | BK7: Forecast | BL7: Forecast | BM7: Forecast | BN7: Forecast | BO7: Forecast | BP7: Forecast | BQ7: Forecast | BR7: Forecast | BS7: Forecast | BT7: Forecast | BU7: Forecast | BV7: Forecast | BW7: Forecast | BX7: Forecast | BY7: Forecast | BZ7: Forecast | CA7: Forecast | CB7: Forecast | CC7: Forecast | CD7: Forecast | CE7: Forecast | CF7: Forecast | CG7: Forecast | CH7: Forecast | CI7: Forecast | CJ7: Forecast | CK7: Forecast | CL7: Forecast | CM7: Forecast | CN7: Forecast | CO7: Forecast | CP7: Forecast | CQ7: Forecast | CR7: Forecast | CS7: Forecast | CT7: Forecast | CU7: Forecast | CV7: Forecast | CW7: Forecast | CX7: Forecast | CY7: Forecast | CZ7: Forecast | DA7: Forecast | DB7: Forecast | DC7: Forecast | DD7: Forecast | DE7: Forecast | DF7: Forecast | DG7: Forecast | DH7: Forecast | DI7: Forecast | DJ7: Forecast | DK7: Forecast | DL7: Forecast | DM7: Forecast | DN7: Forecast | DO7: Forecast | DP7: Forecast | DQ7: Forecast | DR7: Forecast | DS7: Forecast | DT7: Forecast | DU7: Forecast | DV7: Forecast | DW7: Forecast | DX7: Forecast | DY7: Forecast | DZ7: Forecast | EA7: Forecast | EB7: Forecast | EC7: Forecast | ED7: Forecast
B8: =ROUNDUP(B$9/12,0) -> 0 | C8: =ROUNDUP(C$9/12,0) -> 1 | D8: =ROUNDUP(D$9/12,0) -> 1 | E8: =ROUNDUP(E$9/12,0) -> 1 | F8: =ROUNDUP(F$9/12,0) -> 1 | G8: =ROUNDUP(G$9/12,0) -> 1 | H8: =ROUNDUP(H$9/12,0) -> 1 | I8: =ROUNDUP(I$9/12,0) -> 1 | ... ED8: =ROUNDUP(ED$9/12,0) -> 11
C9: {=_xlfn.SEQUENCE(1,('Redlands Inputs'!$D$15+1)*12,1,1)} -> 1 | D9: 2 | E9: 3 | F9: 4 | G9: 5 | H9: 6 | I9: 7 | J9: 8 | K9: 9 | L9: 10 | M9: 11 | N9: 12 | O9: 13 | P9: 14 | Q9: 15 | R9: 16 | S9: 17 | T9: 18 | U9: 19 | V9: 20 | W9: 21 | X9: 22 | Y9: 23 | Z9: 24 | AA9: 25 | AB9: 26 | AC9: 27 | AD9: 28 | AE9: 29 | AF9: 30 | AG9: 31 | AH9: 32 | AI9: 33 | AJ9: 34 | AK9: 35 | AL9: 36 | AM9: 37 | AN9: 38 | AO9: 39 | AP9: 40 | AQ9: 41 | AR9: 42 | AS9: 43 | AT9: 44 | AU9: 45 | AV9: 46 | AW9: 47 | AX9: 48 | AY9: 49 | AZ9: 50 | BA9: 51 | BB9: 52 | BC9: 53 | BD9: 54 | BE9: 55 | BF9: 56 | BG9: 57 | BH9: 58 | BI9: 59 | BJ9: 60 | BK9: 61 | BL9: 62 | BM9: 63 | BN9: 64 | BO9: 65 | BP9: 66 | BQ9: 67 | BR9: 68 | BS9: 69 | BT9: 70 | BU9: 71 | BV9: 72 | BW9: 73 | BX9: 74 | BY9: 75 | BZ9: 76 | CA9: 77 | CB9: 78 | CC9: 79 | CD9: 80 | CE9: 81 | CF9: 82 | CG9: 83 | CH9: 84 | CI9: 85 | CJ9: 86 | CK9: 87 | CL9: 88 | CM9: 89 | CN9: 90 | CO9: 91 | CP9: 92 | CQ9: 93 | CR9: 94 | CS9: 95 | CT9: 96 | CU9: 97 | CV9: 98 | CW9: 99 | CX9: 100 | CY9: 101 | CZ9: 102 | DA9: 103 | DB9: 104 | DC9: 105 | DD9: 106 | DE9: 107 | DF9: 108 | DG9: 109 | DH9: 110 | DI9: 111 | DJ9: 112 | DK9: 113 | DL9: 114 | DM9: 115 | DN9: 116 | DO9: 117 | DP9: 118 | DQ9: 119 | DR9: 120 | DS9: 121 | DT9: 122 | DU9: 123 | DV9: 124 | DW9: 125 | DX9: 126 | DY9: 127 | DZ9: 128 | EA9: 129 | EB9: 130 | EC9: 131 | ED9: 132
A10: Months | B10: =EOMONTH(C10,-12) -> 45322 | C10: =EOMONTH('Redlands Inputs'!D14,0) -> 45688 | D10: =EOMONTH(C10,1) -> 45716 | E10: =EOMONTH(D10,1) -> 45747 | F10: =EOMONTH(E10,1) -> 45777 | G10: =EOMONTH(F10,1) -> 45808 | H10: =EOMONTH(G10,1) -> 45838 | I10: =EOMONTH(H10,1) -> 45869 | J10: =EOMONTH(I10,1) -> 45900 | K10: =EOMONTH(J10,1) -> 45930 | ... ED10: =EOMONTH(EC10,1) -> 49674
A12: Rental Revenue
A13: Base Rent / SF | C13: =(C14/'Redlands Inputs'!$D$7)*12 -> 6.4997762 | D13: =(D14/'Redlands Inputs'!$D$7)*12 -> 6.4997762 | E13: =(E14/'Redlands Inputs'!$D$7)*12 -> 6.4997762 | F13: =(F14/'Redlands Inputs'!$D$7)*12 -> 6.4997762 | G13: =(G14/'Redlands Inputs'!$D$7)*12 -> 6.4997762 | H13: =(H14/'Redlands Inputs'!$D$7)*12 -> 6.4997762 | I13: =(I14/'Redlands Inputs'!$D$7)*12 -> 6.4997762 | J13: =(J14/'Redlands Inputs'!$D$7)*12 -> 6.4997762 | ... ED13: =(ED14/'Redlands Inputs'!$D$7)*12 -> 11.520761
A14: Potential Base Rent | C14: {=_xlfn.IFS('Redlands Inputs'!$G$12="Vacate", _xlfn.IFS(C$9=1,'Redlands Inputs'!$G$22, C$10<='Redlands Inputs'!$H$20,'Redlands Inputs'!$G$22*(1+'Redlands Inputs'!$H$23)^(C$8-1), C$10>'Redlands Inputs'!$H$20,'Redlands Inputs'!$C$26*(1+'Redlands Inputs'!$D$28)^(C$8-1)), 'Redlands Inputs'!$G$12="Market", _xlfn.IFS(C$9=1,'Redlands Inputs'!$G$22, C$10<='Redlands Inputs'!$H$20,'Redlands Inputs'!$G$22*(1+'Redlands Inputs'!$H$23)^(C$8-1), C$10>'Redlands Inputs'!$H$20,(('Redlands Inputs'!$K$17*'Redlands Inputs'!$H$17)/12)*(1+'Redlands Inputs'!$D$28)^(C$8-1)))} -> 324988.81 | D14: {=_xlfn.IFS('Redlands Inputs'!$G$12="Vacate", _xlfn.IFS(D$9=1,'Redlands Inputs'!$G$22, D$10<='Redlands Inputs'!$H$20,'Redlands Inputs'!$G$22*(1+'Redlands Inputs'!$H$23)^(D$8-1), D$10>'Redlands Inputs'!$H$20,'Redlands Inputs'!$C$26*(1+'Redlands Inputs'!$D$28)^(D$8-1)), 'Redlands Inputs'!$G$12="Market", _xlfn.IFS(D$9=1,'Redlands Inputs'!$G$22, D$10<='Redlands Inputs'!$H$20,'Redlands Inputs'!$G$22*(1+'Redlands Inputs'!$H$23)^(D$8-1), D$10>'Redlands Inputs'!$H$20,(('Redlands Inputs'!$K$17*'Redlands Inputs'!$H$17)/12)*(1+'Redlands Inputs'!$D$28)^(D$8-1)))} -> 324988.81 | E14: {=_xlfn.IFS('Redlands Inputs'!$G$12="Vacate", _xlfn.IFS(E$9=1,'Redlands Inputs'!$G$22, E$10<='Redlands Inputs'!$H$20,'Redlands Inputs'!$G$22*(1+'Redlands Inputs'!$H$23)^(E$8-1), E$10>'Redlands Inputs'!$H$20,'Redlands Inputs'!$C$26*(1+'Redlands Inputs'!$D$28)^(E$8-1)), 'Redlands Inputs'!$G$12="Market", _xlfn.IFS(E$9=1,'Redlands Inputs'!$G$22, E$10<='Redlands Inputs'!$H$20,'Redlands Inputs'!$G$22*(1+'Redlands Inputs'!$H$23)^(E$8-1), E$10>'Redlands Inputs'!$H$20,(('Redlands Inputs'!$K$17*'Redlands Inputs'!$H$17)/12)*(1+'Redlands Inputs'!$D$28)^(E$8-1)))} -> 324988.81 | F14: {=_xlfn.IFS('Redlands Inputs'!$G$12="Vacate", _xlfn.IFS(F$9=1,'Redlands Inputs'!$G$22, F$10<='Redlands Inputs'!$H$20,'Redlands Inputs'!$G$22*(1+'Redlands Inputs'!$H$23)^(F$8-1), F$10>'Redlands Inputs'!$H$20,'Redlands Inputs'!$C$26*(1+'Redlands Inputs'!$D$28)^(F$8-1)), 'Redlands Inputs'!$G$12="Market", _xlfn.IFS(F$9=1,'Redlands Inputs'!$G$22, F$10<='Redlands Inputs'!$H$20,'Redlands Inputs'!$G$22*(1+'Redlands Inputs'!$H$23)^(F$8-1), F$10>'Redlands Inputs'!$H$20,(('Redlands Inputs'!$K$17*'Redlands Inputs'!$H$17)/12)*(1+'Redlands Inputs'!$D$28)^(F$8-1)))} -> 324988.81 | G14: {=_xlfn.IFS('Redlands Inputs'!$G$12="Vacate", _xlfn.IFS(G$9=1,'Redlands Inputs'!$G$22, G$10<='Redlands Inputs'!$H$20,'Redlands Inputs'!$G$22*(1+'Redlands Inputs'!$H$23)^(G$8-1), G$10>'Redlands Inputs'!$H$20,'Redlands Inputs'!$C$26*(1+'Redlands Inputs'!$D$28)^(G$8-1)), 'Redlands Inputs'!$G$12="Market", _xlfn.IFS(G$9=1,'Redlands Inputs'!$G$22, G$10<='Redlands Inputs'!$H$20,'Redlands Inputs'!$G$22*(1+'Redlands Inputs'!$H$23)^(G$8-1), G$10>'Redlands Inputs'!$H$20,(('Redlands Inputs'!$K$17*'Redlands Inputs'!$H$17)/12)*(1+'Redlands Inputs'!$D$28)^(G$8-1)))} -> 324988.81 | H14: {=_xlfn.IFS('Redlands Inputs'!$G$12="Vacate", _xlfn.IFS(H$9=1,'Redlands Inputs'!$G$22, H$10<='Redlands Inputs'!$H$20,'Redlands Inputs'!$G$22*(1+'Redlands Inputs'!$H$23)^(H$8-1), H$10>'Redlands Inputs'!$H$20,'Redlands Inputs'!$C$26*(1+'Redlands Inputs'!$D$28)^(H$8-1)), 'Redlands Inputs'!$G$12="Market", _xlfn.IFS(H$9=1,'Redlands Inputs'!$G$22, H$10<='Redlands Inputs'!$H$20,'Redlands Inputs'!$G$22*(1+'Redlands Inputs'!$H$23)^(H$8-1), H$10>'Redlands Inputs'!$H$20,(('Redlands Inputs'!$K$17*'Redlands Inputs'!$H$17)/12)*(1+'Redlands Inputs'!$D$28)^(H$8-1)))} -> 324988.81 | I14: {=_xlfn.IFS('Redlands Inputs'!$G$12="Vacate", _xlfn.IFS(I$9=1,'Redlands Inputs'!$G$22, I$10<='Redlands Inputs'!$H$20,'Redlands Inputs'!$G$22*(1+'Redlands Inputs'!$H$23)^(I$8-1), I$10>'Redlands Inputs'!$H$20,'Redlands Inputs'!$C$26*(1+'Redlands Inputs'!$D$28)^(I$8-1)), 'Redlands Inputs'!$G$12="Market", _xlfn.IFS(I$9=1,'Redlands Inputs'!$G$22, I$10<='Redlands Inputs'!$H$20,'Redlands Inputs'!$G$22*(1+'Redlands Inputs'!$H$23)^(I$8-1), I$10>'Redlands Inputs'!$H$20,(('Redlands Inputs'!$K$17*'Redlands Inputs'!$H$17)/12)*(1+'Redlands Inputs'!$D$28)^(I$8-1)))} -> 324988.81 | J14: {=_xlfn.IFS('Redlands Inputs'!$G$12="Vacate", _xlfn.IFS(J$9=1,'Redlands Inputs'!$G$22, J$10<='Redlands Inputs'!$H$20,'Redlands Inputs'!$G$22*(1+'Redlands Inputs'!$H$23)^(J$8-1), J$10>'Redlands Inputs'!$H$20,'Redlands Inputs'!$C$26*(1+'Redlands Inputs'!$D$28)^(J$8-1)), 'Redlands Inputs'!$G$12="Market", _xlfn.IFS(J$9=1,'Redlands Inputs'!$G$22, J$10<='Redlands Inputs'!$H$20,'Redlands Inputs'!$G$22*(1+'Redlands Inputs'!$H$23)^(J$8-1), J$10>'Redlands Inputs'!$H$20,(('Redlands Inputs'!$K$17*'Redlands Inputs'!$H$17)/12)*(1+'Redlands Inputs'!$D$28)^(J$8-1)))} -> 324988.81 | ... ED14: {=_xlfn.IFS('Redlands Inputs'!$G$12="Vacate", _xlfn.IFS(ED$9=1,'Redlands Inputs'!$G$22, ED$10<='Redlands Inputs'!$H$20,'Redlands Inputs'!$G$22*(1+'Redlands Inputs'!$H$23)^(ED$8-1), ED$10>'Redlands Inputs'!$H$20,'Redlands Inputs'!$C$26*(1+'Redlands Inputs'!$D$28)^(ED$8-1)), 'Redlands Inputs'!$G$12="Market", _xlfn.IFS(ED$9=1,'Redlands Inputs'!$G$22, ED$10<='Redlands Inputs'!$H$20,'Redlands Inputs'!$G$22*(1+'Redlands Inputs'!$H$23)^(ED$8-1), ED$10>'Redlands Inputs'!$H$20,(('Redlands Inputs'!$K$17*'Redlands Inputs'!$H$17)/12)*(1+'Redlands Inputs'!$D$28)^(ED$8-1)))} -> 576038.04
A15: Vacancy & Turnover | C15: {=_xlfn.IFS('Redlands Inputs'!$G$12="Vacate", IF(AND(C10>'Redlands Inputs'!$H$20,C10<'Redlands Inputs'!$D$24)=TRUE,-C$14,0), 'Redlands Inputs'!$G$12="Market", IF(AND(C10>'Redlands Inputs'!$H$20,C10<EOMONTH('Redlands Inputs'!$H$20,'Redlands Inputs'!$K$18))=TRUE,-C$14,0), 'Redlands Inputs'!$G$12="Renew",0)} -> 0 | D15: {=_xlfn.IFS('Redlands Inputs'!$G$12="Vacate", IF(AND(D10>'Redlands Inputs'!$H$20,D10<'Redlands Inputs'!$D$24)=TRUE,-D$14,0), 'Redlands Inputs'!$G$12="Market", IF(AND(D10>'Redlands Inputs'!$H$20,D10<EOMONTH('Redlands Inputs'!$H$20,'Redlands Inputs'!$K$18))=TRUE,-D$14,0), 'Redlands Inputs'!$G$12="Renew",0)} -> 0 | E15: {=_xlfn.IFS('Redlands Inputs'!$G$12="Vacate", IF(AND(E10>'Redlands Inputs'!$H$20,E10<'Redlands Inputs'!$D$24)=TRUE,-E$14,0), 'Redlands Inputs'!$G$12="Market", IF(AND(E10>'Redlands Inputs'!$H$20,E10<EOMONTH('Redlands Inputs'!$H$20,'Redlands Inputs'!$K$18))=TRUE,-E$14,0), 'Redlands Inputs'!$G$12="Renew",0)} -> 0 | F15: {=_xlfn.IFS('Redlands Inputs'!$G$12="Vacate", IF(AND(F10>'Redlands Inputs'!$H$20,F10<'Redlands Inputs'!$D$24)=TRUE,-F$14,0), 'Redlands Inputs'!$G$12="Market", IF(AND(F10>'Redlands Inputs'!$H$20,F10<EOMONTH('Redlands Inputs'!$H$20,'Redlands Inputs'!$K$18))=TRUE,-F$14,0), 'Redlands Inputs'!$G$12="Renew",0)} -> 0 | G15: {=_xlfn.IFS('Redlands Inputs'!$G$12="Vacate", IF(AND(G10>'Redlands Inputs'!$H$20,G10<'Redlands Inputs'!$D$24)=TRUE,-G$14,0), 'Redlands Inputs'!$G$12="Market", IF(AND(G10>'Redlands Inputs'!$H$20,G10<EOMONTH('Redlands Inputs'!$H$20,'Redlands Inputs'!$K$18))=TRUE,-G$14,0), 'Redlands Inputs'!$G$12="Renew",0)} -> 0 | H15: {=_xlfn.IFS('Redlands Inputs'!$G$12="Vacate", IF(AND(H10>'Redlands Inputs'!$H$20,H10<'Redlands Inputs'!$D$24)=TRUE,-H$14,0), 'Redlands Inputs'!$G$12="Market", IF(AND(H10>'Redlands Inputs'!$H$20,H10<EOMONTH('Redlands Inputs'!$H$20,'Redlands Inputs'!$K$18))=TRUE,-H$14,0), 'Redlands Inputs'!$G$12="Renew",0)} -> 0 | I15: {=_xlfn.IFS('Redlands Inputs'!$G$12="Vacate", IF(AND(I10>'Redlands Inputs'!$H$20,I10<'Redlands Inputs'!$D$24)=TRUE,-I$14,0), 'Redlands Inputs'!$G$12="Market", IF(AND(I10>'Redlands Inputs'!$H$20,I10<EOMONTH('Redlands Inputs'!$H$20,'Redlands Inputs'!$K$18))=TRUE,-I$14,0), 'Redlands Inputs'!$G$12="Renew",0)} -> 0 | J15: {=_xlfn.IFS('Redlands Inputs'!$G$12="Vacate", IF(AND(J10>'Redlands Inputs'!$H$20,J10<'Redlands Inputs'!$D$24)=TRUE,-J$14,0), 'Redlands Inputs'!$G$12="Market", IF(AND(J10>'Redlands Inputs'!$H$20,J10<EOMONTH('Redlands Inputs'!$H$20,'Redlands Inputs'!$K$18))=TRUE,-J$14,0), 'Redlands Inputs'!$G$12="Renew",0)} -> 0 | ... ED15: {=_xlfn.IFS('Redlands Inputs'!$G$12="Vacate", IF(AND(ED10>'Redlands Inputs'!$H$20,ED10<'Redlands Inputs'!$D$24)=TRUE,-ED$14,0), 'Redlands Inputs'!$G$12="Market", IF(AND(ED10>'Redlands Inputs'!$H$20,ED10<EOMONTH('Redlands Inputs'!$H$20,'Redlands Inputs'!$K$18))=TRUE,-ED$14,0), 'Redlands Inputs'!$G$12="Renew",0)} -> 0
A16: Free Rent / Concessions
A17: Total Base Rent | C17: =SUM(C14:C16) -> 324988.81 | D17: =SUM(D14:D16) -> 324988.81 | E17: =SUM(E14:E16) -> 324988.81 | F17: =SUM(F14:F16) -> 324988.81 | G17: =SUM(G14:G16) -> 324988.81 | H17: =SUM(H14:H16) -> 324988.81 | I17: =SUM(I14:I16) -> 324988.81 | J17: =SUM(J14:J16) -> 324988.81 | ... ED17: =SUM(ED14:ED16) -> 576038.04
A18: Total Rental Revenue | C18: =C17 -> 324988.81 | D18: =D17 -> 324988.81 | E18: =E17 -> 324988.81 | F18: =F17 -> 324988.81 | G18: =G17 -> 324988.81 | H18: =H17 -> 324988.81 | I18: =I17 -> 324988.81 | J18: =J17 -> 324988.81 | ... ED18: =ED17 -> 576038.04
A20: Other Tenant Revenue
A21: Utilities | C21: =IF(C$15<>0,0,$C39) -> 3750 | D21: =IF(D$15<>0,0,$C39) -> 3750 | E21: =IF(E$15<>0,0,$C39) -> 3750 | F21: =IF(F$15<>0,0,$C39) -> 3750 | G21: =IF(G$15<>0,0,$C39) -> 3750 | H21: =IF(H$15<>0,0,$C39) -> 3750 | I21: =IF(I$15<>0,0,$C39) -> 3750 | J21: =IF(J$15<>0,0,$C39) -> 3750 | ... ED21: =IF(ED$15<>0,0,$C39) -> 3750
A22: Repairs & Maintenance | C22: =IF(C$15<>0,0,$C40) -> 3750 | D22: =IF(D$15<>0,0,$C40) -> 3750 | E22: =IF(E$15<>0,0,$C40) -> 3750 | F22: =IF(F$15<>0,0,$C40) -> 3750 | G22: =IF(G$15<>0,0,$C40) -> 3750 | H22: =IF(H$15<>0,0,$C40) -> 3750 | I22: =IF(I$15<>0,0,$C40) -> 3750 | J22: =IF(J$15<>0,0,$C40) -> 3750 | ... ED22: =IF(ED$15<>0,0,$C40) -> 3750
A23: Insurance | C23: =IF(C$15<>0,0,$C41) -> 1666.6667 | D23: =IF(D$15<>0,0,$C41) -> 1666.6667 | E23: =IF(E$15<>0,0,$C41) -> 1666.6667 | F23: =IF(F$15<>0,0,$C41) -> 1666.6667 | G23: =IF(G$15<>0,0,$C41) -> 1666.6667 | H23: =IF(H$15<>0,0,$C41) -> 1666.6667 | I23: =IF(I$15<>0,0,$C41) -> 1666.6667 | J23: =IF(J$15<>0,0,$C41) -> 1666.6667 | ... ED23: =IF(ED$15<>0,0,$C41) -> 1666.6667
A24: Property Taxes | C24: =IF(C15<>0,0,IF(C$10<'Redlands Inputs'!$H$20,'Redlands Inputs'!$H$7*(1+'Redlands Inputs'!$L$6)^(C$8-1),C$42)) -> 12500 | D24: =IF(D15<>0,0,IF(D$10<'Redlands Inputs'!$H$20,'Redlands Inputs'!$H$7*(1+'Redlands Inputs'!$L$6)^(D$8-1),D$42)) -> 12500 | E24: =IF(E15<>0,0,IF(E$10<'Redlands Inputs'!$H$20,'Redlands Inputs'!$H$7*(1+'Redlands Inputs'!$L$6)^(E$8-1),E$42)) -> 12500 | F24: =IF(F15<>0,0,IF(F$10<'Redlands Inputs'!$H$20,'Redlands Inputs'!$H$7*(1+'Redlands Inputs'!$L$6)^(F$8-1),F$42)) -> 12500 | G24: =IF(G15<>0,0,IF(G$10<'Redlands Inputs'!$H$20,'Redlands Inputs'!$H$7*(1+'Redlands Inputs'!$L$6)^(G$8-1),G$42)) -> 12500 | H24: =IF(H15<>0,0,IF(H$10<'Redlands Inputs'!$H$20,'Redlands Inputs'!$H$7*(1+'Redlands Inputs'!$L$6)^(H$8-1),H$42)) -> 12500 | I24: =IF(I15<>0,0,IF(I$10<'Redlands Inputs'!$H$20,'Redlands Inputs'!$H$7*(1+'Redlands Inputs'!$L$6)^(I$8-1),I$42)) -> 12500 | J24: =IF(J15<>0,0,IF(J$10<'Redlands Inputs'!$H$20,'Redlands Inputs'!$H$7*(1+'Redlands Inputs'!$L$6)^(J$8-1),J$42)) -> 12500 | ... ED24: =IF(ED15<>0,0,IF(ED$10<'Redlands Inputs'!$H$20,'Redlands Inputs'!$H$7*(1+'Redlands Inputs'!$L$6)^(ED$8-1),ED$42)) -> 75179.449
A25: Total Expense Recoveries | C25: =SUM(C21:C24) -> 21666.667 | D25: =SUM(D21:D24) -> 21666.667 | E25: =SUM(E21:E24) -> 21666.667 | F25: =SUM(F21:F24) -> 21666.667 | G25: =SUM(G21:G24) -> 21666.667 | H25: =SUM(H21:H24) -> 21666.667 | I25: =SUM(I21:I24) -> 21666.667 | J25: =SUM(J21:J24) -> 21666.667 | ... ED25: =SUM(ED21:ED24) -> 84346.116
A26: Total Other Tenant Revenue | C26: =SUM(C25) -> 21666.667 | D26: =SUM(D25) -> 21666.667 | E26: =SUM(E25) -> 21666.667 | F26: =SUM(F25) -> 21666.667 | G26: =SUM(G25) -> 21666.667 | H26: =SUM(H25) -> 21666.667 | I26: =SUM(I25) -> 21666.667 | J26: =SUM(J25) -> 21666.667 | ... ED26: =SUM(ED25) -> 84346.116
A28: Total Tenant Revenue | C28: =C18+C26 -> 346655.48 | D28: =D18+D26 -> 346655.48 | E28: =E18+E26 -> 346655.48 | F28: =F18+F26 -> 346655.48 | G28: =G18+G26 -> 346655.48 | H28: =H18+H26 -> 346655.48 | I28: =I18+I26 -> 346655.48 | J28: =J18+J26 -> 346655.48 | ... ED28: =ED18+ED26 -> 660384.16
A30: Potential Gross Revenue | C30: =C28 -> 346655.48 | D30: =D28 -> 346655.48 | E30: =E28 -> 346655.48 | F30: =F28 -> 346655.48 | G30: =G28 -> 346655.48 | H30: =H28 -> 346655.48 | I30: =I28 -> 346655.48 | J30: =J28 -> 346655.48 | ... ED30: =ED28 -> 660384.16
A32: Vacancy & Loss to Lease
A33: Vacancy & L2L | C33: =C30*-'Redlands Inputs'!$D$11 -> -34665.548 | D33: =D30*-'Redlands Inputs'!$D$11 -> -34665.548 | E33: =E30*-'Redlands Inputs'!$D$11 -> -34665.548 | F33: =F30*-'Redlands Inputs'!$D$11 -> -34665.548 | G33: =G30*-'Redlands Inputs'!$D$11 -> -34665.548 | H33: =H30*-'Redlands Inputs'!$D$11 -> -34665.548 | I33: =I30*-'Redlands Inputs'!$D$11 -> -34665.548 | J33: =J30*-'Redlands Inputs'!$D$11 -> -34665.548 | ... ED33: =ED30*-'Redlands Inputs'!$D$11 -> -66038.416
A34: Total Vacancy & Credit Loss | C34: =C33 -> -34665.548 | D34: =D33 -> -34665.548 | E34: =E33 -> -34665.548 | F34: =F33 -> -34665.548 | G34: =G33 -> -34665.548 | H34: =H33 -> -34665.548 | I34: =I33 -> -34665.548 | J34: =J33 -> -34665.548 | ... ED34: =ED33 -> -66038.416
A36: Effective Gross Revenue | C36: =C30+C34 -> 311989.93 | D36: =D30+D34 -> 311989.93 | E36: =E30+E34 -> 311989.93 | F36: =F30+F34 -> 311989.93 | G36: =G30+G34 -> 311989.93 | H36: =H30+H34 -> 311989.93 | I36: =I30+I34 -> 311989.93 | J36: =J30+J34 -> 311989.93 | ... ED36: =ED30+ED34 -> 594345.74
A38: Operating Expenses
A39: Utilities | C39: ='Redlands Inputs'!$H3 -> 3750 | D39: ='Redlands Inputs'!$H3*(1+$C$3)^(D$8-1) -> 3750 | E39: ='Redlands Inputs'!$H3*(1+$C$3)^(E$8-1) -> 3750 | F39: ='Redlands Inputs'!$H3*(1+$C$3)^(F$8-1) -> 3750 | G39: ='Redlands Inputs'!$H3*(1+$C$3)^(G$8-1) -> 3750 | H39: ='Redlands Inputs'!$H3*(1+$C$3)^(H$8-1) -> 3750 | I39: ='Redlands Inputs'!$H3*(1+$C$3)^(I$8-1) -> 3750 | J39: ='Redlands Inputs'!$H3*(1+$C$3)^(J$8-1) -> 3750 | K39: ='Redlands Inputs'!$H3*(1+$C$3)^(K$8-1) -> 3750 | ... ED39: ='Redlands Inputs'!$H3*(1+$C$3)^(ED$8-1) -> 4800.317
A40: Repairs & Maintenance | C40: ='Redlands Inputs'!$H4 -> 3750 | D40: ='Redlands Inputs'!$H4*(1+$C$3)^(D$8-1) -> 3750 | E40: ='Redlands Inputs'!$H4*(1+$C$3)^(E$8-1) -> 3750 | F40: ='Redlands Inputs'!$H4*(1+$C$3)^(F$8-1) -> 3750 | G40: ='Redlands Inputs'!$H4*(1+$C$3)^(G$8-1) -> 3750 | H40: ='Redlands Inputs'!$H4*(1+$C$3)^(H$8-1) -> 3750 | I40: ='Redlands Inputs'!$H4*(1+$C$3)^(I$8-1) -> 3750 | J40: ='Redlands Inputs'!$H4*(1+$C$3)^(J$8-1) -> 3750 | K40: ='Redlands Inputs'!$H4*(1+$C$3)^(K$8-1) -> 3750 | ... ED40: ='Redlands Inputs'!$H4*(1+$C$3)^(ED$8-1) -> 4800.317
A41: Insurance | C41: ='Redlands Inputs'!$H5 -> 1666.6667 | D41: ='Redlands Inputs'!$H5*(1+$C$3)^(D$8-1) -> 1666.6667 | E41: ='Redlands Inputs'!$H5*(1+$C$3)^(E$8-1) -> 1666.6667 | F41: ='Redlands Inputs'!$H5*(1+$C$3)^(F$8-1) -> 1666.6667 | G41: ='Redlands Inputs'!$H5*(1+$C$3)^(G$8-1) -> 1666.6667 | H41: ='Redlands Inputs'!$H5*(1+$C$3)^(H$8-1) -> 1666.6667 | I41: ='Redlands Inputs'!$H5*(1+$C$3)^(I$8-1) -> 1666.6667 | J41: ='Redlands Inputs'!$H5*(1+$C$3)^(J$8-1) -> 1666.6667 | K41: ='Redlands Inputs'!$H5*(1+$C$3)^(K$8-1) -> 1666.6667 | ... ED41: ='Redlands Inputs'!$H5*(1+$C$3)^(ED$8-1) -> 2133.4742
A42: Property Taxes | C42: ='Redlands Inputs'!H6 -> 61673.333 | D42: ='Redlands Inputs'!$H6*(1+'Redlands Inputs'!$L$6)^(D$8-1) -> 61673.333 | E42: ='Redlands Inputs'!$H6*(1+'Redlands Inputs'!$L$6)^(E$8-1) -> 61673.333 | F42: ='Redlands Inputs'!$H6*(1+'Redlands Inputs'!$L$6)^(F$8-1) -> 61673.333 | G42: ='Redlands Inputs'!$H6*(1+'Redlands Inputs'!$L$6)^(G$8-1) -> 61673.333 | H42: ='Redlands Inputs'!$H6*(1+'Redlands Inputs'!$L$6)^(H$8-1) -> 61673.333 | I42: ='Redlands Inputs'!$H6*(1+'Redlands Inputs'!$L$6)^(I$8-1) -> 61673.333 | J42: ='Redlands Inputs'!$H6*(1+'Redlands Inputs'!$L$6)^(J$8-1) -> 61673.333 | K42: ='Redlands Inputs'!$H6*(1+'Redlands Inputs'!$L$6)^(K$8-1) -> 61673.333 | ... ED42: ='Redlands Inputs'!$H6*(1+'Redlands Inputs'!$L$6)^(ED$8-1) -> 75179.449
A43: Management Fee | C43: =C$36*'Redlands Inputs'!$I$8 -> 9359.6978 | D43: =D$36*'Redlands Inputs'!$I$8 -> 9359.6978 | E43: =E$36*'Redlands Inputs'!$I$8 -> 9359.6978 | F43: =F$36*'Redlands Inputs'!$I$8 -> 9359.6978 | G43: =G$36*'Redlands Inputs'!$I$8 -> 9359.6978 | H43: =H$36*'Redlands Inputs'!$I$8 -> 9359.6978 | I43: =I$36*'Redlands Inputs'!$I$8 -> 9359.6978 | J43: =J$36*'Redlands Inputs'!$I$8 -> 9359.6978 | ... ED43: =ED$36*'Redlands Inputs'!$I$8 -> 17830.372
A44: Total Operating Expenses | C44: =+SUM(C39:C43) -> 80199.698 | D44: =+SUM(D39:D43) -> 80199.698 | E44: =+SUM(E39:E43) -> 80199.698 | F44: =+SUM(F39:F43) -> 80199.698 | G44: =+SUM(G39:G43) -> 80199.698 | H44: =+SUM(H39:H43) -> 80199.698 | I44: =+SUM(I39:I43) -> 80199.698 | J44: =+SUM(J39:J43) -> 80199.698 | ... ED44: =+SUM(ED39:ED43) -> 104743.93
A46: Net Operating Income | C46: 246690 | D46: 246690 | E46: 246690 | F46: 246690 | G46: 246690 | H46: 246690 | I46: 246690 | J46: 246690 | K46: 246690 | L46: 246690 | M46: 246690 | N46: 245945 | O46: 253043 | P46: 253043 | Q46: 253043 | R46: 253043 | S46: 253043 | T46: 253043 | U46: 253043 | V46: 253043 | W46: 253043 | X46: 253043 | Y46: 253043 | Z46: 252283 | AA46: 259559 | AB46: 259559 | AC46: 259559 | AD46: 259559 | AE46: 259559 | AF46: 259559 | AG46: 259559 | AH46: 259559 | AI46: 259559 | AJ46: 259559 | AK46: 259559 | AL46: 258784 | AM46: 266242 | AN46: 266242 | AO46: 266242 | AP46: 266242 | AQ46: 266242 | AR46: 266242 | AS46: 266242 | AT46: 266242 | AU46: 266242 | AV46: 266242 | AW46: 266242 | AX46: 265451 | AY46: 273095 | AZ46: 273095 | BA46: 273095 | BB46: 273095 | BC46: 273095 | BD46: 273095 | BE46: 273095 | BF46: 273095 | BG46: 273095 | BH46: 273095 | BI46: 273095 | BJ46: 272289 | BK46: 280124 | BL46: 280124 | BM46: 280124 | BN46: 280124 | BO46: 280124 | BP46: 280124 | BQ46: 280124 | BR46: 280124 | BS46: 280124 | BT46: 280124 | BU46: 280124 | BV46: 279302 | BW46: 287333 | BX46: 287333 | BY46: 287333 | BZ46: 287333 | CA46: 287333 | CB46: 287333 | CC46: 287333 | CD46: 287333 | CE46: 287333 | CF46: 287333 | CG46: 287333 | CH46: 285554 | CI46: -58030 | CJ46: -58030 | CK46: 182680 | CL46: 522255 | CM46: 522255 | CN46: 522255 | CO46: 522255 | CP46: 522255 | CQ46: 522255 | CR46: 522255 | CS46: 522255 | CT46: 522339 | CU46: 522339 | CV46: 522339 | CW46: 536488 | CX46: 536488 | CY46: 536488 | CZ46: 536488 | DA46: 536488 | DB46: 536488 | DC46: 536488 | DD46: 536488 | DE46: 536488 | DF46: 535616 | DG46: 535616 | DH46: 535616 | DI46: 550119 | DJ46: 550119 | DK46: 550119 | DL46: 550119 | DM46: 550119 | DN46: 550119 | DO46: 550119 | DP46: 550119 | DQ46: 550119 | DR46: 549229 | DS46: 498858 | DT46: 498858 | DU46: 513724 | DV46: 513724 | DW46: 513724 | DX46: 513724 | DY46: 513724 | DZ46: 513724 | EA46: 513724 | EB46: 513724 | EC46: 513724 | ED46: 513961
A48: Leasing Costs
A49: Tenant Improvements | C49: =IF(C$10='Redlands Inputs'!$D$24,'Redlands Inputs'!$C$31,0) -> 0 | D49: =IF(D$10='Redlands Inputs'!$D$24,'Redlands Inputs'!$C$31,0) -> 0 | E49: =IF(E$10='Redlands Inputs'!$D$24,'Redlands Inputs'!$C$31,0) -> 0 | F49: =IF(F$10='Redlands Inputs'!$D$24,'Redlands Inputs'!$C$31,0) -> 0 | G49: =IF(G$10='Redlands Inputs'!$D$24,'Redlands Inputs'!$C$31,0) -> 0 | H49: =IF(H$10='Redlands Inputs'!$D$24,'Redlands Inputs'!$C$31,0) -> 0 | I49: =IF(I$10='Redlands Inputs'!$D$24,'Redlands Inputs'!$C$31,0) -> 0 | J49: =IF(J$10='Redlands Inputs'!$D$24,'Redlands Inputs'!$C$31,0) -> 0 | ... ED49: =IF(ED$10='Redlands Inputs'!$D$24,'Redlands Inputs'!$C$31,0) -> 0
A50: Leasing Commissions | C50: =IF(C$10=EDATE('Redlands Inputs'!$D$24,-2),'Redlands Inputs'!$C$34/2,IF(C$10='Redlands Inputs'!$D$24,'Redlands Inputs'!$C$34/2,0)) -> 0 | D50: =IF(D$10=EDATE('Redlands Inputs'!$D$24,-2),'Redlands Inputs'!$C$34/2,IF(D$10='Redlands Inputs'!$D$24,'Redlands Inputs'!$C$34/2,0)) -> 0 | E50: =IF(E$10=EDATE('Redlands Inputs'!$D$24,-2),'Redlands Inputs'!$C$34/2,IF(E$10='Redlands Inputs'!$D$24,'Redlands Inputs'!$C$34/2,0)) -> 0 | F50: =IF(F$10=EDATE('Redlands Inputs'!$D$24,-2),'Redlands Inputs'!$C$34/2,IF(F$10='Redlands Inputs'!$D$24,'Redlands Inputs'!$C$34/2,0)) -> 0 | G50: =IF(G$10=EDATE('Redlands Inputs'!$D$24,-2),'Redlands Inputs'!$C$34/2,IF(G$10='Redlands Inputs'!$D$24,'Redlands Inputs'!$C$34/2,0)) -> 0 | H50: =IF(H$10=EDATE('Redlands Inputs'!$D$24,-2),'Redlands Inputs'!$C$34/2,IF(H$10='Redlands Inputs'!$D$24,'Redlands Inputs'!$C$34/2,0)) -> 0 | I50: =IF(I$10=EDATE('Redlands Inputs'!$D$24,-2),'Redlands Inputs'!$C$34/2,IF(I$10='Redlands Inputs'!$D$24,'Redlands Inputs'!$C$34/2,0)) -> 0 | J50: =IF(J$10=EDATE('Redlands Inputs'!$D$24,-2),'Redlands Inputs'!$C$34/2,IF(J$10='Redlands Inputs'!$D$24,'Redlands Inputs'!$C$34/2,0)) -> 0 | ... ED50: =IF(ED$10=EDATE('Redlands Inputs'!$D$24,-2),'Redlands Inputs'!$C$34/2,IF(ED$10='Redlands Inputs'!$D$24,'Redlands Inputs'!$C$34/2,0)) -> 0
A51: Security Deposits | C51: =IF(C$10='Redlands Inputs'!$D$24,-'Redlands Inputs'!$C$36,0) -> 0 | D51: =IF(D$10='Redlands Inputs'!$D$24,-'Redlands Inputs'!$C$36,0) -> 0 | E51: =IF(E$10='Redlands Inputs'!$D$24,-'Redlands Inputs'!$C$36,0) -> 0 | F51: =IF(F$10='Redlands Inputs'!$D$24,-'Redlands Inputs'!$C$36,0) -> 0 | G51: =IF(G$10='Redlands Inputs'!$D$24,-'Redlands Inputs'!$C$36,0) -> 0 | H51: =IF(H$10='Redlands Inputs'!$D$24,-'Redlands Inputs'!$C$36,0) -> 0 | I51: =IF(I$10='Redlands Inputs'!$D$24,-'Redlands Inputs'!$C$36,0) -> 0 | J51: =IF(J$10='Redlands Inputs'!$D$24,-'Redlands Inputs'!$C$36,0) -> 0 | ... ED51: =IF(ED$10='Redlands Inputs'!$D$24,-'Redlands Inputs'!$C$36,0) -> 0
A52: Total Leasing Costs | C52: =SUM(C49:C51) -> 0 | D52: =SUM(D49:D51) -> 0 | E52: =SUM(E49:E51) -> 0 | F52: =SUM(F49:F51) -> 0 | G52: =SUM(G49:G51) -> 0 | H52: =SUM(H49:H51) -> 0 | I52: =SUM(I49:I51) -> 0 | J52: =SUM(J49:J51) -> 0 | ... ED52: =SUM(ED49:ED51) -> 0
A54: Capital Expenditures
A55: Replacement Reserve | C55: ='Redlands Inputs'!$H$10*(1+'Redlands Inputs'!$L$10)^(C$8-1) -> 50000 | D55: ='Redlands Inputs'!$H$10*(1+'Redlands Inputs'!$L$10)^(D$8-1) -> 50000 | E55: ='Redlands Inputs'!$H$10*(1+'Redlands Inputs'!$L$10)^(E$8-1) -> 50000 | F55: ='Redlands Inputs'!$H$10*(1+'Redlands Inputs'!$L$10)^(F$8-1) -> 50000 | G55: ='Redlands Inputs'!$H$10*(1+'Redlands Inputs'!$L$10)^(G$8-1) -> 50000 | H55: ='Redlands Inputs'!$H$10*(1+'Redlands Inputs'!$L$10)^(H$8-1) -> 50000 | I55: ='Redlands Inputs'!$H$10*(1+'Redlands Inputs'!$L$10)^(I$8-1) -> 50000 | J55: ='Redlands Inputs'!$H$10*(1+'Redlands Inputs'!$L$10)^(J$8-1) -> 50000 | ... ED55: ='Redlands Inputs'!$H$10*(1+'Redlands Inputs'!$L$10)^(ED$8-1) -> 60949.721
A56: Total Capital Expenditures | C56: =C55 -> 50000 | D56: =D55 -> 50000 | E56: =E55 -> 50000 | F56: =F55 -> 50000 | G56: =G55 -> 50000 | H56: =H55 -> 50000 | I56: =I55 -> 50000 | J56: =J55 -> 50000 | ... ED56: =ED55 -> 60949.721
A58: Total Leasing & Capital Costs | C58: =C56+C52 -> 50000 | D58: =D56+D52 -> 50000 | E58: =E56+E52 -> 50000 | F58: =F56+F52 -> 50000 | G58: =G56+G52 -> 50000 | H58: =H56+H52 -> 50000 | I58: =I56+I52 -> 50000 | J58: =J56+J52 -> 50000 | ... ED58: =ED56+ED52 -> 60949.721
A60: Cash Flow Before Debt Service | C60: =C46-C58 -> 196690 | D60: =D46-D58 -> 196690 | E60: =E46-E58 -> 196690 | F60: =F46-F58 -> 196690 | G60: =G46-G58 -> 196690 | H60: =H46-H58 -> 196690 | I60: =I46-I58 -> 196690 | J60: =J46-J58 -> 196690 | ... ED60: =ED46-ED58 -> 453011.28
A62: Acquisition
A63: Purchase Price | B63: =-'Redlands Inputs'!$D$8 -> -67280000
A64: Cost of Sales | B64: =B63*'Redlands Inputs'!$D$9 -> -1345600
A65: Total Acquisition Cost | B65: =SUM(B63:B64) -> -68625600
A67: Disposition
A68: Sale Price | C68: =IF(C$9='Redlands Inputs'!$D$15*12,SUMIF(_xlfn.ANCHORARRAY('Redlands Pro Forma'!$C$9),">120",'Redlands Pro Forma'!$C$46:$ED$46)/'Redlands Inputs'!$D$12,0) -> 0 | D68: =IF(D$9='Redlands Inputs'!$D$15*12,SUMIF(_xlfn.ANCHORARRAY('Redlands Pro Forma'!$C$9),">120",'Redlands Pro Forma'!$C$46:$ED$46)/'Redlands Inputs'!$D$12,0) -> 0 | E68: =IF(E$9='Redlands Inputs'!$D$15*12,SUMIF(_xlfn.ANCHORARRAY('Redlands Pro Forma'!$C$9),">120",'Redlands Pro Forma'!$C$46:$ED$46)/'Redlands Inputs'!$D$12,0) -> 0 | F68: =IF(F$9='Redlands Inputs'!$D$15*12,SUMIF(_xlfn.ANCHORARRAY('Redlands Pro Forma'!$C$9),">120",'Redlands Pro Forma'!$C$46:$ED$46)/'Redlands Inputs'!$D$12,0) -> 0 | G68: =IF(G$9='Redlands Inputs'!$D$15*12,SUMIF(_xlfn.ANCHORARRAY('Redlands Pro Forma'!$C$9),">120",'Redlands Pro Forma'!$C$46:$ED$46)/'Redlands Inputs'!$D$12,0) -> 0 | H68: =IF(H$9='Redlands Inputs'!$D$15*12,SUMIF(_xlfn.ANCHORARRAY('Redlands Pro Forma'!$C$9),">120",'Redlands Pro Forma'!$C$46:$ED$46)/'Redlands Inputs'!$D$12,0) -> 0 | I68: =IF(I$9='Redlands Inputs'!$D$15*12,SUMIF(_xlfn.ANCHORARRAY('Redlands Pro Forma'!$C$9),">120",'Redlands Pro Forma'!$C$46:$ED$46)/'Redlands Inputs'!$D$12,0) -> 0 | J68: =IF(J$9='Redlands Inputs'!$D$15*12,SUMIF(_xlfn.ANCHORARRAY('Redlands Pro Forma'!$C$9),">120",'Redlands Pro Forma'!$C$46:$ED$46)/'Redlands Inputs'!$D$12,0) -> 0 | ... ED68: =IF(ED$9='Redlands Inputs'!$D$15*12,SUMIF(_xlfn.ANCHORARRAY('Redlands Pro Forma'!$C$9),">120",'Redlands Pro Forma'!$C$46:$ED$46)/'Redlands Inputs'!$D$12,0) -> 0
A69: Cost of Sales | C69: =-C$68*'Redlands Inputs'!$D$13 -> 0 | D69: =-D$68*'Redlands Inputs'!$D$13 -> 0 | E69: =-E$68*'Redlands Inputs'!$D$13 -> 0 | F69: =-F$68*'Redlands Inputs'!$D$13 -> 0 | G69: =-G$68*'Redlands Inputs'!$D$13 -> 0 | H69: =-H$68*'Redlands Inputs'!$D$13 -> 0 | I69: =-I$68*'Redlands Inputs'!$D$13 -> 0 | J69: =-J$68*'Redlands Inputs'!$D$13 -> 0 | ... ED69: =-ED$68*'Redlands Inputs'!$D$13 -> 0
A70: Total Sale Proceeds | C70: =SUM(C68:C69) -> 0 | D70: =SUM(D68:D69) -> 0 | E70: =SUM(E68:E69) -> 0 | F70: =SUM(F68:F69) -> 0 | G70: =SUM(G68:G69) -> 0 | H70: =SUM(H68:H69) -> 0 | I70: =SUM(I68:I69) -> 0 | J70: =SUM(J68:J69) -> 0 | ... ED70: =SUM(ED68:ED69) -> 0
A72: Asset Cash Flow | B72: =IF(B$9<='Redlands Inputs'!$D$15*12,B60+B70+B65,0) -> -68625600 | C72: =IF(C$9<='Redlands Inputs'!$D$15*12,C60+C70+C65,0) -> 196690 | D72: =IF(D$9<='Redlands Inputs'!$D$15*12,D60+D70+D65,0) -> 196690 | E72: =IF(E$9<='Redlands Inputs'!$D$15*12,E60+E70+E65,0) -> 196690 | F72: =IF(F$9<='Redlands Inputs'!$D$15*12,F60+F70+F65,0) -> 196690 | G72: =IF(G$9<='Redlands Inputs'!$D$15*12,G60+G70+G65,0) -> 196690 | H72: =IF(H$9<='Redlands Inputs'!$D$15*12,H60+H70+H65,0) -> 196690 | I72: =IF(I$9<='Redlands Inputs'!$D$15*12,I60+I70+I65,0) -> 196690 | ... ED72: =IF(ED$9<='Redlands Inputs'!$D$15*12,ED60+ED70+ED65,0) -> 0
A74: Asset IRR | B74: =XIRR(B72:ED72,B10:ED10) -> 0.075530967
A75: Asset MOIC | B75: =SUMIF(B72:ED72,">0")/-SUMIF(B72:ED72,"<0") -> 2.0106545

Sheet Redlands Inputs
B2: Property | F2: Expenses - Operating | H2: Month 1 | J2: Fixed | K2: Recoverable | L2: Inflation (%)
B3: Address | D3: 2255 W Lugonia. Ave | F3: Utilities | H3: =I3/12 -> 3750 | I3: 45000 | J3: 0.25 | K3: 1 | L3: ='Redlands Pro Forma'!$C$3 -> 0.025
B4: City | D4: Redlands | F4: Repairs & Maintenance | H4: =I4/12 -> 3750 | I4: 45000 | J4: 0.25 | K4: 1 | L4: ='Redlands Pro Forma'!$C$3 -> 0.025
B5: Year Built | D5: 2013 | F5: Insurance | H5: =I5/12 -> 1666.6667 | I5: 20000 | J5: 1 | K5: 1 | L5: ='Redlands Pro Forma'!$C$3 -> 0.025
B6: State | D6: California | F6: Property Taxes | H6: =J6/12 -> 61673.333 | I6: 0.011 | J6: =I6*D8 -> 740080 | K6: 1 | L6: 0.02
B7: Size (RSF) | D7: 600000 | F7: Previous RE Tax | H7: =150000/12 -> 12500
B8: Purchase Price | D8: =ROUND(D16/D10,-4) -> 67280000 | F8: Management Fee | I8: 3.0% | K8: 0
B9: Closing Costs | C9: =D8*D9 -> 1345600 | D9: 0.02 | F9: Expenses - Capital
B10: Entry Cap | D10: 0.0541 | F10: Replacement Reserve | H10: =(I10*D7)/12 -> 50000 | I10: 1 | L10: 0.02
B11: Vacancy | D11: 0.1
B12: Exit Cap | C12: =SUMIF(_xlfn.ANCHORARRAY('Redlands Pro Forma'!$C$9),">120",'Redlands Pro Forma'!$C$46:$ED$46)/'Redlands Inputs'!$D$12 -> 1.103452e+08 | D12: 0.0556 | F12: Upon Expiration | G12: Vacate
B13: Cost of Sales | C13: =C12*D13 -> 2206904 | D13: 0.02
B14: Analysis Start | D14: 45658 | F14: Tenants - Rent Roll
B15: Holding Period | D15: 10 | F15: Name | G15: /mo | H15: Amazon | I15: Recovery Structure | K15: Net
B16: Year 0 NOI | D16: =(3900000-260000) -> 3640000 | F16: Suite | H16: Floor 1 | I16: Upon Expiration | K16: =+G12 -> Vacate
F17: Area | H17: 600000 | I17: Market Blended Rent | K17: =(D22*market_rent)+(H21*(1-D22)) -> 8.1405
F18: Lease Start | H18: 44593 | I18: Blended Months Vacant | K18: =D22*D23+((1-D22)*0) -> 0.7
B19: Market Leasing | F19: Term | H19: 10
B20: Size | C20: Mo | D20: =H17 -> 600000 | F20: Lease Expiry | H20: =EOMONTH(H18,(H19*12)-1) -> 48244
B21: Term Length | D21: 7 | F21: Base Rent | G21: =(H21*H17)/12 -> 306750 | H21: 6.135
B22: Renewal Probability | D22: 0.7 | F22: Current Rent | G22: =(H22*H17)/12 -> 324988.81 | H22: =H21*(1+H23)^(YEARFRAC(H18,D14)) -> 6.4997762
B23: Months Vacant | D23: 1 | F23: Rent Increase | H23: 0.02
B24: Lease Start Date | D24: =EDATE(H20,D23) -> 48273 | F24: Type | H24: Fixed Steps
B25: Base Rent (/sf) | D25: 9
B26: Base Rent | C26: =D26/12 -> 450000 | D26: =market_rent*D20 -> 5400000
B27: Rent Increase Type | D27: Fixed Steps | F27: Recoverable Expenses - NNN | H27: Month 1
B28: Rent Increase (%) | D28: 0.025 | F28: Utilities | H28: ='Redlands Pro Forma'!$C39 -> 3750
B29: Free Rent | D29: 2 | F29: Repairs & Maintenance | H29: ='Redlands Pro Forma'!$C40 -> 3750
B30: Tenant Improvements | F30: Insurance | H30: ='Redlands Pro Forma'!$C41 -> 1666.6667
B31: New | C31: =D31*D20 -> 2400000 | D31: 4 | F31: Property Taxes | H31: ='Redlands Pro Forma'!$C42 -> 61673.333
B32: Renew | D32: 2
B33: Leasing Commissions
B34: New | C34: =(market_rent*D20*D21)*D34 -> 2268000 | D34: 0.06
B35: Renew | D35: 0.03
B36: Security Deposit | C36: =D36*C26 -> 1800000 | D36: 4
B38: Cap Rate
A39: Rent Growth | B39: ='Redlands Pro Forma'!B74 -> 0.075530967 | C39: =D39-2000000 -> 63280000 | D39: =E39-2000000 -> 65280000 | E39: =D8 -> 67280000 | F39: =E39+2000000 -> 69280000 | G39: =F39+2000000 -> 71280000
B40: =B41-0.0025 -> 0.0506 | C40: 0.090119866 | D40: 0.093800363 | E40: 0.093800363 | F40: 0.090119866 | G40: 0.083156732
B41: =B42-0.0025 -> 0.0531 | C41: 0.094294378 | D41: 0.097980696 | E41: 0.097980696 | F41: 0.094294378 | G41: 0.087319836
B42: =D12 -> 0.0556 | C42: 0.094294378 | D42: 0.097980696 | E42: 0.097980696 | F42: 0.094294378 | G42: 0.087319836
B43: =B42+0.0025 -> 0.0581 | C43: 0.090119866 | D43: 0.093800363 | E43: 0.093800363 | F43: 0.090119866 | G43: 0.083156732
B44: =B43+0.0025 -> 0.0606 | C44: 0.082474086 | D44: 0.086144403 | E44: 0.086144403 | F44: 0.082474086 | G44: 0.075530967

Sheet Redlands Partnership Returns
C2: Equity CF Scenarios
C3: Scenario 1 - Renew - NNN - Best | F3: 3062344 | G3: 2875958.6 | H3: 3221272.4 | I3: 3303323.2 | J3: 3387149.6 | K3: 2379292.2 | L3: 3013539.1 | M3: 4645824.6 | N3: 5320076.8 | O3: 6372690.9
C4: Scenario 2 - Tenant Vacates - NNN - | F4: 3297407.2 | G4: 3116695.2 | H4: 3467804.2 | I4: 3555774.9 | J4: 3645648.5 | K4: 3133217.8 | L4: 2921441.5 | M4: 1299478.4 | N4: 5151818.7 | O4: 6528038.8
C5: Scenario 3 Base - Renew + Prop Tax Cap (Modified Gross) | F5: 2961581.2 | G5: 3026116 | H5: 3092100.7 | I5: 3159568.9 | J5: 3228555.3 | K5: 2223215.9 | L5: 2833285.3 | M5: 4150900.1 | N5: 4805922.5 | O5: 5847898
C6: Scenario 4 - Worst Case - 10 Months + Other | F6: 2961581.2 | G6: 2761116 | H6: 3092100.7 | I6: 3159568.9 | J6: 3228555.3 | K6: 3105871.5 | L6: 2303306.4 | M6: -1160718 | N6: 3761067 | O6: 4678376.9
E8: {=_xlfn.SEQUENCE(1,12,0,1)} -> 0 | F8: 1 | G8: 2 | H8: 3 | I8: 4 | J8: 5 | K8: 6 | L8: 7 | M8: 8 | N8: 9 | O8: 10 | P8: 11 | Z8: Permanent
E9: =EDATE(F9,-12) -> 45292 | F9: 45658 | G9: =EDATE(F9,12) -> 46023 | H9: =EDATE(G9,12) -> 46388 | I9: =EDATE(H9,12) -> 46753 | J9: =EDATE(I9,12) -> 47119 | K9: =EDATE(J9,12) -> 47484 | L9: =EDATE(K9,12) -> 47849 | M9: =EDATE(L9,12) -> 48214 | N9: =EDATE(M9,12) -> 48580 | ... P9: =EDATE(O9,12) -> 49310 | R9: Equity Assumptions | V9: Debt Assumptions | W9: Permanant | AB9: \
C10: Equity CF | E10: =-X12-E48 -> -68849457 | F10: =CHOOSE($S$10,F$3,F$4,F$5,F6) -> 2961581.2 | G10: =CHOOSE($S$10,G$3,G$4,G$5,G6) -> 2761116 | H10: =CHOOSE($S$10,H$3,H$4,H$5,H6) -> 3092100.7 | I10: =CHOOSE($S$10,I$3,I$4,I$5,I6) -> 3159568.9 | J10: =CHOOSE($S$10,J$3,J$4,J$5,J6) -> 3228555.3 | K10: =CHOOSE($S$10,K$3,K$4,K$5,K6) -> 3105871.5 | L10: =CHOOSE($S$10,L$3,L$4,L$5,L6) -> 2303306.4 | M10: =CHOOSE($S$10,M$3,M$4,M$5,M6) -> -1160718 | N10: =CHOOSE($S$10,N$3,N$4,N$5,N6) -> 3761067 | O10: =CHOOSE($S$10,O$3,O$4,O$5,O6)+S21 -> 1.1502357e+08 | R10: Scenario: | S10: 4 | W10: 0 | X10: Year 1 | AB10: =EOMONTH($X$15,0) -> 45688 | AC10: =EOMONTH($X$15,0) -> 45688 | AD10: =EOMONTH($X$15,0) -> 45688 | AE10: =EOMONTH($X$15,0) -> 45688 | AF10: =EOMONTH($X$15,0) -> 45688 | AG10: =EOMONTH($X$15,0) -> 45688 | AH10: =EOMONTH($X$15,0) -> 45688 | AI10: =EOMONTH($X$15,0) -> 45688 | ... AL10: =EOMONTH($X$15,0) -> 45688
C11: Debt Cash Flow | E11: =AB17 -> 35607581 | F11: =AC17 -> -2444444.4 | G11: =AD17 -> -2444444.4 | H11: =AE17 -> -2444444.4 | I11: =AF17 -> -2444444.4 | J11: =AG17 -> -2444444.4 | K11: =AH17 -> -2444444.4 | L11: =AI17 -> -2444444.4 | ... P11: =AM17 -> 0 | R11: Limited Partner | S11: 0.9 | V11: Leading NOI | X11: 3300000 | AB11: {=_xlfn.SEQUENCE(1,11,0,1)} -> 0 | AC11: 1 | AD11: 2 | AE11: 3 | AF11: 4 | AG11: 5 | AH11: 6 | AI11: 7 | AJ11: 8 | AK11: 9 | AL11: 10
R12: General Partner | S12: 0.1 | V12: Purchase Price | X12: ='Redlands Inputs'!D8 -> 67280000 | Z12: Debt
C13: Equity CF (Levered) | E13: =SUM(E10:E11) -> -33241876 | F13: =SUM(F10:F11) -> 517136.75 | G13: =SUM(G10:G11) -> 316671.6 | H13: =SUM(H10:H11) -> 647656.25 | I13: =SUM(I10:I11) -> 715124.45 | J13: =SUM(J10:J11) -> 784110.81 | K13: =SUM(K10:K11) -> 661427.09 | L13: =SUM(L10:L11) -> -141138.08 | ... P13: =SUM(P10:P11) -> 0 | R13: Distribution Fee | S13: 0.05 | V13: Entry Cap | X13: 0.0525 | Z13: Origination Fee | AB13: =-AB14*$X$20 -> -269074.92
V14: Terms | Z14: Loan Proceeds | AB14: =X27 -> 35876655
R15: Tier 1 | V15: Start Date | X15: 45658 | Z15: Debt Service | AC15: =-IF(AC$10<=$X$16,PMT($X$17/12,$X$18,-$X$27)*12,0) -> -2444444.4 | AD15: =-IF(AD$10<=$X$16,PMT($X$17/12,$X$18,-$X$27)*12,0) -> -2444444.4 | AE15: =-IF(AE$10<=$X$16,PMT($X$17/12,$X$18,-$X$27)*12,0) -> -2444444.4 | AF15: =-IF(AF$10<=$X$16,PMT($X$17/12,$X$18,-$X$27)*12,0) -> -2444444.4 | AG15: =-IF(AG$10<=$X$16,PMT($X$17/12,$X$18,-$X$27)*12,0) -> -2444444.4 | AH15: =-IF(AH$10<=$X$16,PMT($X$17/12,$X$18,-$X$27)*12,0) -> -2444444.4 | AI15: =-IF(AI$10<=$X$16,PMT($X$17/12,$X$18,-$X$27)*12,0) -> -2444444.4 | AJ15: =-IF(AJ$10<=$X$16,PMT($X$17/12,$X$18,-$X$27)*12,0) -> -2444444.4 | ... AL15: =-IF(AL$10<=$X$16,PMT($X$17/12,$X$18,-$X$27)*12,0) -> -2444444.4
C16: Tier 1 - Preferred Return (EP & S) | R16: Limited Partner | V16: End Date | W16: 10 | X16: 49310 | Z16: Loan Repayment | AC16: =-IF(AC11=$X$22,SUM($X$27,CUMPRINC($X$17,$X$19/12,$X$27,1,AC11,0)),0) -> 0 | AD16: =-IF(AD11=$X$22,SUM($X$27,CUMPRINC($X$17,$X$19/12,$X$27,1,AD11,0)),0) -> 0 | AE16: =-IF(AE11=$X$22,SUM($X$27,CUMPRINC($X$17,$X$19/12,$X$27,1,AE11,0)),0) -> 0 | AF16: =-IF(AF11=$X$22,SUM($X$27,CUMPRINC($X$17,$X$19/12,$X$27,1,AF11,0)),0) -> 0 | AG16: =-IF(AG11=$X$22,SUM($X$27,CUMPRINC($X$17,$X$19/12,$X$27,1,AG11,0)),0) -> 0 | AH16: =-IF(AH11=$X$22,SUM($X$27,CUMPRINC($X$17,$X$19/12,$X$27,1,AH11,0)),0) -> 0 | AI16: =-IF(AI11=$X$22,SUM($X$27,CUMPRINC($X$17,$X$19/12,$X$27,1,AI11,0)),0) -> 0 | AJ16: =-IF(AJ11=$X$22,SUM($X$27,CUMPRINC($X$17,$X$19/12,$X$27,1,AJ11,0)),0) -> 0 | ... AL16: =-IF(AL11=$X$22,SUM($X$27,CUMPRINC($X$17,$X$19/12,$X$27,1,AL11,0)),0) -> -29499606
C17: Beginning Balance | E17: =D25 -> 0 | F17: =E25 -> 33241876 | G17: =F25 -> 36048927 | H17: =G25 -> 39337148 | I17: =H25 -> 42623207 | J17: =I25 -> 46170403 | K17: =J25 -> 50003333 | L17: =K25 -> 54342239 | ... P17: =O25 -> 0 | R17: Preffered Return | S17: 0.1 | V17: Rate | X17: 0.055 | Z17: Debt CF | AB17: =SUM(AB13:AB16) -> 35607581 | AC17: =SUM(AC13:AC16) -> -2444444.4 | AD17: =SUM(AD13:AD16) -> -2444444.4 | AE17: =SUM(AE13:AE16) -> -2444444.4 | AF17: =SUM(AF13:AF16) -> -2444444.4 | AG17: =SUM(AG13:AG16) -> -2444444.4 | AH17: =SUM(AH13:AH16) -> -2444444.4 | AI17: =SUM(AI13:AI16) -> -2444444.4 | ... AL17: =SUM(AL13:AL16) -> -31944050
C18: Contribution | E18: =IF(E13<0,-E$13,0) -> 33241876 | F18: =IF(F13<0,-F$13,0) -> 0 | G18: =IF(G13<0,-G$13,0) -> 0 | H18: =IF(H13<0,-H$13,0) -> 0 | I18: =IF(I13<0,-I$13,0) -> 0 | J18: =IF(J13<0,-J$13,0) -> 0 | K18: =IF(K13<0,-K$13,0) -> 0 | L18: =IF(L13<0,-L$13,0) -> 141138.08 | ... P18: =IF(P13<0,-P$13,0) -> 0 | R18: Tier 2 | V18: Amortization | X18: 360
C19: Pref Earned | E19: =E$17*$S$17 -> 0 | F19: =F$17*$S$17 -> 3324187.6 | G19: =G$17*$S$17 -> 3604892.7 | H19: =H$17*$S$17 -> 3933714.8 | I19: =I$17*$S$17 -> 4262320.7 | J19: =J$17*$S$17 -> 4617040.3 | K19: =K$17*$S$17 -> 5000333.3 | L19: =L$17*$S$17 -> 5434223.9 | ... P19: =P$17*$S$17 -> 0 | R19: Limited Partner | S19: 0.8 | V19: Loan Length | X19: =X18 -> 360 | Z19: IRR | AB19: =IRR(AB17:AL17) -> 0.055348471
C20: Pref Paid | E20: =IF(E$13>0,-MIN(SUM(D23,E19),E$13),0) -> 0 | F20: =IF(F$13>0,-MIN(SUM(E23,F19),F$13),0) -> -517136.75 | G20: =IF(G$13>0,-MIN(SUM(F23,G19),G$13),0) -> -316671.6 | H20: =IF(H$13>0,-MIN(SUM(G23,H19),H$13),0) -> -647656.25 | I20: =IF(I$13>0,-MIN(SUM(H23,I19),I$13),0) -> -715124.45 | J20: =IF(J$13>0,-MIN(SUM(I23,J19),J$13),0) -> -784110.81 | K20: =IF(K$13>0,-MIN(SUM(J23,K19),K$13),0) -> -661427.09 | L20: =IF(L$13>0,-MIN(SUM(K23,L19),L$13),0) -> 0 | ... P20: =IF(P$13>0,-MIN(SUM(O23,P19),P$13),0) -> 0 | R20: General Partner | S20: 0.2 | V20: Origination Fee | X20: 0.0075 | Z20: EM | AB20: =-SUMIF(AB17:AL17,"<0")/SUMIF(AB17:AL17,">0") -> 1.5149597
C21: Pref Unpaid | E21: =SUM(E19:E20) -> 0 | F21: =SUM(F19:F20) -> 2807050.9 | G21: =SUM(G19:G20) -> 3288221.1 | H21: =SUM(H19:H20) -> 3286058.6 | I21: =SUM(I19:I20) -> 3547196.3 | J21: =SUM(J19:J20) -> 3832929.5 | K21: =SUM(K19:K20) -> 4338906.2 | L21: =SUM(L19:L20) -> 5434223.9 | ... P21: =SUM(P19:P20) -> 0 | R21: Sale Price | S21: ='Redlands Inputs'!$C$12 -> 1.103452e+08 | V21: Loan Type | X21: Fixed
C22: Equity Repaid | E22: =-IF(E13>0,MIN(SUM(E20,E13),D24),0) -> 0 | F22: =-IF(F13>0,MIN(SUM(F20,F13),E24),0) -> 0 | G22: =-IF(G13>0,MIN(SUM(G20,G13),F24),0) -> 0 | H22: =-IF(H13>0,MIN(SUM(H20,H13),G24),0) -> 0 | I22: =-IF(I13>0,MIN(SUM(I20,I13),H24),0) -> 0 | J22: =-IF(J13>0,MIN(SUM(J20,J13),I24),0) -> 0 | K22: =-IF(K13>0,MIN(SUM(K20,K13),J24),0) -> 0 | L22: =-IF(L13>0,MIN(SUM(L20,L13),K24),0) -> 0 | ... P22: =-IF(P13>0,MIN(SUM(P20,P13),O24),0) -> 0 | V22: Sale Year | X22: 10
C23: Ending Balance - Cumulative Unpaid Pref | E23: =D23+E21 -> 0 | F23: =E23+F21 -> 2807050.9 | G23: =F23+G21 -> 6095272 | H23: =G23+H21 -> 9381330.6 | I23: =H23+I21 -> 12928527 | J23: =I23+J21 -> 16761456 | K23: =J23+K21 -> 21100363 | L23: =K23+L21 -> 26534587 | ... P23: =O23+P21 -> 0 | V23: Constraints
C24: Ending Balance - Equity Contribution | E24: =D24+E18+E22 -> 33241876 | F24: =E24+F18+F22 -> 33241876 | G24: =F24+G18+G22 -> 33241876 | H24: =G24+H18+H22 -> 33241876 | I24: =H24+I18+I22 -> 33241876 | J24: =I24+J18+J22 -> 33241876 | K24: =J24+K18+K22 -> 33241876 | L24: =K24+L18+L22 -> 33383015 | ... P24: =O24+P18+P22 -> 0 | V24: DY | W24: =X11/X24 -> 44000000 | X24: 0.075
C25: Total Ending Balance | E25: =SUM(E23:E24) -> 33241876 | F25: =SUM(F23:F24) -> 36048927 | G25: =SUM(G23:G24) -> 39337148 | H25: =SUM(H23:H24) -> 42623207 | I25: =SUM(I23:I24) -> 46170403 | J25: =SUM(J23:J24) -> 50003333 | K25: =SUM(K23:K24) -> 54342239 | L25: =SUM(L23:L24) -> 59917601 | ... P25: =SUM(P23:P24) -> 0 | V25: DSCR | W25: =PV(X17/12,X18,-(X11/X25/12)) -> 35876655 | X25: 1.35
V26: LTV | W26: =X26*X12 -> 43732000 | X26: 0.65
V27: Loan Amount | X27: =MIN(W24:W26) -> 35876655
C28: Tier 1 Cash Flow | E28: =SUM(E18,E20,E22) -> 33241876 | F28: =SUM(F18,F20,F22) -> -517136.75 | G28: =SUM(G18,G20,G22) -> -316671.6 | H28: =SUM(H18,H20,H22) -> -647656.25 | I28: =SUM(I18,I20,I22) -> -715124.45 | J28: =SUM(J18,J20,J22) -> -784110.81 | K28: =SUM(K18,K20,K22) -> -661427.09 | L28: =SUM(L18,L20,L22) -> 141138.08 | ... P28: =SUM(P18,P20,P22) -> 0
C31: EP Cash Flow | E31: =E28*$S$11 -> 29917689 | F31: =F28*$S$11 -> -465423.08 | G31: =G28*$S$11 -> -285004.44 | H31: =H28*$S$11 -> -582890.62 | I31: =I28*$S$11 -> -643612.01 | J31: =J28*$S$11 -> -705699.73 | K31: =K28*$S$11 -> -595284.38 | L31: =L28*$S$11 -> 127024.27 | ... P31: =P28*$S$11 -> 0
C32: Equity Partner CF IRR | E32: =IRR(E31:P31) -> 0.1
C34: Sponsor Cash Flow | E34: =E31-E28 -> -3324187.6 | F34: =F31-F28 -> 51713.675 | G34: =G31-G28 -> 31667.16 | H34: =H31-H28 -> 64765.625 | I34: =I31-I28 -> 71512.445 | J34: =J31-J28 -> 78411.081 | K34: =K31-K28 -> 66142.709 | L34: =L31-L28 -> -14113.808 | ... P34: =P31-P28 -> 0
C35: Equity Sponsor CF IRR | E35: =IRR(E34:P34) -> 0.1
C37: Tier 1 Residual Cash Flow | E37: =E13+E28 -> 0 | F37: =F13+F28 -> 0 | G37: =G13+G28 -> 0 | H37: =H13+H28 -> 0 | I37: =I13+I28 -> 0 | J37: =J13+J28 -> 0 | K37: =K13+K28 -> 0 | L37: =L13+L28 -> 0 | ... P37: =P13+P28 -> 0
C39: Tier 2 Equity Partner Distribution | E39: =-E37*$S$19 -> 0 | F39: =-F37*$S$19 -> 0 | G39: =-G37*$S$19 -> 0 | H39: =-H37*$S$19 -> 0 | I39: =-I37*$S$19 -> 0 | J39: =-J37*$S$19 -> 0 | K39: =-K37*$S$19 -> 0 | L39: =-L37*$S$19 -> 0 | ... P39: =-P37*$S$19 -> 0
C40: Total Cash Flows through Tier 2 | E40: =E39+E31 -> 29917689 | F40: =F39+F31 -> -465423.08 | G40: =G39+G31 -> -285004.44 | H40: =H39+H31 -> -582890.62 | I40: =I39+I31 -> -643612.01 | J40: =J39+J31 -> -705699.73 | K40: =K39+K31 -> -595284.38 | L40: =L39+L31 -> 127024.27 | ... P40: =P39+P31 -> 0
C41: Equity Partner CF IRR | E41: =XIRR(E40:P40,E9:P9) -> 0.100402
C43: Tier 2 Sponsor Distribution | E43: =E37*$S$20 -> 0 | F43: =F37*$S$20 -> 0 | G43: =G37*$S$20 -> 0 | H43: =H37*$S$20 -> 0 | I43: =I37*$S$20 -> 0 | J43: =J37*$S$20 -> 0 | K43: =K37*$S$20 -> 0 | L43: =L37*$S$20 -> 0 | ... P43: =P37*$S$20 -> 0
C44: Total Cash Flows through Tier 2 | E44: =E43+E34 -> -3324187.6 | F44: =F43+F34 -> 51713.675 | G44: =G43+G34 -> 31667.16 | H44: =H43+H34 -> 64765.625 | I44: =I43+I34 -> 71512.445 | J44: =J43+J34 -> 78411.081 | K44: =K43+K34 -> 66142.709 | L44: =L43+L34 -> -14113.808 | ... P44: =P43+P34 -> 0
C45: Equity Sponsor CF IRR | E45: =XIRR(E44:P44,E9:P9) -> 0.10101109
C47: Fees
C48: Distribution Fee to Sponsor | E48: 1569457 | O48: 3153406
C50: Total Sponsor CF | E50: =E48+E44 -> -1754730.6 | F50: =F48+F44 -> 51713.675 | G50: =G48+G44 -> 31667.16 | H50: =H48+H44 -> 64765.625 | I50: =I48+I44 -> 71512.445 | J50: =J48+J44 -> 78411.081 | K50: =K48+K44 -> 66142.709 | L50: =L48+L44 -> -14113.808 | ... O50: =O48+O44 -> 11502882
E51: =XIRR(E50:P50,E9:P9) -> 0.21571609
C54: Asset IRR | E54: =E10 -> -68849457 | F54: =F10 -> 2961581.2 | G54: =G10 -> 2761116 | H54: =H10 -> 3092100.7 | I54: =I10 -> 3159568.9 | J54: =J10 -> 3228555.3 | K54: =K10 -> 3105871.5 | L54: =L10 -> 2303306.4 | ... O54: =O10 -> 1.1502357e+08
E55: =IRR(E54:O54) -> 0.081937358

Sheet Cap Rate Analysis
L2: 1 | O2: hbs | P2: Max | Q2: Analysis Year | R2: Variance | T2: Assumed Growth Rate | U2: 0.03
B3: Street Address | C3: Property Cap Rate | D3: Size | E3: Sale Date | F3: Sale Year | G3: Sale Price / SF | H3: Sale Price | I3: / SF | J3: NOI | K3: NOI / SF | L3: Weights | O3: =MIN(F4:F8) -> 2005 | P3: =MAX(F4:F8) -> 2015 | Q3: =YEAR(TODAY()) -> 2025 | R3: =Q3-P3 -> 10 | T3: Street Address | U3: Year | V3: Size | W3: Current | X3: NOI | Y3: Standarized NOI | Z3: NOI per SF | AA3: Weight
B4: 10444 Corporate Drive, Redlands, CA 92374 | C4: 0.04662073 | D4: 527000 | E4: 42361 | F4: 2015 | G4: 87.67 | H4: 46202090 | I4: 87.67 | J4: 2153975.2 | K4: 4.0872394 | L4: 0.25 | N4: Cap Rate | O4: =SUMPRODUCT({0.0557,0.0624,0.0534},{0.4,0.4,0.2}) -> 0.05792 | P4: =SUMPRODUCT({0.0466,0.0524,0.0534},{0.4,0.4,0.2}) -> 0.05028 | Q4: =AVERAGE(O4:P4) -> 0.0541 | R4: =Q4+(R3*0.00015) -> 0.0556 | T4: 10444 Corporate Drive, Redlands, CA 92374 | U4: =F4 -> 2015 | V4: =D4 -> 527000 | W4: =YEAR(TODAY())-U4 -> 10 | X4: =INDEX($J$4:$J$8,MATCH($T4,B4:B8)) -> 2153975.2 | Y4: =X4*(1+$U$2)^(W4-1) -> 2810449 | Z4: =Y4/D4 -> 5.3329204 | AA4: =L4 -> 0.25
B5: East San Bernardino Avenue, Redlands, CA 92408 | C5: 0.05236506 | D5: 586000 | E5: 41613 | F5: 2013 | G5: 67.06 | H5: 39297160 | I5: 67.06 | J5: 2057798.1 | K5: 3.5116009 | L5: 0.3 | T5: East San Bernardino Avenue, Redlands, CA 92408 | U5: =F5 -> 2013 | V5: =D5 -> 586000 | W5: =YEAR(TODAY())-U5 -> 12 | X5: =INDEX($J$4:$J$8,MATCH($T5,B5:B9)) -> 3030769.2 | Y5: =X5*(1+$U$2)^(W5-1) -> 4195293.4 | Z5: =Y5/D5 -> 7.1592038 | AA5: =L5 -> 0.3
B6: 9425 California Street, Redlands, CA 92374 | C6: 0.05571152 | D6: 784000 | E6: 39079 | F6: 2006 | G6: 68.88 | H6: 54001920 | I6: 68.88 | J6: 3008529 | K6: 3.8374095 | L6: 0.15 | T6: 9425 California Street, Redlands, CA 92374 | U6: =F6 -> 2006 | V6: =D6 -> 784000 | W6: =YEAR(TODAY())-U6 -> 19 | X6: =INDEX($J$4:$J$8,MATCH($T6,B6:B10)) -> 3008529 | Y6: =X6*(1+$U$2)^(W6-1) -> 5121819.3 | Z6: =Y6/D6 -> 6.5329328 | AA6: =L6 -> 0.15
B7: 26682 Almond Avenue, Redlands, CA 92374 | C7: 0.05571152 | D7: 584000 | E7: 39022 | F7: 2006 | G7: 67.64 | H7: 39501760 | I7: 67.64 | J7: 2200703.1 | K7: 3.7683272 | L7: 0.15 | T7: 26682 Almond Avenue, Redlands, CA 92374 | U7: =F7 -> 2006 | V7: =D7 -> 584000 | W7: =YEAR(TODAY())-U7 -> 19 | X7: =INDEX($J$4:$J$8,MATCH($T7,B7:B11)) -> 2153975.2 | Y7: =X7*(1+$U$2)^(W7-1) -> 3666998.5 | Z7: =Y7/D7 -> 6.2791071 | AA7: =L7 -> 0.15
B8: 2300 West San Bernardino Avenue, Redlands, CA 92374 | C8: 0.06236279 | D8: 575000 | E8: 38508 | F8: 2005 | G8: 84.52 | H8: 48599000 | I8: 84.52 | J8: 3030769.2 | K8: 5.270903 | L8: 0.15 | T8: 2300 West San Bernardino Avenue, Redlands, CA 92374 | U8: =F8 -> 2005 | V8: =D8 -> 575000 | W8: =YEAR(TODAY())-U8 -> 20 | X8: =INDEX($J$4:$J$8,MATCH($T8,B8:B12)) -> 2153975.2 | Y8: =X8*(1+$U$2)^(W8-1) -> 3777008.5 | Z8: =Y8/D8 -> 6.5687104 | AA8: =L8 -> 0.15
B9: Benchmark (Weighted Average) | C9: =SUMPRODUCT($C$4:$C$8,$L$4:$L$8) -> 0.053432575 | D9: =SUMPRODUCT(D$4:D$8,$L$4:$L$8) -> 599000 | H9: =SUMPRODUCT(H$4:H$8,$L$4:$L$8) -> 44655072 | I9: =SUMPRODUCT(I$4:I$8,$L$4:$L$8) -> 75.1915 | J9: =SUMPRODUCT(J$4:J$8,$L$4:$L$8) -> 2391833.4 | K9: =SUMPRODUCT(K$4:K$8,$L$4:$L$8) -> 4.0067861 | L9: =SUM(L4:L8) -> 1 | T9: Benchmark | Y9: =SUMPRODUCT(Y$4:Y$8,AA4:AA8) -> 3846074.2 | AA9: =SUM(AA4:AA8) -> 1

Sheet Growth Rates
D4: 46357 | E4: =EDATE(D4,12) -> 46722 | F4: =EDATE(E4,12) -> 47088 | G4: =EDATE(F4,12) -> 47453 | H4: =EDATE(G4,12) -> 47818 | I4: =EDATE(H4,12) -> 48183 | J4: =EDATE(I4,12) -> 48549 | K4: =EDATE(J4,12) -> 48914 | L4: =EDATE(K4,12) -> 49279 | ... N4: =EDATE(M4,12) -> 50010
B5: General Inflation | D5: 0.03 | E5: 0.03 | F5: 0.03 | G5: 0.03 | H5: 0.03 | I5: 0.03 | J5: 0.03 | K5: 0.03 | L5: 0.03 | M5: 0.03 | N5: 0.03
B6: Market Rent Inflation | D6: 0.03 | E6: 0.03 | F6: 0.03 | G6: 0.03 | H6: 0.03 | I6: 0.022 | J6: 0.022 | K6: 0.022 | L6: 0.022 | M6: 0.022 | N6: 0.022
B7: Expense Inflation | D7: 0.03 | E7: 0.03 | F7: 0.03 | G7: 0.03 | H7: 0.03 | I7: 0.03 | J7: 0.03 | K7: 0.03 | L7: 0.03 | M7: 0.03 | N7: 0.03

Sheet Rent Summary
B2: Effective Rent Market Summary
E3: Count | F3: Min | G3: Max | H3: SD | I3: Average Effective Rent
B4: Inland Empire | E4: 50 | F4: 6.89242 | G4: 20.4175 | H4: 2.5608557 | I4: 11.74845
C5: Colton | E5: 1 | F5: 10.2039 | G5: 10.2039 | I5: 10.2039
D6: 250,001-350,000 | E6: 1 | F6: 10.2039 | G6: 10.2039 | I6: 10.2039
C7: Loma Linda | E7: 3 | F7: 13.0548 | G7: 14.1289 | H7: 0.54345147 | I7: 13.639867
D8: 250,001-350,000 | E8: 1 | F8: 13.7359 | G8: 13.7359 | I8: 13.7359
D9: 50,001-150,000 | E9: 2 | F9: 13.0548 | G9: 14.1289 | H9: 0.75950339 | I9: 13.59185
C10: Redlands | E10: 32 | F10: 6.89242 | G10: 20.4175 | H10: 2.6320308 | I10: 11.672032
D11: 0-50,000 | E11: 12 | F11: 9.07241 | G11: 20.4175 | H11: 2.9801098 | I11: 12.404307
D12: 150,001-250,000 | E12: 2 | F12: 9.18398 | G12: 14.9824 | H12: 4.1001021 | I12: 12.08319
D13: 250,001-350,000 | E13: 1 | F13: 12.901 | G13: 12.901 | I13: 12.901
D14: 350,001-450,000 | E14: 2 | F14: 10.0171 | G14: 13.1526 | H14: 2.2171333 | I14: 11.58485
D15: 450,001-600,000 | E15: 2 | F15: 10.0691 | G15: 13.67495 | H15: 2.549721 | I15: 11.872025
D16: 50,001-150,000 | E16: 9 | F16: 9.0859 | G16: 14.7399 | H16: 2.1684749 | I16: 11.803631
D17: 600,001-750,000 | E17: 2 | F17: 8.70586 | G17: 8.74871 | H17: 0.030299526 | I17: 8.727285
D18: 750,000+ | E18: 2 | F18: 6.89242 | G18: 10.09254 | H18: 2.2628266 | I18: 8.49248
C19: San Bernardino | E19: 14 | F19: 7.35182 | G19: 16.583 | H19: 2.6672912 | I19: 11.628142
D20: 0-50,000 | E20: 8 | F20: 8.32503 | G20: 15.5779 | H20: 2.1085725 | I20: 11.577487
D21: 250,001-350,000 | E21: 1 | F21: 8.39927 | G21: 8.39927 | I21: 8.39927
D22: 450,001-600,000 | E22: 1 | F22: 7.35182 | G22: 7.35182 | I22: 7.35182
D23: 50,001-150,000 | E23: 4 | F23: 11.1859 | G23: 16.583 | H23: 2.3796639 | I23: 13.60575
B24: Los Angeles | E24: 50 | F24: 10.7525 | G24: 30.2333 | H24: 4.7616267 | I24: 19.067257
C25: Carson | E25: 19 | F25: 10.7525 | G25: 21.9904 | H25: 3.8169864 | I25: 16.560663
D26: 0-50,000 | E26: 8 | F26: 10.7525 | G26: 18.473 | H26: 2.3564069 | I26: 12.962438
D27: 150,001-250,000 | E27: 5 | F27: 18.03055 | G27: 21.9904 | H27: 1.6933218 | I27: 19.78795
D28: 250,001-350,000 | E28: 1 | F28: 20.28085 | G28: 20.28085 | I28: 20.28085
D29: 50,001-150,000 | E29: 5 | F29: 14.9052 | G29: 21.6977 | H29: 2.5724724 | I29: 18.3465
C30: Gardena | E30: 3 | F30: 11.7541 | G30: 25.7664 | H30: 7.3447642 | I30: 20.032967
D31: 0-50,000 | E31: 1 | F31: 25.7664 | G31: 25.7664 | I31: 25.7664
D32: 50,001-150,000 | E32: 2 | F32: 11.7541 | G32: 22.5784 | H32: 7.6539359 | I32: 17.16625
C33: Torrance | E33: 28 | F33: 12.102 | G33: 30.2333 | H33: 4.5019173 | I33: 20.664691
D34: 0-50,000 | E34: 8 | F34: 12.102 | G34: 30.2333 | H34: 5.7697141 | I34: 20.502594
D35: 150,001-250,000 | E35: 3 | F35: 19.51805 | G35: 27.9826 | H35: 4.6589024 | I35: 22.625867
D36: 250,001-350,000 | E36: 5 | F36: 16.2203 | G36: 25.5206 | H36: 3.6797274 | I36: 19.08812
D37: 350,001-450,000 | E37: 1 | F37: 18.5248 | G37: 18.5248 | I37: 18.5248
D38: 50,001-150,000 | E38: 9 | F38: 16.7513 | G38: 28.9685 | H38: 4.1221069 | I38: 22.1494
D39: 600,001-750,000 | E39: 1 | F39: 16.1212 | G39: 16.1212 | I39: 16.1212
D40: 750,000+ | E40: 1 | F40: 17.2818 | G40: 17.2818 | I40: 17.2818

Sheet Rent Table
A1: Street Address | B1: City | C1: State | D1: Zip Code | E1: Market | F1: Sector | G1: Date As Of | H1: Zip Code Grade | I1: Size | J1: Size Type | K1: Effective Rent* ($/Size Type) | L1: Avg. Transaction Size | M1: Avg. Lease Terms (Months) | N1: Avg. Work Value ($/Size Type) | O1: Avg. Free Months | P1: Floors | Q1: Year Built | R1: Year Renovated | S1: Size (SF)
A2: 1000 Francisco Street | B2: Torrance | C2: CA | D2: 90502 | E2: Los Angeles | F2: Industrial | G2: 45566 | H2: A++ | I2: 298000 | J2: SF | K2: 25.5206 | L2: 298000 | M2: 63 | N2: 2.5 | O2: 3 | P2: 1 | Q2: 1975 | R2: - | S2: {=_xlfn.IFS(AND('Rent Table'!$I2>0,'Rent Table'!$I2<=50000),"0-50,000", AND('Rent Table'!$I2 > 50000, 'Rent Table'!$I2 <= 150000), "50,001-150,000", AND('Rent Table'!$I2 > 150000, 'Rent Table'!$I2 <= 250000), "150,001-250,000", AND('Rent Table'!$I2 > 250000, 'Rent Table'!$I2 <= 350000), "250,001-350,000", AND('Rent Table'!$I2 > 350000, 'Rent Table'!$I2 <= 450000), "350,001-450,000", AND('Rent Table'!$I2 > 450000, 'Rent Table'!$I2 <= 600000), "450,001-600,000", AND('Rent Table'!$I2 > 600000, 'Rent Table'!$I2 <= 750000), "600,001-750,000",'Rent Table'!$I2 > 750000, "750,000+", TRUE, "Undefined" )} -> 250,001-350,000
A3: 1000 West 190th Street | B3: Torrance | C3: CA | D3: 90502 | E3: Los Angeles | F3: Industrial | G3: 45566 | H3: A++ | I3: 129556 | J3: SF | K3: 22.0341 | L3: 129256 | M3: 120 | N3: - | O3: - | P3: 1 | Q3: 2000 | R3: - | S3: {=_xlfn.IFS(AND('Rent Table'!$I3>0,'Rent Table'!$I3<=50000),"0-50,000", AND('Rent Table'!$I3 > 50000, 'Rent Table'!$I3 <= 150000), "50,001-150,000", AND('Rent Table'!$I3 > 150000, 'Rent Table'!$I3 <= 250000), "150,001-250,000", AND('Rent Table'!$I3 > 250000, 'Rent Table'!$I3 <= 350000), "250,001-350,000", AND('Rent Table'!$I3 > 350000, 'Rent Table'!$I3 <= 450000), "350,001-450,000", AND('Rent Table'!$I3 > 450000, 'Rent Table'!$I3 <= 600000), "450,001-600,000", AND('Rent Table'!$I3 > 600000, 'Rent Table'!$I3 <= 750000), "600,001-750,000",'Rent Table'!$I3 > 750000, "750,000+", TRUE, "Undefined" )} -> 50,001-150,000
A4: 1001 Knox Street | B4: Torrance | C4: CA | D4: 90502 | E4: Los Angeles | F4: Industrial | G4: 45566 | H4: A++ | I4: 49112 | J4: SF | K4: 30.2333 | L4: 49112 | M4: 123 | N4: 20 | O4: 3 | P4: 1 | Q4: 1981 | R4: - | S4: {=_xlfn.IFS(AND('Rent Table'!$I4>0,'Rent Table'!$I4<=50000),"0-50,000", AND('Rent Table'!$I4 > 50000, 'Rent Table'!$I4 <= 150000), "50,001-150,000", AND('Rent Table'!$I4 > 150000, 'Rent Table'!$I4 <= 250000), "150,001-250,000", AND('Rent Table'!$I4 > 250000, 'Rent Table'!$I4 <= 350000), "250,001-350,000", AND('Rent Table'!$I4 > 350000, 'Rent Table'!$I4 <= 450000), "350,001-450,000", AND('Rent Table'!$I4 > 450000, 'Rent Table'!$I4 <= 600000), "450,001-600,000", AND('Rent Table'!$I4 > 600000, 'Rent Table'!$I4 <= 750000), "600,001-750,000",'Rent Table'!$I4 > 750000, "750,000+", TRUE, "Undefined" )} -> 0-50,000
A5: 1011 Francisco Street | B5: Torrance | C5: CA | D5: 90502 | E5: Los Angeles | F5: Industrial | G5: 45566 | H5: A++ | I5: 45550 | J5: SF | K5: 18.1314 | L5: 45550 | M5: 85 | N5: - | O5: 1 | P5: 1 | Q5: 1979 | R5: - | S5: {=_xlfn.IFS(AND('Rent Table'!$I5>0,'Rent Table'!$I5<=50000),"0-50,000", AND('Rent Table'!$I5 > 50000, 'Rent Table'!$I5 <= 150000), "50,001-150,000", AND('Rent Table'!$I5 > 150000, 'Rent Table'!$I5 <= 250000), "150,001-250,000", AND('Rent Table'!$I5 > 250000, 'Rent Table'!$I5 <= 350000), "250,001-350,000", AND('Rent Table'!$I5 > 350000, 'Rent Table'!$I5 <= 450000), "350,001-450,000", AND('Rent Table'!$I5 > 450000, 'Rent Table'!$I5 <= 600000), "450,001-600,000", AND('Rent Table'!$I5 > 600000, 'Rent Table'!$I5 <= 750000), "600,001-750,000",'Rent Table'!$I5 > 750000, "750,000+", TRUE, "Undefined" )} -> 0-50,000
A6: 1024 East Del Amo Boulevard | B6: Carson | C6: CA | D6: 90746 | E6: Los Angeles | F6: Industrial | G6: 45566 | H6: A+ | I6: 36580 | J6: SF | K6: 18.473 | L6: 18301 | M6: 62 | N6: - | O6: - | P6: 1 | Q6: 1977 | R6: - | S6: {=_xlfn.IFS(AND('Rent Table'!$I6>0,'Rent Table'!$I6<=50000),"0-50,000", AND('Rent Table'!$I6 > 50000, 'Rent Table'!$I6 <= 150000), "50,001-150,000", AND('Rent Table'!$I6 > 150000, 'Rent Table'!$I6 <= 250000), "150,001-250,000", AND('Rent Table'!$I6 > 250000, 'Rent Table'!$I6 <= 350000), "250,001-350,000", AND('Rent Table'!$I6 > 350000, 'Rent Table'!$I6 <= 450000), "350,001-450,000", AND('Rent Table'!$I6 > 450000, 'Rent Table'!$I6 <= 600000), "450,001-600,000", AND('Rent Table'!$I6 > 600000, 'Rent Table'!$I6 <= 750000), "600,001-750,000",'Rent Table'!$I6 > 750000, "750,000+", TRUE, "Undefined" )} -> 0-50,000
A7: 1048 East Burgrove Street | B7: Carson | C7: CA | D7: 90746 | E7: Los Angeles | F7: Industrial | G7: 45566 | H7: A+ | I7: 75194 | J7: SF | K7: 19.1764 | L7: 53474 | M7: 36 | N7: - | O7: - | P7: 1 | Q7: 1972 | R7: 1973 | S7: {=_xlfn.IFS(AND('Rent Table'!$I7>0,'Rent Table'!$I7<=50000),"0-50,000", AND('Rent Table'!$I7 > 50000, 'Rent Table'!$I7 <= 150000), "50,001-150,000", AND('Rent Table'!$I7 > 150000, 'Rent Table'!$I7 <= 250000), "150,001-250,000", AND('Rent Table'!$I7 > 250000, 'Rent Table'!$I7 <= 350000), "250,001-350,000", AND('Rent Table'!$I7 > 350000, 'Rent Table'!$I7 <= 450000), "350,001-450,000", AND('Rent Table'!$I7 > 450000, 'Rent Table'!$I7 <= 600000), "450,001-600,000", AND('Rent Table'!$I7 > 600000, 'Rent Table'!$I7 <= 750000), "600,001-750,000",'Rent Table'!$I7 > 750000, "750,000+", TRUE, "Undefined" )} -> 50,001-150,000
A8: 1062 East Del Amo Boulevard | B8: Carson | C8: CA | D8: 90746 | E8: Los Angeles | F8: Industrial | G8: 45566 | H8: A+ | I8: 121551 | J8: SF | K8: 14.9052 | L8: 33855 | M8: 61.5 | N8: 0.5 | O8: 2 | P8: 1 | Q8: 1972 | R8: - | S8: {=_xlfn.IFS(AND('Rent Table'!$I8>0,'Rent Table'!$I8<=50000),"0-50,000", AND('Rent Table'!$I8 > 50000, 'Rent Table'!$I8 <= 150000), "50,001-150,000", AND('Rent Table'!$I8 > 150000, 'Rent Table'!$I8 <= 250000), "150,001-250,000", AND('Rent Table'!$I8 > 250000, 'Rent Table'!$I8 <= 350000), "250,001-350,000", AND('Rent Table'!$I8 > 350000, 'Rent Table'!$I8 <= 450000), "350,001-450,000", AND('Rent Table'!$I8 > 450000, 'Rent Table'!$I8 <= 600000), "450,001-600,000", AND('Rent Table'!$I8 > 600000, 'Rent Table'!$I8 <= 750000), "600,001-750,000",'Rent Table'!$I8 > 750000, "750,000+", TRUE, "Undefined" )} -> 50,001-150,000
A9: 1227 Knox Street | B9: Torrance | C9: CA | D9: 90502 | E9: Los Angeles | F9: Industrial | G9: 45566 | H9: A++ | I9: 16000 | J9: SF | K9: 12.102 | L9: 16000 | M9: 36 | N9: - | O9: 1 | P9: 1 | Q9: 1974 | R9: - | S9: {=_xlfn.IFS(AND('Rent Table'!$I9>0,'Rent Table'!$I9<=50000),"0-50,000", AND('Rent Table'!$I9 > 50000, 'Rent Table'!$I9 <= 150000), "50,001-150,000", AND('Rent Table'!$I9 > 150000, 'Rent Table'!$I9 <= 250000), "150,001-250,000", AND('Rent Table'!$I9 > 250000, 'Rent Table'!$I9 <= 350000), "250,001-350,000", AND('Rent Table'!$I9 > 350000, 'Rent Table'!$I9 <= 450000), "350,001-450,000", AND('Rent Table'!$I9 > 450000, 'Rent Table'!$I9 <= 600000), "450,001-600,000", AND('Rent Table'!$I9 > 600000, 'Rent Table'!$I9 <= 750000), "600,001-750,000",'Rent Table'!$I9 > 750000, "750,000+", TRUE, "Undefined" )} -> 0-50,000
A10: 1234 Francisco Street | B10: Torrance | C10: CA | D10: 90502 | E10: Los Angeles | F10: Industrial | G10: 45566 | H10: A++ | I10: 14950 | J10: SF | K10: 15.3947 | L10: 14950 | M10: 61.5 | N10: - | O10: 3 | P10: 1 | Q10: 1964 | R10: - | S10: {=_xlfn.IFS(AND('Rent Table'!$I10>0,'Rent Table'!$I10<=50000),"0-50,000", AND('Rent Table'!$I10 > 50000, 'Rent Table'!$I10 <= 150000), "50,001-150,000", AND('Rent Table'!$I10 > 150000, 'Rent Table'!$I10 <= 250000), "150,001-250,000", AND('Rent Table'!$I10 > 250000, 'Rent Table'!$I10 <= 350000), "250,001-350,000", AND('Rent Table'!$I10 > 350000, 'Rent Table'!$I10 <= 450000), "350,001-450,000", AND('Rent Table'!$I10 > 450000, 'Rent Table'!$I10 <= 600000), "450,001-600,000", AND('Rent Table'!$I10 > 600000, 'Rent Table'!$I10 <= 750000), "600,001-750,000",'Rent Table'!$I10 > 750000, "750,000+", TRUE, "Undefined" )} -> 0-50,000
A11: 1380-1400 Charles Willard Street | B11: Carson | C11: CA | D11: 90746 | E11: Los Angeles | F11: Industrial | G11: 45566 | H11: A+ | I11: 250272 | J11: SF | K11: 20.28085 | L11: 148706 | M11: 36.75 | N11: - | O11: - | P11: 1 | Q11: 2003 | R11: - | S11: {=_xlfn.IFS(AND('Rent Table'!$I11>0,'Rent Table'!$I11<=50000),"0-50,000", AND('Rent Table'!$I11 > 50000, 'Rent Table'!$I11 <= 150000), "50,001-150,000", AND('Rent Table'!$I11 > 150000, 'Rent Table'!$I11 <= 250000), "150,001-250,000", AND('Rent Table'!$I11 > 250000, 'Rent Table'!$I11 <= 350000), "250,001-350,000", AND('Rent Table'!$I11 > 350000, 'Rent Table'!$I11 <= 450000), "350,001-450,000", AND('Rent Table'!$I11 > 450000, 'Rent Table'!$I11 <= 600000), "450,001-600,000", AND('Rent Table'!$I11 > 600000, 'Rent Table'!$I11 <= 750000), "600,001-750,000",'Rent Table'!$I11 > 750000, "750,000+", TRUE, "Undefined" )} -> 250,001-350,000
A12: 1450 Glenn Curtiss Street | B12: Carson | C12: CA | D12: 90746 | E12: Los Angeles | F12: Industrial | G12: 45566 | H12: A+ | I12: 182554 | J12: SF | K12: 19.0129 | L12: 182554 | M12: 60 | N12: 1.1 | O12: - | P12: 1 | Q12: 2005 | R12: - | S12: {=_xlfn.IFS(AND('Rent Table'!$I12>0,'Rent Table'!$I12<=50000),"0-50,000", AND('Rent Table'!$I12 > 50000, 'Rent Table'!$I12 <= 150000), "50,001-150,000", AND('Rent Table'!$I12 > 150000, 'Rent Table'!$I12 <= 250000), "150,001-250,000", AND('Rent Table'!$I12 > 250000, 'Rent Table'!$I12 <= 350000), "250,001-350,000", AND('Rent Table'!$I12 > 350000, 'Rent Table'!$I12 <= 450000), "350,001-450,000", AND('Rent Table'!$I12 > 450000, 'Rent Table'!$I12 <= 600000), "450,001-600,000", AND('Rent Table'!$I12 > 600000, 'Rent Table'!$I12 <= 750000), "600,001-750,000",'Rent Table'!$I12 > 750000, "750,000+", TRUE, "Undefined" )} -> 150,001-250,000
A13: 1450-1480 Charles Willard Street | B13: Carson | C13: CA | D13: 90746 | E13: Los Angeles | F13: Industrial | G13: 45566 | H13: A+ | I13: 81893 | J13: SF | K13: 19.08 | L13: 81532 | M13: 59 | N13: - | O13: 1 | P13: 1 | Q13: 2007 | R13: - | S13: {=_xlfn.IFS(AND('Rent Table'!$I13>0,'Rent Table'!$I13<=50000),"0-50,000", AND('Rent Table'!$I13 > 50000, 'Rent Table'!$I13 <= 150000), "50,001-150,000", AND('Rent Table'!$I13 > 150000, 'Rent Table'!$I13 <= 250000), "150,001-250,000", AND('Rent Table'!$I13 > 250000, 'Rent Table'!$I13 <= 350000), "250,001-350,000", AND('Rent Table'!$I13 > 350000, 'Rent Table'!$I13 <= 450000), "350,001-450,000", AND('Rent Table'!$I13 > 450000, 'Rent Table'!$I13 <= 600000), "450,001-600,000", AND('Rent Table'!$I13 > 600000, 'Rent Table'!$I13 <= 750000), "600,001-750,000",'Rent Table'!$I13 > 750000, "750,000+", TRUE, "Undefined" )} -> 50,001-150,000
A14: 1451 West Knox Street | B14: Torrance | C14: CA | D14: 90501 | E14: Los Angeles | F14: Industrial | G14: 45566 | H14: A++ | I14: 153000 | J14: SF | K14: 27.9826 | L14: 152790 | M14: 65 | N14: 1 | O14: - | P14: 1 | Q14: 2005 | R14: - | S14: {=_xlfn.IFS(AND('Rent Table'!$I14>0,'Rent Table'!$I14<=50000),"0-50,000", AND('Rent Table'!$I14 > 50000, 'Rent Table'!$I14 <= 150000), "50,001-150,000", AND('Rent Table'!$I14 > 150000, 'Rent Table'!$I14 <= 250000), "150,001-250,000", AND('Rent Table'!$I14 > 250000, 'Rent Table'!$I14 <= 350000), "250,001-350,000", AND('Rent Table'!$I14 > 350000, 'Rent Table'!$I14 <= 450000), "350,001-450,000", AND('Rent Table'!$I14 > 450000, 'Rent Table'!$I14 <= 600000), "450,001-600,000", AND('Rent Table'!$I14 > 600000, 'Rent Table'!$I14 <= 750000), "600,001-750,000",'Rent Table'!$I14 > 750000, "750,000+", TRUE, "Undefined" )} -> 150,001-250,000
A15: 1452 West Knox Street | B15: Torrance | C15: CA | D15: 90501 | E15: Los Angeles | F15: Industrial | G15: 45566 | H15: A++ | I15: 442550 | J15: SF | K15: 18.5248 | L15: 442550 | M15: 65 | N15: 2.82 | O15: 5.5 | P15: - | Q15: 2003 | R15: 2004 | S15: {=_xlfn.IFS(AND('Rent Table'!$I15>0,'Rent Table'!$I15<=50000),"0-50,000", AND('Rent Table'!$I15 > 50000, 'Rent Table'!$I15 <= 150000), "50,001-150,000", AND('Rent Table'!$I15 > 150000, 'Rent Table'!$I15 <= 250000), "150,001-250,000", AND('Rent Table'!$I15 > 250000, 'Rent Table'!$I15 <= 350000), "250,001-350,000", AND('Rent Table'!$I15 > 350000, 'Rent Table'!$I15 <= 450000), "350,001-450,000", AND('Rent Table'!$I15 > 450000, 'Rent Table'!$I15 <= 600000), "450,001-600,000", AND('Rent Table'!$I15 > 600000, 'Rent Table'!$I15 <= 750000), "600,001-750,000",'Rent Table'!$I15 > 750000, "750,000+", TRUE, "Undefined" )} -> 350,001-450,000
A16: 1457 Glenn Curtiss Street | B16: Carson | C16: CA | D16: 90746 | E16: Los Angeles | F16: Industrial | G16: 45566 | H16: A+ | I16: 76028 | J16: SF | K16: 16.8732 | L16: 76028 | M16: 48 | N16: 0.53 | O16: 1 | P16: 1 | Q16: 2006 | R16: - | S16: {=_xlfn.IFS(AND('Rent Table'!$I16>0,'Rent Table'!$I16<=50000),"0-50,000", AND('Rent Table'!$I16 > 50000, 'Rent Table'!$I16 <= 150000), "50,001-150,000", AND('Rent Table'!$I16 > 150000, 'Rent Table'!$I16 <= 250000), "150,001-250,000", AND('Rent Table'!$I16 > 250000, 'Rent Table'!$I16 <= 350000), "250,001-350,000", AND('Rent Table'!$I16 > 350000, 'Rent Table'!$I16 <= 450000), "350,001-450,000", AND('Rent Table'!$I16 > 450000, 'Rent Table'!$I16 <= 600000), "450,001-600,000", AND('Rent Table'!$I16 > 600000, 'Rent Table'!$I16 <= 750000), "600,001-750,000",'Rent Table'!$I16 > 750000, "750,000+", TRUE, "Undefined" )} -> 50,001-150,000
A17: 1460-1490 Beachey Place | B17: Carson | C17: CA | D17: 90746 | E17: Los Angeles | F17: Industrial | G17: 45566 | H17: A+ | I17: 185375 | J17: SF | K17: 18.03055 | L17: 40905 | M17: 61.5 | N17: 1 | O17: 1.5 | P17: 1 | Q17: 2005 | R17: - | S17: {=_xlfn.IFS(AND('Rent Table'!$I17>0,'Rent Table'!$I17<=50000),"0-50,000", AND('Rent Table'!$I17 > 50000, 'Rent Table'!$I17 <= 150000), "50,001-150,000", AND('Rent Table'!$I17 > 150000, 'Rent Table'!$I17 <= 250000), "150,001-250,000", AND('Rent Table'!$I17 > 250000, 'Rent Table'!$I17 <= 350000), "250,001-350,000", AND('Rent Table'!$I17 > 350000, 'Rent Table'!$I17 <= 450000), "350,001-450,000", AND('Rent Table'!$I17 > 450000, 'Rent Table'!$I17 <= 600000), "450,001-600,000", AND('Rent Table'!$I17 > 600000, 'Rent Table'!$I17 <= 750000), "600,001-750,000",'Rent Table'!$I17 > 750000, "750,000+", TRUE, "Undefined" )} -> 150,001-250,000
A18: 1500 Glenn Curtiss Street | B18: Carson | C18: CA | D18: 90746 | E18: Los Angeles | F18: Industrial | G18: 45566 | H18: A+ | I18: 242143 | J18: SF | K18: 21.1519 | L18: 48330 | M18: 64 | N18: - | O18: 4 | P18: 1 | Q18: 2002 | R18: - | S18: {=_xlfn.IFS(AND('Rent Table'!$I18>0,'Rent Table'!$I18<=50000),"0-50,000", AND('Rent Table'!$I18 > 50000, 'Rent Table'!$I18 <= 150000), "50,001-150,000", AND('Rent Table'!$I18 > 150000, 'Rent Table'!$I18 <= 250000), "150,001-250,000", AND('Rent Table'!$I18 > 250000, 'Rent Table'!$I18 <= 350000), "250,001-350,000", AND('Rent Table'!$I18 > 350000, 'Rent Table'!$I18 <= 450000), "350,001-450,000", AND('Rent Table'!$I18 > 450000, 'Rent Table'!$I18 <= 600000), "450,001-600,000", AND('Rent Table'!$I18 > 600000, 'Rent Table'!$I18 <= 750000), "600,001-750,000",'Rent Table'!$I18 > 750000, "750,000+", TRUE, "Undefined" )} -> 150,001-250,000
A19: 1521 Francisco Street | B19: Torrance | C19: CA | D19: 90501 | E19: Los Angeles | F19: Industrial | G19: 45566 | H19: A++ | I19: 46479 | J19: SF | K19: 20.3035 | L19: 23949 | M19: 35 | N19: - | O19: 1 | P19: - | Q19: 2011 | R19: 2012 | S19: {=_xlfn.IFS(AND('Rent Table'!$I19>0,'Rent Table'!$I19<=50000),"0-50,000", AND('Rent Table'!$I19 > 50000, 'Rent Table'!$I19 <= 150000), "50,001-150,000", AND('Rent Table'!$I19 > 150000, 'Rent Table'!$I19 <= 250000), "150,001-250,000", AND('Rent Table'!$I19 > 250000, 'Rent Table'!$I19 <= 350000), "250,001-350,000", AND('Rent Table'!$I19 > 350000, 'Rent Table'!$I19 <= 450000), "350,001-450,000", AND('Rent Table'!$I19 > 450000, 'Rent Table'!$I19 <= 600000), "450,001-600,000", AND('Rent Table'!$I19 > 600000, 'Rent Table'!$I19 <= 750000), "600,001-750,000",'Rent Table'!$I19 > 750000, "750,000+", TRUE, "Undefined" )} -> 0-50,000
A20: 1533-1543 East Del Amo Boulevard | B20: Carson | C20: CA | D20: 90746 | E20: Los Angeles | F20: Industrial | G20: 45566 | H20: A+ | I20: 35186 | J20: SF | K20: 12.4838 | L20: 17666 | M20: 36 | N20: - | O20: 0.5 | P20: 1 | Q20: 1971 | R20: - | S20: {=_xlfn.IFS(AND('Rent Table'!$I20>0,'Rent Table'!$I20<=50000),"0-50,000", AND('Rent Table'!$I20 > 50000, 'Rent Table'!$I20 <= 150000), "50,001-150,000", AND('Rent Table'!$I20 > 150000, 'Rent Table'!$I20 <= 250000), "150,001-250,000", AND('Rent Table'!$I20 > 250000, 'Rent Table'!$I20 <= 350000), "250,001-350,000", AND('Rent Table'!$I20 > 350000, 'Rent Table'!$I20 <= 450000), "350,001-450,000", AND('Rent Table'!$I20 > 450000, 'Rent Table'!$I20 <= 600000), "450,001-600,000", AND('Rent Table'!$I20 > 600000, 'Rent Table'!$I20 <= 750000), "600,001-750,000",'Rent Table'!$I20 > 750000, "750,000+", TRUE, "Undefined" )} -> 0-50,000
A21: 1540-1560 West 190th Street | B21: Torrance | C21: CA | D21: 90501 | E21: Los Angeles | F21: Industrial | G21: 45566 | H21: A++ | I21: 117460 | J21: SF | K21: 25.9481 | L21: 90133 | M21: 60 | N21: - | O21: - | P21: 1 | Q21: 2000 | R21: - | S21: {=_xlfn.IFS(AND('Rent Table'!$I21>0,'Rent Table'!$I21<=50000),"0-50,000", AND('Rent Table'!$I21 > 50000, 'Rent Table'!$I21 <= 150000), "50,001-150,000", AND('Rent Table'!$I21 > 150000, 'Rent Table'!$I21 <= 250000), "150,001-250,000", AND('Rent Table'!$I21 > 250000, 'Rent Table'!$I21 <= 350000), "250,001-350,000", AND('Rent Table'!$I21 > 350000, 'Rent Table'!$I21 <= 450000), "350,001-450,000", AND('Rent Table'!$I21 > 450000, 'Rent Table'!$I21 <= 600000), "450,001-600,000", AND('Rent Table'!$I21 > 600000, 'Rent Table'!$I21 <= 750000), "600,001-750,000",'Rent Table'!$I21 > 750000, "750,000+", TRUE, "Undefined" )} -> 50,001-150,000
A22: 1545 Francisco Street | B22: Torrance | C22: CA | D22: 90501 | E22: Los Angeles | F22: Industrial | G22: 45566 | H22: A++ | I22: 277000 | J22: SF | K22: 16.2203 | L22: 106898 | M22: 61 | N22: 1 | O22: 1 | P22: 2 | Q22: 2012 | R22: 2013 | S22: {=_xlfn.IFS(AND('Rent Table'!$I22>0,'Rent Table'!$I22<=50000),"0-50,000", AND('Rent Table'!$I22 > 50000, 'Rent Table'!$I22 <= 150000), "50,001-150,000", AND('Rent Table'!$I22 > 150000, 'Rent Table'!$I22 <= 250000), "150,001-250,000", AND('Rent Table'!$I22 > 250000, 'Rent Table'!$I22 <= 350000), "250,001-350,000", AND('Rent Table'!$I22 > 350000, 'Rent Table'!$I22 <= 450000), "350,001-450,000", AND('Rent Table'!$I22 > 450000, 'Rent Table'!$I22 <= 600000), "450,001-600,000", AND('Rent Table'!$I22 > 600000, 'Rent Table'!$I22 <= 750000), "600,001-750,000",'Rent Table'!$I22 > 750000, "750,000+", TRUE, "Undefined" )} -> 250,001-350,000
A23: 1550-1650 Charles Willard Street | B23: Carson | C23: CA | D23: 90746 | E23: Los Angeles | F23: Industrial | G23: 45566 | H23: A+ | I23: 210938 | J23: SF | K23: 21.9904 | L23: 107753 | M23: 64 | N23: 1.5 | O23: 1 | P23: 1 | Q23: 2000 | R23: 2005 | S23: {=_xlfn.IFS(AND('Rent Table'!$I23>0,'Rent Table'!$I23<=50000),"0-50,000", AND('Rent Table'!$I23 > 50000, 'Rent Table'!$I23 <= 150000), "50,001-150,000", AND('Rent Table'!$I23 > 150000, 'Rent Table'!$I23 <= 250000), "150,001-250,000", AND('Rent Table'!$I23 > 250000, 'Rent Table'!$I23 <= 350000), "250,001-350,000", AND('Rent Table'!$I23 > 350000, 'Rent Table'!$I23 <= 450000), "350,001-450,000", AND('Rent Table'!$I23 > 450000, 'Rent Table'!$I23 <= 600000), "450,001-600,000", AND('Rent Table'!$I23 > 600000, 'Rent Table'!$I23 <= 750000), "600,001-750,000",'Rent Table'!$I23 > 750000, "750,000+", TRUE, "Undefined" )} -> 150,001-250,000
A24: 1561 Beachey Place | B24: Carson | C24: CA | D24: 90746 | E24: Los Angeles | F24: Industrial | G24: 45566 | H24: A+ | I24: 108873 | J24: SF | K24: 21.6977 | L24: 107603 | M24: 60 | N24: - | O24: 2 | P24: 2 | Q24: 2004 | R24: 2005 | S24: {=_xlfn.IFS(AND('Rent Table'!$I24>0,'Rent Table'!$I24<=50000),"0-50,000", AND('Rent Table'!$I24 > 50000, 'Rent Table'!$I24 <= 150000), "50,001-150,000", AND('Rent Table'!$I24 > 150000, 'Rent Table'!$I24 <= 250000), "150,001-250,000", AND('Rent Table'!$I24 > 250000, 'Rent Table'!$I24 <= 350000), "250,001-350,000", AND('Rent Table'!$I24 > 350000, 'Rent Table'!$I24 <= 450000), "350,001-450,000", AND('Rent Table'!$I24 > 450000, 'Rent Table'!$I24 <= 600000), "450,001-600,000", AND('Rent Table'!$I24 > 600000, 'Rent Table'!$I24 <= 750000), "600,001-750,000",'Rent Table'!$I24 > 750000, "750,000+", TRUE, "Undefined" )} -> 50,001-150,000
A25: 1640 West 190th Street | B25: Torrance | C25: CA | D25: 90501 | E25: Los Angeles | F25: Industrial | G25: 45566 | H25: A++ | I25: 123345 | J25: SF | K25: 28.9685 | L25: 123345 | M25: 120 | N25: - | O25: 1.5 | P25: 1 | Q25: 2000 | R25: - | S25: {=_xlfn.IFS(AND('Rent Table'!$I25>0,'Rent Table'!$I25<=50000),"0-50,000", AND('Rent Table'!$I25 > 50000, 'Rent Table'!$I25 <= 150000), "50,001-150,000", AND('Rent Table'!$I25 > 150000, 'Rent Table'!$I25 <= 250000), "150,001-250,000", AND('Rent Table'!$I25 > 250000, 'Rent Table'!$I25 <= 350000), "250,001-350,000", AND('Rent Table'!$I25 > 350000, 'Rent Table'!$I25 <= 450000), "350,001-450,000", AND('Rent Table'!$I25 > 450000, 'Rent Table'!$I25 <= 600000), "450,001-600,000", AND('Rent Table'!$I25 > 600000, 'Rent Table'!$I25 <= 750000), "600,001-750,000",'Rent Table'!$I25 > 750000, "750,000+", TRUE, "Undefined" )} -> 50,001-150,000
A26: 1667 East Del Amo Boulevard | B26: Carson | C26: CA | D26: 90746 | E26: Los Angeles | F26: Industrial | G26: 45566 | H26: A+ | I26: 16863 | J26: SF | K26: 11.3567 | L26: 1752 | M26: 24 | N26: - | O26: - | P26: 1 | Q26: 1970 | R26: - | S26: {=_xlfn.IFS(AND('Rent Table'!$I26>0,'Rent Table'!$I26<=50000),"0-50,000", AND('Rent Table'!$I26 > 50000, 'Rent Table'!$I26 <= 150000), "50,001-150,000", AND('Rent Table'!$I26 > 150000, 'Rent Table'!$I26 <= 250000), "150,001-250,000", AND('Rent Table'!$I26 > 250000, 'Rent Table'!$I26 <= 350000), "250,001-350,000", AND('Rent Table'!$I26 > 350000, 'Rent Table'!$I26 <= 450000), "350,001-450,000", AND('Rent Table'!$I26 > 450000, 'Rent Table'!$I26 <= 600000), "450,001-600,000", AND('Rent Table'!$I26 > 600000, 'Rent Table'!$I26 <= 750000), "600,001-750,000",'Rent Table'!$I26 > 750000, "750,000+", TRUE, "Undefined" )} -> 0-50,000
A27: 1681 East Del Amo Boulevard | B27: Carson | C27: CA | D27: 90746 | E27: Los Angeles | F27: Industrial | G27: 45566 | H27: A+ | I27: 16862 | J27: SF | K27: 10.7525 | L27: 2592 | M27: 36 | N27: - | O27: - | P27: 1 | Q27: 1970 | R27: - | S27: {=_xlfn.IFS(AND('Rent Table'!$I27>0,'Rent Table'!$I27<=50000),"0-50,000", AND('Rent Table'!$I27 > 50000, 'Rent Table'!$I27 <= 150000), "50,001-150,000", AND('Rent Table'!$I27 > 150000, 'Rent Table'!$I27 <= 250000), "150,001-250,000", AND('Rent Table'!$I27 > 250000, 'Rent Table'!$I27 <= 350000), "250,001-350,000", AND('Rent Table'!$I27 > 350000, 'Rent Table'!$I27 <= 450000), "350,001-450,000", AND('Rent Table'!$I27 > 450000, 'Rent Table'!$I27 <= 600000), "450,001-600,000", AND('Rent Table'!$I27 > 600000, 'Rent Table'!$I27 <= 750000), "600,001-750,000",'Rent Table'!$I27 > 750000, "750,000+", TRUE, "Undefined" )} -> 0-50,000
A28: 1683 East Del Amo Boulevard | B28: Carson | C28: CA | D28: 90746 | E28: Los Angeles | F28: Industrial | G28: 45566 | H28: A+ | I28: 16882 | J28: SF | K28: 12.214405 | L28: 2555 | M28: 48.5 | N28: - | O28: 1 | P28: 1 | Q28: 1970 | R28: - | S28: {=_xlfn.IFS(AND('Rent Table'!$I28>0,'Rent Table'!$I28<=50000),"0-50,000", AND('Rent Table'!$I28 > 50000, 'Rent Table'!$I28 <= 150000), "50,001-150,000", AND('Rent Table'!$I28 > 150000, 'Rent Table'!$I28 <= 250000), "150,001-250,000", AND('Rent Table'!$I28 > 250000, 'Rent Table'!$I28 <= 350000), "250,001-350,000", AND('Rent Table'!$I28 > 350000, 'Rent Table'!$I28 <= 450000), "350,001-450,000", AND('Rent Table'!$I28 > 450000, 'Rent Table'!$I28 <= 600000), "450,001-600,000", AND('Rent Table'!$I28 > 600000, 'Rent Table'!$I28 <= 750000), "600,001-750,000",'Rent Table'!$I28 > 750000, "750,000+", TRUE, "Undefined" )} -> 0-50,000
A29: 1685 East Del Amo Boulevard | B29: Carson | C29: CA | D29: 90746 | E29: Los Angeles | F29: Industrial | G29: 45566 | H29: A+ | I29: 16862 | J29: SF | K29: 12.9391 | L29: 1752 | M29: 36 | N29: - | O29: - | P29: 1 | Q29: 1970 | R29: - | S29: {=_xlfn.IFS(AND('Rent Table'!$I29>0,'Rent Table'!$I29<=50000),"0-50,000", AND('Rent Table'!$I29 > 50000, 'Rent Table'!$I29 <= 150000), "50,001-150,000", AND('Rent Table'!$I29 > 150000, 'Rent Table'!$I29 <= 250000), "150,001-250,000", AND('Rent Table'!$I29 > 250000, 'Rent Table'!$I29 <= 350000), "250,001-350,000", AND('Rent Table'!$I29 > 350000, 'Rent Table'!$I29 <= 450000), "350,001-450,000", AND('Rent Table'!$I29 > 450000, 'Rent Table'!$I29 <= 600000), "450,001-600,000", AND('Rent Table'!$I29 > 600000, 'Rent Table'!$I29 <= 750000), "600,001-750,000",'Rent Table'!$I29 > 750000, "750,000+", TRUE, "Undefined" )} -> 0-50,000
A30: 1689 East Del Amo Boulevard | B30: Carson | C30: CA | D30: 90746 | E30: Los Angeles | F30: Industrial | G30: 45566 | H30: A+ | I30: 40332 | J30: SF | K30: 12.4644 | L30: 1752 | M30: 36 | N30: - | O30: - | P30: 1 | Q30: 1970 | R30: - | S30: {=_xlfn.IFS(AND('Rent Table'!$I30>0,'Rent Table'!$I30<=50000),"0-50,000", AND('Rent Table'!$I30 > 50000, 'Rent Table'!$I30 <= 150000), "50,001-150,000", AND('Rent Table'!$I30 > 150000, 'Rent Table'!$I30 <= 250000), "150,001-250,000", AND('Rent Table'!$I30 > 250000, 'Rent Table'!$I30 <= 350000), "250,001-350,000", AND('Rent Table'!$I30 > 350000, 'Rent Table'!$I30 <= 450000), "350,001-450,000", AND('Rent Table'!$I30 > 450000, 'Rent Table'!$I30 <= 600000), "450,001-600,000", AND('Rent Table'!$I30 > 600000, 'Rent Table'!$I30 <= 750000), "600,001-750,000",'Rent Table'!$I30 > 750000, "750,000+", TRUE, "Undefined" )} -> 0-50,000
A31: 1693 East Del Amo Boulevard | B31: Carson | C31: CA | D31: 90746 | E31: Los Angeles | F31: Industrial | G31: 45566 | H31: A+ | I31: 16863 | J31: SF | K31: 13.0156 | L31: 2336 | M31: 24 | N31: - | O31: - | P31: 1 | Q31: 1970 | R31: - | S31: {=_xlfn.IFS(AND('Rent Table'!$I31>0,'Rent Table'!$I31<=50000),"0-50,000", AND('Rent Table'!$I31 > 50000, 'Rent Table'!$I31 <= 150000), "50,001-150,000", AND('Rent Table'!$I31 > 150000, 'Rent Table'!$I31 <= 250000), "150,001-250,000", AND('Rent Table'!$I31 > 250000, 'Rent Table'!$I31 <= 350000), "250,001-350,000", AND('Rent Table'!$I31 > 350000, 'Rent Table'!$I31 <= 450000), "350,001-450,000", AND('Rent Table'!$I31 > 450000, 'Rent Table'!$I31 <= 600000), "450,001-600,000", AND('Rent Table'!$I31 > 600000, 'Rent Table'!$I31 <= 750000), "600,001-750,000",'Rent Table'!$I31 > 750000, "750,000+", TRUE, "Undefined" )} -> 0-50,000
A32: 1810 195th Street | B32: Torrance | C32: CA | D32: 90501 | E32: Los Angeles | F32: Industrial | G32: 45566 | H32: A++ | I32: 107140 | J32: SF | K32: 19.7753 | L32: 107140 | M32: 123 | N32: 3 | O32: 3 | P32: - | Q32: 2022 | R32: - | S32: {=_xlfn.IFS(AND('Rent Table'!$I32>0,'Rent Table'!$I32<=50000),"0-50,000", AND('Rent Table'!$I32 > 50000, 'Rent Table'!$I32 <= 150000), "50,001-150,000", AND('Rent Table'!$I32 > 150000, 'Rent Table'!$I32 <= 250000), "150,001-250,000", AND('Rent Table'!$I32 > 250000, 'Rent Table'!$I32 <= 350000), "250,001-350,000", AND('Rent Table'!$I32 > 350000, 'Rent Table'!$I32 <= 450000), "350,001-450,000", AND('Rent Table'!$I32 > 450000, 'Rent Table'!$I32 <= 600000), "450,001-600,000", AND('Rent Table'!$I32 > 600000, 'Rent Table'!$I32 <= 750000), "600,001-750,000",'Rent Table'!$I32 > 750000, "750,000+", TRUE, "Undefined" )} -> 50,001-150,000
A33: 1820 195th Street | B33: Torrance | C33: CA | D33: 90501 | E33: Los Angeles | F33: Industrial | G33: 45566 | H33: A++ | I33: 104544 | J33: SF | K33: 20.2742 | L33: 104544 | M33: 123 | N33: 3 | O33: 3 | P33: - | Q33: 2022 | R33: - | S33: {=_xlfn.IFS(AND('Rent Table'!$I33>0,'Rent Table'!$I33<=50000),"0-50,000", AND('Rent Table'!$I33 > 50000, 'Rent Table'!$I33 <= 150000), "50,001-150,000", AND('Rent Table'!$I33 > 150000, 'Rent Table'!$I33 <= 250000), "150,001-250,000", AND('Rent Table'!$I33 > 250000, 'Rent Table'!$I33 <= 350000), "250,001-350,000", AND('Rent Table'!$I33 > 350000, 'Rent Table'!$I33 <= 450000), "350,001-450,000", AND('Rent Table'!$I33 > 450000, 'Rent Table'!$I33 <= 600000), "450,001-600,000", AND('Rent Table'!$I33 > 600000, 'Rent Table'!$I33 <= 750000), "600,001-750,000",'Rent Table'!$I33 > 750000, "750,000+", TRUE, "Undefined" )} -> 50,001-150,000
A34: 1830 West 205th Street | B34: Torrance | C34: CA | D34: 90501 | E34: Los Angeles | F34: Industrial | G34: 45566 | H34: A++ | I34: 31505 | J34: SF | K34: 24.8275 | L34: 31505 | M34: 84 | N34: 7.94 | O34: 3 | P34: 1 | Q34: 1978 | R34: 1993 | S34: {=_xlfn.IFS(AND('Rent Table'!$I34>0,'Rent Table'!$I34<=50000),"0-50,000", AND('Rent Table'!$I34 > 50000, 'Rent Table'!$I34 <= 150000), "50,001-150,000", AND('Rent Table'!$I34 > 150000, 'Rent Table'!$I34 <= 250000), "150,001-250,000", AND('Rent Table'!$I34 > 250000, 'Rent Table'!$I34 <= 350000), "250,001-350,000", AND('Rent Table'!$I34 > 350000, 'Rent Table'!$I34 <= 450000), "350,001-450,000", AND('Rent Table'!$I34 > 450000, 'Rent Table'!$I34 <= 600000), "450,001-600,000", AND('Rent Table'!$I34 > 600000, 'Rent Table'!$I34 <= 750000), "600,001-750,000",'Rent Table'!$I34 > 750000, "750,000+", TRUE, "Undefined" )} -> 0-50,000
A35: 18300 Central Avenue | B35: Carson | C35: CA | D35: 90746 | E35: Los Angeles | F35: Industrial | G35: 45566 | H35: A+ | I35: 183473 | J35: SF | K35: 18.754 | L35: 183473 | M35: 120 | N35: - | O35: 1 | P35: 1 | Q35: 2000 | R35: - | S35: {=_xlfn.IFS(AND('Rent Table'!$I35>0,'Rent Table'!$I35<=50000),"0-50,000", AND('Rent Table'!$I35 > 50000, 'Rent Table'!$I35 <= 150000), "50,001-150,000", AND('Rent Table'!$I35 > 150000, 'Rent Table'!$I35 <= 250000), "150,001-250,000", AND('Rent Table'!$I35 > 250000, 'Rent Table'!$I35 <= 350000), "250,001-350,000", AND('Rent Table'!$I35 > 350000, 'Rent Table'!$I35 <= 450000), "350,001-450,000", AND('Rent Table'!$I35 > 450000, 'Rent Table'!$I35 <= 600000), "450,001-600,000", AND('Rent Table'!$I35 > 600000, 'Rent Table'!$I35 <= 750000), "600,001-750,000",'Rent Table'!$I35 > 750000, "750,000+", TRUE, "Undefined" )} -> 150,001-250,000
A36: 1845 West 205th Street | B36: Torrance | C36: CA | D36: 90501 | E36: Los Angeles | F36: Industrial | G36: 45566 | H36: A++ | I36: 34505 | J36: SF | K36: 24.277 | L36: 25301 | M36: 89 | N36: - | O36: 4.34 | P36: 1 | Q36: 1978 | R36: - | S36: {=_xlfn.IFS(AND('Rent Table'!$I36>0,'Rent Table'!$I36<=50000),"0-50,000", AND('Rent Table'!$I36 > 50000, 'Rent Table'!$I36 <= 150000), "50,001-150,000", AND('Rent Table'!$I36 > 150000, 'Rent Table'!$I36 <= 250000), "150,001-250,000", AND('Rent Table'!$I36 > 250000, 'Rent Table'!$I36 <= 350000), "250,001-350,000", AND('Rent Table'!$I36 > 350000, 'Rent Table'!$I36 <= 450000), "350,001-450,000", AND('Rent Table'!$I36 > 450000, 'Rent Table'!$I36 <= 600000), "450,001-600,000", AND('Rent Table'!$I36 > 600000, 'Rent Table'!$I36 <= 750000), "600,001-750,000",'Rent Table'!$I36 > 750000, "750,000+", TRUE, "Undefined" )} -> 0-50,000
A37: 18600 Crenshaw Boulevard | B37: Torrance | C37: CA | D37: 90504 | E37: Los Angeles | F37: Industrial | G37: 45566 | H37: A++ | I37: 77843 | J37: SF | K37: 16.7513 | L37: 29978 | M37: 120 | N37: - | O37: 4 | P37: 1 | Q37: 1974 | R37: - | S37: {=_xlfn.IFS(AND('Rent Table'!$I37>0,'Rent Table'!$I37<=50000),"0-50,000", AND('Rent Table'!$I37 > 50000, 'Rent Table'!$I37 <= 150000), "50,001-150,000", AND('Rent Table'!$I37 > 150000, 'Rent Table'!$I37 <= 250000), "150,001-250,000", AND('Rent Table'!$I37 > 250000, 'Rent Table'!$I37 <= 350000), "250,001-350,000", AND('Rent Table'!$I37 > 350000, 'Rent Table'!$I37 <= 450000), "350,001-450,000", AND('Rent Table'!$I37 > 450000, 'Rent Table'!$I37 <= 600000), "450,001-600,000", AND('Rent Table'!$I37 > 600000, 'Rent Table'!$I37 <= 750000), "600,001-750,000",'Rent Table'!$I37 > 750000, "750,000+", TRUE, "Undefined" )} -> 50,001-150,000
A38: 19000-19010 South Vermont Avenue | B38: Gardena | C38: CA | D38: 90248 | E38: Los Angeles | F38: Industrial | G38: 45505 | H38: A++ | I38: 45585 | J38: SF | K38: 25.7664 | L38: 20497 | M38: 120 | N38: - | O38: - | P38: 1 | Q38: 1970 | R38: 1982 | S38: {=_xlfn.IFS(AND('Rent Table'!$I38>0,'Rent Table'!$I38<=50000),"0-50,000", AND('Rent Table'!$I38 > 50000, 'Rent Table'!$I38 <= 150000), "50,001-150,000", AND('Rent Table'!$I38 > 150000, 'Rent Table'!$I38 <= 250000), "150,001-250,000", AND('Rent Table'!$I38 > 250000, 'Rent Table'!$I38 <= 350000), "250,001-350,000", AND('Rent Table'!$I38 > 350000, 'Rent Table'!$I38 <= 450000), "350,001-450,000", AND('Rent Table'!$I38 > 450000, 'Rent Table'!$I38 <= 600000), "450,001-600,000", AND('Rent Table'!$I38 > 600000, 'Rent Table'!$I38 <= 750000), "600,001-750,000",'Rent Table'!$I38 > 750000, "750,000+", TRUE, "Undefined" )} -> 0-50,000
A39: 19032 South Vermont Avenue | B39: Gardena | C39: CA | D39: 90248 | E39: Los Angeles | F39: Industrial | G39: 45566 | H39: A++ | I39: 100080 | J39: SF | K39: 11.7541 | L39: 33850 | M39: 24 | N39: - | O39: - | P39: 1 | Q39: 1970 | R39: 1972 | S39: {=_xlfn.IFS(AND('Rent Table'!$I39>0,'Rent Table'!$I39<=50000),"0-50,000", AND('Rent Table'!$I39 > 50000, 'Rent Table'!$I39 <= 150000), "50,001-150,000", AND('Rent Table'!$I39 > 150000, 'Rent Table'!$I39 <= 250000), "150,001-250,000", AND('Rent Table'!$I39 > 250000, 'Rent Table'!$I39 <= 350000), "250,001-350,000", AND('Rent Table'!$I39 > 350000, 'Rent Table'!$I39 <= 450000), "350,001-450,000", AND('Rent Table'!$I39 > 450000, 'Rent Table'!$I39 <= 600000), "450,001-600,000", AND('Rent Table'!$I39 > 600000, 'Rent Table'!$I39 <= 750000), "600,001-750,000",'Rent Table'!$I39 > 750000, "750,000+", TRUE, "Undefined" )} -> 50,001-150,000
A40: 19038 South Vermont Avenue | B40: Gardena | C40: CA | D40: 90248 | E40: Los Angeles | F40: Industrial | G40: 45566 | H40: A++ | I40: 100080 | J40: SF | K40: 22.5784 | L40: 49690 | M40: 120.5 | N40: - | O40: - | P40: 1 | Q40: 1970 | R40: 1972 | S40: {=_xlfn.IFS(AND('Rent Table'!$I40>0,'Rent Table'!$I40<=50000),"0-50,000", AND('Rent Table'!$I40 > 50000, 'Rent Table'!$I40 <= 150000), "50,001-150,000", AND('Rent Table'!$I40 > 150000, 'Rent Table'!$I40 <= 250000), "150,001-250,000", AND('Rent Table'!$I40 > 250000, 'Rent Table'!$I40 <= 350000), "250,001-350,000", AND('Rent Table'!$I40 > 350000, 'Rent Table'!$I40 <= 450000), "350,001-450,000", AND('Rent Table'!$I40 > 450000, 'Rent Table'!$I40 <= 600000), "450,001-600,000", AND('Rent Table'!$I40 > 600000, 'Rent Table'!$I40 <= 750000), "600,001-750,000",'Rent Table'!$I40 > 750000, "750,000+", TRUE, "Undefined" )} -> 50,001-150,000
A41: 19145 Gramercy Place | B41: Torrance | C41: CA | D41: 90501 | E41: Los Angeles | F41: Industrial | G41: 45566 | H41: A++ | I41: 102279 | J41: SF | K41: 22.426 | L41: 102143 | M41: 120 | N41: 10 | O41: 2 | P41: 1 | Q41: 1982 | R41: 1983 | S41: {=_xlfn.IFS(AND('Rent Table'!$I41>0,'Rent Table'!$I41<=50000),"0-50,000", AND('Rent Table'!$I41 > 50000, 'Rent Table'!$I41 <= 150000), "50,001-150,000", AND('Rent Table'!$I41 > 150000, 'Rent Table'!$I41 <= 250000), "150,001-250,000", AND('Rent Table'!$I41 > 250000, 'Rent Table'!$I41 <= 350000), "250,001-350,000", AND('Rent Table'!$I41 > 350000, 'Rent Table'!$I41 <= 450000), "350,001-450,000", AND('Rent Table'!$I41 > 450000, 'Rent Table'!$I41 <= 600000), "450,001-600,000", AND('Rent Table'!$I41 > 600000, 'Rent Table'!$I41 <= 750000), "600,001-750,000",'Rent Table'!$I41 > 750000, "750,000+", TRUE, "Undefined" )} -> 50,001-150,000
A42: 19200-19270 South Western Avenue | B42: Torrance | C42: CA | D42: 90501 | E42: Los Angeles | F42: Industrial | G42: 45566 | H42: A++ | I42: 684900 | J42: SF | K42: 16.1212 | L42: 342450 | M42: 91 | N42: 1 | O42: 2.5 | P42: 1 | Q42: 1998 | R42: - | S42: {=_xlfn.IFS(AND('Rent Table'!$I42>0,'Rent Table'!$I42<=50000),"0-50,000", AND('Rent Table'!$I42 > 50000, 'Rent Table'!$I42 <= 150000), "50,001-150,000", AND('Rent Table'!$I42 > 150000, 'Rent Table'!$I42 <= 250000), "150,001-250,000", AND('Rent Table'!$I42 > 250000, 'Rent Table'!$I42 <= 350000), "250,001-350,000", AND('Rent Table'!$I42 > 350000, 'Rent Table'!$I42 <= 450000), "350,001-450,000", AND('Rent Table'!$I42 > 450000, 'Rent Table'!$I42 <= 600000), "450,001-600,000", AND('Rent Table'!$I42 > 600000, 'Rent Table'!$I42 <= 750000), "600,001-750,000",'Rent Table'!$I42 > 750000, "750,000+", TRUE, "Undefined" )} -> 600,001-750,000
A43: 19301 Prairie Avenue | B43: Torrance | C43: CA | D43: 90503 | E43: Los Angeles | F43: Industrial | G43: 45566 | H43: A++ | I43: 108320 | J43: SF | K43: 25.8251 | L43: 108320 | M43: 89 | N43: 6 | O43: 5 | P43: - | Q43: 2023 | R43: - | S43: {=_xlfn.IFS(AND('Rent Table'!$I43>0,'Rent Table'!$I43<=50000),"0-50,000", AND('Rent Table'!$I43 > 50000, 'Rent Table'!$I43 <= 150000), "50,001-150,000", AND('Rent Table'!$I43 > 150000, 'Rent Table'!$I43 <= 250000), "150,001-250,000", AND('Rent Table'!$I43 > 250000, 'Rent Table'!$I43 <= 350000), "250,001-350,000", AND('Rent Table'!$I43 > 350000, 'Rent Table'!$I43 <= 450000), "350,001-450,000", AND('Rent Table'!$I43 > 450000, 'Rent Table'!$I43 <= 600000), "450,001-600,000", AND('Rent Table'!$I43 > 600000, 'Rent Table'!$I43 <= 750000), "600,001-750,000",'Rent Table'!$I43 > 750000, "750,000+", TRUE, "Undefined" )} -> 50,001-150,000
A44: 19340-19370 Van Ness Avenue | B44: Torrance | C44: CA | D44: 90501 | E44: Los Angeles | F44: Industrial | G44: 45505 | H44: A++ | I44: 43133 | J44: SF | K44: 18.75135 | L44: 24393 | M44: 48 | N44: - | O44: 3.5 | P44: 1 | Q44: 1977 | R44: - | S44: {=_xlfn.IFS(AND('Rent Table'!$I44>0,'Rent Table'!$I44<=50000),"0-50,000", AND('Rent Table'!$I44 > 50000, 'Rent Table'!$I44 <= 150000), "50,001-150,000", AND('Rent Table'!$I44 > 150000, 'Rent Table'!$I44 <= 250000), "150,001-250,000", AND('Rent Table'!$I44 > 250000, 'Rent Table'!$I44 <= 350000), "250,001-350,000", AND('Rent Table'!$I44 > 350000, 'Rent Table'!$I44 <= 450000), "350,001-450,000", AND('Rent Table'!$I44 > 450000, 'Rent Table'!$I44 <= 600000), "450,001-600,000", AND('Rent Table'!$I44 > 600000, 'Rent Table'!$I44 <= 750000), "600,001-750,000",'Rent Table'!$I44 > 750000, "750,000+", TRUE, "Undefined" )} -> 0-50,000
A45: 19400 Harborgate Way | B45: Torrance | C45: CA | D45: 90501 | E45: Los Angeles | F45: Industrial | G45: 45566 | H45: A++ | I45: 860000 | J45: SF | K45: 17.2818 | L45: 127608 | M45: 130 | N45: - | O45: - | P45: - | Q45: 2003 | R45: 2004 | S45: {=_xlfn.IFS(AND('Rent Table'!$I45>0,'Rent Table'!$I45<=50000),"0-50,000", AND('Rent Table'!$I45 > 50000, 'Rent Table'!$I45 <= 150000), "50,001-150,000", AND('Rent Table'!$I45 > 150000, 'Rent Table'!$I45 <= 250000), "150,001-250,000", AND('Rent Table'!$I45 > 250000, 'Rent Table'!$I45 <= 350000), "250,001-350,000", AND('Rent Table'!$I45 > 350000, 'Rent Table'!$I45 <= 450000), "350,001-450,000", AND('Rent Table'!$I45 > 450000, 'Rent Table'!$I45 <= 600000), "450,001-600,000", AND('Rent Table'!$I45 > 600000, 'Rent Table'!$I45 <= 750000), "600,001-750,000",'Rent Table'!$I45 > 750000, "750,000+", TRUE, "Undefined" )} -> 750,000+
A46: 19400 South Western Avenue | B46: Torrance | C46: CA | D46: 90501 | E46: Los Angeles | F46: Industrial | G46: 45566 | H46: A++ | I46: 259327 | J46: SF | K46: 17.7651 | L46: 259327 | M46: 62 | N46: 1.75 | O46: 1 | P46: 1 | Q46: 1998 | R46: - | S46: {=_xlfn.IFS(AND('Rent Table'!$I46>0,'Rent Table'!$I46<=50000),"0-50,000", AND('Rent Table'!$I46 > 50000, 'Rent Table'!$I46 <= 150000), "50,001-150,000", AND('Rent Table'!$I46 > 150000, 'Rent Table'!$I46 <= 250000), "150,001-250,000", AND('Rent Table'!$I46 > 250000, 'Rent Table'!$I46 <= 350000), "250,001-350,000", AND('Rent Table'!$I46 > 350000, 'Rent Table'!$I46 <= 450000), "350,001-450,000", AND('Rent Table'!$I46 > 450000, 'Rent Table'!$I46 <= 600000), "450,001-600,000", AND('Rent Table'!$I46 > 600000, 'Rent Table'!$I46 <= 750000), "600,001-750,000",'Rent Table'!$I46 > 750000, "750,000+", TRUE, "Undefined" )} -> 250,001-350,000
A47: 19500-19600 South Vermont Avenue | B47: Torrance | C47: CA | D47: 90502 | E47: Los Angeles | F47: Industrial | G47: 45566 | H47: A++ | I47: 208896 | J47: SF | K47: 20.37695 | L47: 101767 | M47: 69 | N47: 2 | O47: 3 | P47: 1 | Q47: 1980 | R47: - | S47: {=_xlfn.IFS(AND('Rent Table'!$I47>0,'Rent Table'!$I47<=50000),"0-50,000", AND('Rent Table'!$I47 > 50000, 'Rent Table'!$I47 <= 150000), "50,001-150,000", AND('Rent Table'!$I47 > 150000, 'Rent Table'!$I47 <= 250000), "150,001-250,000", AND('Rent Table'!$I47 > 250000, 'Rent Table'!$I47 <= 350000), "250,001-350,000", AND('Rent Table'!$I47 > 350000, 'Rent Table'!$I47 <= 450000), "350,001-450,000", AND('Rent Table'!$I47 > 450000, 'Rent Table'!$I47 <= 600000), "450,001-600,000", AND('Rent Table'!$I47 > 600000, 'Rent Table'!$I47 <= 750000), "600,001-750,000",'Rent Table'!$I47 > 750000, "750,000+", TRUE, "Undefined" )} -> 150,001-250,000
A48: 19600 South Western Avenue | B48: Torrance | C48: CA | D48: 90501 | E48: Los Angeles | F48: Industrial | G48: 45566 | H48: A++ | I48: 314559 | J48: SF | K48: 17.5816 | L48: 314559 | M48: 95.5 | N48: 3.25 | O48: 2 | P48: 1 | Q48: 1998 | R48: - | S48: {=_xlfn.IFS(AND('Rent Table'!$I48>0,'Rent Table'!$I48<=50000),"0-50,000", AND('Rent Table'!$I48 > 50000, 'Rent Table'!$I48 <= 150000), "50,001-150,000", AND('Rent Table'!$I48 > 150000, 'Rent Table'!$I48 <= 250000), "150,001-250,000", AND('Rent Table'!$I48 > 250000, 'Rent Table'!$I48 <= 350000), "250,001-350,000", AND('Rent Table'!$I48 > 350000, 'Rent Table'!$I48 <= 450000), "350,001-450,000", AND('Rent Table'!$I48 > 450000, 'Rent Table'!$I48 <= 600000), "450,001-600,000", AND('Rent Table'!$I48 > 600000, 'Rent Table'!$I48 <= 750000), "600,001-750,000",'Rent Table'!$I48 > 750000, "750,000+", TRUE, "Undefined" )} -> 250,001-350,000
A49: 19600-19688 Van Ness Avenue | B49: Torrance | C49: CA | D49: 90501 | E49: Los Angeles | F49: Industrial | G49: 45566 | H49: A++ | I49: 177372 | J49: SF | K49: 19.51805 | L49: 88660 | M49: 96.5 | N49: - | O49: 2 | P49: 1 | Q49: 2001 | R49: - | S49: {=_xlfn.IFS(AND('Rent Table'!$I49>0,'Rent Table'!$I49<=50000),"0-50,000", AND('Rent Table'!$I49 > 50000, 'Rent Table'!$I49 <= 150000), "50,001-150,000", AND('Rent Table'!$I49 > 150000, 'Rent Table'!$I49 <= 250000), "150,001-250,000", AND('Rent Table'!$I49 > 250000, 'Rent Table'!$I49 <= 350000), "250,001-350,000", AND('Rent Table'!$I49 > 350000, 'Rent Table'!$I49 <= 450000), "350,001-450,000", AND('Rent Table'!$I49 > 450000, 'Rent Table'!$I49 <= 600000), "450,001-600,000", AND('Rent Table'!$I49 > 600000, 'Rent Table'!$I49 <= 750000), "600,001-750,000",'Rent Table'!$I49 > 750000, "750,000+", TRUE, "Undefined" )} -> 150,001-250,000
A50: 19601 Hamilton Avenue | B50: Torrance | C50: CA | D50: 90502 | E50: Los Angeles | F50: Industrial | G50: 45566 | H50: A++ | I50: 72808 | J50: SF | K50: 17.342 | L50: 72808 | M50: 61 | N50: 6.5 | O50: 1 | P50: 2 | Q50: 1985 | R50: 2005 | S50: {=_xlfn.IFS(AND('Rent Table'!$I50>0,'Rent Table'!$I50<=50000),"0-50,000", AND('Rent Table'!$I50 > 50000, 'Rent Table'!$I50 <= 150000), "50,001-150,000", AND('Rent Table'!$I50 > 150000, 'Rent Table'!$I50 <= 250000), "150,001-250,000", AND('Rent Table'!$I50 > 250000, 'Rent Table'!$I50 <= 350000), "250,001-350,000", AND('Rent Table'!$I50 > 350000, 'Rent Table'!$I50 <= 450000), "350,001-450,000", AND('Rent Table'!$I50 > 450000, 'Rent Table'!$I50 <= 600000), "450,001-600,000", AND('Rent Table'!$I50 > 600000, 'Rent Table'!$I50 <= 750000), "600,001-750,000",'Rent Table'!$I50 > 750000, "750,000+", TRUE, "Undefined" )} -> 50,001-150,000
A51: 19681 Pacific Gateway Drive | B51: Torrance | C51: CA | D51: 90502 | E51: Los Angeles | F51: Industrial | G51: 45566 | H51: A++ | I51: 251606 | J51: SF | K51: 18.353 | L51: 251606 | M51: 124 | N51: 10 | O51: 4 | P51: 1 | Q51: 2021 | R51: - | S51: {=_xlfn.IFS(AND('Rent Table'!$I51>0,'Rent Table'!$I51<=50000),"0-50,000", AND('Rent Table'!$I51 > 50000, 'Rent Table'!$I51 <= 150000), "50,001-150,000", AND('Rent Table'!$I51 > 150000, 'Rent Table'!$I51 <= 250000), "150,001-250,000", AND('Rent Table'!$I51 > 250000, 'Rent Table'!$I51 <= 350000), "250,001-350,000", AND('Rent Table'!$I51 > 350000, 'Rent Table'!$I51 <= 450000), "350,001-450,000", AND('Rent Table'!$I51 > 450000, 'Rent Table'!$I51 <= 600000), "450,001-600,000", AND('Rent Table'!$I51 > 600000, 'Rent Table'!$I51 <= 750000), "600,001-750,000",'Rent Table'!$I51 > 750000, "750,000+", TRUE, "Undefined" )} -> 250,001-350,000
A52: 1603 East Steel Road | B52: Colton | C52: CA | D52: 92324 | E52: Inland Empire | F52: Industrial | G52: 45566 | H52: A- | I52: 331000 | J52: SF | K52: 10.2039 | L52: 169143 | M52: 60 | N52: 0.59 | O52: 1 | P52: 2 | Q52: 2014 | R52: 2015 | S52: {=_xlfn.IFS(AND('Rent Table'!$I52>0,'Rent Table'!$I52<=50000),"0-50,000", AND('Rent Table'!$I52 > 50000, 'Rent Table'!$I52 <= 150000), "50,001-150,000", AND('Rent Table'!$I52 > 150000, 'Rent Table'!$I52 <= 250000), "150,001-250,000", AND('Rent Table'!$I52 > 250000, 'Rent Table'!$I52 <= 350000), "250,001-350,000", AND('Rent Table'!$I52 > 350000, 'Rent Table'!$I52 <= 450000), "350,001-450,000", AND('Rent Table'!$I52 > 450000, 'Rent Table'!$I52 <= 600000), "450,001-600,000", AND('Rent Table'!$I52 > 600000, 'Rent Table'!$I52 <= 750000), "600,001-750,000",'Rent Table'!$I52 > 750000, "750,000+", TRUE, "Undefined" )} -> 250,001-350,000
A53: 1861 Mountain View Avenue | B53: Loma Linda | C53: CA | D53: 92354 | E53: Inland Empire | F53: Industrial | G53: 45566 | H53: A- | I53: 114057 | J53: SF | K53: 14.1289 | L53: 114057 | M53: 62 | N53: 2 | O53: 2 | P53: 1 | Q53: 2022 | R53: 2023 | S53: {=_xlfn.IFS(AND('Rent Table'!$I53>0,'Rent Table'!$I53<=50000),"0-50,000", AND('Rent Table'!$I53 > 50000, 'Rent Table'!$I53 <= 150000), "50,001-150,000", AND('Rent Table'!$I53 > 150000, 'Rent Table'!$I53 <= 250000), "150,001-250,000", AND('Rent Table'!$I53 > 250000, 'Rent Table'!$I53 <= 350000), "250,001-350,000", AND('Rent Table'!$I53 > 350000, 'Rent Table'!$I53 <= 450000), "350,001-450,000", AND('Rent Table'!$I53 > 450000, 'Rent Table'!$I53 <= 600000), "450,001-600,000", AND('Rent Table'!$I53 > 600000, 'Rent Table'!$I53 <= 750000), "600,001-750,000",'Rent Table'!$I53 > 750000, "750,000+", TRUE, "Undefined" )} -> 50,001-150,000
A54: 1865 Mountain View Avenue | B54: Loma Linda | C54: CA | D54: 92354 | E54: Inland Empire | F54: Industrial | G54: 45566 | H54: A- | I54: 304262 | J54: SF | K54: 13.7359 | L54: 304262 | M54: 123 | N54: 6 | O54: 3 | P54: 1 | Q54: 2022 | R54: 2023 | S54: {=_xlfn.IFS(AND('Rent Table'!$I54>0,'Rent Table'!$I54<=50000),"0-50,000", AND('Rent Table'!$I54 > 50000, 'Rent Table'!$I54 <= 150000), "50,001-150,000", AND('Rent Table'!$I54 > 150000, 'Rent Table'!$I54 <= 250000), "150,001-250,000", AND('Rent Table'!$I54 > 250000, 'Rent Table'!$I54 <= 350000), "250,001-350,000", AND('Rent Table'!$I54 > 350000, 'Rent Table'!$I54 <= 450000), "350,001-450,000", AND('Rent Table'!$I54 > 450000, 'Rent Table'!$I54 <= 600000), "450,001-600,000", AND('Rent Table'!$I54 > 600000, 'Rent Table'!$I54 <= 750000), "600,001-750,000",'Rent Table'!$I54 > 750000, "750,000+", TRUE, "Undefined" )} -> 250,001-350,000
A55: 25525 Redlands Boulevard | B55: Loma Linda | C55: CA | D55: 92354 | E55: Inland Empire | F55: Industrial | G55: 45566 | H55: A- | I55: 80000 | J55: SF | K55: 13.0548 | L55: 80000 | M55: 122 | N55: - | O55: 2 | P55: - | Q55: 1944 | R55: - | S55: {=_xlfn.IFS(AND('Rent Table'!$I55>0,'Rent Table'!$I55<=50000),"0-50,000", AND('Rent Table'!$I55 > 50000, 'Rent Table'!$I55 <= 150000), "50,001-150,000", AND('Rent Table'!$I55 > 150000, 'Rent Table'!$I55 <= 250000), "150,001-250,000", AND('Rent Table'!$I55 > 250000, 'Rent Table'!$I55 <= 350000), "250,001-350,000", AND('Rent Table'!$I55 > 350000, 'Rent Table'!$I55 <= 450000), "350,001-450,000", AND('Rent Table'!$I55 > 450000, 'Rent Table'!$I55 <= 600000), "450,001-600,000", AND('Rent Table'!$I55 > 600000, 'Rent Table'!$I55 <= 750000), "600,001-750,000",'Rent Table'!$I55 > 750000, "750,000+", TRUE, "Undefined" )} -> 50,001-150,000
A56: 10421 Corporate Drive | B56: Redlands | C56: CA | D56: 92374 | E56: Inland Empire | F56: Industrial | G56: 45566 | H56: A- | I56: 23120 | J56: SF | K56: 9.07241 | L56: 23120 | M56: 72 | N56: - | O56: 2 | P56: - | Q56: 1987 | R56: - | S56: {=_xlfn.IFS(AND('Rent Table'!$I56>0,'Rent Table'!$I56<=50000),"0-50,000", AND('Rent Table'!$I56 > 50000, 'Rent Table'!$I56 <= 150000), "50,001-150,000", AND('Rent Table'!$I56 > 150000, 'Rent Table'!$I56 <= 250000), "150,001-250,000", AND('Rent Table'!$I56 > 250000, 'Rent Table'!$I56 <= 350000), "250,001-350,000", AND('Rent Table'!$I56 > 350000, 'Rent Table'!$I56 <= 450000), "350,001-450,000", AND('Rent Table'!$I56 > 450000, 'Rent Table'!$I56 <= 600000), "450,001-600,000", AND('Rent Table'!$I56 > 600000, 'Rent Table'!$I56 <= 750000), "600,001-750,000",'Rent Table'!$I56 > 750000, "750,000+", TRUE, "Undefined" )} -> 0-50,000
A57: 10446 Enterprise Drive | B57: Redlands | C57: CA | D57: 92374 | E57: Inland Empire | F57: Industrial | G57: 45566 | H57: A- | I57: 9670 | J57: SF | K57: 9.85711 | L57: 9670 | M57: 36 | N57: - | O57: 1 | P57: 1 | Q57: 1991 | R57: - | S57: {=_xlfn.IFS(AND('Rent Table'!$I57>0,'Rent Table'!$I57<=50000),"0-50,000", AND('Rent Table'!$I57 > 50000, 'Rent Table'!$I57 <= 150000), "50,001-150,000", AND('Rent Table'!$I57 > 150000, 'Rent Table'!$I57 <= 250000), "150,001-250,000", AND('Rent Table'!$I57 > 250000, 'Rent Table'!$I57 <= 350000), "250,001-350,000", AND('Rent Table'!$I57 > 350000, 'Rent Table'!$I57 <= 450000), "350,001-450,000", AND('Rent Table'!$I57 > 450000, 'Rent Table'!$I57 <= 600000), "450,001-600,000", AND('Rent Table'!$I57 > 600000, 'Rent Table'!$I57 <= 750000), "600,001-750,000",'Rent Table'!$I57 > 750000, "750,000+", TRUE, "Undefined" )} -> 0-50,000
A58: 1115 Research Drive | B58: Redlands | C58: CA | D58: 92374 | E58: Inland Empire | F58: Industrial | G58: 45566 | H58: A- | I58: 31000 | J58: SF | K58: 12.7346 | L58: 8946 | M58: 64 | N58: - | O58: - | P58: 1 | Q58: 1991 | R58: - | S58: {=_xlfn.IFS(AND('Rent Table'!$I58>0,'Rent Table'!$I58<=50000),"0-50,000", AND('Rent Table'!$I58 > 50000, 'Rent Table'!$I58 <= 150000), "50,001-150,000", AND('Rent Table'!$I58 > 150000, 'Rent Table'!$I58 <= 250000), "150,001-250,000", AND('Rent Table'!$I58 > 250000, 'Rent Table'!$I58 <= 350000), "250,001-350,000", AND('Rent Table'!$I58 > 350000, 'Rent Table'!$I58 <= 450000), "350,001-450,000", AND('Rent Table'!$I58 > 450000, 'Rent Table'!$I58 <= 600000), "450,001-600,000", AND('Rent Table'!$I58 > 600000, 'Rent Table'!$I58 <= 750000), "600,001-750,000",'Rent Table'!$I58 > 750000, "750,000+", TRUE, "Undefined" )} -> 0-50,000
A59: 1125 Research Drive | B59: Redlands | C59: CA | D59: 92374 | E59: Inland Empire | F59: Industrial | G59: 45566 | H59: A- | I59: 32135 | J59: SF | K59: 12.3047 | L59: 15643 | M59: 63 | N59: - | O59: 3 | P59: 1 | Q59: 1991 | R59: - | S59: {=_xlfn.IFS(AND('Rent Table'!$I59>0,'Rent Table'!$I59<=50000),"0-50,000", AND('Rent Table'!$I59 > 50000, 'Rent Table'!$I59 <= 150000), "50,001-150,000", AND('Rent Table'!$I59 > 150000, 'Rent Table'!$I59 <= 250000), "150,001-250,000", AND('Rent Table'!$I59 > 250000, 'Rent Table'!$I59 <= 350000), "250,001-350,000", AND('Rent Table'!$I59 > 350000, 'Rent Table'!$I59 <= 450000), "350,001-450,000", AND('Rent Table'!$I59 > 450000, 'Rent Table'!$I59 <= 600000), "450,001-600,000", AND('Rent Table'!$I59 > 600000, 'Rent Table'!$I59 <= 750000), "600,001-750,000",'Rent Table'!$I59 > 750000, "750,000+", TRUE, "Undefined" )} -> 0-50,000
A60: 1235 Indiana Court | B60: Redlands | C60: CA | D60: 92374 | E60: Inland Empire | F60: Industrial | G60: 45566 | H60: A- | I60: 27516 | J60: SF | K60: 20.4175 | L60: 1207 | M60: 60 | N60: - | O60: - | P60: - | Q60: 1990 | R60: - | S60: {=_xlfn.IFS(AND('Rent Table'!$I60>0,'Rent Table'!$I60<=50000),"0-50,000", AND('Rent Table'!$I60 > 50000, 'Rent Table'!$I60 <= 150000), "50,001-150,000", AND('Rent Table'!$I60 > 150000, 'Rent Table'!$I60 <= 250000), "150,001-250,000", AND('Rent Table'!$I60 > 250000, 'Rent Table'!$I60 <= 350000), "250,001-350,000", AND('Rent Table'!$I60 > 350000, 'Rent Table'!$I60 <= 450000), "350,001-450,000", AND('Rent Table'!$I60 > 450000, 'Rent Table'!$I60 <= 600000), "450,001-600,000", AND('Rent Table'!$I60 > 600000, 'Rent Table'!$I60 <= 750000), "600,001-750,000",'Rent Table'!$I60 > 750000, "750,000+", TRUE, "Undefined" )} -> 0-50,000
A61: 1419 West State Street | B61: Redlands | C61: CA | D61: 92373 | E61: Inland Empire | F61: Industrial | G61: 45566 | H61: A- | I61: 17659 | J61: SF | K61: 10.5063 | L61: 17659 | M61: 62 | N61: - | O61: 2 | P61: 1 | Q61: 1987 | R61: 1988 | S61: {=_xlfn.IFS(AND('Rent Table'!$I61>0,'Rent Table'!$I61<=50000),"0-50,000", AND('Rent Table'!$I61 > 50000, 'Rent Table'!$I61 <= 150000), "50,001-150,000", AND('Rent Table'!$I61 > 150000, 'Rent Table'!$I61 <= 250000), "150,001-250,000", AND('Rent Table'!$I61 > 250000, 'Rent Table'!$I61 <= 350000), "250,001-350,000", AND('Rent Table'!$I61 > 350000, 'Rent Table'!$I61 <= 450000), "350,001-450,000", AND('Rent Table'!$I61 > 450000, 'Rent Table'!$I61 <= 600000), "450,001-600,000", AND('Rent Table'!$I61 > 600000, 'Rent Table'!$I61 <= 750000), "600,001-750,000",'Rent Table'!$I61 > 750000, "750,000+", TRUE, "Undefined" )} -> 0-50,000
A62: 1645 West Park Avenue | B62: Redlands | C62: CA | D62: 92373 | E62: Inland Empire | F62: Industrial | G62: 45566 | H62: A- | I62: 40800 | J62: SF | K62: 12.3778 | L62: 20400 | M62: 61 | N62: - | O62: - | P62: 1 | Q62: 2017 | R62: - | S62: {=_xlfn.IFS(AND('Rent Table'!$I62>0,'Rent Table'!$I62<=50000),"0-50,000", AND('Rent Table'!$I62 > 50000, 'Rent Table'!$I62 <= 150000), "50,001-150,000", AND('Rent Table'!$I62 > 150000, 'Rent Table'!$I62 <= 250000), "150,001-250,000", AND('Rent Table'!$I62 > 250000, 'Rent Table'!$I62 <= 350000), "250,001-350,000", AND('Rent Table'!$I62 > 350000, 'Rent Table'!$I62 <= 450000), "350,001-450,000", AND('Rent Table'!$I62 > 450000, 'Rent Table'!$I62 <= 600000), "450,001-600,000", AND('Rent Table'!$I62 > 600000, 'Rent Table'!$I62 <= 750000), "600,001-750,000",'Rent Table'!$I62 > 750000, "750,000+", TRUE, "Undefined" )} -> 0-50,000
A63: 1670 West Park Avenue | B63: Redlands | C63: CA | D63: 92373 | E63: Inland Empire | F63: Industrial | G63: 45566 | H63: A- | I63: 29000 | J63: SF | K63: 13.4695 | L63: 29000 | M63: 48 | N63: - | O63: - | P63: - | Q63: 2017 | R63: 2018 | S63: {=_xlfn.IFS(AND('Rent Table'!$I63>0,'Rent Table'!$I63<=50000),"0-50,000", AND('Rent Table'!$I63 > 50000, 'Rent Table'!$I63 <= 150000), "50,001-150,000", AND('Rent Table'!$I63 > 150000, 'Rent Table'!$I63 <= 250000), "150,001-250,000", AND('Rent Table'!$I63 > 250000, 'Rent Table'!$I63 <= 350000), "250,001-350,000", AND('Rent Table'!$I63 > 350000, 'Rent Table'!$I63 <= 450000), "350,001-450,000", AND('Rent Table'!$I63 > 450000, 'Rent Table'!$I63 <= 600000), "450,001-600,000", AND('Rent Table'!$I63 > 600000, 'Rent Table'!$I63 <= 750000), "600,001-750,000",'Rent Table'!$I63 > 750000, "750,000+", TRUE, "Undefined" )} -> 0-50,000
A64: 1939 West Park Avenue | B64: Redlands | C64: CA | D64: 92373 | E64: Inland Empire | F64: Industrial | G64: 45566 | H64: A- | I64: 21612 | J64: SF | K64: 11.7579 | L64: 21612 | M64: 48 | N64: - | O64: - | P64: 1 | Q64: 2007 | R64: - | S64: {=_xlfn.IFS(AND('Rent Table'!$I64>0,'Rent Table'!$I64<=50000),"0-50,000", AND('Rent Table'!$I64 > 50000, 'Rent Table'!$I64 <= 150000), "50,001-150,000", AND('Rent Table'!$I64 > 150000, 'Rent Table'!$I64 <= 250000), "150,001-250,000", AND('Rent Table'!$I64 > 250000, 'Rent Table'!$I64 <= 350000), "250,001-350,000", AND('Rent Table'!$I64 > 350000, 'Rent Table'!$I64 <= 450000), "350,001-450,000", AND('Rent Table'!$I64 > 450000, 'Rent Table'!$I64 <= 600000), "450,001-600,000", AND('Rent Table'!$I64 > 600000, 'Rent Table'!$I64 <= 750000), "600,001-750,000",'Rent Table'!$I64 > 750000, "750,000+", TRUE, "Undefined" )} -> 0-50,000
A65: 1941 West Park Avenue | B65: Redlands | C65: CA | D65: 92373 | E65: Inland Empire | F65: Industrial | G65: 45566 | H65: A- | I65: 19370 | J65: SF | K65: 14.149 | L65: 19370 | M65: 61 | N65: 1.17 | O65: 1 | P65: 1 | Q65: 2023 | R65: - | S65: {=_xlfn.IFS(AND('Rent Table'!$I65>0,'Rent Table'!$I65<=50000),"0-50,000", AND('Rent Table'!$I65 > 50000, 'Rent Table'!$I65 <= 150000), "50,001-150,000", AND('Rent Table'!$I65 > 150000, 'Rent Table'!$I65 <= 250000), "150,001-250,000", AND('Rent Table'!$I65 > 250000, 'Rent Table'!$I65 <= 350000), "250,001-350,000", AND('Rent Table'!$I65 > 350000, 'Rent Table'!$I65 <= 450000), "350,001-450,000", AND('Rent Table'!$I65 > 450000, 'Rent Table'!$I65 <= 600000), "450,001-600,000", AND('Rent Table'!$I65 > 600000, 'Rent Table'!$I65 <= 750000), "600,001-750,000",'Rent Table'!$I65 > 750000, "750,000+", TRUE, "Undefined" )} -> 0-50,000
A66: 1972 Essex Court | B66: Redlands | C66: CA | D66: 92373 | E66: Inland Empire | F66: Industrial | G66: 45566 | H66: A- | I66: 15636 | J66: SF | K66: 12.5485 | L66: 15636 | M66: 60 | N66: - | O66: - | P66: 1 | Q66: 2002 | R66: - | S66: {=_xlfn.IFS(AND('Rent Table'!$I66>0,'Rent Table'!$I66<=50000),"0-50,000", AND('Rent Table'!$I66 > 50000, 'Rent Table'!$I66 <= 150000), "50,001-150,000", AND('Rent Table'!$I66 > 150000, 'Rent Table'!$I66 <= 250000), "150,001-250,000", AND('Rent Table'!$I66 > 250000, 'Rent Table'!$I66 <= 350000), "250,001-350,000", AND('Rent Table'!$I66 > 350000, 'Rent Table'!$I66 <= 450000), "350,001-450,000", AND('Rent Table'!$I66 > 450000, 'Rent Table'!$I66 <= 600000), "450,001-600,000", AND('Rent Table'!$I66 > 600000, 'Rent Table'!$I66 <= 750000), "600,001-750,000",'Rent Table'!$I66 > 750000, "750,000+", TRUE, "Undefined" )} -> 0-50,000
A67: 2351 West Lugonia Avenue | B67: Redlands | C67: CA | D67: 92374 | E67: Inland Empire | F67: Industrial | G67: 45566 | H67: A- | I67: 28681 | J67: SF | K67: 9.65636 | L67: 28181 | M67: 45 | N67: - | O67: - | P67: 1 | Q67: 2003 | R67: - | S67: {=_xlfn.IFS(AND('Rent Table'!$I67>0,'Rent Table'!$I67<=50000),"0-50,000", AND('Rent Table'!$I67 > 50000, 'Rent Table'!$I67 <= 150000), "50,001-150,000", AND('Rent Table'!$I67 > 150000, 'Rent Table'!$I67 <= 250000), "150,001-250,000", AND('Rent Table'!$I67 > 250000, 'Rent Table'!$I67 <= 350000), "250,001-350,000", AND('Rent Table'!$I67 > 350000, 'Rent Table'!$I67 <= 450000), "350,001-450,000", AND('Rent Table'!$I67 > 450000, 'Rent Table'!$I67 <= 600000), "450,001-600,000", AND('Rent Table'!$I67 > 600000, 'Rent Table'!$I67 <= 750000), "600,001-750,000",'Rent Table'!$I67 > 750000, "750,000+", TRUE, "Undefined" )} -> 0-50,000
A68: 1251 Research Drive | B68: Redlands | C68: CA | D68: 92374 | E68: Inland Empire | F68: Industrial | G68: 45566 | H68: A- | I68: 118000 | J68: SF | K68: 9.983765 | L68: 70318 | M68: 92.5 | N68: 1 | O68: 2.5 | P68: 1 | Q68: 1990 | R68: - | S68: {=_xlfn.IFS(AND('Rent Table'!$I68>0,'Rent Table'!$I68<=50000),"0-50,000", AND('Rent Table'!$I68 > 50000, 'Rent Table'!$I68 <= 150000), "50,001-150,000", AND('Rent Table'!$I68 > 150000, 'Rent Table'!$I68 <= 250000), "150,001-250,000", AND('Rent Table'!$I68 > 250000, 'Rent Table'!$I68 <= 350000), "250,001-350,000", AND('Rent Table'!$I68 > 350000, 'Rent Table'!$I68 <= 450000), "350,001-450,000", AND('Rent Table'!$I68 > 450000, 'Rent Table'!$I68 <= 600000), "450,001-600,000", AND('Rent Table'!$I68 > 600000, 'Rent Table'!$I68 <= 750000), "600,001-750,000",'Rent Table'!$I68 > 750000, "750,000+", TRUE, "Undefined" )} -> 50,001-150,000
A69: 1455 Research Drive | B69: Redlands | C69: CA | D69: 92374 | E69: Inland Empire | F69: Industrial | G69: 45566 | H69: A- | I69: 147677 | J69: SF | K69: 14.7399 | L69: 73838 | M69: 62 | N69: - | O69: 2 | P69: 1 | Q69: 2006 | R69: - | S69: {=_xlfn.IFS(AND('Rent Table'!$I69>0,'Rent Table'!$I69<=50000),"0-50,000", AND('Rent Table'!$I69 > 50000, 'Rent Table'!$I69 <= 150000), "50,001-150,000", AND('Rent Table'!$I69 > 150000, 'Rent Table'!$I69 <= 250000), "150,001-250,000", AND('Rent Table'!$I69 > 250000, 'Rent Table'!$I69 <= 350000), "250,001-350,000", AND('Rent Table'!$I69 > 350000, 'Rent Table'!$I69 <= 450000), "350,001-450,000", AND('Rent Table'!$I69 > 450000, 'Rent Table'!$I69 <= 600000), "450,001-600,000", AND('Rent Table'!$I69 > 600000, 'Rent Table'!$I69 <= 750000), "600,001-750,000",'Rent Table'!$I69 > 750000, "750,000+", TRUE, "Undefined" )} -> 50,001-150,000
A70: 2456 West Lugonia Avenue | B70: Redlands | C70: CA | D70: 92374 | E70: Inland Empire | F70: Industrial | G70: 45566 | H70: A- | I70: 128141 | J70: SF | K70: 9.0859 | L70: 128141 | M70: 123 | N70: - | O70: 3 | P70: 1 | Q70: 2008 | R70: - | S70: {=_xlfn.IFS(AND('Rent Table'!$I70>0,'Rent Table'!$I70<=50000),"0-50,000", AND('Rent Table'!$I70 > 50000, 'Rent Table'!$I70 <= 150000), "50,001-150,000", AND('Rent Table'!$I70 > 150000, 'Rent Table'!$I70 <= 250000), "150,001-250,000", AND('Rent Table'!$I70 > 250000, 'Rent Table'!$I70 <= 350000), "250,001-350,000", AND('Rent Table'!$I70 > 350000, 'Rent Table'!$I70 <= 450000), "350,001-450,000", AND('Rent Table'!$I70 > 450000, 'Rent Table'!$I70 <= 600000), "450,001-600,000", AND('Rent Table'!$I70 > 600000, 'Rent Table'!$I70 <= 750000), "600,001-750,000",'Rent Table'!$I70 > 750000, "750,000+", TRUE, "Undefined" )} -> 50,001-150,000
A71: 2459 Almond Avenue | B71: Redlands | C71: CA | D71: 92374 | E71: Inland Empire | F71: Industrial | G71: 45566 | H71: A- | I71: 149275 | J71: SF | K71: 9.89598 | L71: 149275 | M71: 62 | N71: 1 | O71: 2 | P71: 2 | Q71: 2008 | R71: - | S71: {=_xlfn.IFS(AND('Rent Table'!$I71>0,'Rent Table'!$I71<=50000),"0-50,000", AND('Rent Table'!$I71 > 50000, 'Rent Table'!$I71 <= 150000), "50,001-150,000", AND('Rent Table'!$I71 > 150000, 'Rent Table'!$I71 <= 250000), "150,001-250,000", AND('Rent Table'!$I71 > 250000, 'Rent Table'!$I71 <= 350000), "250,001-350,000", AND('Rent Table'!$I71 > 350000, 'Rent Table'!$I71 <= 450000), "350,001-450,000", AND('Rent Table'!$I71 > 450000, 'Rent Table'!$I71 <= 600000), "450,001-600,000", AND('Rent Table'!$I71 > 600000, 'Rent Table'!$I71 <= 750000), "600,001-750,000",'Rent Table'!$I71 > 750000, "750,000+", TRUE, "Undefined" )} -> 50,001-150,000
A72: 2470 West Lugonia Avenue | B72: Redlands | C72: CA | D72: 92374 | E72: Inland Empire | F72: Industrial | G72: 45566 | H72: A- | I72: 104072 | J72: SF | K72: 14.5142 | L72: 104072 | M72: 61 | N72: - | O72: 1 | P72: 1 | Q72: 2008 | R72: - | S72: {=_xlfn.IFS(AND('Rent Table'!$I72>0,'Rent Table'!$I72<=50000),"0-50,000", AND('Rent Table'!$I72 > 50000, 'Rent Table'!$I72 <= 150000), "50,001-150,000", AND('Rent Table'!$I72 > 150000, 'Rent Table'!$I72 <= 250000), "150,001-250,000", AND('Rent Table'!$I72 > 250000, 'Rent Table'!$I72 <= 350000), "250,001-350,000", AND('Rent Table'!$I72 > 350000, 'Rent Table'!$I72 <= 450000), "350,001-450,000", AND('Rent Table'!$I72 > 450000, 'Rent Table'!$I72 <= 600000), "450,001-600,000", AND('Rent Table'!$I72 > 600000, 'Rent Table'!$I72 <= 750000), "600,001-750,000",'Rent Table'!$I72 > 750000, "750,000+", TRUE, "Undefined" )} -> 50,001-150,000
A73: 10843 New Jersey Street | B73: Redlands | C73: CA | D73: 92373 | E73: Inland Empire | F73: Industrial | G73: 45566 | H73: A- | I73: 179400 | J73: SF | K73: 14.9824 | L73: 179400 | M73: 86 | N73: 12 | O73: 2 | P73: - | Q73: 2022 | R73: - | S73: {=_xlfn.IFS(AND('Rent Table'!$I73>0,'Rent Table'!$I73<=50000),"0-50,000", AND('Rent Table'!$I73 > 50000, 'Rent Table'!$I73 <= 150000), "50,001-150,000", AND('Rent Table'!$I73 > 150000, 'Rent Table'!$I73 <= 250000), "150,001-250,000", AND('Rent Table'!$I73 > 250000, 'Rent Table'!$I73 <= 350000), "250,001-350,000", AND('Rent Table'!$I73 > 350000, 'Rent Table'!$I73 <= 450000), "350,001-450,000", AND('Rent Table'!$I73 > 450000, 'Rent Table'!$I73 <= 600000), "450,001-600,000", AND('Rent Table'!$I73 > 600000, 'Rent Table'!$I73 <= 750000), "600,001-750,000",'Rent Table'!$I73 > 750000, "750,000+", TRUE, "Undefined" )} -> 150,001-250,000
A74: 1675 West Park Avenue | B74: Redlands | C74: CA | D74: 92373 | E74: Inland Empire | F74: Industrial | G74: 45566 | H74: A- | I74: 156694 | J74: SF | K74: 9.18398 | L74: 156694 | M74: 88 | N74: 6.75 | O74: 4 | P74: 1 | Q74: 2019 | R74: - | S74: {=_xlfn.IFS(AND('Rent Table'!$I74>0,'Rent Table'!$I74<=50000),"0-50,000", AND('Rent Table'!$I74 > 50000, 'Rent Table'!$I74 <= 150000), "50,001-150,000", AND('Rent Table'!$I74 > 150000, 'Rent Table'!$I74 <= 250000), "150,001-250,000", AND('Rent Table'!$I74 > 250000, 'Rent Table'!$I74 <= 350000), "250,001-350,000", AND('Rent Table'!$I74 > 350000, 'Rent Table'!$I74 <= 450000), "350,001-450,000", AND('Rent Table'!$I74 > 450000, 'Rent Table'!$I74 <= 600000), "450,001-600,000", AND('Rent Table'!$I74 > 600000, 'Rent Table'!$I74 <= 750000), "600,001-750,000",'Rent Table'!$I74 > 750000, "750,000+", TRUE, "Undefined" )} -> 150,001-250,000
A75: 1300 California Street | B75: Redlands | C75: CA | D75: 92374 | E75: Inland Empire | F75: Industrial | G75: 45566 | H75: A- | I75: 771839 | J75: SF | K75: 6.89242 | L75: 771839 | M75: 84 | N75: 4 | O75: 7.25 | P75: 1 | Q75: 2015 | R75: - | S75: {=_xlfn.IFS(AND('Rent Table'!$I75>0,'Rent Table'!$I75<=50000),"0-50,000", AND('Rent Table'!$I75 > 50000, 'Rent Table'!$I75 <= 150000), "50,001-150,000", AND('Rent Table'!$I75 > 150000, 'Rent Table'!$I75 <= 250000), "150,001-250,000", AND('Rent Table'!$I75 > 250000, 'Rent Table'!$I75 <= 350000), "250,001-350,000", AND('Rent Table'!$I75 > 350000, 'Rent Table'!$I75 <= 450000), "350,001-450,000", AND('Rent Table'!$I75 > 450000, 'Rent Table'!$I75 <= 600000), "450,001-600,000", AND('Rent Table'!$I75 > 600000, 'Rent Table'!$I75 <= 750000), "600,001-750,000",'Rent Table'!$I75 > 750000, "750,000+", TRUE, "Undefined" )} -> 750,000+
A76: 1730 Marigold Avenue | B76: Redlands | C76: CA | D76: 92374 | E76: Inland Empire | F76: Industrial | G76: 45566 | H76: A- | I76: 328000 | J76: SF | K76: 12.901 | L76: 327790 | M76: 64 | N76: 2.5 | O76: 2 | P76: 1 | Q76: 2008 | R76: - | S76: {=_xlfn.IFS(AND('Rent Table'!$I76>0,'Rent Table'!$I76<=50000),"0-50,000", AND('Rent Table'!$I76 > 50000, 'Rent Table'!$I76 <= 150000), "50,001-150,000", AND('Rent Table'!$I76 > 150000, 'Rent Table'!$I76 <= 250000), "150,001-250,000", AND('Rent Table'!$I76 > 250000, 'Rent Table'!$I76 <= 350000), "250,001-350,000", AND('Rent Table'!$I76 > 350000, 'Rent Table'!$I76 <= 450000), "350,001-450,000", AND('Rent Table'!$I76 > 450000, 'Rent Table'!$I76 <= 600000), "450,001-600,000", AND('Rent Table'!$I76 > 600000, 'Rent Table'!$I76 <= 750000), "600,001-750,000",'Rent Table'!$I76 > 750000, "750,000+", TRUE, "Undefined" )} -> 250,001-350,000
A77: 2185 West Lugonia Avenue | B77: Redlands | C77: CA | D77: 92374 | E77: Inland Empire | F77: Industrial | G77: 45566 | H77: A- | I77: 500602 | J77: SF | K77: 13.67495 | L77: 500602 | M77: 55.25 | N77: - | O77: - | P77: 2 | Q77: 2016 | R77: - | S77: {=_xlfn.IFS(AND('Rent Table'!$I77>0,'Rent Table'!$I77<=50000),"0-50,000", AND('Rent Table'!$I77 > 50000, 'Rent Table'!$I77 <= 150000), "50,001-150,000", AND('Rent Table'!$I77 > 150000, 'Rent Table'!$I77 <= 250000), "150,001-250,000", AND('Rent Table'!$I77 > 250000, 'Rent Table'!$I77 <= 350000), "250,001-350,000", AND('Rent Table'!$I77 > 350000, 'Rent Table'!$I77 <= 450000), "350,001-450,000", AND('Rent Table'!$I77 > 450000, 'Rent Table'!$I77 <= 600000), "450,001-600,000", AND('Rent Table'!$I77 > 600000, 'Rent Table'!$I77 <= 750000), "600,001-750,000",'Rent Table'!$I77 > 750000, "750,000+", TRUE, "Undefined" )} -> 450,001-600,000
A78: 2220 Almond Avenue | B78: Redlands | C78: CA | D78: 92374 | E78: Inland Empire | F78: Industrial | G78: 45566 | H78: A- | I78: 412000 | J78: SF | K78: 10.0171 | L78: 411879 | M78: 122 | N78: 0.55 | O78: 2 | P78: 1 | Q78: 2007 | R78: - | S78: {=_xlfn.IFS(AND('Rent Table'!$I78>0,'Rent Table'!$I78<=50000),"0-50,000", AND('Rent Table'!$I78 > 50000, 'Rent Table'!$I78 <= 150000), "50,001-150,000", AND('Rent Table'!$I78 > 150000, 'Rent Table'!$I78 <= 250000), "150,001-250,000", AND('Rent Table'!$I78 > 250000, 'Rent Table'!$I78 <= 350000), "250,001-350,000", AND('Rent Table'!$I78 > 350000, 'Rent Table'!$I78 <= 450000), "350,001-450,000", AND('Rent Table'!$I78 > 450000, 'Rent Table'!$I78 <= 600000), "450,001-600,000", AND('Rent Table'!$I78 > 600000, 'Rent Table'!$I78 <= 750000), "600,001-750,000",'Rent Table'!$I78 > 750000, "750,000+", TRUE, "Undefined" )} -> 350,001-450,000
A79: 2301 West San Bernardino Avenue | B79: Redlands | C79: CA | D79: 92374 | E79: Inland Empire | F79: Industrial | G79: 45566 | H79: A- | I79: 983986 | J79: SF | K79: 10.09254 | L79: 896662 | M79: 63.5 | N79: 0.875 | O79: 2 | P79: 1 | Q79: 2004 | R79: - | S79: {=_xlfn.IFS(AND('Rent Table'!$I79>0,'Rent Table'!$I79<=50000),"0-50,000", AND('Rent Table'!$I79 > 50000, 'Rent Table'!$I79 <= 150000), "50,001-150,000", AND('Rent Table'!$I79 > 150000, 'Rent Table'!$I79 <= 250000), "150,001-250,000", AND('Rent Table'!$I79 > 250000, 'Rent Table'!$I79 <= 350000), "250,001-350,000", AND('Rent Table'!$I79 > 350000, 'Rent Table'!$I79 <= 450000), "350,001-450,000", AND('Rent Table'!$I79 > 450000, 'Rent Table'!$I79 <= 600000), "450,001-600,000", AND('Rent Table'!$I79 > 600000, 'Rent Table'!$I79 <= 750000), "600,001-750,000",'Rent Table'!$I79 > 750000, "750,000+", TRUE, "Undefined" )} -> 750,000+
A80: 2501 West San Bernardino Avenue | B80: Redlands | C80: CA | D80: 92374 | E80: Inland Empire | F80: Industrial | G80: 45566 | H80: A- | I80: 683269 | J80: SF | K80: 8.70586 | L80: 683269 | M80: 120 | N80: 2 | O80: 3 | P80: 1 | Q80: 2005 | R80: - | S80: {=_xlfn.IFS(AND('Rent Table'!$I80>0,'Rent Table'!$I80<=50000),"0-50,000", AND('Rent Table'!$I80 > 50000, 'Rent Table'!$I80 <= 150000), "50,001-150,000", AND('Rent Table'!$I80 > 150000, 'Rent Table'!$I80 <= 250000), "150,001-250,000", AND('Rent Table'!$I80 > 250000, 'Rent Table'!$I80 <= 350000), "250,001-350,000", AND('Rent Table'!$I80 > 350000, 'Rent Table'!$I80 <= 450000), "350,001-450,000", AND('Rent Table'!$I80 > 450000, 'Rent Table'!$I80 <= 600000), "450,001-600,000", AND('Rent Table'!$I80 > 600000, 'Rent Table'!$I80 <= 750000), "600,001-750,000",'Rent Table'!$I80 > 750000, "750,000+", TRUE, "Undefined" )} -> 600,001-750,000
A81: 26525 Pioneer Avenue | B81: Redlands | C81: CA | D81: 92374 | E81: Inland Empire | F81: Industrial | G81: 45566 | H81: A- | I81: 375839 | J81: SF | K81: 13.1526 | L81: 375839 | M81: 60 | N81: - | O81: - | P81: 1 | Q81: 2014 | R81: - | S81: {=_xlfn.IFS(AND('Rent Table'!$I81>0,'Rent Table'!$I81<=50000),"0-50,000", AND('Rent Table'!$I81 > 50000, 'Rent Table'!$I81 <= 150000), "50,001-150,000", AND('Rent Table'!$I81 > 150000, 'Rent Table'!$I81 <= 250000), "150,001-250,000", AND('Rent Table'!$I81 > 250000, 'Rent Table'!$I81 <= 350000), "250,001-350,000", AND('Rent Table'!$I81 > 350000, 'Rent Table'!$I81 <= 450000), "350,001-450,000", AND('Rent Table'!$I81 > 450000, 'Rent Table'!$I81 <= 600000), "450,001-600,000", AND('Rent Table'!$I81 > 600000, 'Rent Table'!$I81 <= 750000), "600,001-750,000",'Rent Table'!$I81 > 750000, "750,000+", TRUE, "Undefined" )} -> 350,001-450,000
A82: 26597 San Bernardino Avenue | B82: Redlands | C82: CA | D82: 92374 | E82: Inland Empire | F82: Industrial | G82: 45566 | H82: A- | I82: 557213 | J82: SF | K82: 10.0691 | L82: 557213 | M82: 60 | N82: - | O82: - | P82: 1 | Q82: 2012 | R82: - | S82: {=_xlfn.IFS(AND('Rent Table'!$I82>0,'Rent Table'!$I82<=50000),"0-50,000", AND('Rent Table'!$I82 > 50000, 'Rent Table'!$I82 <= 150000), "50,001-150,000", AND('Rent Table'!$I82 > 150000, 'Rent Table'!$I82 <= 250000), "150,001-250,000", AND('Rent Table'!$I82 > 250000, 'Rent Table'!$I82 <= 350000), "250,001-350,000", AND('Rent Table'!$I82 > 350000, 'Rent Table'!$I82 <= 450000), "350,001-450,000", AND('Rent Table'!$I82 > 450000, 'Rent Table'!$I82 <= 600000), "450,001-600,000", AND('Rent Table'!$I82 > 600000, 'Rent Table'!$I82 <= 750000), "600,001-750,000",'Rent Table'!$I82 > 750000, "750,000+", TRUE, "Undefined" )} -> 450,001-600,000
A83: 26635 Pioneer Avenue | B83: Redlands | C83: CA | D83: 92374 | E83: Inland Empire | F83: Industrial | G83: 45566 | H83: A- | I83: 616542 | J83: SF | K83: 8.74871 | L83: 616542 | M83: 61 | N83: 1 | O83: 1 | P83: 1 | Q83: 2011 | R83: - | S83: {=_xlfn.IFS(AND('Rent Table'!$I83>0,'Rent Table'!$I83<=50000),"0-50,000", AND('Rent Table'!$I83 > 50000, 'Rent Table'!$I83 <= 150000), "50,001-150,000", AND('Rent Table'!$I83 > 150000, 'Rent Table'!$I83 <= 250000), "150,001-250,000", AND('Rent Table'!$I83 > 250000, 'Rent Table'!$I83 <= 350000), "250,001-350,000", AND('Rent Table'!$I83 > 350000, 'Rent Table'!$I83 <= 450000), "350,001-450,000", AND('Rent Table'!$I83 > 450000, 'Rent Table'!$I83 <= 600000), "450,001-600,000", AND('Rent Table'!$I83 > 600000, 'Rent Table'!$I83 <= 750000), "600,001-750,000",'Rent Table'!$I83 > 750000, "750,000+", TRUE, "Undefined" )} -> 600,001-750,000
A84: 10756 Nevada Street | B84: Redlands | C84: CA | D84: 92373 | E84: Inland Empire | F84: Industrial | G84: 45566 | H84: A- | I84: 88967 | J84: SF | K84: 13.6725 | L84: 88967 | M84: 63 | N84: - | O84: 4 | P84: 1 | Q84: 2023 | R84: - | S84: {=_xlfn.IFS(AND('Rent Table'!$I84>0,'Rent Table'!$I84<=50000),"0-50,000", AND('Rent Table'!$I84 > 50000, 'Rent Table'!$I84 <= 150000), "50,001-150,000", AND('Rent Table'!$I84 > 150000, 'Rent Table'!$I84 <= 250000), "150,001-250,000", AND('Rent Table'!$I84 > 250000, 'Rent Table'!$I84 <= 350000), "250,001-350,000", AND('Rent Table'!$I84 > 350000, 'Rent Table'!$I84 <= 450000), "350,001-450,000", AND('Rent Table'!$I84 > 450000, 'Rent Table'!$I84 <= 600000), "450,001-600,000", AND('Rent Table'!$I84 > 600000, 'Rent Table'!$I84 <= 750000), "600,001-750,000",'Rent Table'!$I84 > 750000, "750,000+", TRUE, "Undefined" )} -> 50,001-150,000
A85: 1351 West Park Avenue | B85: Redlands | C85: CA | D85: 92373 | E85: Inland Empire | F85: Industrial | G85: 45566 | H85: A- | I85: 83451 | J85: SF | K85: 12.642233 | L85: 19145 | M85: 84 | N85: 2 | O85: - | P85: 1 | Q85: 2007 | R85: - | S85: {=_xlfn.IFS(AND('Rent Table'!$I85>0,'Rent Table'!$I85<=50000),"0-50,000", AND('Rent Table'!$I85 > 50000, 'Rent Table'!$I85 <= 150000), "50,001-150,000", AND('Rent Table'!$I85 > 150000, 'Rent Table'!$I85 <= 250000), "150,001-250,000", AND('Rent Table'!$I85 > 250000, 'Rent Table'!$I85 <= 350000), "250,001-350,000", AND('Rent Table'!$I85 > 350000, 'Rent Table'!$I85 <= 450000), "350,001-450,000", AND('Rent Table'!$I85 > 450000, 'Rent Table'!$I85 <= 600000), "450,001-600,000", AND('Rent Table'!$I85 > 600000, 'Rent Table'!$I85 <= 750000), "600,001-750,000",'Rent Table'!$I85 > 750000, "750,000+", TRUE, "Undefined" )} -> 50,001-150,000
A86: 1450 Mountain View Avenue | B86: Redlands | C86: CA | D86: 92374 | E86: Inland Empire | F86: Industrial | G86: 45566 | H86: A- | I86: 99582 | J86: SF | K86: 11.6535 | L86: 99580 | M86: 124 | N86: 1.6 | O86: 4 | P86: 1 | Q86: 2008 | R86: - | S86: {=_xlfn.IFS(AND('Rent Table'!$I86>0,'Rent Table'!$I86<=50000),"0-50,000", AND('Rent Table'!$I86 > 50000, 'Rent Table'!$I86 <= 150000), "50,001-150,000", AND('Rent Table'!$I86 > 150000, 'Rent Table'!$I86 <= 250000), "150,001-250,000", AND('Rent Table'!$I86 > 250000, 'Rent Table'!$I86 <= 350000), "250,001-350,000", AND('Rent Table'!$I86 > 350000, 'Rent Table'!$I86 <= 450000), "350,001-450,000", AND('Rent Table'!$I86 > 450000, 'Rent Table'!$I86 <= 600000), "450,001-600,000", AND('Rent Table'!$I86 > 600000, 'Rent Table'!$I86 <= 750000), "600,001-750,000",'Rent Table'!$I86 > 750000, "750,000+", TRUE, "Undefined" )} -> 50,001-150,000
A87: 2466 West Lugonia Avenue | B87: Redlands | C87: CA | D87: 92374 | E87: Inland Empire | F87: Industrial | G87: 45566 | H87: A- | I87: 99363 | J87: SF | K87: 10.0447 | L87: 99363 | M87: 61 | N87: - | O87: 1 | P87: 1 | Q87: 2008 | R87: - | S87: {=_xlfn.IFS(AND('Rent Table'!$I87>0,'Rent Table'!$I87<=50000),"0-50,000", AND('Rent Table'!$I87 > 50000, 'Rent Table'!$I87 <= 150000), "50,001-150,000", AND('Rent Table'!$I87 > 150000, 'Rent Table'!$I87 <= 250000), "150,001-250,000", AND('Rent Table'!$I87 > 250000, 'Rent Table'!$I87 <= 350000), "250,001-350,000", AND('Rent Table'!$I87 > 350000, 'Rent Table'!$I87 <= 450000), "350,001-450,000", AND('Rent Table'!$I87 > 450000, 'Rent Table'!$I87 <= 600000), "450,001-600,000", AND('Rent Table'!$I87 > 600000, 'Rent Table'!$I87 <= 750000), "600,001-750,000",'Rent Table'!$I87 > 750000, "750,000+", TRUE, "Undefined" )} -> 50,001-150,000
A88: 1055 East Cooley Avenue | B88: San Bernardino | C88: CA | D88: 92408 | E88: Inland Empire | F88: Industrial | G88: 45566 | H88: A- | I88: 72000 | J88: SF | K88: 12.2991 | L88: 72000 | M88: 89 | N88: 2.33 | O88: 2 | P88: - | Q88: 1986 | R88: - | S88: {=_xlfn.IFS(AND('Rent Table'!$I88>0,'Rent Table'!$I88<=50000),"0-50,000", AND('Rent Table'!$I88 > 50000, 'Rent Table'!$I88 <= 150000), "50,001-150,000", AND('Rent Table'!$I88 > 150000, 'Rent Table'!$I88 <= 250000), "150,001-250,000", AND('Rent Table'!$I88 > 250000, 'Rent Table'!$I88 <= 350000), "250,001-350,000", AND('Rent Table'!$I88 > 350000, 'Rent Table'!$I88 <= 450000), "350,001-450,000", AND('Rent Table'!$I88 > 450000, 'Rent Table'!$I88 <= 600000), "450,001-600,000", AND('Rent Table'!$I88 > 600000, 'Rent Table'!$I88 <= 750000), "600,001-750,000",'Rent Table'!$I88 > 750000, "750,000+", TRUE, "Undefined" )} -> 50,001-150,000
A89: 1335 Riverview Drive | B89: San Bernardino | C89: CA | D89: 92408 | E89: Inland Empire | F89: Industrial | G89: 45566 | H89: A- | I89: 19142 | J89: SF | K89: 11.8502 | L89: 19142 | M89: 120 | N89: - | O89: 4 | P89: 1 | Q89: 2008 | R89: - | S89: {=_xlfn.IFS(AND('Rent Table'!$I89>0,'Rent Table'!$I89<=50000),"0-50,000", AND('Rent Table'!$I89 > 50000, 'Rent Table'!$I89 <= 150000), "50,001-150,000", AND('Rent Table'!$I89 > 150000, 'Rent Table'!$I89 <= 250000), "150,001-250,000", AND('Rent Table'!$I89 > 250000, 'Rent Table'!$I89 <= 350000), "250,001-350,000", AND('Rent Table'!$I89 > 350000, 'Rent Table'!$I89 <= 450000), "350,001-450,000", AND('Rent Table'!$I89 > 450000, 'Rent Table'!$I89 <= 600000), "450,001-600,000", AND('Rent Table'!$I89 > 600000, 'Rent Table'!$I89 <= 750000), "600,001-750,000",'Rent Table'!$I89 > 750000, "750,000+", TRUE, "Undefined" )} -> 0-50,000
A90: 1350 South Waterman Avenue | B90: San Bernardino | C90: CA | D90: 92408 | E90: Inland Empire | F90: Industrial | G90: 45566 | H90: A- | I90: 553592 | J90: SF | K90: 7.35182 | L90: 553592 | M90: 88 | N90: 7 | O90: 4 | P90: 1 | Q90: 2018 | R90: - | S90: {=_xlfn.IFS(AND('Rent Table'!$I90>0,'Rent Table'!$I90<=50000),"0-50,000", AND('Rent Table'!$I90 > 50000, 'Rent Table'!$I90 <= 150000), "50,001-150,000", AND('Rent Table'!$I90 > 150000, 'Rent Table'!$I90 <= 250000), "150,001-250,000", AND('Rent Table'!$I90 > 250000, 'Rent Table'!$I90 <= 350000), "250,001-350,000", AND('Rent Table'!$I90 > 350000, 'Rent Table'!$I90 <= 450000), "350,001-450,000", AND('Rent Table'!$I90 > 450000, 'Rent Table'!$I90 <= 600000), "450,001-600,000", AND('Rent Table'!$I90 > 600000, 'Rent Table'!$I90 <= 750000), "600,001-750,000",'Rent Table'!$I90 > 750000, "750,000+", TRUE, "Undefined" )} -> 450,001-600,000
A91: 1385 South Tippecanoe Avenue | B91: San Bernardino | C91: CA | D91: 92408 | E91: Inland Empire | F91: Industrial | G91: 45566 | H91: A- | I91: 81286 | J91: SF | K91: 14.355 | L91: 81286 | M91: 37 | N91: - | O91: 1 | P91: 2 | Q91: 2018 | R91: - | S91: {=_xlfn.IFS(AND('Rent Table'!$I91>0,'Rent Table'!$I91<=50000),"0-50,000", AND('Rent Table'!$I91 > 50000, 'Rent Table'!$I91 <= 150000), "50,001-150,000", AND('Rent Table'!$I91 > 150000, 'Rent Table'!$I91 <= 250000), "150,001-250,000", AND('Rent Table'!$I91 > 250000, 'Rent Table'!$I91 <= 350000), "250,001-350,000", AND('Rent Table'!$I91 > 350000, 'Rent Table'!$I91 <= 450000), "350,001-450,000", AND('Rent Table'!$I91 > 450000, 'Rent Table'!$I91 <= 600000), "450,001-600,000", AND('Rent Table'!$I91 > 600000, 'Rent Table'!$I91 <= 750000), "600,001-750,000",'Rent Table'!$I91 > 750000, "750,000+", TRUE, "Undefined" )} -> 50,001-150,000
A92: 1390 South Tippecanoe Avenue | B92: San Bernardino | C92: CA | D92: 92408 | E92: Inland Empire | F92: Industrial | G92: 45566 | H92: A- | I92: 65360 | J92: SF | K92: 11.1859 | L92: 43600 | M92: 89 | N92: - | O92: 4 | P92: - | Q92: 1989 | R92: - | S92: {=_xlfn.IFS(AND('Rent Table'!$I92>0,'Rent Table'!$I92<=50000),"0-50,000", AND('Rent Table'!$I92 > 50000, 'Rent Table'!$I92 <= 150000), "50,001-150,000", AND('Rent Table'!$I92 > 150000, 'Rent Table'!$I92 <= 250000), "150,001-250,000", AND('Rent Table'!$I92 > 250000, 'Rent Table'!$I92 <= 350000), "250,001-350,000", AND('Rent Table'!$I92 > 350000, 'Rent Table'!$I92 <= 450000), "350,001-450,000", AND('Rent Table'!$I92 > 450000, 'Rent Table'!$I92 <= 600000), "450,001-600,000", AND('Rent Table'!$I92 > 600000, 'Rent Table'!$I92 <= 750000), "600,001-750,000",'Rent Table'!$I92 > 750000, "750,000+", TRUE, "Undefined" )} -> 50,001-150,000
A93: 1425 Victoria Court | B93: San Bernardino | C93: CA | D93: 92408 | E93: Inland Empire | F93: Industrial | G93: 45566 | H93: A- | I93: 23748 | J93: SF | K93: 11.743167 | L93: 8246.667 | M93: 61 | N93: - | O93: 2.3333333 | P93: - | Q93: 1988 | R93: - | S93: {=_xlfn.IFS(AND('Rent Table'!$I93>0,'Rent Table'!$I93<=50000),"0-50,000", AND('Rent Table'!$I93 > 50000, 'Rent Table'!$I93 <= 150000), "50,001-150,000", AND('Rent Table'!$I93 > 150000, 'Rent Table'!$I93 <= 250000), "150,001-250,000", AND('Rent Table'!$I93 > 250000, 'Rent Table'!$I93 <= 350000), "250,001-350,000", AND('Rent Table'!$I93 > 350000, 'Rent Table'!$I93 <= 450000), "350,001-450,000", AND('Rent Table'!$I93 > 450000, 'Rent Table'!$I93 <= 600000), "450,001-600,000", AND('Rent Table'!$I93 > 600000, 'Rent Table'!$I93 <= 750000), "600,001-750,000",'Rent Table'!$I93 > 750000, "750,000+", TRUE, "Undefined" )} -> 0-50,000
A94: 1442 South Gage Street | B94: San Bernardino | C94: CA | D94: 92408 | E94: Inland Empire | F94: Industrial | G94: 45566 | H94: A- | I94: 6600 | J94: SF | K94: 10.9107 | L94: 6600 | M94: 36 | N94: - | O94: - | P94: 1 | Q94: 1989 | R94: - | S94: {=_xlfn.IFS(AND('Rent Table'!$I94>0,'Rent Table'!$I94<=50000),"0-50,000", AND('Rent Table'!$I94 > 50000, 'Rent Table'!$I94 <= 150000), "50,001-150,000", AND('Rent Table'!$I94 > 150000, 'Rent Table'!$I94 <= 250000), "150,001-250,000", AND('Rent Table'!$I94 > 250000, 'Rent Table'!$I94 <= 350000), "250,001-350,000", AND('Rent Table'!$I94 > 350000, 'Rent Table'!$I94 <= 450000), "350,001-450,000", AND('Rent Table'!$I94 > 450000, 'Rent Table'!$I94 <= 600000), "450,001-600,000", AND('Rent Table'!$I94 > 600000, 'Rent Table'!$I94 <= 750000), "600,001-750,000",'Rent Table'!$I94 > 750000, "750,000+", TRUE, "Undefined" )} -> 0-50,000
A95: 1445 South Tippecanoe Avenue | B95: San Bernardino | C95: CA | D95: 92408 | E95: Inland Empire | F95: Industrial | G95: 45566 | H95: A- | I95: 344000 | J95: SF | K95: 8.39927 | L95: 205398 | M95: 126 | N95: 5 | O95: 6 | P95: 1 | Q95: 2018 | R95: - | S95: {=_xlfn.IFS(AND('Rent Table'!$I95>0,'Rent Table'!$I95<=50000),"0-50,000", AND('Rent Table'!$I95 > 50000, 'Rent Table'!$I95 <= 150000), "50,001-150,000", AND('Rent Table'!$I95 > 150000, 'Rent Table'!$I95 <= 250000), "150,001-250,000", AND('Rent Table'!$I95 > 250000, 'Rent Table'!$I95 <= 350000), "250,001-350,000", AND('Rent Table'!$I95 > 350000, 'Rent Table'!$I95 <= 450000), "350,001-450,000", AND('Rent Table'!$I95 > 450000, 'Rent Table'!$I95 <= 600000), "450,001-600,000", AND('Rent Table'!$I95 > 600000, 'Rent Table'!$I95 <= 750000), "600,001-750,000",'Rent Table'!$I95 > 750000, "750,000+", TRUE, "Undefined" )} -> 250,001-350,000
A96: 1445-1455 Riverview Drive | B96: San Bernardino | C96: CA | D96: 92408 | E96: Inland Empire | F96: Industrial | G96: 45566 | H96: A- | I96: 116645 | J96: SF | K96: 16.583 | L96: 116645 | M96: 36 | N96: - | O96: - | P96: 1 | Q96: 1980 | R96: - | S96: {=_xlfn.IFS(AND('Rent Table'!$I96>0,'Rent Table'!$I96<=50000),"0-50,000", AND('Rent Table'!$I96 > 50000, 'Rent Table'!$I96 <= 150000), "50,001-150,000", AND('Rent Table'!$I96 > 150000, 'Rent Table'!$I96 <= 250000), "150,001-250,000", AND('Rent Table'!$I96 > 250000, 'Rent Table'!$I96 <= 350000), "250,001-350,000", AND('Rent Table'!$I96 > 350000, 'Rent Table'!$I96 <= 450000), "350,001-450,000", AND('Rent Table'!$I96 > 450000, 'Rent Table'!$I96 <= 600000), "450,001-600,000", AND('Rent Table'!$I96 > 600000, 'Rent Table'!$I96 <= 750000), "600,001-750,000",'Rent Table'!$I96 > 750000, "750,000+", TRUE, "Undefined" )} -> 50,001-150,000
A97: 1615 Riverview Drive | B97: San Bernardino | C97: CA | D97: 92408 | E97: Inland Empire | F97: Industrial | G97: 45566 | H97: A- | I97: 18710 | J97: SF | K97: 10.7996 | L97: 8160 | M97: 36 | N97: - | O97: - | P97: 1 | Q97: 1982 | R97: - | S97: {=_xlfn.IFS(AND('Rent Table'!$I97>0,'Rent Table'!$I97<=50000),"0-50,000", AND('Rent Table'!$I97 > 50000, 'Rent Table'!$I97 <= 150000), "50,001-150,000", AND('Rent Table'!$I97 > 150000, 'Rent Table'!$I97 <= 250000), "150,001-250,000", AND('Rent Table'!$I97 > 250000, 'Rent Table'!$I97 <= 350000), "250,001-350,000", AND('Rent Table'!$I97 > 350000, 'Rent Table'!$I97 <= 450000), "350,001-450,000", AND('Rent Table'!$I97 > 450000, 'Rent Table'!$I97 <= 600000), "450,001-600,000", AND('Rent Table'!$I97 > 600000, 'Rent Table'!$I97 <= 750000), "600,001-750,000",'Rent Table'!$I97 > 750000, "750,000+", TRUE, "Undefined" )} -> 0-50,000
A98: 1655 Riverview Drive | B98: San Bernardino | C98: CA | D98: 92408 | E98: Inland Empire | F98: Industrial | G98: 45566 | H98: A- | I98: 8000 | J98: SF | K98: 15.5779 | L98: 8000 | M98: 59.75 | N98: - | O98: 1 | P98: 1 | Q98: 1980 | R98: - | S98: {=_xlfn.IFS(AND('Rent Table'!$I98>0,'Rent Table'!$I98<=50000),"0-50,000", AND('Rent Table'!$I98 > 50000, 'Rent Table'!$I98 <= 150000), "50,001-150,000", AND('Rent Table'!$I98 > 150000, 'Rent Table'!$I98 <= 250000), "150,001-250,000", AND('Rent Table'!$I98 > 250000, 'Rent Table'!$I98 <= 350000), "250,001-350,000", AND('Rent Table'!$I98 > 350000, 'Rent Table'!$I98 <= 450000), "350,001-450,000", AND('Rent Table'!$I98 > 450000, 'Rent Table'!$I98 <= 600000), "450,001-600,000", AND('Rent Table'!$I98 > 600000, 'Rent Table'!$I98 <= 750000), "600,001-750,000",'Rent Table'!$I98 > 750000, "750,000+", TRUE, "Undefined" )} -> 0-50,000
A99: 1811-1833 Riverview Drive | B99: San Bernardino | C99: CA | D99: 92408 | E99: Inland Empire | F99: Industrial | G99: 45566 | H99: A- | I99: 44000 | J99: SF | K99: 10.4113 | L99: 8800 | M99: 61 | N99: - | O99: 1 | P99: 1 | Q99: 1984 | R99: - | S99: {=_xlfn.IFS(AND('Rent Table'!$I99>0,'Rent Table'!$I99<=50000),"0-50,000", AND('Rent Table'!$I99 > 50000, 'Rent Table'!$I99 <= 150000), "50,001-150,000", AND('Rent Table'!$I99 > 150000, 'Rent Table'!$I99 <= 250000), "150,001-250,000", AND('Rent Table'!$I99 > 250000, 'Rent Table'!$I99 <= 350000), "250,001-350,000", AND('Rent Table'!$I99 > 350000, 'Rent Table'!$I99 <= 450000), "350,001-450,000", AND('Rent Table'!$I99 > 450000, 'Rent Table'!$I99 <= 600000), "450,001-600,000", AND('Rent Table'!$I99 > 600000, 'Rent Table'!$I99 <= 750000), "600,001-750,000",'Rent Table'!$I99 > 750000, "750,000+", TRUE, "Undefined" )} -> 0-50,000
A100: 1833 Riverview Drive | B100: San Bernardino | C100: CA | D100: 92408 | E100: Inland Empire | F100: Industrial | G100: 45566 | H100: A- | I100: 44000 | J100: SF | K100: 8.32503 | L100: 8800 | M100: 39 | N100: - | O100: 4 | P100: 1 | Q100: 1981 | R100: - | S100: {=_xlfn.IFS(AND('Rent Table'!$I100>0,'Rent Table'!$I100<=50000),"0-50,000", AND('Rent Table'!$I100 > 50000, 'Rent Table'!$I100 <= 150000), "50,001-150,000", AND('Rent Table'!$I100 > 150000, 'Rent Table'!$I100 <= 250000), "150,001-250,000", AND('Rent Table'!$I100 > 250000, 'Rent Table'!$I100 <= 350000), "250,001-350,000", AND('Rent Table'!$I100 > 350000, 'Rent Table'!$I100 <= 450000), "350,001-450,000", AND('Rent Table'!$I100 > 450000, 'Rent Table'!$I100 <= 600000), "450,001-600,000", AND('Rent Table'!$I100 > 600000, 'Rent Table'!$I100 <= 750000), "600,001-750,000",'Rent Table'!$I100 > 750000, "750,000+", TRUE, "Undefined" )} -> 0-50,000
...

Sheet Sales Table
A1: Appended Table
B4: Portfolio / Property Name | C4: Street Address | D4: City | E4: State | F4: Country | G4: Zip Code | H4: Sector | I4: Subsector | J4: Sector Attribute | K4: Part of Mixed Use Development | L4: Market | M4: Submarket | N4: Size | O4: Size Type | P4: Sale Date | Q4: Stake Sold | R4: Local Currency Sale Price (M) | S4: Local Currency Symbol | T4: Sale Price Per (in Local Currency) | U4: Selected Currency Sale Price ($) (M) | V4: Submarket Grade | W4: Property Cap Rate | X4: Property Cap Rate Type | Y4: Part of a Portfolio? | Z4: Buyer | AA4: Seller | AB4: Buyer Objective | AC4: To be demolished | AD4: Buyer Broker | AE4: Seller Broker | AF4: Land Area (acres) | AG4: Stories | AH4: Parking | AI4: Buildings | AJ4: Year Built | AK4: Year Renovated | AL4: Occupancy | AM4: Green Street Market Cap Rate | AN4: Submarket Cap Rate | AO4: Zip Code Cap Rate | AP4: Lender | AQ4: 1st Mortgage | AR4: Verified?
B5: 1971 Essex Court | C5: 1971 Essex Court, Redlands, CA 92373 | D5: Redlands | E5: CA | F5: United States | G5: 92373 | H5: Industrial | I5: Flex Industrial | K5: No | L5: Inland Empire | M5: IE-East Redlands | N5: 21228 | O5: SF | P5: 45295 | Q5: 1 | R5: 5.1 | S5: $ | T5: 240.25 | V5: A- | W5: 0.04052253 | X5: Green Street Market Estimate | Y5: No | Z5: CMJ Brother's Corp. | AC5: No | AF5: 1.183 | AG5: 1 | AI5: 1 | AJ5: 2001 | AM5: 0.047 | AN5: 0.0481871 | AO5: 0.04791285 | AP5: Rediger Investments | AQ5: 2550000 | AR5: Yes
B6: 1425 Cooley Court | C6: 1425 Cooley Court, San Bernardino, CA 92408 | D6: San Bernardino | E6: CA | F6: United States | G6: 92408 | H6: Industrial | I6: Warehouse | J6: Light Industrial | K6: No | L6: Inland Empire | M6: IE-East Redlands | N6: 78012 | O6: SF | P6: 45205 | Q6: 1 | R6: 11.1 | S6: $ | T6: 142.29 | V6: A- | W6: 0.0424211 | X6: Green Street Market Estimate | Y6: No | AC6: No | AF6: 2.81 | AG6: 2 | AI6: 1 | AJ6: 1988 | AM6: 0.047 | AN6: 0.0481871 | AO6: 0.04791285 | AP6: Symetra Financial | AQ6: 6400000 | AR6: Yes
B7: 1320 Riverview Drive | C7: 1320 Riverview Drive, San Bernardino, CA 92408 | D7: San Bernardino | E7: CA | F7: United States | G7: 92408 | H7: Industrial | I7: Warehouse | J7: Light Industrial | K7: No | L7: Inland Empire | M7: IE-East Redlands | N7: 23397 | O7: SF | P7: 45201 | Q7: 1 | R7: 5.62 | S7: $ | T7: 240.01 | V7: A- | W7: 0.0424211 | X7: Green Street Market Estimate | Y7: No | AA7: Rogina Family Living Trust | AC7: No | AF7: 1.24 | AG7: 2 | AI7: 1 | AJ7: 2004 | AM7: 0.047 | AN7: 0.0481871 | AO7: 0.04791285 | AP7: Wells Fargo Bank | AQ7: 3369200 | AR7: Yes
B8: 401 Alabama Street | C8: 401 Alabama Street, Redlands, CA 92373 | D8: Redlands | E8: CA | F8: United States | G8: 92373 | H8: Industrial | I8: Warehouse | J8: Light Industrial | K8: No | L8: Inland Empire | M8: IE-East Redlands | N8: 95500 | O8: SF | P8: 45051 | Q8: 1 | R8: 27.25 | S8: $ | T8: 285.34 | V8: A- | W8: 0.043 | X8: As Reported | Y8: No | Z8: General Investment & Development Cos. | AA8: Investment Building Group | AC8: No | AE8: CBRE Group | AF8: 4.526 | AG8: 1 | AI8: 1 | AJ8: 2017 | AL8: 1 | AM8: 0.047 | AN8: 0.0481871 | AO8: 0.04791285 | AR8: Yes
B9: Carnegie Business Center | C9: 720 East Carnegie Drive, San Bernardino, CA 92408 | D9: San Bernardino | E9: CA | F9: United States | G9: 92408 | H9: Industrial | I9: Warehouse | J9: Light Industrial | K9: No | L9: Inland Empire | M9: IE-East Redlands | N9: 51438 | O9: SF | P9: 44715 | Q9: 1 | R9: 11.02 | S9: $ | T9: 214.19 | V9: A- | W9: 0.0577 | X9: As Reported | Y9: No | AA9: Entrada Partners | AC9: No | AD9: CBRE Group | AE9: CBRE Group | AH9: 0 | AI9: 1 | AJ9: 1987 | AL9: 0.95 | AM9: 0.047 | AN9: 0.0481871 | AO9: 0.04791285 | AR9: Yes
B10: 1990 Riverview Drive | C10: 1990 Riverview Drive, San Bernardino, CA 92408 | D10: San Bernardino | E10: CA | F10: United States | G10: 92408 | H10: Industrial | I10: Warehouse | K10: No | L10: Inland Empire | M10: IE-East Redlands | N10: 20473 | O10: SF | P10: 44704 | Q10: 1 | R10: 24 | S10: $ | T10: 1,172.28 | V10: A- | W10: 0.03667045 | X10: Green Street Market Estimate | Y10: No | AC10: No | AD10: CBRE Group | AH10: 0 | AJ10: 1980 | AM10: 0.047 | AN10: 0.0481871 | AO10: 0.04791285 | AR10: Yes
B11: 1393 East San Bernardino Avenue | C11: 1393 East San Bernardino Avenue, San Bernardino, CA 92408 | D11: San Bernardino | E11: CA | F11: United States | G11: 92408 | H11: Industrial | I11: Warehouse | J11: Light Industrial | K11: No | L11: Inland Empire | M11: IE-East Redlands | N11: 117125 | O11: SF | P11: 44696 | Q11: 1 | R11: 20 | S11: $ | T11: 170.76 | V11: A- | W11: 0.03667045 | X11: Green Street Market Estimate | Y11: No | Z11: First Industrial Realty Trust (FR) | AC11: No | AM11: 0.047 | AN11: 0.0481871 | AO11: 0.04791285 | AR11: Yes
B12: 301 Tennessee Street | C12: 301 Tennessee Street, Redlands, CA 92373 | D12: Redlands | E12: CA | F12: United States | G12: 92373 | H12: Industrial | I12: Warehouse | J12: Manufacturing / Heavy Industrial | K12: No | L12: Inland Empire | M12: IE-East Redlands | N12: 193469 | O12: SF | P12: 44665 | Q12: 1 | R12: 18.25 | S12: $ | T12: 94.33 | V12: A- | W12: 0.03412073 | X12: Green Street Market Estimate | Y12: No | Z12: Stos Partners | AA12: ESRI | AC12: No | AE12: Savills | AH12: 0 | AM12: 0.047 | AN12: 0.0481871 | AO12: 0.04791285 | AR12: Yes
B13: 1939 West Park Avenue | C13: 1939 West Park Avenue, Redlands, CA 92373 | D13: Redlands | E13: CA | F13: United States | G13: 92373 | H13: Industrial | I13: Warehouse | K13: No | L13: Inland Empire | M13: IE-East Redlands | N13: 21612 | O13: SF | P13: 44651 | Q13: 1 | R13: 5.96 | S13: $ | T13: 275.77 | V13: A- | W13: 0.03162073 | X13: Green Street Market Estimate | Y13: No | Z13: Scott Barnes | AA13: John C. Steinmann | AC13: No | AD13: CBRE Group | AE13: CBRE Group | AG13: 1 | AH13: 0 | AJ13: 2007 | AM13: 0.047 | AN13: 0.0481871 | AO13: 0.04791285 | AR13: Yes
B14: I-215 Commerce Center | C14: 1648 Ashley Way, Colton, CA 92324 | D14: Colton | E14: CA | F14: United States | G14: 92324 | H14: Industrial | I14: Warehouse | K14: No | L14: Inland Empire | M14: IE-East Redlands | N14: 225353 | O14: SF | P14: 44439 | Q14: 1 | R14: 57.5 | S14: $ | T14: 255.16 | V14: A- | W14: 0.028 | X14: As Reported | Y14: No | Z14: Zurich Alternative Asset Management | AA14: Transwestern Development Company | AC14: No | AE14: CBRE Group | AH14: 0 | AJ14: 2021 | AL14: 1 | AM14: 0.047 | AN14: 0.0481871 | AO14: 0.04791285 | AR14: Yes
B15: Washington Commerce Center | C15: 998 South Washington Avenue, San Bernardino, CA 92408 | D15: San Bernardino | E15: CA | F15: United States | G15: 92408 | H15: Industrial | I15: Warehouse | K15: No | L15: Inland Empire | M15: IE-East Redlands | N15: 574984 | O15: SF | P15: 44423 | Q15: 1 | S15: $ | T15: 164.53 | V15: A- | Y15: Yes | Z15: PGIM | AA15: Crow Holdings | AC15: No | AE15: Eastdil Secured | AH15: 0 | AM15: 0.047 | AN15: 0.0481871 | AO15: 0.04791285 | AR15: Yes
B16: Washington Commerce Center, Building 3 | C16: 998 South Washington Avenue, San Bernardino, CA 92408 | D16: San Bernardino | E16: CA | F16: United States | G16: 92408 | H16: Industrial | I16: Warehouse | K16: No | L16: Inland Empire | M16: IE-East Redlands | N16: 146800 | O16: SF | P16: 44423 | Q16: 1 | V16: A- | Y16: Yes | Z16: PGIM | AA16: Crow Holdings | AC16: No | AE16: Eastdil Secured | AH16: 0 | AM16: 0.047 | AN16: 0.0481871 | AO16: 0.04791285 | AR16: Yes
B17: Washington Commerce Center, Building 2 | C17: 975 South Washington Avenue, San Bernardino, CA 92408 | D17: San Bernardino | E17: CA | F17: United States | G17: 92408 | H17: Industrial | I17: Warehouse | K17: No | L17: Inland Empire | M17: IE-East Redlands | N17: 179584 | O17: SF | P17: 44423 | Q17: 1 | V17: A- | Y17: Yes | Z17: PGIM | AA17: Crow Holdings | AC17: No | AE17: Eastdil Secured | AH17: 0 | AM17: 0.047 | AN17: 0.0481871 | AO17: 0.04791285 | AR17: Yes
B18: Dedeaux Business Park Redlands | C18: 509 Alabama Street, Redlands, CA 92373 | D18: Redlands | E18: CA | F18: United States | G18: 92373 | H18: Industrial | I18: Warehouse | K18: No | L18: Inland Empire | M18: IE-East Redlands | N18: 74000 | O18: SF | P18: 44320 | Q18: 1 | R18: 16.9 | S18: $ | T18: 228.38 | V18: A- | W18: 0.0371 | X18: As Reported | Y18: No | Z18: LBA Realty | AA18: Brasa Capital; Dedeaux Properties | AC18: No | AD18: Cushman & Wakefield | AE18: Cushman & Wakefield; Lee & Associates | AH18: 0 | AM18: 0.047 | AN18: 0.0481871 | AO18: 0.04791285 | AR18: Yes
B19: 1255 Research Drive | C19: 1255 Research Drive, Redlands, CA 92374 | D19: Redlands | E19: CA | F19: United States | G19: 92374 | H19: Industrial | I19: Warehouse | K19: No | L19: Inland Empire | M19: IE-East Redlands | N19: 118000 | O19: SF | P19: 44295 | Q19: 1 | R19: 18.38 | S19: $ | T19: 155.72 | V19: A- | W19: 0.03612073 | X19: Green Street Market Estimate | Y19: No | Z19: EQT Exeter | AA19: Garner Holt Productions Inc. | AC19: No | AE19: Colliers | AH19: 0 | AM19: 0.047 | AN19: 0.0481871 | AO19: 0.04791285 | AR19: Yes
