Workbook
Name analysis_start: 'Torrance Inputs'!$D$18
Name analysis_start: #REF!
Name market_rent: 'Torrance Inputs'!$D$32
Name market_rent: #REF!

Sheet Annual Pro Forma
A2: Market Rent Inflation
A3: Expense Inflation
A4: Cash Flow Projections
A5: Redlands Industrial Property
B7: Actuals | C7: Forecast | D7: Forecast | E7: Forecast | F7: Forecast | G7: Forecast | H7: Forecast | I7: Forecast | J7: Forecast | K7: Forecast | L7: Forecast | M7: Forward T12
B8: 0 | C8: =B8+1 -> 1 | D8: =C8+1 -> 2 | E8: =D8+1 -> 3 | F8: =E8+1 -> 4 | G8: =F8+1 -> 5 | H8: =G8+1 -> 6 | I8: =H8+1 -> 7 | J8: =I8+1 -> 8 | ... M8: =L8+1 -> 11
B9: =EOMONTH(C9,-12) -> 45322 | C9: =EDATE('Torrance Inputs'!analysis_start,0) -> 45658 | D9: =EOMONTH(C9,12) -> 46053 | E9: =EOMONTH(D9,12) -> 46418 | F9: =EOMONTH(E9,12) -> 46783 | G9: =EOMONTH(F9,12) -> 47149 | H9: =EOMONTH(G9,12) -> 47514 | I9: =EOMONTH(H9,12) -> 47879 | J9: =EOMONTH(I9,12) -> 48244 | K9: =EOMONTH(J9,12) -> 48610 | ... M9: =EOMONTH(L9,12) -> 49340
A10: Months
A12: Rental Revenue
A13: Base Rent / SF / Year | C13: =SUMIF('Torrance Pro Forma'!$B$8:$ED$8,'Annual Pro Forma'!C$8,'Torrance Pro Forma'!$B13:$ED13) -> 48 | D13: =SUMIF('Torrance Pro Forma'!$B$8:$ED$8,'Annual Pro Forma'!D$8,'Torrance Pro Forma'!$B13:$ED13) -> 48.96 | E13: =SUMIF('Torrance Pro Forma'!$B$8:$ED$8,'Annual Pro Forma'!E$8,'Torrance Pro Forma'!$B13:$ED13) -> 49.9392 | F13: =SUMIF('Torrance Pro Forma'!$B$8:$ED$8,'Annual Pro Forma'!F$8,'Torrance Pro Forma'!$B13:$ED13) -> 50.937984 | G13: =SUMIF('Torrance Pro Forma'!$B$8:$ED$8,'Annual Pro Forma'!G$8,'Torrance Pro Forma'!$B13:$ED13) -> 0 | H13: =SUMIF('Torrance Pro Forma'!$B$8:$ED$8,'Annual Pro Forma'!H$8,'Torrance Pro Forma'!$B13:$ED13) -> 212.84272 | I13: =SUMIF('Torrance Pro Forma'!$B$8:$ED$8,'Annual Pro Forma'!I$8,'Torrance Pro Forma'!$B13:$ED13) -> 217.09957 | J13: =SUMIF('Torrance Pro Forma'!$B$8:$ED$8,'Annual Pro Forma'!J$8,'Torrance Pro Forma'!$B13:$ED13) -> 221.44157 | ... M13: =SUMIF('Torrance Pro Forma'!$B$8:$ED$8,'Annual Pro Forma'!M$8,'Torrance Pro Forma'!$B13:$ED13) -> 234.99556
A14: Tenant 1 | C14: =SUMIF('Torrance Pro Forma'!$B$8:$ED$8,'Annual Pro Forma'!C$8,'Torrance Pro Forma'!$B14:$ED14) -> 1100000 | D14: =SUMIF('Torrance Pro Forma'!$B$8:$ED$8,'Annual Pro Forma'!D$8,'Torrance Pro Forma'!$B14:$ED14) -> 1122000 | E14: =SUMIF('Torrance Pro Forma'!$B$8:$ED$8,'Annual Pro Forma'!E$8,'Torrance Pro Forma'!$B14:$ED14) -> 1144440 | F14: =SUMIF('Torrance Pro Forma'!$B$8:$ED$8,'Annual Pro Forma'!F$8,'Torrance Pro Forma'!$B14:$ED14) -> 1167328.8 | G14: =SUMIF('Torrance Pro Forma'!$B$8:$ED$8,'Annual Pro Forma'!G$8,'Torrance Pro Forma'!$B14:$ED14) -> 0 | H14: =SUMIF('Torrance Pro Forma'!$B$8:$ED$8,'Annual Pro Forma'!H$8,'Torrance Pro Forma'!$B14:$ED14) -> 2438822.8 | I14: =SUMIF('Torrance Pro Forma'!$B$8:$ED$8,'Annual Pro Forma'!I$8,'Torrance Pro Forma'!$B14:$ED14) -> 2487599.3 | J14: =SUMIF('Torrance Pro Forma'!$B$8:$ED$8,'Annual Pro Forma'!J$8,'Torrance Pro Forma'!$B14:$ED14) -> 2537351.3 | ... M14: =SUMIF('Torrance Pro Forma'!$B$8:$ED$8,'Annual Pro Forma'!M$8,'Torrance Pro Forma'!$B14:$ED14) -> 2692657.5
A15: Tenant 2 | C15: =SUMIF('Torrance Pro Forma'!$B$8:$ED$8,'Annual Pro Forma'!C$8,'Torrance Pro Forma'!$B15:$ED15) -> 0 | D15: =SUMIF('Torrance Pro Forma'!$B$8:$ED$8,'Annual Pro Forma'!D$8,'Torrance Pro Forma'!$B15:$ED15) -> 0 | E15: =SUMIF('Torrance Pro Forma'!$B$8:$ED$8,'Annual Pro Forma'!E$8,'Torrance Pro Forma'!$B15:$ED15) -> 0 | F15: =SUMIF('Torrance Pro Forma'!$B$8:$ED$8,'Annual Pro Forma'!F$8,'Torrance Pro Forma'!$B15:$ED15) -> 0 | G15: =SUMIF('Torrance Pro Forma'!$B$8:$ED$8,'Annual Pro Forma'!G$8,'Torrance Pro Forma'!$B15:$ED15) -> 0 | H15: =SUMIF('Torrance Pro Forma'!$B$8:$ED$8,'Annual Pro Forma'!H$8,'Torrance Pro Forma'!$B15:$ED15) -> 2438822.8 | I15: =SUMIF('Torrance Pro Forma'!$B$8:$ED$8,'Annual Pro Forma'!I$8,'Torrance Pro Forma'!$B15:$ED15) -> 2487599.3 | J15: =SUMIF('Torrance Pro Forma'!$B$8:$ED$8,'Annual Pro Forma'!J$8,'Torrance Pro Forma'!$B15:$ED15) -> 2537351.3 | ... M15: =SUMIF('Torrance Pro Forma'!$B$8:$ED$8,'Annual Pro Forma'!M$8,'Torrance Pro Forma'!$B15:$ED15) -> 2692657.5
A16: Potential Base Rent | C16: =SUMIF('Torrance Pro Forma'!$B$8:$ED$8,'Annual Pro Forma'!C$8,'Torrance Pro Forma'!$B16:$ED16) -> 1100000 | D16: =SUMIF('Torrance Pro Forma'!$B$8:$ED$8,'Annual Pro Forma'!D$8,'Torrance Pro Forma'!$B16:$ED16) -> 1122000 | E16: =SUMIF('Torrance Pro Forma'!$B$8:$ED$8,'Annual Pro Forma'!E$8,'Torrance Pro Forma'!$B16:$ED16) -> 1144440 | F16: =SUMIF('Torrance Pro Forma'!$B$8:$ED$8,'Annual Pro Forma'!F$8,'Torrance Pro Forma'!$B16:$ED16) -> 1167328.8 | G16: =SUMIF('Torrance Pro Forma'!$B$8:$ED$8,'Annual Pro Forma'!G$8,'Torrance Pro Forma'!$B16:$ED16) -> 0 | H16: =SUMIF('Torrance Pro Forma'!$B$8:$ED$8,'Annual Pro Forma'!H$8,'Torrance Pro Forma'!$B16:$ED16) -> 4877645.7 | I16: =SUMIF('Torrance Pro Forma'!$B$8:$ED$8,'Annual Pro Forma'!I$8,'Torrance Pro Forma'!$B16:$ED16) -> 4975198.6 | J16: =SUMIF('Torrance Pro Forma'!$B$8:$ED$8,'Annual Pro Forma'!J$8,'Torrance Pro Forma'!$B16:$ED16) -> 5074702.6 | ... M16: =SUMIF('Torrance Pro Forma'!$B$8:$ED$8,'Annual Pro Forma'!M$8,'Torrance Pro Forma'!$B16:$ED16) -> 5385314.9
A17: Vacancy / Turnover | C17: =SUMIF('Torrance Pro Forma'!$B$8:$ED$8,'Annual Pro Forma'!C$8,'Torrance Pro Forma'!$B17:$ED17) -> 0 | D17: =SUMIF('Torrance Pro Forma'!$B$8:$ED$8,'Annual Pro Forma'!D$8,'Torrance Pro Forma'!$B17:$ED17) -> 0 | E17: =SUMIF('Torrance Pro Forma'!$B$8:$ED$8,'Annual Pro Forma'!E$8,'Torrance Pro Forma'!$B17:$ED17) -> 0 | F17: =SUMIF('Torrance Pro Forma'!$B$8:$ED$8,'Annual Pro Forma'!F$8,'Torrance Pro Forma'!$B17:$ED17) -> 0 | G17: =SUMIF('Torrance Pro Forma'!$B$8:$ED$8,'Annual Pro Forma'!G$8,'Torrance Pro Forma'!$B17:$ED17) -> 0 | H17: =SUMIF('Torrance Pro Forma'!$B$8:$ED$8,'Annual Pro Forma'!H$8,'Torrance Pro Forma'!$B17:$ED17) -> 0 | I17: =SUMIF('Torrance Pro Forma'!$B$8:$ED$8,'Annual Pro Forma'!I$8,'Torrance Pro Forma'!$B17:$ED17) -> 0 | J17: =SUMIF('Torrance Pro Forma'!$B$8:$ED$8,'Annual Pro Forma'!J$8,'Torrance Pro Forma'!$B17:$ED17) -> 0 | ... M17: =SUMIF('Torrance Pro Forma'!$B$8:$ED$8,'Annual Pro Forma'!M$8,'Torrance Pro Forma'!$B17:$ED17) -> 0
A18: Security Deposit | C18: =SUMIF('Torrance Pro Forma'!$B$8:$ED$8,'Annual Pro Forma'!C$8,'Torrance Pro Forma'!$B18:$ED18) -> 0 | D18: =SUMIF('Torrance Pro Forma'!$B$8:$ED$8,'Annual Pro Forma'!D$8,'Torrance Pro Forma'!$B18:$ED18) -> 0 | E18: =SUMIF('Torrance Pro Forma'!$B$8:$ED$8,'Annual Pro Forma'!E$8,'Torrance Pro Forma'!$B18:$ED18) -> 0 | F18: =SUMIF('Torrance Pro Forma'!$B$8:$ED$8,'Annual Pro Forma'!F$8,'Torrance Pro Forma'!$B18:$ED18) -> 0 | G18: =SUMIF('Torrance Pro Forma'!$B$8:$ED$8,'Annual Pro Forma'!G$8,'Torrance Pro Forma'!$B18:$ED18) -> 0 | H18: =SUMIF('Torrance Pro Forma'!$B$8:$ED$8,'Annual Pro Forma'!H$8,'Torrance Pro Forma'!$B18:$ED18) -> 504166.67 | I18: =SUMIF('Torrance Pro Forma'!$B$8:$ED$8,'Annual Pro Forma'!I$8,'Torrance Pro Forma'!$B18:$ED18) -> 0 | J18: =SUMIF('Torrance Pro Forma'!$B$8:$ED$8,'Annual Pro Forma'!J$8,'Torrance Pro Forma'!$B18:$ED18) -> 0 | ... M18: =SUMIF('Torrance Pro Forma'!$B$8:$ED$8,'Annual Pro Forma'!M$8,'Torrance Pro Forma'!$B18:$ED18) -> 0
A19: Free Rent / Concessions | C19: =SUMIF('Torrance Pro Forma'!$B$8:$ED$8,'Annual Pro Forma'!C$8,'Torrance Pro Forma'!$B19:$ED19) -> 0 | D19: =SUMIF('Torrance Pro Forma'!$B$8:$ED$8,'Annual Pro Forma'!D$8,'Torrance Pro Forma'!$B19:$ED19) -> 0 | E19: =SUMIF('Torrance Pro Forma'!$B$8:$ED$8,'Annual Pro Forma'!E$8,'Torrance Pro Forma'!$B19:$ED19) -> 0 | F19: =SUMIF('Torrance Pro Forma'!$B$8:$ED$8,'Annual Pro Forma'!F$8,'Torrance Pro Forma'!$B19:$ED19) -> 0 | G19: =SUMIF('Torrance Pro Forma'!$B$8:$ED$8,'Annual Pro Forma'!G$8,'Torrance Pro Forma'!$B19:$ED19) -> 0 | H19: =SUMIF('Torrance Pro Forma'!$B$8:$ED$8,'Annual Pro Forma'!H$8,'Torrance Pro Forma'!$B19:$ED19) -> -57614.525 | I19: =SUMIF('Torrance Pro Forma'!$B$8:$ED$8,'Annual Pro Forma'!I$8,'Torrance Pro Forma'!$B19:$ED19) -> -57614.525 | J19: =SUMIF('Torrance Pro Forma'!$B$8:$ED$8,'Annual Pro Forma'!J$8,'Torrance Pro Forma'!$B19:$ED19) -> -57614.525 | ... M19: =SUMIF('Torrance Pro Forma'!$B$8:$ED$8,'Annual Pro Forma'!M$8,'Torrance Pro Forma'!$B19:$ED19) -> -57614.525
A20: Total Base Rent | C20: =SUMIF('Torrance Pro Forma'!$B$8:$ED$8,'Annual Pro Forma'!C$8,'Torrance Pro Forma'!$B20:$ED20) -> 1100000 | D20: =SUMIF('Torrance Pro Forma'!$B$8:$ED$8,'Annual Pro Forma'!D$8,'Torrance Pro Forma'!$B20:$ED20) -> 1122000 | E20: =SUMIF('Torrance Pro Forma'!$B$8:$ED$8,'Annual Pro Forma'!E$8,'Torrance Pro Forma'!$B20:$ED20) -> 1144440 | F20: =SUMIF('Torrance Pro Forma'!$B$8:$ED$8,'Annual Pro Forma'!F$8,'Torrance Pro Forma'!$B20:$ED20) -> 1167328.8 | G20: =SUMIF('Torrance Pro Forma'!$B$8:$ED$8,'Annual Pro Forma'!G$8,'Torrance Pro Forma'!$B20:$ED20) -> 0 | H20: =SUMIF('Torrance Pro Forma'!$B$8:$ED$8,'Annual Pro Forma'!H$8,'Torrance Pro Forma'!$B20:$ED20) -> 5324197.8 | I20: =SUMIF('Torrance Pro Forma'!$B$8:$ED$8,'Annual Pro Forma'!I$8,'Torrance Pro Forma'!$B20:$ED20) -> 4917584.1 | J20: =SUMIF('Torrance Pro Forma'!$B$8:$ED$8,'Annual Pro Forma'!J$8,'Torrance Pro Forma'!$B20:$ED20) -> 5017088 | ... M20: =SUMIF('Torrance Pro Forma'!$B$8:$ED$8,'Annual Pro Forma'!M$8,'Torrance Pro Forma'!$B20:$ED20) -> 5327700.4
A21: Total Rental Revenue | C21: =SUMIF('Torrance Pro Forma'!$B$8:$ED$8,'Annual Pro Forma'!C$8,'Torrance Pro Forma'!$B21:$ED21) -> 1100000 | D21: =SUMIF('Torrance Pro Forma'!$B$8:$ED$8,'Annual Pro Forma'!D$8,'Torrance Pro Forma'!$B21:$ED21) -> 1122000 | E21: =SUMIF('Torrance Pro Forma'!$B$8:$ED$8,'Annual Pro Forma'!E$8,'Torrance Pro Forma'!$B21:$ED21) -> 1144440 | F21: =SUMIF('Torrance Pro Forma'!$B$8:$ED$8,'Annual Pro Forma'!F$8,'Torrance Pro Forma'!$B21:$ED21) -> 1167328.8 | G21: =SUMIF('Torrance Pro Forma'!$B$8:$ED$8,'Annual Pro Forma'!G$8,'Torrance Pro Forma'!$B21:$ED21) -> 0 | H21: =SUMIF('Torrance Pro Forma'!$B$8:$ED$8,'Annual Pro Forma'!H$8,'Torrance Pro Forma'!$B21:$ED21) -> 5324197.8 | I21: =SUMIF('Torrance Pro Forma'!$B$8:$ED$8,'Annual Pro Forma'!I$8,'Torrance Pro Forma'!$B21:$ED21) -> 4917584.1 | J21: =SUMIF('Torrance Pro Forma'!$B$8:$ED$8,'Annual Pro Forma'!J$8,'Torrance Pro Forma'!$B21:$ED21) -> 5017088 | ... M21: =SUMIF('Torrance Pro Forma'!$B$8:$ED$8,'Annual Pro Forma'!M$8,'Torrance Pro Forma'!$B21:$ED21) -> 5327700.4
C22: =SUMIF('Torrance Pro Forma'!$B$8:$ED$8,'Annual Pro Forma'!C$8,'Torrance Pro Forma'!$B22:$ED22) -> 0 | D22: =SUMIF('Torrance Pro Forma'!$B$8:$ED$8,'Annual Pro Forma'!D$8,'Torrance Pro Forma'!$B22:$ED22) -> 0 | E22: =SUMIF('Torrance Pro Forma'!$B$8:$ED$8,'Annual Pro Forma'!E$8,'Torrance Pro Forma'!$B22:$ED22) -> 0 | F22: =SUMIF('Torrance Pro Forma'!$B$8:$ED$8,'Annual Pro Forma'!F$8,'Torrance Pro Forma'!$B22:$ED22) -> 0 | G22: =SUMIF('Torrance Pro Forma'!$B$8:$ED$8,'Annual Pro Forma'!G$8,'Torrance Pro Forma'!$B22:$ED22) -> 0 | H22: =SUMIF('Torrance Pro Forma'!$B$8:$ED$8,'Annual Pro Forma'!H$8,'Torrance Pro Forma'!$B22:$ED22) -> 0 | I22: =SUMIF('Torrance Pro Forma'!$B$8:$ED$8,'Annual Pro Forma'!I$8,'Torrance Pro Forma'!$B22:$ED22) -> 0 | J22: =SUMIF('Torrance Pro Forma'!$B$8:$ED$8,'Annual Pro Forma'!J$8,'Torrance Pro Forma'!$B22:$ED22) -> 0 | ... M22: =SUMIF('Torrance Pro Forma'!$B$8:$ED$8,'Annual Pro Forma'!M$8,'Torrance Pro Forma'!$B22:$ED22) -> 0
A23: Other Tenant Revenue | C23: =SUMIF('Torrance Pro Forma'!$B$8:$ED$8,'Annual Pro Forma'!C$8,'Torrance Pro Forma'!$B23:$ED23) -> 0 | D23: =SUMIF('Torrance Pro Forma'!$B$8:$ED$8,'Annual Pro Forma'!D$8,'Torrance Pro Forma'!$B23:$ED23) -> 0 | E23: =SUMIF('Torrance Pro Forma'!$B$8:$ED$8,'Annual Pro Forma'!E$8,'Torrance Pro Forma'!$B23:$ED23) -> 0 | F23: =SUMIF('Torrance Pro Forma'!$B$8:$ED$8,'Annual Pro Forma'!F$8,'Torrance Pro Forma'!$B23:$ED23) -> 0 | G23: =SUMIF('Torrance Pro Forma'!$B$8:$ED$8,'Annual Pro Forma'!G$8,'Torrance Pro Forma'!$B23:$ED23) -> 0 | H23: =SUMIF('Torrance Pro Forma'!$B$8:$ED$8,'Annual Pro Forma'!H$8,'Torrance Pro Forma'!$B23:$ED23) -> 0 | I23: =SUMIF('Torrance Pro Forma'!$B$8:$ED$8,'Annual Pro Forma'!I$8,'Torrance Pro Forma'!$B23:$ED23) -> 0 | J23: =SUMIF('Torrance Pro Forma'!$B$8:$ED$8,'Annual Pro Forma'!J$8,'Torrance Pro Forma'!$B23:$ED23) -> 0 | ... M23: =SUMIF('Torrance Pro Forma'!$B$8:$ED$8,'Annual Pro Forma'!M$8,'Torrance Pro Forma'!$B23:$ED23) -> 0
A24: Utilities | C24: =SUMIF('Torrance Pro Forma'!$B$8:$ED$8,'Annual Pro Forma'!C$8,'Torrance Pro Forma'!$B24:$ED24) -> 15000 | D24: =SUMIF('Torrance Pro Forma'!$B$8:$ED$8,'Annual Pro Forma'!D$8,'Torrance Pro Forma'!$B24:$ED24) -> 15000 | E24: =SUMIF('Torrance Pro Forma'!$B$8:$ED$8,'Annual Pro Forma'!E$8,'Torrance Pro Forma'!$B24:$ED24) -> 15000 | F24: =SUMIF('Torrance Pro Forma'!$B$8:$ED$8,'Annual Pro Forma'!F$8,'Torrance Pro Forma'!$B24:$ED24) -> 15000 | G24: =SUMIF('Torrance Pro Forma'!$B$8:$ED$8,'Annual Pro Forma'!G$8,'Torrance Pro Forma'!$B24:$ED24) -> 0 | H24: =SUMIF('Torrance Pro Forma'!$B$8:$ED$8,'Annual Pro Forma'!H$8,'Torrance Pro Forma'!$B24:$ED24) -> 15000 | I24: =SUMIF('Torrance Pro Forma'!$B$8:$ED$8,'Annual Pro Forma'!I$8,'Torrance Pro Forma'!$B24:$ED24) -> 15000 | J24: =SUMIF('Torrance Pro Forma'!$B$8:$ED$8,'Annual Pro Forma'!J$8,'Torrance Pro Forma'!$B24:$ED24) -> 15000 | ... M24: =SUMIF('Torrance Pro Forma'!$B$8:$ED$8,'Annual Pro Forma'!M$8,'Torrance Pro Forma'!$B24:$ED24) -> 15000
A25: Repairs & Maintenance | C25: =SUMIF('Torrance Pro Forma'!$B$8:$ED$8,'Annual Pro Forma'!C$8,'Torrance Pro Forma'!$B25:$ED25) -> 15000 | D25: =SUMIF('Torrance Pro Forma'!$B$8:$ED$8,'Annual Pro Forma'!D$8,'Torrance Pro Forma'!$B25:$ED25) -> 15450 | E25: =SUMIF('Torrance Pro Forma'!$B$8:$ED$8,'Annual Pro Forma'!E$8,'Torrance Pro Forma'!$B25:$ED25) -> 15913.5 | F25: =SUMIF('Torrance Pro Forma'!$B$8:$ED$8,'Annual Pro Forma'!F$8,'Torrance Pro Forma'!$B25:$ED25) -> 16390.905 | G25: =SUMIF('Torrance Pro Forma'!$B$8:$ED$8,'Annual Pro Forma'!G$8,'Torrance Pro Forma'!$B25:$ED25) -> 0 | H25: =SUMIF('Torrance Pro Forma'!$B$8:$ED$8,'Annual Pro Forma'!H$8,'Torrance Pro Forma'!$B25:$ED25) -> 17389.111 | I25: =SUMIF('Torrance Pro Forma'!$B$8:$ED$8,'Annual Pro Forma'!I$8,'Torrance Pro Forma'!$B25:$ED25) -> 17910.784 | J25: =SUMIF('Torrance Pro Forma'!$B$8:$ED$8,'Annual Pro Forma'!J$8,'Torrance Pro Forma'!$B25:$ED25) -> 18448.108 | ... M25: =SUMIF('Torrance Pro Forma'!$B$8:$ED$8,'Annual Pro Forma'!M$8,'Torrance Pro Forma'!$B25:$ED25) -> 20158.746
A26: Insurance | C26: =SUMIF('Torrance Pro Forma'!$B$8:$ED$8,'Annual Pro Forma'!C$8,'Torrance Pro Forma'!$B26:$ED26) -> 5000 | D26: =SUMIF('Torrance Pro Forma'!$B$8:$ED$8,'Annual Pro Forma'!D$8,'Torrance Pro Forma'!$B26:$ED26) -> 5150 | E26: =SUMIF('Torrance Pro Forma'!$B$8:$ED$8,'Annual Pro Forma'!E$8,'Torrance Pro Forma'!$B26:$ED26) -> 5304.5 | F26: =SUMIF('Torrance Pro Forma'!$B$8:$ED$8,'Annual Pro Forma'!F$8,'Torrance Pro Forma'!$B26:$ED26) -> 5463.635 | G26: =SUMIF('Torrance Pro Forma'!$B$8:$ED$8,'Annual Pro Forma'!G$8,'Torrance Pro Forma'!$B26:$ED26) -> 0 | H26: =SUMIF('Torrance Pro Forma'!$B$8:$ED$8,'Annual Pro Forma'!H$8,'Torrance Pro Forma'!$B26:$ED26) -> 5796.3704 | I26: =SUMIF('Torrance Pro Forma'!$B$8:$ED$8,'Annual Pro Forma'!I$8,'Torrance Pro Forma'!$B26:$ED26) -> 5970.2615 | J26: =SUMIF('Torrance Pro Forma'!$B$8:$ED$8,'Annual Pro Forma'!J$8,'Torrance Pro Forma'!$B26:$ED26) -> 6149.3693 | ... M26: =SUMIF('Torrance Pro Forma'!$B$8:$ED$8,'Annual Pro Forma'!M$8,'Torrance Pro Forma'!$B26:$ED26) -> 6719.5819
A27: Property Taxes | C27: =SUMIF('Torrance Pro Forma'!$B$8:$ED$8,'Annual Pro Forma'!C$8,'Torrance Pro Forma'!$B27:$ED27) -> 0 | D27: =SUMIF('Torrance Pro Forma'!$B$8:$ED$8,'Annual Pro Forma'!D$8,'Torrance Pro Forma'!$B27:$ED27) -> 0 | E27: =SUMIF('Torrance Pro Forma'!$B$8:$ED$8,'Annual Pro Forma'!E$8,'Torrance Pro Forma'!$B27:$ED27) -> 0 | F27: =SUMIF('Torrance Pro Forma'!$B$8:$ED$8,'Annual Pro Forma'!F$8,'Torrance Pro Forma'!$B27:$ED27) -> 0 | G27: =SUMIF('Torrance Pro Forma'!$B$8:$ED$8,'Annual Pro Forma'!G$8,'Torrance Pro Forma'!$B27:$ED27) -> 0 | H27: =SUMIF('Torrance Pro Forma'!$B$8:$ED$8,'Annual Pro Forma'!H$8,'Torrance Pro Forma'!$B27:$ED27) -> 213175.19 | I27: =SUMIF('Torrance Pro Forma'!$B$8:$ED$8,'Annual Pro Forma'!I$8,'Torrance Pro Forma'!$B27:$ED27) -> 217438.69 | J27: =SUMIF('Torrance Pro Forma'!$B$8:$ED$8,'Annual Pro Forma'!J$8,'Torrance Pro Forma'!$B27:$ED27) -> 221787.46 | ... M27: =SUMIF('Torrance Pro Forma'!$B$8:$ED$8,'Annual Pro Forma'!M$8,'Torrance Pro Forma'!$B27:$ED27) -> 235362.63
A28: Total Expense Recoveries | C28: =SUMIF('Torrance Pro Forma'!$B$8:$ED$8,'Annual Pro Forma'!C$8,'Torrance Pro Forma'!$B28:$ED28) -> 35000 | D28: =SUMIF('Torrance Pro Forma'!$B$8:$ED$8,'Annual Pro Forma'!D$8,'Torrance Pro Forma'!$B28:$ED28) -> 35600 | E28: =SUMIF('Torrance Pro Forma'!$B$8:$ED$8,'Annual Pro Forma'!E$8,'Torrance Pro Forma'!$B28:$ED28) -> 36218 | F28: =SUMIF('Torrance Pro Forma'!$B$8:$ED$8,'Annual Pro Forma'!F$8,'Torrance Pro Forma'!$B28:$ED28) -> 36854.54 | G28: =SUMIF('Torrance Pro Forma'!$B$8:$ED$8,'Annual Pro Forma'!G$8,'Torrance Pro Forma'!$B28:$ED28) -> 0 | H28: =SUMIF('Torrance Pro Forma'!$B$8:$ED$8,'Annual Pro Forma'!H$8,'Torrance Pro Forma'!$B28:$ED28) -> 251360.67 | I28: =SUMIF('Torrance Pro Forma'!$B$8:$ED$8,'Annual Pro Forma'!I$8,'Torrance Pro Forma'!$B28:$ED28) -> 256319.74 | J28: =SUMIF('Torrance Pro Forma'!$B$8:$ED$8,'Annual Pro Forma'!J$8,'Torrance Pro Forma'!$B28:$ED28) -> 261384.94 | ... M28: =SUMIF('Torrance Pro Forma'!$B$8:$ED$8,'Annual Pro Forma'!M$8,'Torrance Pro Forma'!$B28:$ED28) -> 277240.96
A29: Total Other Tenant Revenue | C29: =SUMIF('Torrance Pro Forma'!$B$8:$ED$8,'Annual Pro Forma'!C$8,'Torrance Pro Forma'!$B29:$ED29) -> 35000 | D29: =SUMIF('Torrance Pro Forma'!$B$8:$ED$8,'Annual Pro Forma'!D$8,'Torrance Pro Forma'!$B29:$ED29) -> 35600 | E29: =SUMIF('Torrance Pro Forma'!$B$8:$ED$8,'Annual Pro Forma'!E$8,'Torrance Pro Forma'!$B29:$ED29) -> 36218 | F29: =SUMIF('Torrance Pro Forma'!$B$8:$ED$8,'Annual Pro Forma'!F$8,'Torrance Pro Forma'!$B29:$ED29) -> 36854.54 | G29: =SUMIF('Torrance Pro Forma'!$B$8:$ED$8,'Annual Pro Forma'!G$8,'Torrance Pro Forma'!$B29:$ED29) -> 0 | H29: =SUMIF('Torrance Pro Forma'!$B$8:$ED$8,'Annual Pro Forma'!H$8,'Torrance Pro Forma'!$B29:$ED29) -> 251360.67 | I29: =SUMIF('Torrance Pro Forma'!$B$8:$ED$8,'Annual Pro Forma'!I$8,'Torrance Pro Forma'!$B29:$ED29) -> 256319.74 | J29: =SUMIF('Torrance Pro Forma'!$B$8:$ED$8,'Annual Pro Forma'!J$8,'Torrance Pro Forma'!$B29:$ED29) -> 261384.94 | ... M29: =SUMIF('Torrance Pro Forma'!$B$8:$ED$8,'Annual Pro Forma'!M$8,'Torrance Pro Forma'!$B29:$ED29) -> 277240.96
C30: =SUMIF('Torrance Pro Forma'!$B$8:$ED$8,'Annual Pro Forma'!C$8,'Torrance Pro Forma'!$B30:$ED30) -> 0 | D30: =SUMIF('Torrance Pro Forma'!$B$8:$ED$8,'Annual Pro Forma'!D$8,'Torrance Pro Forma'!$B30:$ED30) -> 0 | E30: =SUMIF('Torrance Pro Forma'!$B$8:$ED$8,'Annual Pro Forma'!E$8,'Torrance Pro Forma'!$B30:$ED30) -> 0 | F30: =SUMIF('Torrance Pro Forma'!$B$8:$ED$8,'Annual Pro Forma'!F$8,'Torrance Pro Forma'!$B30:$ED30) -> 0 | G30: =SUMIF('Torrance Pro Forma'!$B$8:$ED$8,'Annual Pro Forma'!G$8,'Torrance Pro Forma'!$B30:$ED30) -> 0 | H30: =SUMIF('Torrance Pro Forma'!$B$8:$ED$8,'Annual Pro Forma'!H$8,'Torrance Pro Forma'!$B30:$ED30) -> 0 | I30: =SUMIF('Torrance Pro Forma'!$B$8:$ED$8,'Annual Pro Forma'!I$8,'Torrance Pro Forma'!$B30:$ED30) -> 0 | J30: =SUMIF('Torrance Pro Forma'!$B$8:$ED$8,'Annual Pro Forma'!J$8,'Torrance Pro Forma'!$B30:$ED30) -> 0 | ... M30: =SUMIF('Torrance Pro Forma'!$B$8:$ED$8,'Annual Pro Forma'!M$8,'Torrance Pro Forma'!$B30:$ED30) -> 0
A31: Total Tenant Revenue | C31: =SUMIF('Torrance Pro Forma'!$B$8:$ED$8,'Annual Pro Forma'!C$8,'Torrance Pro Forma'!$B31:$ED31) -> 1135000 | D31: =SUMIF('Torrance Pro Forma'!$B$8:$ED$8,'Annual Pro Forma'!D$8,'Torrance Pro Forma'!$B31:$ED31) -> 1157600 | E31: =SUMIF('Torrance Pro Forma'!$B$8:$ED$8,'Annual Pro Forma'!E$8,'Torrance Pro Forma'!$B31:$ED31) -> 1180658 | F31: =SUMIF('Torrance Pro Forma'!$B$8:$ED$8,'Annual Pro Forma'!F$8,'Torrance Pro Forma'!$B31:$ED31) -> 1204183.3 | G31: =SUMIF('Torrance Pro Forma'!$B$8:$ED$8,'Annual Pro Forma'!G$8,'Torrance Pro Forma'!$B31:$ED31) -> 0 | H31: =SUMIF('Torrance Pro Forma'!$B$8:$ED$8,'Annual Pro Forma'!H$8,'Torrance Pro Forma'!$B31:$ED31) -> 5575558.5 | I31: =SUMIF('Torrance Pro Forma'!$B$8:$ED$8,'Annual Pro Forma'!I$8,'Torrance Pro Forma'!$B31:$ED31) -> 5173903.8 | J31: =SUMIF('Torrance Pro Forma'!$B$8:$ED$8,'Annual Pro Forma'!J$8,'Torrance Pro Forma'!$B31:$ED31) -> 5278473 | ... M31: =SUMIF('Torrance Pro Forma'!$B$8:$ED$8,'Annual Pro Forma'!M$8,'Torrance Pro Forma'!$B31:$ED31) -> 5604941.4
C32: =SUMIF('Torrance Pro Forma'!$B$8:$ED$8,'Annual Pro Forma'!C$8,'Torrance Pro Forma'!$B32:$ED32) -> 0 | D32: =SUMIF('Torrance Pro Forma'!$B$8:$ED$8,'Annual Pro Forma'!D$8,'Torrance Pro Forma'!$B32:$ED32) -> 0 | E32: =SUMIF('Torrance Pro Forma'!$B$8:$ED$8,'Annual Pro Forma'!E$8,'Torrance Pro Forma'!$B32:$ED32) -> 0 | F32: =SUMIF('Torrance Pro Forma'!$B$8:$ED$8,'Annual Pro Forma'!F$8,'Torrance Pro Forma'!$B32:$ED32) -> 0 | G32: =SUMIF('Torrance Pro Forma'!$B$8:$ED$8,'Annual Pro Forma'!G$8,'Torrance Pro Forma'!$B32:$ED32) -> 0 | H32: =SUMIF('Torrance Pro Forma'!$B$8:$ED$8,'Annual Pro Forma'!H$8,'Torrance Pro Forma'!$B32:$ED32) -> 0 | I32: =SUMIF('Torrance Pro Forma'!$B$8:$ED$8,'Annual Pro Forma'!I$8,'Torrance Pro Forma'!$B32:$ED32) -> 0 | J32: =SUMIF('Torrance Pro Forma'!$B$8:$ED$8,'Annual Pro Forma'!J$8,'Torrance Pro Forma'!$B32:$ED32) -> 0 | ... M32: =SUMIF('Torrance Pro Forma'!$B$8:$ED$8,'Annual Pro Forma'!M$8,'Torrance Pro Forma'!$B32:$ED32) -> 0
A33: Other Income | C33: =SUMIF('Torrance Pro Forma'!$B$8:$ED$8,'Annual Pro Forma'!C$8,'Torrance Pro Forma'!$B33:$ED33) -> 0 | D33: =SUMIF('Torrance Pro Forma'!$B$8:$ED$8,'Annual Pro Forma'!D$8,'Torrance Pro Forma'!$B33:$ED33) -> 0 | E33: =SUMIF('Torrance Pro Forma'!$B$8:$ED$8,'Annual Pro Forma'!E$8,'Torrance Pro Forma'!$B33:$ED33) -> 0 | F33: =SUMIF('Torrance Pro Forma'!$B$8:$ED$8,'Annual Pro Forma'!F$8,'Torrance Pro Forma'!$B33:$ED33) -> 0 | G33: =SUMIF('Torrance Pro Forma'!$B$8:$ED$8,'Annual Pro Forma'!G$8,'Torrance Pro Forma'!$B33:$ED33) -> 0 | H33: =SUMIF('Torrance Pro Forma'!$B$8:$ED$8,'Annual Pro Forma'!H$8,'Torrance Pro Forma'!$B33:$ED33) -> 0 | I33: =SUMIF('Torrance Pro Forma'!$B$8:$ED$8,'Annual Pro Forma'!I$8,'Torrance Pro Forma'!$B33:$ED33) -> 0 | J33: =SUMIF('Torrance Pro Forma'!$B$8:$ED$8,'Annual Pro Forma'!J$8,'Torrance Pro Forma'!$B33:$ED33) -> 0 | ... M33: =SUMIF('Torrance Pro Forma'!$B$8:$ED$8,'Annual Pro Forma'!M$8,'Torrance Pro Forma'!$B33:$ED33) -> 0
A34: Parking Income | C34: =SUMIF('Torrance Pro Forma'!$B$8:$ED$8,'Annual Pro Forma'!C$8,'Torrance Pro Forma'!$B34:$ED34) -> 190740 | D34: =SUMIF('Torrance Pro Forma'!$B$8:$ED$8,'Annual Pro Forma'!D$8,'Torrance Pro Forma'!$B34:$ED34) -> 194554.8 | E34: =SUMIF('Torrance Pro Forma'!$B$8:$ED$8,'Annual Pro Forma'!E$8,'Torrance Pro Forma'!$B34:$ED34) -> 198445.9 | F34: =SUMIF('Torrance Pro Forma'!$B$8:$ED$8,'Annual Pro Forma'!F$8,'Torrance Pro Forma'!$B34:$ED34) -> 202414.81 | G34: =SUMIF('Torrance Pro Forma'!$B$8:$ED$8,'Annual Pro Forma'!G$8,'Torrance Pro Forma'!$B34:$ED34) -> 0 | H34: =SUMIF('Torrance Pro Forma'!$B$8:$ED$8,'Annual Pro Forma'!H$8,'Torrance Pro Forma'!$B34:$ED34) -> 210592.37 | I34: =SUMIF('Torrance Pro Forma'!$B$8:$ED$8,'Annual Pro Forma'!I$8,'Torrance Pro Forma'!$B34:$ED34) -> 214804.22 | J34: =SUMIF('Torrance Pro Forma'!$B$8:$ED$8,'Annual Pro Forma'!J$8,'Torrance Pro Forma'!$B34:$ED34) -> 219100.3 | ... M34: =SUMIF('Torrance Pro Forma'!$B$8:$ED$8,'Annual Pro Forma'!M$8,'Torrance Pro Forma'!$B34:$ED34) -> 232511
A35: Total Other Income | C35: =SUMIF('Torrance Pro Forma'!$B$8:$ED$8,'Annual Pro Forma'!C$8,'Torrance Pro Forma'!$B35:$ED35) -> 190740 | D35: =SUMIF('Torrance Pro Forma'!$B$8:$ED$8,'Annual Pro Forma'!D$8,'Torrance Pro Forma'!$B35:$ED35) -> 194554.8 | E35: =SUMIF('Torrance Pro Forma'!$B$8:$ED$8,'Annual Pro Forma'!E$8,'Torrance Pro Forma'!$B35:$ED35) -> 198445.9 | F35: =SUMIF('Torrance Pro Forma'!$B$8:$ED$8,'Annual Pro Forma'!F$8,'Torrance Pro Forma'!$B35:$ED35) -> 202414.81 | G35: =SUMIF('Torrance Pro Forma'!$B$8:$ED$8,'Annual Pro Forma'!G$8,'Torrance Pro Forma'!$B35:$ED35) -> 0 | H35: =SUMIF('Torrance Pro Forma'!$B$8:$ED$8,'Annual Pro Forma'!H$8,'Torrance Pro Forma'!$B35:$ED35) -> 210592.37 | I35: =SUMIF('Torrance Pro Forma'!$B$8:$ED$8,'Annual Pro Forma'!I$8,'Torrance Pro Forma'!$B35:$ED35) -> 214804.22 | J35: =SUMIF('Torrance Pro Forma'!$B$8:$ED$8,'Annual Pro Forma'!J$8,'Torrance Pro Forma'!$B35:$ED35) -> 219100.3 | ... M35: =SUMIF('Torrance Pro Forma'!$B$8:$ED$8,'Annual Pro Forma'!M$8,'Torrance Pro Forma'!$B35:$ED35) -> 232511
C36: =SUMIF('Torrance Pro Forma'!$B$8:$ED$8,'Annual Pro Forma'!C$8,'Torrance Pro Forma'!$B36:$ED36) -> 0 | D36: =SUMIF('Torrance Pro Forma'!$B$8:$ED$8,'Annual Pro Forma'!D$8,'Torrance Pro Forma'!$B36:$ED36) -> 0 | E36: =SUMIF('Torrance Pro Forma'!$B$8:$ED$8,'Annual Pro Forma'!E$8,'Torrance Pro Forma'!$B36:$ED36) -> 0 | F36: =SUMIF('Torrance Pro Forma'!$B$8:$ED$8,'Annual Pro Forma'!F$8,'Torrance Pro Forma'!$B36:$ED36) -> 0 | G36: =SUMIF('Torrance Pro Forma'!$B$8:$ED$8,'Annual Pro Forma'!G$8,'Torrance Pro Forma'!$B36:$ED36) -> 0 | H36: =SUMIF('Torrance Pro Forma'!$B$8:$ED$8,'Annual Pro Forma'!H$8,'Torrance Pro Forma'!$B36:$ED36) -> 0 | I36: =SUMIF('Torrance Pro Forma'!$B$8:$ED$8,'Annual Pro Forma'!I$8,'Torrance Pro Forma'!$B36:$ED36) -> 0 | J36: =SUMIF('Torrance Pro Forma'!$B$8:$ED$8,'Annual Pro Forma'!J$8,'Torrance Pro Forma'!$B36:$ED36) -> 0 | ... M36: =SUMIF('Torrance Pro Forma'!$B$8:$ED$8,'Annual Pro Forma'!M$8,'Torrance Pro Forma'!$B36:$ED36) -> 0
A37: Potential Gross Revenue | C37: =SUMIF('Torrance Pro Forma'!$B$8:$ED$8,'Annual Pro Forma'!C$8,'Torrance Pro Forma'!$B37:$ED37) -> 1325740 | D37: =SUMIF('Torrance Pro Forma'!$B$8:$ED$8,'Annual Pro Forma'!D$8,'Torrance Pro Forma'!$B37:$ED37) -> 1352154.8 | E37: =SUMIF('Torrance Pro Forma'!$B$8:$ED$8,'Annual Pro Forma'!E$8,'Torrance Pro Forma'!$B37:$ED37) -> 1379103.9 | F37: =SUMIF('Torrance Pro Forma'!$B$8:$ED$8,'Annual Pro Forma'!F$8,'Torrance Pro Forma'!$B37:$ED37) -> 1406598.2 | G37: =SUMIF('Torrance Pro Forma'!$B$8:$ED$8,'Annual Pro Forma'!G$8,'Torrance Pro Forma'!$B37:$ED37) -> 0 | H37: =SUMIF('Torrance Pro Forma'!$B$8:$ED$8,'Annual Pro Forma'!H$8,'Torrance Pro Forma'!$B37:$ED37) -> 5786150.8 | I37: =SUMIF('Torrance Pro Forma'!$B$8:$ED$8,'Annual Pro Forma'!I$8,'Torrance Pro Forma'!$B37:$ED37) -> 5388708 | J37: =SUMIF('Torrance Pro Forma'!$B$8:$ED$8,'Annual Pro Forma'!J$8,'Torrance Pro Forma'!$B37:$ED37) -> 5497573.3 | ... M37: =SUMIF('Torrance Pro Forma'!$B$8:$ED$8,'Annual Pro Forma'!M$8,'Torrance Pro Forma'!$B37:$ED37) -> 5837452.4
C38: =SUMIF('Torrance Pro Forma'!$B$8:$ED$8,'Annual Pro Forma'!C$8,'Torrance Pro Forma'!$B38:$ED38) -> 0 | D38: =SUMIF('Torrance Pro Forma'!$B$8:$ED$8,'Annual Pro Forma'!D$8,'Torrance Pro Forma'!$B38:$ED38) -> 0 | E38: =SUMIF('Torrance Pro Forma'!$B$8:$ED$8,'Annual Pro Forma'!E$8,'Torrance Pro Forma'!$B38:$ED38) -> 0 | F38: =SUMIF('Torrance Pro Forma'!$B$8:$ED$8,'Annual Pro Forma'!F$8,'Torrance Pro Forma'!$B38:$ED38) -> 0 | G38: =SUMIF('Torrance Pro Forma'!$B$8:$ED$8,'Annual Pro Forma'!G$8,'Torrance Pro Forma'!$B38:$ED38) -> 0 | H38: =SUMIF('Torrance Pro Forma'!$B$8:$ED$8,'Annual Pro Forma'!H$8,'Torrance Pro Forma'!$B38:$ED38) -> 0 | I38: =SUMIF('Torrance Pro Forma'!$B$8:$ED$8,'Annual Pro Forma'!I$8,'Torrance Pro Forma'!$B38:$ED38) -> 0 | J38: =SUMIF('Torrance Pro Forma'!$B$8:$ED$8,'Annual Pro Forma'!J$8,'Torrance Pro Forma'!$B38:$ED38) -> 0 | ... M38: =SUMIF('Torrance Pro Forma'!$B$8:$ED$8,'Annual Pro Forma'!M$8,'Torrance Pro Forma'!$B38:$ED38) -> 0
A39: General Vacancy & Credit Loss | C39: =SUMIF('Torrance Pro Forma'!$B$8:$ED$8,'Annual Pro Forma'!C$8,'Torrance Pro Forma'!$B39:$ED39) -> 0 | D39: =SUMIF('Torrance Pro Forma'!$B$8:$ED$8,'Annual Pro Forma'!D$8,'Torrance Pro Forma'!$B39:$ED39) -> 0 | E39: =SUMIF('Torrance Pro Forma'!$B$8:$ED$8,'Annual Pro Forma'!E$8,'Torrance Pro Forma'!$B39:$ED39) -> 0 | F39: =SUMIF('Torrance Pro Forma'!$B$8:$ED$8,'Annual Pro Forma'!F$8,'Torrance Pro Forma'!$B39:$ED39) -> 0 | G39: =SUMIF('Torrance Pro Forma'!$B$8:$ED$8,'Annual Pro Forma'!G$8,'Torrance Pro Forma'!$B39:$ED39) -> 0 | H39: =SUMIF('Torrance Pro Forma'!$B$8:$ED$8,'Annual Pro Forma'!H$8,'Torrance Pro Forma'!$B39:$ED39) -> 0 | I39: =SUMIF('Torrance Pro Forma'!$B$8:$ED$8,'Annual Pro Forma'!I$8,'Torrance Pro Forma'!$B39:$ED39) -> 0 | J39: =SUMIF('Torrance Pro Forma'!$B$8:$ED$8,'Annual Pro Forma'!J$8,'Torrance Pro Forma'!$B39:$ED39) -> 0 | ... M39: =SUMIF('Torrance Pro Forma'!$B$8:$ED$8,'Annual Pro Forma'!M$8,'Torrance Pro Forma'!$B39:$ED39) -> 0
A40: Vacancy & L2L | C40: =SUMIF('Torrance Pro Forma'!$B$8:$ED$8,'Annual Pro Forma'!C$8,'Torrance Pro Forma'!$B40:$ED40) -> 0 | D40: =SUMIF('Torrance Pro Forma'!$B$8:$ED$8,'Annual Pro Forma'!D$8,'Torrance Pro Forma'!$B40:$ED40) -> 0 | E40: =SUMIF('Torrance Pro Forma'!$B$8:$ED$8,'Annual Pro Forma'!E$8,'Torrance Pro Forma'!$B40:$ED40) -> 0 | F40: =SUMIF('Torrance Pro Forma'!$B$8:$ED$8,'Annual Pro Forma'!F$8,'Torrance Pro Forma'!$B40:$ED40) -> 0 | G40: =SUMIF('Torrance Pro Forma'!$B$8:$ED$8,'Annual Pro Forma'!G$8,'Torrance Pro Forma'!$B40:$ED40) -> 0 | H40: =SUMIF('Torrance Pro Forma'!$B$8:$ED$8,'Annual Pro Forma'!H$8,'Torrance Pro Forma'!$B40:$ED40) -> 0 | I40: =SUMIF('Torrance Pro Forma'!$B$8:$ED$8,'Annual Pro Forma'!I$8,'Torrance Pro Forma'!$B40:$ED40) -> 0 | J40: =SUMIF('Torrance Pro Forma'!$B$8:$ED$8,'Annual Pro Forma'!J$8,'Torrance Pro Forma'!$B40:$ED40) -> 0 | ... M40: =SUMIF('Torrance Pro Forma'!$B$8:$ED$8,'Annual Pro Forma'!M$8,'Torrance Pro Forma'!$B40:$ED40) -> 0
A41: Total Vacancy & Credit Loss | C41: =SUMIF('Torrance Pro Forma'!$B$8:$ED$8,'Annual Pro Forma'!C$8,'Torrance Pro Forma'!$B41:$ED41) -> 0 | D41: =SUMIF('Torrance Pro Forma'!$B$8:$ED$8,'Annual Pro Forma'!D$8,'Torrance Pro Forma'!$B41:$ED41) -> 0 | E41: =SUMIF('Torrance Pro Forma'!$B$8:$ED$8,'Annual Pro Forma'!E$8,'Torrance Pro Forma'!$B41:$ED41) -> 0 | F41: =SUMIF('Torrance Pro Forma'!$B$8:$ED$8,'Annual Pro Forma'!F$8,'Torrance Pro Forma'!$B41:$ED41) -> 0 | G41: =SUMIF('Torrance Pro Forma'!$B$8:$ED$8,'Annual Pro Forma'!G$8,'Torrance Pro Forma'!$B41:$ED41) -> 0 | H41: =SUMIF('Torrance Pro Forma'!$B$8:$ED$8,'Annual Pro Forma'!H$8,'Torrance Pro Forma'!$B41:$ED41) -> 0 | I41: =SUMIF('Torrance Pro Forma'!$B$8:$ED$8,'Annual Pro Forma'!I$8,'Torrance Pro Forma'!$B41:$ED41) -> 0 | J41: =SUMIF('Torrance Pro Forma'!$B$8:$ED$8,'Annual Pro Forma'!J$8,'Torrance Pro Forma'!$B41:$ED41) -> 0 | ... M41: =SUMIF('Torrance Pro Forma'!$B$8:$ED$8,'Annual Pro Forma'!M$8,'Torrance Pro Forma'!$B41:$ED41) -> 0
C42: =SUMIF('Torrance Pro Forma'!$B$8:$ED$8,'Annual Pro Forma'!C$8,'Torrance Pro Forma'!$B42:$ED42) -> 0 | D42: =SUMIF('Torrance Pro Forma'!$B$8:$ED$8,'Annual Pro Forma'!D$8,'Torrance Pro Forma'!$B42:$ED42) -> 0 | E42: =SUMIF('Torrance Pro Forma'!$B$8:$ED$8,'Annual Pro Forma'!E$8,'Torrance Pro Forma'!$B42:$ED42) -> 0 | F42: =SUMIF('Torrance Pro Forma'!$B$8:$ED$8,'Annual Pro Forma'!F$8,'Torrance Pro Forma'!$B42:$ED42) -> 0 | G42: =SUMIF('Torrance Pro Forma'!$B$8:$ED$8,'Annual Pro Forma'!G$8,'Torrance Pro Forma'!$B42:$ED42) -> 0 | H42: =SUMIF('Torrance Pro Forma'!$B$8:$ED$8,'Annual Pro Forma'!H$8,'Torrance Pro Forma'!$B42:$ED42) -> 0 | I42: =SUMIF('Torrance Pro Forma'!$B$8:$ED$8,'Annual Pro Forma'!I$8,'Torrance Pro Forma'!$B42:$ED42) -> 0 | J42: =SUMIF('Torrance Pro Forma'!$B$8:$ED$8,'Annual Pro Forma'!J$8,'Torrance Pro Forma'!$B42:$ED42) -> 0 | ... M42: =SUMIF('Torrance Pro Forma'!$B$8:$ED$8,'Annual Pro Forma'!M$8,'Torrance Pro Forma'!$B42:$ED42) -> 0
A43: Effective Gross Revenue | C43: =SUMIF('Torrance Pro Forma'!$B$8:$ED$8,'Annual Pro Forma'!C$8,'Torrance Pro Forma'!$B43:$ED43) -> 1325740 | D43: =SUMIF('Torrance Pro Forma'!$B$8:$ED$8,'Annual Pro Forma'!D$8,'Torrance Pro Forma'!$B43:$ED43) -> 1352154.8 | E43: =SUMIF('Torrance Pro Forma'!$B$8:$ED$8,'Annual Pro Forma'!E$8,'Torrance Pro Forma'!$B43:$ED43) -> 1379103.9 | F43: =SUMIF('Torrance Pro Forma'!$B$8:$ED$8,'Annual Pro Forma'!F$8,'Torrance Pro Forma'!$B43:$ED43) -> 1406598.2 | G43: =SUMIF('Torrance Pro Forma'!$B$8:$ED$8,'Annual Pro Forma'!G$8,'Torrance Pro Forma'!$B43:$ED43) -> 0 | H43: =SUMIF('Torrance Pro Forma'!$B$8:$ED$8,'Annual Pro Forma'!H$8,'Torrance Pro Forma'!$B43:$ED43) -> 5786150.8 | I43: =SUMIF('Torrance Pro Forma'!$B$8:$ED$8,'Annual Pro Forma'!I$8,'Torrance Pro Forma'!$B43:$ED43) -> 5388708 | J43: =SUMIF('Torrance Pro Forma'!$B$8:$ED$8,'Annual Pro Forma'!J$8,'Torrance Pro Forma'!$B43:$ED43) -> 5497573.3 | ... M43: =SUMIF('Torrance Pro Forma'!$B$8:$ED$8,'Annual Pro Forma'!M$8,'Torrance Pro Forma'!$B43:$ED43) -> 5837452.4
C44: =SUMIF('Torrance Pro Forma'!$B$8:$ED$8,'Annual Pro Forma'!C$8,'Torrance Pro Forma'!$B44:$ED44) -> 0 | D44: =SUMIF('Torrance Pro Forma'!$B$8:$ED$8,'Annual Pro Forma'!D$8,'Torrance Pro Forma'!$B44:$ED44) -> 0 | E44: =SUMIF('Torrance Pro Forma'!$B$8:$ED$8,'Annual Pro Forma'!E$8,'Torrance Pro Forma'!$B44:$ED44) -> 0 | F44: =SUMIF('Torrance Pro Forma'!$B$8:$ED$8,'Annual Pro Forma'!F$8,'Torrance Pro Forma'!$B44:$ED44) -> 0 | G44: =SUMIF('Torrance Pro Forma'!$B$8:$ED$8,'Annual Pro Forma'!G$8,'Torrance Pro Forma'!$B44:$ED44) -> 0 | H44: =SUMIF('Torrance Pro Forma'!$B$8:$ED$8,'Annual Pro Forma'!H$8,'Torrance Pro Forma'!$B44:$ED44) -> 0 | I44: =SUMIF('Torrance Pro Forma'!$B$8:$ED$8,'Annual Pro Forma'!I$8,'Torrance Pro Forma'!$B44:$ED44) -> 0 | J44: =SUMIF('Torrance Pro Forma'!$B$8:$ED$8,'Annual Pro Forma'!J$8,'Torrance Pro Forma'!$B44:$ED44) -> 0 | ... M44: =SUMIF('Torrance Pro Forma'!$B$8:$ED$8,'Annual Pro Forma'!M$8,'Torrance Pro Forma'!$B44:$ED44) -> 0
A45: Operating Expenses | C45: =SUMIF('Torrance Pro Forma'!$B$8:$ED$8,'Annual Pro Forma'!C$8,'Torrance Pro Forma'!$B45:$ED45) -> 0 | D45: =SUMIF('Torrance Pro Forma'!$B$8:$ED$8,'Annual Pro Forma'!D$8,'Torrance Pro Forma'!$B45:$ED45) -> 0 | E45: =SUMIF('Torrance Pro Forma'!$B$8:$ED$8,'Annual Pro Forma'!E$8,'Torrance Pro Forma'!$B45:$ED45) -> 0 | F45: =SUMIF('Torrance Pro Forma'!$B$8:$ED$8,'Annual Pro Forma'!F$8,'Torrance Pro Forma'!$B45:$ED45) -> 0 | G45: =SUMIF('Torrance Pro Forma'!$B$8:$ED$8,'Annual Pro Forma'!G$8,'Torrance Pro Forma'!$B45:$ED45) -> 0 | H45: =SUMIF('Torrance Pro Forma'!$B$8:$ED$8,'Annual Pro Forma'!H$8,'Torrance Pro Forma'!$B45:$ED45) -> 0 | I45: =SUMIF('Torrance Pro Forma'!$B$8:$ED$8,'Annual Pro Forma'!I$8,'Torrance Pro Forma'!$B45:$ED45) -> 0 | J45: =SUMIF('Torrance Pro Forma'!$B$8:$ED$8,'Annual Pro Forma'!J$8,'Torrance Pro Forma'!$B45:$ED45) -> 0 | ... M45: =SUMIF('Torrance Pro Forma'!$B$8:$ED$8,'Annual Pro Forma'!M$8,'Torrance Pro Forma'!$B45:$ED45) -> 0
A46: Utilities | B46: =SUMIF('Torrance Pro Forma'!$B$8:$ED$8,'Annual Pro Forma'!B$8,'Torrance Pro Forma'!$B46:$ED46) -> 1250 | C46: =SUMIF('Torrance Pro Forma'!$B$8:$ED$8,'Annual Pro Forma'!C$8,'Torrance Pro Forma'!$B46:$ED46) -> 15000 | D46: =SUMIF('Torrance Pro Forma'!$B$8:$ED$8,'Annual Pro Forma'!D$8,'Torrance Pro Forma'!$B46:$ED46) -> 15450 | E46: =SUMIF('Torrance Pro Forma'!$B$8:$ED$8,'Annual Pro Forma'!E$8,'Torrance Pro Forma'!$B46:$ED46) -> 15913.5 | F46: =SUMIF('Torrance Pro Forma'!$B$8:$ED$8,'Annual Pro Forma'!F$8,'Torrance Pro Forma'!$B46:$ED46) -> 16390.905 | G46: =SUMIF('Torrance Pro Forma'!$B$8:$ED$8,'Annual Pro Forma'!G$8,'Torrance Pro Forma'!$B46:$ED46) -> 0 | H46: =SUMIF('Torrance Pro Forma'!$B$8:$ED$8,'Annual Pro Forma'!H$8,'Torrance Pro Forma'!$B46:$ED46) -> 17389.111 | I46: =SUMIF('Torrance Pro Forma'!$B$8:$ED$8,'Annual Pro Forma'!I$8,'Torrance Pro Forma'!$B46:$ED46) -> 17910.784 | ... M46: =SUMIF('Torrance Pro Forma'!$B$8:$ED$8,'Annual Pro Forma'!M$8,'Torrance Pro Forma'!$B46:$ED46) -> 20158.746
A47: Repairs & Maintenance | B47: =SUMIF('Torrance Pro Forma'!$B$8:$ED$8,'Annual Pro Forma'!B$8,'Torrance Pro Forma'!$B47:$ED47) -> 1250 | C47: =SUMIF('Torrance Pro Forma'!$B$8:$ED$8,'Annual Pro Forma'!C$8,'Torrance Pro Forma'!$B47:$ED47) -> 15000 | D47: =SUMIF('Torrance Pro Forma'!$B$8:$ED$8,'Annual Pro Forma'!D$8,'Torrance Pro Forma'!$B47:$ED47) -> 15450 | E47: =SUMIF('Torrance Pro Forma'!$B$8:$ED$8,'Annual Pro Forma'!E$8,'Torrance Pro Forma'!$B47:$ED47) -> 15913.5 | F47: =SUMIF('Torrance Pro Forma'!$B$8:$ED$8,'Annual Pro Forma'!F$8,'Torrance Pro Forma'!$B47:$ED47) -> 16390.905 | G47: =SUMIF('Torrance Pro Forma'!$B$8:$ED$8,'Annual Pro Forma'!G$8,'Torrance Pro Forma'!$B47:$ED47) -> 0 | H47: =SUMIF('Torrance Pro Forma'!$B$8:$ED$8,'Annual Pro Forma'!H$8,'Torrance Pro Forma'!$B47:$ED47) -> 17389.111 | I47: =SUMIF('Torrance Pro Forma'!$B$8:$ED$8,'Annual Pro Forma'!I$8,'Torrance Pro Forma'!$B47:$ED47) -> 17910.784 | ... M47: =SUMIF('Torrance Pro Forma'!$B$8:$ED$8,'Annual Pro Forma'!M$8,'Torrance Pro Forma'!$B47:$ED47) -> 20158.746
A48: Insurance | B48: =SUMIF('Torrance Pro Forma'!$B$8:$ED$8,'Annual Pro Forma'!B$8,'Torrance Pro Forma'!$B48:$ED48) -> 417 | C48: =SUMIF('Torrance Pro Forma'!$B$8:$ED$8,'Annual Pro Forma'!C$8,'Torrance Pro Forma'!$B48:$ED48) -> 5000 | D48: =SUMIF('Torrance Pro Forma'!$B$8:$ED$8,'Annual Pro Forma'!D$8,'Torrance Pro Forma'!$B48:$ED48) -> 5150 | E48: =SUMIF('Torrance Pro Forma'!$B$8:$ED$8,'Annual Pro Forma'!E$8,'Torrance Pro Forma'!$B48:$ED48) -> 5304.5 | F48: =SUMIF('Torrance Pro Forma'!$B$8:$ED$8,'Annual Pro Forma'!F$8,'Torrance Pro Forma'!$B48:$ED48) -> 5463.635 | G48: =SUMIF('Torrance Pro Forma'!$B$8:$ED$8,'Annual Pro Forma'!G$8,'Torrance Pro Forma'!$B48:$ED48) -> 0 | H48: =SUMIF('Torrance Pro Forma'!$B$8:$ED$8,'Annual Pro Forma'!H$8,'Torrance Pro Forma'!$B48:$ED48) -> 5796.3704 | I48: =SUMIF('Torrance Pro Forma'!$B$8:$ED$8,'Annual Pro Forma'!I$8,'Torrance Pro Forma'!$B48:$ED48) -> 5970.2615 | ... M48: =SUMIF('Torrance Pro Forma'!$B$8:$ED$8,'Annual Pro Forma'!M$8,'Torrance Pro Forma'!$B48:$ED48) -> 6719.5819
A49: Property Taxes | B49: =SUMIF('Torrance Pro Forma'!$B$8:$ED$8,'Annual Pro Forma'!B$8,'Torrance Pro Forma'!$B49:$ED49) -> 16089.944 | C49: =SUMIF('Torrance Pro Forma'!$B$8:$ED$8,'Annual Pro Forma'!C$8,'Torrance Pro Forma'!$B49:$ED49) -> 193079.33 | D49: =SUMIF('Torrance Pro Forma'!$B$8:$ED$8,'Annual Pro Forma'!D$8,'Torrance Pro Forma'!$B49:$ED49) -> 196940.92 | E49: =SUMIF('Torrance Pro Forma'!$B$8:$ED$8,'Annual Pro Forma'!E$8,'Torrance Pro Forma'!$B49:$ED49) -> 200879.74 | F49: =SUMIF('Torrance Pro Forma'!$B$8:$ED$8,'Annual Pro Forma'!F$8,'Torrance Pro Forma'!$B49:$ED49) -> 204897.33 | G49: =SUMIF('Torrance Pro Forma'!$B$8:$ED$8,'Annual Pro Forma'!G$8,'Torrance Pro Forma'!$B49:$ED49) -> 208995.28 | H49: =SUMIF('Torrance Pro Forma'!$B$8:$ED$8,'Annual Pro Forma'!H$8,'Torrance Pro Forma'!$B49:$ED49) -> 213175.19 | I49: =SUMIF('Torrance Pro Forma'!$B$8:$ED$8,'Annual Pro Forma'!I$8,'Torrance Pro Forma'!$B49:$ED49) -> 217438.69 | ... M49: =SUMIF('Torrance Pro Forma'!$B$8:$ED$8,'Annual Pro Forma'!M$8,'Torrance Pro Forma'!$B49:$ED49) -> 235362.63
A50: Management Fee | B50: =SUMIF('Torrance Pro Forma'!$B$8:$ED$8,'Annual Pro Forma'!B$8,'Torrance Pro Forma'!$B50:$ED50) -> 3314.35 | C50: =SUMIF('Torrance Pro Forma'!$B$8:$ED$8,'Annual Pro Forma'!C$8,'Torrance Pro Forma'!$B50:$ED50) -> 36457.85 | D50: =SUMIF('Torrance Pro Forma'!$B$8:$ED$8,'Annual Pro Forma'!D$8,'Torrance Pro Forma'!$B50:$ED50) -> 40564.644 | E50: =SUMIF('Torrance Pro Forma'!$B$8:$ED$8,'Annual Pro Forma'!E$8,'Torrance Pro Forma'!$B50:$ED50) -> 41373.117 | F50: =SUMIF('Torrance Pro Forma'!$B$8:$ED$8,'Annual Pro Forma'!F$8,'Torrance Pro Forma'!$B50:$ED50) -> 42197.945 | G50: =SUMIF('Torrance Pro Forma'!$B$8:$ED$8,'Annual Pro Forma'!G$8,'Torrance Pro Forma'!$B50:$ED50) -> 0 | H50: =SUMIF('Torrance Pro Forma'!$B$8:$ED$8,'Annual Pro Forma'!H$8,'Torrance Pro Forma'!$B50:$ED50) -> 173584.53 | I50: =SUMIF('Torrance Pro Forma'!$B$8:$ED$8,'Annual Pro Forma'!I$8,'Torrance Pro Forma'!$B50:$ED50) -> 161661.24 | ... M50: =SUMIF('Torrance Pro Forma'!$B$8:$ED$8,'Annual Pro Forma'!M$8,'Torrance Pro Forma'!$B50:$ED50) -> 175123.57
A51: Total Operating Expenses | B51: =SUMIF('Torrance Pro Forma'!$B$8:$ED$8,'Annual Pro Forma'!B$8,'Torrance Pro Forma'!$B51:$ED51) -> 0 | C51: =SUMIF('Torrance Pro Forma'!$B$8:$ED$8,'Annual Pro Forma'!C$8,'Torrance Pro Forma'!$B51:$ED51) -> 264537.18 | D51: =SUMIF('Torrance Pro Forma'!$B$8:$ED$8,'Annual Pro Forma'!D$8,'Torrance Pro Forma'!$B51:$ED51) -> 273555.56 | E51: =SUMIF('Torrance Pro Forma'!$B$8:$ED$8,'Annual Pro Forma'!E$8,'Torrance Pro Forma'!$B51:$ED51) -> 279384.36 | F51: =SUMIF('Torrance Pro Forma'!$B$8:$ED$8,'Annual Pro Forma'!F$8,'Torrance Pro Forma'!$B51:$ED51) -> 285340.72 | G51: =SUMIF('Torrance Pro Forma'!$B$8:$ED$8,'Annual Pro Forma'!G$8,'Torrance Pro Forma'!$B51:$ED51) -> 208995.28 | H51: =SUMIF('Torrance Pro Forma'!$B$8:$ED$8,'Annual Pro Forma'!H$8,'Torrance Pro Forma'!$B51:$ED51) -> 427334.3 | I51: =SUMIF('Torrance Pro Forma'!$B$8:$ED$8,'Annual Pro Forma'!I$8,'Torrance Pro Forma'!$B51:$ED51) -> 420891.76 | ... M51: =SUMIF('Torrance Pro Forma'!$B$8:$ED$8,'Annual Pro Forma'!M$8,'Torrance Pro Forma'!$B51:$ED51) -> 457523.27
A53: Net Operating Income | B53: =SUMIF('Torrance Pro Forma'!$B$8:$ED$8,'Annual Pro Forma'!B$8,'Torrance Pro Forma'!$B53:$ED53) -> 0 | C53: =SUMIF('Torrance Pro Forma'!$B$8:$ED$8,'Annual Pro Forma'!C$8,'Torrance Pro Forma'!$B53:$ED53) -> 1061202.8 | D53: =SUMIF('Torrance Pro Forma'!$B$8:$ED$8,'Annual Pro Forma'!D$8,'Torrance Pro Forma'!$B53:$ED53) -> 1078599.2 | E53: =SUMIF('Torrance Pro Forma'!$B$8:$ED$8,'Annual Pro Forma'!E$8,'Torrance Pro Forma'!$B53:$ED53) -> 1099719.5 | F53: =SUMIF('Torrance Pro Forma'!$B$8:$ED$8,'Annual Pro Forma'!F$8,'Torrance Pro Forma'!$B53:$ED53) -> 1121257.4 | G53: =SUMIF('Torrance Pro Forma'!$B$8:$ED$8,'Annual Pro Forma'!G$8,'Torrance Pro Forma'!$B53:$ED53) -> -208995.28 | H53: =SUMIF('Torrance Pro Forma'!$B$8:$ED$8,'Annual Pro Forma'!H$8,'Torrance Pro Forma'!$B53:$ED53) -> 5358816.5 | I53: =SUMIF('Torrance Pro Forma'!$B$8:$ED$8,'Annual Pro Forma'!I$8,'Torrance Pro Forma'!$B53:$ED53) -> 4967816.3 | ... M53: =SUMIF('Torrance Pro Forma'!$B$8:$ED$8,'Annual Pro Forma'!M$8,'Torrance Pro Forma'!$B53:$ED53) -> 5379929.1
A55: Debt Service
A56: Construction Loan
A57: Permanent Loan
A58: Total Debt Service
A61: Leasing Costs | B61: =SUMIF('Torrance Pro Forma'!$B$8:$ED$8,'Annual Pro Forma'!B$8,'Torrance Pro Forma'!$B55:$ED55) -> 0 | C61: =SUMIF('Torrance Pro Forma'!$B$8:$ED$8,'Annual Pro Forma'!C$8,'Torrance Pro Forma'!$B55:$ED55) -> 0 | D61: =SUMIF('Torrance Pro Forma'!$B$8:$ED$8,'Annual Pro Forma'!D$8,'Torrance Pro Forma'!$B55:$ED55) -> 0 | E61: =SUMIF('Torrance Pro Forma'!$B$8:$ED$8,'Annual Pro Forma'!E$8,'Torrance Pro Forma'!$B55:$ED55) -> 0 | F61: =SUMIF('Torrance Pro Forma'!$B$8:$ED$8,'Annual Pro Forma'!F$8,'Torrance Pro Forma'!$B55:$ED55) -> 0 | G61: =SUMIF('Torrance Pro Forma'!$B$8:$ED$8,'Annual Pro Forma'!G$8,'Torrance Pro Forma'!$B55:$ED55) -> 0 | H61: =SUMIF('Torrance Pro Forma'!$B$8:$ED$8,'Annual Pro Forma'!H$8,'Torrance Pro Forma'!$B55:$ED55) -> 0 | I61: =SUMIF('Torrance Pro Forma'!$B$8:$ED$8,'Annual Pro Forma'!I$8,'Torrance Pro Forma'!$B55:$ED55) -> 0 | ... M61: =SUMIF('Torrance Pro Forma'!$B$8:$ED$8,'Annual Pro Forma'!M$8,'Torrance Pro Forma'!$B55:$ED55) -> 0
A62: Tenant Improvements | B62: =SUMIF('Torrance Pro Forma'!$B$8:$ED$8,'Annual Pro Forma'!B$8,'Torrance Pro Forma'!$B56:$ED56) -> 0 | C62: =SUMIF('Torrance Pro Forma'!$B$8:$ED$8,'Annual Pro Forma'!C$8,'Torrance Pro Forma'!$B56:$ED56) -> 0 | D62: =SUMIF('Torrance Pro Forma'!$B$8:$ED$8,'Annual Pro Forma'!D$8,'Torrance Pro Forma'!$B56:$ED56) -> 0 | E62: =SUMIF('Torrance Pro Forma'!$B$8:$ED$8,'Annual Pro Forma'!E$8,'Torrance Pro Forma'!$B56:$ED56) -> 0 | F62: =SUMIF('Torrance Pro Forma'!$B$8:$ED$8,'Annual Pro Forma'!F$8,'Torrance Pro Forma'!$B56:$ED56) -> 0 | G62: =SUMIF('Torrance Pro Forma'!$B$8:$ED$8,'Annual Pro Forma'!G$8,'Torrance Pro Forma'!$B56:$ED56) -> 0 | H62: =SUMIF('Torrance Pro Forma'!$B$8:$ED$8,'Annual Pro Forma'!H$8,'Torrance Pro Forma'!$B56:$ED56) -> 550000 | I62: =SUMIF('Torrance Pro Forma'!$B$8:$ED$8,'Annual Pro Forma'!I$8,'Torrance Pro Forma'!$B56:$ED56) -> 0 | ... M62: =SUMIF('Torrance Pro Forma'!$B$8:$ED$8,'Annual Pro Forma'!M$8,'Torrance Pro Forma'!$B56:$ED56) -> 0
A63: Leasing Commissions | B63: =SUMIF('Torrance Pro Forma'!$B$8:$ED$8,'Annual Pro Forma'!B$8,'Torrance Pro Forma'!$B57:$ED57) -> 0 | C63: =SUMIF('Torrance Pro Forma'!$B$8:$ED$8,'Annual Pro Forma'!C$8,'Torrance Pro Forma'!$B57:$ED57) -> 0 | D63: =SUMIF('Torrance Pro Forma'!$B$8:$ED$8,'Annual Pro Forma'!D$8,'Torrance Pro Forma'!$B57:$ED57) -> 0 | E63: =SUMIF('Torrance Pro Forma'!$B$8:$ED$8,'Annual Pro Forma'!E$8,'Torrance Pro Forma'!$B57:$ED57) -> 0 | F63: =SUMIF('Torrance Pro Forma'!$B$8:$ED$8,'Annual Pro Forma'!F$8,'Torrance Pro Forma'!$B57:$ED57) -> 0 | G63: =SUMIF('Torrance Pro Forma'!$B$8:$ED$8,'Annual Pro Forma'!G$8,'Torrance Pro Forma'!$B57:$ED57) -> 317625 | H63: =SUMIF('Torrance Pro Forma'!$B$8:$ED$8,'Annual Pro Forma'!H$8,'Torrance Pro Forma'!$B57:$ED57) -> 635250 | I63: =SUMIF('Torrance Pro Forma'!$B$8:$ED$8,'Annual Pro Forma'!I$8,'Torrance Pro Forma'!$B57:$ED57) -> 0 | ... M63: =SUMIF('Torrance Pro Forma'!$B$8:$ED$8,'Annual Pro Forma'!M$8,'Torrance Pro Forma'!$B57:$ED57) -> 0
A64: Total Leasing Costs | B64: =SUMIF('Torrance Pro Forma'!$B$8:$ED$8,'Annual Pro Forma'!B$8,'Torrance Pro Forma'!$B58:$ED58) -> 0 | C64: =SUMIF('Torrance Pro Forma'!$B$8:$ED$8,'Annual Pro Forma'!C$8,'Torrance Pro Forma'!$B58:$ED58) -> 0 | D64: =SUMIF('Torrance Pro Forma'!$B$8:$ED$8,'Annual Pro Forma'!D$8,'Torrance Pro Forma'!$B58:$ED58) -> 0 | E64: =SUMIF('Torrance Pro Forma'!$B$8:$ED$8,'Annual Pro Forma'!E$8,'Torrance Pro Forma'!$B58:$ED58) -> 0 | F64: =SUMIF('Torrance Pro Forma'!$B$8:$ED$8,'Annual Pro Forma'!F$8,'Torrance Pro Forma'!$B58:$ED58) -> 0 | G64: =SUMIF('Torrance Pro Forma'!$B$8:$ED$8,'Annual Pro Forma'!G$8,'Torrance Pro Forma'!$B58:$ED58) -> 317625 | H64: =SUMIF('Torrance Pro Forma'!$B$8:$ED$8,'Annual Pro Forma'!H$8,'Torrance Pro Forma'!$B58:$ED58) -> 1185250 | I64: =SUMIF('Torrance Pro Forma'!$B$8:$ED$8,'Annual Pro Forma'!I$8,'Torrance Pro Forma'!$B58:$ED58) -> 0 | ... M64: =SUMIF('Torrance Pro Forma'!$B$8:$ED$8,'Annual Pro Forma'!M$8,'Torrance Pro Forma'!$B58:$ED58) -> 0
B65: =SUMIF('Torrance Pro Forma'!$B$8:$ED$8,'Annual Pro Forma'!B$8,'Torrance Pro Forma'!$B59:$ED59) -> 0 | C65: =SUMIF('Torrance Pro Forma'!$B$8:$ED$8,'Annual Pro Forma'!C$8,'Torrance Pro Forma'!$B59:$ED59) -> 0 | D65: =SUMIF('Torrance Pro Forma'!$B$8:$ED$8,'Annual Pro Forma'!D$8,'Torrance Pro Forma'!$B59:$ED59) -> 0 | E65: =SUMIF('Torrance Pro Forma'!$B$8:$ED$8,'Annual Pro Forma'!E$8,'Torrance Pro Forma'!$B59:$ED59) -> 0 | F65: =SUMIF('Torrance Pro Forma'!$B$8:$ED$8,'Annual Pro Forma'!F$8,'Torrance Pro Forma'!$B59:$ED59) -> 0 | G65: =SUMIF('Torrance Pro Forma'!$B$8:$ED$8,'Annual Pro Forma'!G$8,'Torrance Pro Forma'!$B59:$ED59) -> 317625 | H65: =SUMIF('Torrance Pro Forma'!$B$8:$ED$8,'Annual Pro Forma'!H$8,'Torrance Pro Forma'!$B59:$ED59) -> 1185250 | I65: =SUMIF('Torrance Pro Forma'!$B$8:$ED$8,'Annual Pro Forma'!I$8,'Torrance Pro Forma'!$B59:$ED59) -> 0 | ... M65: =SUMIF('Torrance Pro Forma'!$B$8:$ED$8,'Annual Pro Forma'!M$8,'Torrance Pro Forma'!$B59:$ED59) -> 0
A66: Capital Expenditures | B66: =SUMIF('Torrance Pro Forma'!$B$8:$ED$8,'Annual Pro Forma'!B$8,'Torrance Pro Forma'!$B60:$ED60) -> 0 | C66: =SUMIF('Torrance Pro Forma'!$B$8:$ED$8,'Annual Pro Forma'!C$8,'Torrance Pro Forma'!$B60:$ED60) -> 0 | D66: =SUMIF('Torrance Pro Forma'!$B$8:$ED$8,'Annual Pro Forma'!D$8,'Torrance Pro Forma'!$B60:$ED60) -> 0 | E66: =SUMIF('Torrance Pro Forma'!$B$8:$ED$8,'Annual Pro Forma'!E$8,'Torrance Pro Forma'!$B60:$ED60) -> 0 | F66: =SUMIF('Torrance Pro Forma'!$B$8:$ED$8,'Annual Pro Forma'!F$8,'Torrance Pro Forma'!$B60:$ED60) -> 0 | G66: =SUMIF('Torrance Pro Forma'!$B$8:$ED$8,'Annual Pro Forma'!G$8,'Torrance Pro Forma'!$B60:$ED60) -> 0 | H66: =SUMIF('Torrance Pro Forma'!$B$8:$ED$8,'Annual Pro Forma'!H$8,'Torrance Pro Forma'!$B60:$ED60) -> 0 | I66: =SUMIF('Torrance Pro Forma'!$B$8:$ED$8,'Annual Pro Forma'!I$8,'Torrance Pro Forma'!$B60:$ED60) -> 0 | ... M66: =SUMIF('Torrance Pro Forma'!$B$8:$ED$8,'Annual Pro Forma'!M$8,'Torrance Pro Forma'!$B60:$ED60) -> 0
A67: Replacement Reserve | B67: =SUMIF('Torrance Pro Forma'!$B$8:$ED$8,'Annual Pro Forma'!B$8,'Torrance Pro Forma'!$B61:$ED61) -> 0 | C67: =SUMIF('Torrance Pro Forma'!$B$8:$ED$8,'Annual Pro Forma'!C$8,'Torrance Pro Forma'!$B61:$ED61) -> 137500 | D67: =SUMIF('Torrance Pro Forma'!$B$8:$ED$8,'Annual Pro Forma'!D$8,'Torrance Pro Forma'!$B61:$ED61) -> 140250 | E67: =SUMIF('Torrance Pro Forma'!$B$8:$ED$8,'Annual Pro Forma'!E$8,'Torrance Pro Forma'!$B61:$ED61) -> 143055 | F67: =SUMIF('Torrance Pro Forma'!$B$8:$ED$8,'Annual Pro Forma'!F$8,'Torrance Pro Forma'!$B61:$ED61) -> 145916.1 | G67: =SUMIF('Torrance Pro Forma'!$B$8:$ED$8,'Annual Pro Forma'!G$8,'Torrance Pro Forma'!$B61:$ED61) -> 148834.42 | H67: =SUMIF('Torrance Pro Forma'!$B$8:$ED$8,'Annual Pro Forma'!H$8,'Torrance Pro Forma'!$B61:$ED61) -> 151811.11 | I67: =SUMIF('Torrance Pro Forma'!$B$8:$ED$8,'Annual Pro Forma'!I$8,'Torrance Pro Forma'!$B61:$ED61) -> 154847.33 | ... M67: =SUMIF('Torrance Pro Forma'!$B$8:$ED$8,'Annual Pro Forma'!M$8,'Torrance Pro Forma'!$B61:$ED61) -> 167611.73
A68: Tenant Buyout Expense | B68: =SUMIF('Torrance Pro Forma'!$B$8:$ED$8,'Annual Pro Forma'!B$8,'Torrance Pro Forma'!$B62:$ED62) -> 0 | C68: =SUMIF('Torrance Pro Forma'!$B$8:$ED$8,'Annual Pro Forma'!C$8,'Torrance Pro Forma'!$B62:$ED62) -> 0 | D68: =SUMIF('Torrance Pro Forma'!$B$8:$ED$8,'Annual Pro Forma'!D$8,'Torrance Pro Forma'!$B62:$ED62) -> 0 | E68: =SUMIF('Torrance Pro Forma'!$B$8:$ED$8,'Annual Pro Forma'!E$8,'Torrance Pro Forma'!$B62:$ED62) -> 0 | F68: =SUMIF('Torrance Pro Forma'!$B$8:$ED$8,'Annual Pro Forma'!F$8,'Torrance Pro Forma'!$B62:$ED62) -> 1540000 | G68: =SUMIF('Torrance Pro Forma'!$B$8:$ED$8,'Annual Pro Forma'!G$8,'Torrance Pro Forma'!$B62:$ED62) -> 0 | H68: =SUMIF('Torrance Pro Forma'!$B$8:$ED$8,'Annual Pro Forma'!H$8,'Torrance Pro Forma'!$B62:$ED62) -> 0 | I68: =SUMIF('Torrance Pro Forma'!$B$8:$ED$8,'Annual Pro Forma'!I$8,'Torrance Pro Forma'!$B62:$ED62) -> 0 | ... M68: =SUMIF('Torrance Pro Forma'!$B$8:$ED$8,'Annual Pro Forma'!M$8,'Torrance Pro Forma'!$B62:$ED62) -> 0
A69: Total Capital Expenditures | B69: =SUMIF('Torrance Pro Forma'!$B$8:$ED$8,'Annual Pro Forma'!B$8,'Torrance Pro Forma'!$B63:$ED63) -> 0 | C69: =SUMIF('Torrance Pro Forma'!$B$8:$ED$8,'Annual Pro Forma'!C$8,'Torrance Pro Forma'!$B63:$ED63) -> 137500 | D69: =SUMIF('Torrance Pro Forma'!$B$8:$ED$8,'Annual Pro Forma'!D$8,'Torrance Pro Forma'!$B63:$ED63) -> 140250 | E69: =SUMIF('Torrance Pro Forma'!$B$8:$ED$8,'Annual Pro Forma'!E$8,'Torrance Pro Forma'!$B63:$ED63) -> 143055 | F69: =SUMIF('Torrance Pro Forma'!$B$8:$ED$8,'Annual Pro Forma'!F$8,'Torrance Pro Forma'!$B63:$ED63) -> 1685916.1 | G69: =SUMIF('Torrance Pro Forma'!$B$8:$ED$8,'Annual Pro Forma'!G$8,'Torrance Pro Forma'!$B63:$ED63) -> 148834.42 | H69: =SUMIF('Torrance Pro Forma'!$B$8:$ED$8,'Annual Pro Forma'!H$8,'Torrance Pro Forma'!$B63:$ED63) -> 151811.11 | I69: =SUMIF('Torrance Pro Forma'!$B$8:$ED$8,'Annual Pro Forma'!I$8,'Torrance Pro Forma'!$B63:$ED63) -> 154847.33 | ... M69: =SUMIF('Torrance Pro Forma'!$B$8:$ED$8,'Annual Pro Forma'!M$8,'Torrance Pro Forma'!$B63:$ED63) -> 167611.73
A71: Total Leasing & Capital Costs | B71: =SUMIF('Torrance Pro Forma'!$B$8:$ED$8,'Annual Pro Forma'!B$8,'Torrance Pro Forma'!$B65:$ED65) -> 0 | C71: =SUMIF('Torrance Pro Forma'!$B$8:$ED$8,'Annual Pro Forma'!C$8,'Torrance Pro Forma'!$B65:$ED65) -> 137500 | D71: =SUMIF('Torrance Pro Forma'!$B$8:$ED$8,'Annual Pro Forma'!D$8,'Torrance Pro Forma'!$B65:$ED65) -> 140250 | E71: =SUMIF('Torrance Pro Forma'!$B$8:$ED$8,'Annual Pro Forma'!E$8,'Torrance Pro Forma'!$B65:$ED65) -> 143055 | F71: =SUMIF('Torrance Pro Forma'!$B$8:$ED$8,'Annual Pro Forma'!F$8,'Torrance Pro Forma'!$B65:$ED65) -> 1685916.1 | G71: =SUMIF('Torrance Pro Forma'!$B$8:$ED$8,'Annual Pro Forma'!G$8,'Torrance Pro Forma'!$B65:$ED65) -> 466459.42 | H71: =SUMIF('Torrance Pro Forma'!$B$8:$ED$8,'Annual Pro Forma'!H$8,'Torrance Pro Forma'!$B65:$ED65) -> 1337061.1 | I71: =SUMIF('Torrance Pro Forma'!$B$8:$ED$8,'Annual Pro Forma'!I$8,'Torrance Pro Forma'!$B65:$ED65) -> 154847.33 | ... M71: =SUMIF('Torrance Pro Forma'!$B$8:$ED$8,'Annual Pro Forma'!M$8,'Torrance Pro Forma'!$B65:$ED65) -> 167611.73
B72: =SUMIF('Torrance Pro Forma'!$B$8:$ED$8,'Annual Pro Forma'!B$8,'Torrance Pro Forma'!$B66:$ED66) -> 0 | C72: =SUMIF('Torrance Pro Forma'!$B$8:$ED$8,'Annual Pro Forma'!C$8,'Torrance Pro Forma'!$B66:$ED66) -> 0 | D72: =SUMIF('Torrance Pro Forma'!$B$8:$ED$8,'Annual Pro Forma'!D$8,'Torrance Pro Forma'!$B66:$ED66) -> 0 | E72: =SUMIF('Torrance Pro Forma'!$B$8:$ED$8,'Annual Pro Forma'!E$8,'Torrance Pro Forma'!$B66:$ED66) -> 0 | F72: =SUMIF('Torrance Pro Forma'!$B$8:$ED$8,'Annual Pro Forma'!F$8,'Torrance Pro Forma'!$B66:$ED66) -> 0 | G72: =SUMIF('Torrance Pro Forma'!$B$8:$ED$8,'Annual Pro Forma'!G$8,'Torrance Pro Forma'!$B66:$ED66) -> 0 | H72: =SUMIF('Torrance Pro Forma'!$B$8:$ED$8,'Annual Pro Forma'!H$8,'Torrance Pro Forma'!$B66:$ED66) -> 0 | I72: =SUMIF('Torrance Pro Forma'!$B$8:$ED$8,'Annual Pro Forma'!I$8,'Torrance Pro Forma'!$B66:$ED66) -> 0 | ... M72: =SUMIF('Torrance Pro Forma'!$B$8:$ED$8,'Annual Pro Forma'!M$8,'Torrance Pro Forma'!$B66:$ED66) -> 0
A73: Construction Cost | B73: =SUMIF('Torrance Pro Forma'!$B$8:$ED$8,'Annual Pro Forma'!B$8,'Torrance Pro Forma'!$B67:$ED67) -> 0 | C73: =SUMIF('Torrance Pro Forma'!$B$8:$ED$8,'Annual Pro Forma'!C$8,'Torrance Pro Forma'!$B67:$ED67) -> 0 | D73: =SUMIF('Torrance Pro Forma'!$B$8:$ED$8,'Annual Pro Forma'!D$8,'Torrance Pro Forma'!$B67:$ED67) -> 0 | E73: =SUMIF('Torrance Pro Forma'!$B$8:$ED$8,'Annual Pro Forma'!E$8,'Torrance Pro Forma'!$B67:$ED67) -> 0 | F73: =SUMIF('Torrance Pro Forma'!$B$8:$ED$8,'Annual Pro Forma'!F$8,'Torrance Pro Forma'!$B67:$ED67) -> 0 | G73: =SUMIF('Torrance Pro Forma'!$B$8:$ED$8,'Annual Pro Forma'!G$8,'Torrance Pro Forma'!$B67:$ED67) -> 0 | H73: =SUMIF('Torrance Pro Forma'!$B$8:$ED$8,'Annual Pro Forma'!H$8,'Torrance Pro Forma'!$B67:$ED67) -> 0 | I73: =SUMIF('Torrance Pro Forma'!$B$8:$ED$8,'Annual Pro Forma'!I$8,'Torrance Pro Forma'!$B67:$ED67) -> 0 | ... M73: =SUMIF('Torrance Pro Forma'!$B$8:$ED$8,'Annual Pro Forma'!M$8,'Torrance Pro Forma'!$B67:$ED67) -> 0
A74: Soft Costs | B74: =SUMIF('Torrance Pro Forma'!$B$8:$ED$8,'Annual Pro Forma'!B$8,'Torrance Pro Forma'!$B68:$ED68) -> 0 | C74: =SUMIF('Torrance Pro Forma'!$B$8:$ED$8,'Annual Pro Forma'!C$8,'Torrance Pro Forma'!$B68:$ED68) -> 0 | D74: =SUMIF('Torrance Pro Forma'!$B$8:$ED$8,'Annual Pro Forma'!D$8,'Torrance Pro Forma'!$B68:$ED68) -> 0 | E74: =SUMIF('Torrance Pro Forma'!$B$8:$ED$8,'Annual Pro Forma'!E$8,'Torrance Pro Forma'!$B68:$ED68) -> 0 | F74: =SUMIF('Torrance Pro Forma'!$B$8:$ED$8,'Annual Pro Forma'!F$8,'Torrance Pro Forma'!$B68:$ED68) -> 0 | G74: =SUMIF('Torrance Pro Forma'!$B$8:$ED$8,'Annual Pro Forma'!G$8,'Torrance Pro Forma'!$B68:$ED68) -> 1500000 | H74: =SUMIF('Torrance Pro Forma'!$B$8:$ED$8,'Annual Pro Forma'!H$8,'Torrance Pro Forma'!$B68:$ED68) -> 1500000 | I74: =SUMIF('Torrance Pro Forma'!$B$8:$ED$8,'Annual Pro Forma'!I$8,'Torrance Pro Forma'!$B68:$ED68) -> 0 | ... M74: =SUMIF('Torrance Pro Forma'!$B$8:$ED$8,'Annual Pro Forma'!M$8,'Torrance Pro Forma'!$B68:$ED68) -> 0
A75: Demolition | B75: =SUMIF('Torrance Pro Forma'!$B$8:$ED$8,'Annual Pro Forma'!B$8,'Torrance Pro Forma'!$B69:$ED69) -> 0 | C75: =SUMIF('Torrance Pro Forma'!$B$8:$ED$8,'Annual Pro Forma'!C$8,'Torrance Pro Forma'!$B69:$ED69) -> 0 | D75: =SUMIF('Torrance Pro Forma'!$B$8:$ED$8,'Annual Pro Forma'!D$8,'Torrance Pro Forma'!$B69:$ED69) -> 0 | E75: =SUMIF('Torrance Pro Forma'!$B$8:$ED$8,'Annual Pro Forma'!E$8,'Torrance Pro Forma'!$B69:$ED69) -> 0 | F75: =SUMIF('Torrance Pro Forma'!$B$8:$ED$8,'Annual Pro Forma'!F$8,'Torrance Pro Forma'!$B69:$ED69) -> 0 | G75: =SUMIF('Torrance Pro Forma'!$B$8:$ED$8,'Annual Pro Forma'!G$8,'Torrance Pro Forma'!$B69:$ED69) -> 0 | H75: =SUMIF('Torrance Pro Forma'!$B$8:$ED$8,'Annual Pro Forma'!H$8,'Torrance Pro Forma'!$B69:$ED69) -> 0 | I75: =SUMIF('Torrance Pro Forma'!$B$8:$ED$8,'Annual Pro Forma'!I$8,'Torrance Pro Forma'!$B69:$ED69) -> 1500000 | ... M75: =SUMIF('Torrance Pro Forma'!$B$8:$ED$8,'Annual Pro Forma'!M$8,'Torrance Pro Forma'!$B69:$ED69) -> 0
A76: Building Const. | B76: =SUMIF('Torrance Pro Forma'!$B$8:$ED$8,'Annual Pro Forma'!B$8,'Torrance Pro Forma'!$B70:$ED70) -> 0 | C76: =SUMIF('Torrance Pro Forma'!$B$8:$ED$8,'Annual Pro Forma'!C$8,'Torrance Pro Forma'!$B70:$ED70) -> 0 | D76: =SUMIF('Torrance Pro Forma'!$B$8:$ED$8,'Annual Pro Forma'!D$8,'Torrance Pro Forma'!$B70:$ED70) -> 0 | E76: =SUMIF('Torrance Pro Forma'!$B$8:$ED$8,'Annual Pro Forma'!E$8,'Torrance Pro Forma'!$B70:$ED70) -> 0 | F76: =SUMIF('Torrance Pro Forma'!$B$8:$ED$8,'Annual Pro Forma'!F$8,'Torrance Pro Forma'!$B70:$ED70) -> 0 | G76: =SUMIF('Torrance Pro Forma'!$B$8:$ED$8,'Annual Pro Forma'!G$8,'Torrance Pro Forma'!$B70:$ED70) -> 0 | H76: =SUMIF('Torrance Pro Forma'!$B$8:$ED$8,'Annual Pro Forma'!H$8,'Torrance Pro Forma'!$B70:$ED70) -> 0 | I76: =SUMIF('Torrance Pro Forma'!$B$8:$ED$8,'Annual Pro Forma'!I$8,'Torrance Pro Forma'!$B70:$ED70) -> 12500000 | ... M76: =SUMIF('Torrance Pro Forma'!$B$8:$ED$8,'Annual Pro Forma'!M$8,'Torrance Pro Forma'!$B70:$ED70) -> 0
A77: Site Work | B77: =SUMIF('Torrance Pro Forma'!$B$8:$ED$8,'Annual Pro Forma'!B$8,'Torrance Pro Forma'!$B71:$ED71) -> 0 | C77: =SUMIF('Torrance Pro Forma'!$B$8:$ED$8,'Annual Pro Forma'!C$8,'Torrance Pro Forma'!$B71:$ED71) -> 0 | D77: =SUMIF('Torrance Pro Forma'!$B$8:$ED$8,'Annual Pro Forma'!D$8,'Torrance Pro Forma'!$B71:$ED71) -> 0 | E77: =SUMIF('Torrance Pro Forma'!$B$8:$ED$8,'Annual Pro Forma'!E$8,'Torrance Pro Forma'!$B71:$ED71) -> 0 | F77: =SUMIF('Torrance Pro Forma'!$B$8:$ED$8,'Annual Pro Forma'!F$8,'Torrance Pro Forma'!$B71:$ED71) -> 0 | G77: =SUMIF('Torrance Pro Forma'!$B$8:$ED$8,'Annual Pro Forma'!G$8,'Torrance Pro Forma'!$B71:$ED71) -> 0 | H77: =SUMIF('Torrance Pro Forma'!$B$8:$ED$8,'Annual Pro Forma'!H$8,'Torrance Pro Forma'!$B71:$ED71) -> 0 | I77: =SUMIF('Torrance Pro Forma'!$B$8:$ED$8,'Annual Pro Forma'!I$8,'Torrance Pro Forma'!$B71:$ED71) -> 400000 | ... M77: =SUMIF('Torrance Pro Forma'!$B$8:$ED$8,'Annual Pro Forma'!M$8,'Torrance Pro Forma'!$B71:$ED71) -> 0
A78: Lease Up - Broker Fee | B78: =SUMIF('Torrance Pro Forma'!$B$8:$ED$8,'Annual Pro Forma'!B$8,'Torrance Pro Forma'!$B72:$ED72) -> 0 | C78: =SUMIF('Torrance Pro Forma'!$B$8:$ED$8,'Annual Pro Forma'!C$8,'Torrance Pro Forma'!$B72:$ED72) -> 0 | D78: =SUMIF('Torrance Pro Forma'!$B$8:$ED$8,'Annual Pro Forma'!D$8,'Torrance Pro Forma'!$B72:$ED72) -> 0 | E78: =SUMIF('Torrance Pro Forma'!$B$8:$ED$8,'Annual Pro Forma'!E$8,'Torrance Pro Forma'!$B72:$ED72) -> 0 | F78: =SUMIF('Torrance Pro Forma'!$B$8:$ED$8,'Annual Pro Forma'!F$8,'Torrance Pro Forma'!$B72:$ED72) -> 0 | G78: =SUMIF('Torrance Pro Forma'!$B$8:$ED$8,'Annual Pro Forma'!G$8,'Torrance Pro Forma'!$B72:$ED72) -> 0 | H78: =SUMIF('Torrance Pro Forma'!$B$8:$ED$8,'Annual Pro Forma'!H$8,'Torrance Pro Forma'!$B72:$ED72) -> 0 | I78: =SUMIF('Torrance Pro Forma'!$B$8:$ED$8,'Annual Pro Forma'!I$8,'Torrance Pro Forma'!$B72:$ED72) -> 100000 | ... M78: =SUMIF('Torrance Pro Forma'!$B$8:$ED$8,'Annual Pro Forma'!M$8,'Torrance Pro Forma'!$B72:$ED72) -> 0
A79: Total Construction Cost | B79: =SUMIF('Torrance Pro Forma'!$B$8:$ED$8,'Annual Pro Forma'!B$8,'Torrance Pro Forma'!$B73:$ED73) -> 0 | C79: =SUMIF('Torrance Pro Forma'!$B$8:$ED$8,'Annual Pro Forma'!C$8,'Torrance Pro Forma'!$B73:$ED73) -> 0 | D79: =SUMIF('Torrance Pro Forma'!$B$8:$ED$8,'Annual Pro Forma'!D$8,'Torrance Pro Forma'!$B73:$ED73) -> 0 | E79: =SUMIF('Torrance Pro Forma'!$B$8:$ED$8,'Annual Pro Forma'!E$8,'Torrance Pro Forma'!$B73:$ED73) -> 0 | F79: =SUMIF('Torrance Pro Forma'!$B$8:$ED$8,'Annual Pro Forma'!F$8,'Torrance Pro Forma'!$B73:$ED73) -> 0 | G79: =SUMIF('Torrance Pro Forma'!$B$8:$ED$8,'Annual Pro Forma'!G$8,'Torrance Pro Forma'!$B73:$ED73) -> 1500000 | H79: =SUMIF('Torrance Pro Forma'!$B$8:$ED$8,'Annual Pro Forma'!H$8,'Torrance Pro Forma'!$B73:$ED73) -> 1500000 | I79: =SUMIF('Torrance Pro Forma'!$B$8:$ED$8,'Annual Pro Forma'!I$8,'Torrance Pro Forma'!$B73:$ED73) -> 14500000 | ... M79: =SUMIF('Torrance Pro Forma'!$B$8:$ED$8,'Annual Pro Forma'!M$8,'Torrance Pro Forma'!$B73:$ED73) -> 0
A81: Cash Flow Before Debt Service | B81: =SUMIF('Torrance Pro Forma'!$B$8:$ED$8,'Annual Pro Forma'!B$8,'Torrance Pro Forma'!$B75:$ED75) -> 0 | C81: =SUMIF('Torrance Pro Forma'!$B$8:$ED$8,'Annual Pro Forma'!C$8,'Torrance Pro Forma'!$B75:$ED75) -> 923702.82 | D81: =SUMIF('Torrance Pro Forma'!$B$8:$ED$8,'Annual Pro Forma'!D$8,'Torrance Pro Forma'!$B75:$ED75) -> 938349.24 | E81: =SUMIF('Torrance Pro Forma'!$B$8:$ED$8,'Annual Pro Forma'!E$8,'Torrance Pro Forma'!$B75:$ED75) -> 956664.54 | F81: =SUMIF('Torrance Pro Forma'!$B$8:$ED$8,'Annual Pro Forma'!F$8,'Torrance Pro Forma'!$B75:$ED75) -> -564658.67 | G81: =SUMIF('Torrance Pro Forma'!$B$8:$ED$8,'Annual Pro Forma'!G$8,'Torrance Pro Forma'!$B75:$ED75) -> -2175454.7 | H81: =SUMIF('Torrance Pro Forma'!$B$8:$ED$8,'Annual Pro Forma'!H$8,'Torrance Pro Forma'!$B75:$ED75) -> 2521755.4 | I81: =SUMIF('Torrance Pro Forma'!$B$8:$ED$8,'Annual Pro Forma'!I$8,'Torrance Pro Forma'!$B75:$ED75) -> -9687031.1 | ... M81: =SUMIF('Torrance Pro Forma'!$B$8:$ED$8,'Annual Pro Forma'!M$8,'Torrance Pro Forma'!$B75:$ED75) -> 5212317.4
B82: =SUMIF('Torrance Pro Forma'!$B$8:$ED$8,'Annual Pro Forma'!B$8,'Torrance Pro Forma'!$B76:$ED76) -> 0 | C82: =SUMIF('Torrance Pro Forma'!$B$8:$ED$8,'Annual Pro Forma'!C$8,'Torrance Pro Forma'!$B76:$ED76) -> 0 | D82: =SUMIF('Torrance Pro Forma'!$B$8:$ED$8,'Annual Pro Forma'!D$8,'Torrance Pro Forma'!$B76:$ED76) -> 0 | E82: =SUMIF('Torrance Pro Forma'!$B$8:$ED$8,'Annual Pro Forma'!E$8,'Torrance Pro Forma'!$B76:$ED76) -> 0 | F82: =SUMIF('Torrance Pro Forma'!$B$8:$ED$8,'Annual Pro Forma'!F$8,'Torrance Pro Forma'!$B76:$ED76) -> 0 | G82: =SUMIF('Torrance Pro Forma'!$B$8:$ED$8,'Annual Pro Forma'!G$8,'Torrance Pro Forma'!$B76:$ED76) -> 0 | H82: =SUMIF('Torrance Pro Forma'!$B$8:$ED$8,'Annual Pro Forma'!H$8,'Torrance Pro Forma'!$B76:$ED76) -> 0 | I82: =SUMIF('Torrance Pro Forma'!$B$8:$ED$8,'Annual Pro Forma'!I$8,'Torrance Pro Forma'!$B76:$ED76) -> 0 | ... M82: =SUMIF('Torrance Pro Forma'!$B$8:$ED$8,'Annual Pro Forma'!M$8,'Torrance Pro Forma'!$B76:$ED76) -> 0
A83: Acquisition | B83: =SUMIF('Torrance Pro Forma'!$B$8:$ED$8,'Annual Pro Forma'!B$8,'Torrance Pro Forma'!$B77:$ED77) -> 0 | C83: =SUMIF('Torrance Pro Forma'!$B$8:$ED$8,'Annual Pro Forma'!C$8,'Torrance Pro Forma'!$B77:$ED77) -> 0 | D83: =SUMIF('Torrance Pro Forma'!$B$8:$ED$8,'Annual Pro Forma'!D$8,'Torrance Pro Forma'!$B77:$ED77) -> 0 | E83: =SUMIF('Torrance Pro Forma'!$B$8:$ED$8,'Annual Pro Forma'!E$8,'Torrance Pro Forma'!$B77:$ED77) -> 0 | F83: =SUMIF('Torrance Pro Forma'!$B$8:$ED$8,'Annual Pro Forma'!F$8,'Torrance Pro Forma'!$B77:$ED77) -> 0 | G83: =SUMIF('Torrance Pro Forma'!$B$8:$ED$8,'Annual Pro Forma'!G$8,'Torrance Pro Forma'!$B77:$ED77) -> 0 | H83: =SUMIF('Torrance Pro Forma'!$B$8:$ED$8,'Annual Pro Forma'!H$8,'Torrance Pro Forma'!$B77:$ED77) -> 0 | I83: =SUMIF('Torrance Pro Forma'!$B$8:$ED$8,'Annual Pro Forma'!I$8,'Torrance Pro Forma'!$B77:$ED77) -> 0 | ... M83: =SUMIF('Torrance Pro Forma'!$B$8:$ED$8,'Annual Pro Forma'!M$8,'Torrance Pro Forma'!$B77:$ED77) -> 0
A84: Purchase Price | B84: =SUMIF('Torrance Pro Forma'!$B$8:$ED$8,'Annual Pro Forma'!B$8,'Torrance Pro Forma'!$B78:$ED78) -> -17552667 | C84: =SUMIF('Torrance Pro Forma'!$B$8:$ED$8,'Annual Pro Forma'!C$8,'Torrance Pro Forma'!$B78:$ED78) -> 0 | D84: =SUMIF('Torrance Pro Forma'!$B$8:$ED$8,'Annual Pro Forma'!D$8,'Torrance Pro Forma'!$B78:$ED78) -> 0 | E84: =SUMIF('Torrance Pro Forma'!$B$8:$ED$8,'Annual Pro Forma'!E$8,'Torrance Pro Forma'!$B78:$ED78) -> 0 | F84: =SUMIF('Torrance Pro Forma'!$B$8:$ED$8,'Annual Pro Forma'!F$8,'Torrance Pro Forma'!$B78:$ED78) -> 0 | G84: =SUMIF('Torrance Pro Forma'!$B$8:$ED$8,'Annual Pro Forma'!G$8,'Torrance Pro Forma'!$B78:$ED78) -> 0 | H84: =SUMIF('Torrance Pro Forma'!$B$8:$ED$8,'Annual Pro Forma'!H$8,'Torrance Pro Forma'!$B78:$ED78) -> 0 | I84: =SUMIF('Torrance Pro Forma'!$B$8:$ED$8,'Annual Pro Forma'!I$8,'Torrance Pro Forma'!$B78:$ED78) -> 0 | ... M84: =SUMIF('Torrance Pro Forma'!$B$8:$ED$8,'Annual Pro Forma'!M$8,'Torrance Pro Forma'!$B78:$ED78) -> 0
A85: Cost of Sales | B85: =SUMIF('Torrance Pro Forma'!$B$8:$ED$8,'Annual Pro Forma'!B$8,'Torrance Pro Forma'!$B79:$ED79) -> 351053.33 | C85: =SUMIF('Torrance Pro Forma'!$B$8:$ED$8,'Annual Pro Forma'!C$8,'Torrance Pro Forma'!$B79:$ED79) -> 0 | D85: =SUMIF('Torrance Pro Forma'!$B$8:$ED$8,'Annual Pro Forma'!D$8,'Torrance Pro Forma'!$B79:$ED79) -> 0 | E85: =SUMIF('Torrance Pro Forma'!$B$8:$ED$8,'Annual Pro Forma'!E$8,'Torrance Pro Forma'!$B79:$ED79) -> 0 | F85: =SUMIF('Torrance Pro Forma'!$B$8:$ED$8,'Annual Pro Forma'!F$8,'Torrance Pro Forma'!$B79:$ED79) -> 0 | G85: =SUMIF('Torrance Pro Forma'!$B$8:$ED$8,'Annual Pro Forma'!G$8,'Torrance Pro Forma'!$B79:$ED79) -> 0 | H85: =SUMIF('Torrance Pro Forma'!$B$8:$ED$8,'Annual Pro Forma'!H$8,'Torrance Pro Forma'!$B79:$ED79) -> 0 | I85: =SUMIF('Torrance Pro Forma'!$B$8:$ED$8,'Annual Pro Forma'!I$8,'Torrance Pro Forma'!$B79:$ED79) -> 0 | ... M85: =SUMIF('Torrance Pro Forma'!$B$8:$ED$8,'Annual Pro Forma'!M$8,'Torrance Pro Forma'!$B79:$ED79) -> 0
A86: Total Acquisition Cost | B86: =SUMIF('Torrance Pro Forma'!$B$8:$ED$8,'Annual Pro Forma'!B$8,'Torrance Pro Forma'!$B80:$ED80) -> -17201613 | C86: =SUMIF('Torrance Pro Forma'!$B$8:$ED$8,'Annual Pro Forma'!C$8,'Torrance Pro Forma'!$B80:$ED80) -> 0 | D86: =SUMIF('Torrance Pro Forma'!$B$8:$ED$8,'Annual Pro Forma'!D$8,'Torrance Pro Forma'!$B80:$ED80) -> 0 | E86: =SUMIF('Torrance Pro Forma'!$B$8:$ED$8,'Annual Pro Forma'!E$8,'Torrance Pro Forma'!$B80:$ED80) -> 0 | F86: =SUMIF('Torrance Pro Forma'!$B$8:$ED$8,'Annual Pro Forma'!F$8,'Torrance Pro Forma'!$B80:$ED80) -> 0 | G86: =SUMIF('Torrance Pro Forma'!$B$8:$ED$8,'Annual Pro Forma'!G$8,'Torrance Pro Forma'!$B80:$ED80) -> 0 | H86: =SUMIF('Torrance Pro Forma'!$B$8:$ED$8,'Annual Pro Forma'!H$8,'Torrance Pro Forma'!$B80:$ED80) -> 0 | I86: =SUMIF('Torrance Pro Forma'!$B$8:$ED$8,'Annual Pro Forma'!I$8,'Torrance Pro Forma'!$B80:$ED80) -> 0 | ... M86: =SUMIF('Torrance Pro Forma'!$B$8:$ED$8,'Annual Pro Forma'!M$8,'Torrance Pro Forma'!$B80:$ED80) -> 0
A88: Disposition | B88: =SUMIF('Torrance Pro Forma'!$B$8:$ED$8,'Annual Pro Forma'!B$8,'Torrance Pro Forma'!$B82:$ED82) -> 0 | C88: =SUMIF('Torrance Pro Forma'!$B$8:$ED$8,'Annual Pro Forma'!C$8,'Torrance Pro Forma'!$B82:$ED82) -> 0 | D88: =SUMIF('Torrance Pro Forma'!$B$8:$ED$8,'Annual Pro Forma'!D$8,'Torrance Pro Forma'!$B82:$ED82) -> 0 | E88: =SUMIF('Torrance Pro Forma'!$B$8:$ED$8,'Annual Pro Forma'!E$8,'Torrance Pro Forma'!$B82:$ED82) -> 0 | F88: =SUMIF('Torrance Pro Forma'!$B$8:$ED$8,'Annual Pro Forma'!F$8,'Torrance Pro Forma'!$B82:$ED82) -> 0 | G88: =SUMIF('Torrance Pro Forma'!$B$8:$ED$8,'Annual Pro Forma'!G$8,'Torrance Pro Forma'!$B82:$ED82) -> 0 | H88: =SUMIF('Torrance Pro Forma'!$B$8:$ED$8,'Annual Pro Forma'!H$8,'Torrance Pro Forma'!$B82:$ED82) -> 0 | I88: =SUMIF('Torrance Pro Forma'!$B$8:$ED$8,'Annual Pro Forma'!I$8,'Torrance Pro Forma'!$B82:$ED82) -> 0 | ... M88: =SUMIF('Torrance Pro Forma'!$B$8:$ED$8,'Annual Pro Forma'!M$8,'Torrance Pro Forma'!$B82:$ED82) -> 0
A89: Sale Price | B89: =SUMIF('Torrance Pro Forma'!$B$8:$ED$8,'Annual Pro Forma'!B$8,'Torrance Pro Forma'!$B83:$ED83) -> 0 | C89: =SUMIF('Torrance Pro Forma'!$B$8:$ED$8,'Annual Pro Forma'!C$8,'Torrance Pro Forma'!$B83:$ED83) -> 0 | D89: =SUMIF('Torrance Pro Forma'!$B$8:$ED$8,'Annual Pro Forma'!D$8,'Torrance Pro Forma'!$B83:$ED83) -> 0 | E89: =SUMIF('Torrance Pro Forma'!$B$8:$ED$8,'Annual Pro Forma'!E$8,'Torrance Pro Forma'!$B83:$ED83) -> 0 | F89: =SUMIF('Torrance Pro Forma'!$B$8:$ED$8,'Annual Pro Forma'!F$8,'Torrance Pro Forma'!$B83:$ED83) -> 0 | G89: =SUMIF('Torrance Pro Forma'!$B$8:$ED$8,'Annual Pro Forma'!G$8,'Torrance Pro Forma'!$B83:$ED83) -> 0 | H89: =SUMIF('Torrance Pro Forma'!$B$8:$ED$8,'Annual Pro Forma'!H$8,'Torrance Pro Forma'!$B83:$ED83) -> 0 | I89: =SUMIF('Torrance Pro Forma'!$B$8:$ED$8,'Annual Pro Forma'!I$8,'Torrance Pro Forma'!$B83:$ED83) -> 0 | ... M89: =SUMIF('Torrance Pro Forma'!$B$8:$ED$8,'Annual Pro Forma'!M$8,'Torrance Pro Forma'!$B83:$ED83) -> 0
A90: Cost of Sales | B90: =SUMIF('Torrance Pro Forma'!$B$8:$ED$8,'Annual Pro Forma'!B$8,'Torrance Pro Forma'!$B84:$ED84) -> 0 | C90: =SUMIF('Torrance Pro Forma'!$B$8:$ED$8,'Annual Pro Forma'!C$8,'Torrance Pro Forma'!$B84:$ED84) -> 0 | D90: =SUMIF('Torrance Pro Forma'!$B$8:$ED$8,'Annual Pro Forma'!D$8,'Torrance Pro Forma'!$B84:$ED84) -> 0 | E90: =SUMIF('Torrance Pro Forma'!$B$8:$ED$8,'Annual Pro Forma'!E$8,'Torrance Pro Forma'!$B84:$ED84) -> 0 | F90: =SUMIF('Torrance Pro Forma'!$B$8:$ED$8,'Annual Pro Forma'!F$8,'Torrance Pro Forma'!$B84:$ED84) -> 0 | G90: =SUMIF('Torrance Pro Forma'!$B$8:$ED$8,'Annual Pro Forma'!G$8,'Torrance Pro Forma'!$B84:$ED84) -> 0 | H90: =SUMIF('Torrance Pro Forma'!$B$8:$ED$8,'Annual Pro Forma'!H$8,'Torrance Pro Forma'!$B84:$ED84) -> 0 | I90: =SUMIF('Torrance Pro Forma'!$B$8:$ED$8,'Annual Pro Forma'!I$8,'Torrance Pro Forma'!$B84:$ED84) -> 0 | ... M90: =SUMIF('Torrance Pro Forma'!$B$8:$ED$8,'Annual Pro Forma'!M$8,'Torrance Pro Forma'!$B84:$ED84) -> 0
A91: Total Sale Proceeds | B91: =SUMIF('Torrance Pro Forma'!$B$8:$ED$8,'Annual Pro Forma'!B$8,'Torrance Pro Forma'!$B85:$ED85) -> 0 | C91: =SUMIF('Torrance Pro Forma'!$B$8:$ED$8,'Annual Pro Forma'!C$8,'Torrance Pro Forma'!$B85:$ED85) -> 0 | D91: =SUMIF('Torrance Pro Forma'!$B$8:$ED$8,'Annual Pro Forma'!D$8,'Torrance Pro Forma'!$B85:$ED85) -> 0 | E91: =SUMIF('Torrance Pro Forma'!$B$8:$ED$8,'Annual Pro Forma'!E$8,'Torrance Pro Forma'!$B85:$ED85) -> 0 | F91: =SUMIF('Torrance Pro Forma'!$B$8:$ED$8,'Annual Pro Forma'!F$8,'Torrance Pro Forma'!$B85:$ED85) -> 0 | G91: =SUMIF('Torrance Pro Forma'!$B$8:$ED$8,'Annual Pro Forma'!G$8,'Torrance Pro Forma'!$B85:$ED85) -> 0 | H91: =SUMIF('Torrance Pro Forma'!$B$8:$ED$8,'Annual Pro Forma'!H$8,'Torrance Pro Forma'!$B85:$ED85) -> 0 | I91: =SUMIF('Torrance Pro Forma'!$B$8:$ED$8,'Annual Pro Forma'!I$8,'Torrance Pro Forma'!$B85:$ED85) -> 0 | ... M91: =SUMIF('Torrance Pro Forma'!$B$8:$ED$8,'Annual Pro Forma'!M$8,'Torrance Pro Forma'!$B85:$ED85) -> 0
A93: Asset Cash Flow | B93: =SUMIF('Torrance Pro Forma'!$B$8:$ED$8,'Annual Pro Forma'!B$8,'Torrance Pro Forma'!$B87:$ED87) -> -17201613 | C93: =SUMIF('Torrance Pro Forma'!$B$8:$ED$8,'Annual Pro Forma'!C$8,'Torrance Pro Forma'!$B87:$ED87) -> 923702.82 | D93: =SUMIF('Torrance Pro Forma'!$B$8:$ED$8,'Annual Pro Forma'!D$8,'Torrance Pro Forma'!$B87:$ED87) -> 938349.24 | E93: =SUMIF('Torrance Pro Forma'!$B$8:$ED$8,'Annual Pro Forma'!E$8,'Torrance Pro Forma'!$B87:$ED87) -> 956664.54 | F93: =SUMIF('Torrance Pro Forma'!$B$8:$ED$8,'Annual Pro Forma'!F$8,'Torrance Pro Forma'!$B87:$ED87) -> -564658.67 | G93: =SUMIF('Torrance Pro Forma'!$B$8:$ED$8,'Annual Pro Forma'!G$8,'Torrance Pro Forma'!$B87:$ED87) -> -2175454.7 | H93: =SUMIF('Torrance Pro Forma'!$B$8:$ED$8,'Annual Pro Forma'!H$8,'Torrance Pro Forma'!$B87:$ED87) -> 2521755.4 | I93: =SUMIF('Torrance Pro Forma'!$B$8:$ED$8,'Annual Pro Forma'!I$8,'Torrance Pro Forma'!$B87:$ED87) -> -9687031.1 | ... M93: =SUMIF('Torrance Pro Forma'!$B$8:$ED$8,'Annual Pro Forma'!M$8,'Torrance Pro Forma'!$B87:$ED87) -> 0
A96: Asset IRR | B96: =XIRR(B93:M93,B9:M9) -> 0.19156041
A97: Asset MOIC | B97: =SUMIF(B93:M93,">0")/-SUMIF(B93:M93,"<0") -> 3.6532318

Sheet Torrance Pro Forma
C1: year 1-5 | D1: year 6-10
A2: Market Rent Inflation | C2: 0.03 | D2: 0.022
A3: Expense Inflation | C3: 0.03
A4: Cash Flow Projections
A5: Redlands Industrial Property
B7: Actuals | C7: Forecast | D7: Forecast | E7: Forecast | F7: Forecast | G7: Forecast | H7: Forecast | I7: Forecast | J7: Forecast | K7: Forecast | L7: Forecast | M7: Forecast | N7: Forecast | O7: Forecast | P7: Forecast | Q7: Forecast | R7: Forecast | S7: Forecast | T7: Forecast | U7: Forecast | V7: Forecast | W7: Forecast | X7: Forecast | Y7: Forecast | Z7: Forecast | AA7: Forecast | AB7: Forecast | AC7: Forecast | AD7: Forecast | AE7: Forecast | AF7: Forecast | AG7: Forecast | AH7: Forecast | AI7: Forecast | AJ7: Forecast | AK7: Forecast | AL7: Forecast | AM7: Forecast | AN7: Forecast | AO7: Forecast | AP7: Forecast | AQ7: Forecast | AR7: Forecast | AS7: Forecast | AT7: Forecast | AU7: Forecast | AV7: Forecast | AW7: Forecast | AX7: Forecast | AY7: Forecast | AZ7: Forecast | BA7: Forecast | BB7: Forecast | BC7: Forecast | BD7: Forecast | BE7: Forecast | BF7: Forecast | BG7: Forecast | BH7: Forecast | BI7: Forecast | BJ7: Forecast | BK7: Forecast | BL7: Forecast | BM7: Forecast | BN7: Forecast | BO7: Forecast | BP7: Forecast | BQ7: Forecast | BR7: Forecast | BS7: Forecast | BT7: Forecast | BU7: Forecast | BV7: Forecast | BW7: Forecast | BX7: Forecast | BY7: Forecast | BZ7: Forecast | CA7: Forecast | CB7: Forecast | CC7: Forecast | CD7: Forecast | CE7: Forecast | CF7: Forecast | CG7: Forecast | CH7: Forecast | CI7: Forecast | CJ7: Forecast | CK7: Forecast | CL7: Forecast | CM7: Forecast | CN7: Forecast | CO7: Forecast | CP7: Forecast | CQ7: Forecast | CR7: Forecast | CS7: Forecast | CT7: Forecast | CU7: Forecast | CV7: Forecast | CW7: Forecast | CX7: Forecast | CY7: Forecast | CZ7: Forecast | DA7: Forecast | DB7: Forecast | DC7: Forecast | DD7: Forecast | DE7: Forecast | DF7: Forecast | DG7: Forecast | DH7: Forecast | DI7: Forecast | DJ7: Forecast | DK7: Forecast | DL7: Forecast | DM7: Forecast | DN7: Forecast | DO7: Forecast | DP7: Forecast | DQ7: Forecast | DR7: Forecast | DS7: Forecast | DT7: Forecast | DU7: Forecast | DV7: Forecast | DW7: Forecast | DX7: Forecast | DY7: Forecast | DZ7: Forecast | EA7: Forecast | EB7: Forecast | EC7: Forecast | ED7: Forecast
B8: =ROUNDUP(B$9/12,0) -> 0 | C8: =ROUNDUP(C$9/12,0) -> 1 | D8: =ROUNDUP(D$9/12,0) -> 1 | E8: =ROUNDUP(E$9/12,0) -> 1 | F8: =ROUNDUP(F$9/12,0) -> 1 | G8: =ROUNDUP(G$9/12,0) -> 1 | H8: =ROUNDUP(H$9/12,0) -> 1 | I8: =ROUNDUP(I$9/12,0) -> 1 | ... ED8: =ROUNDUP(ED$9/12,0) -> 11
C9: {=_xlfn.SEQUENCE(1,('Torrance Inputs'!$D$20+1)*12,1,1)} -> 1 | D9: 2 | E9: 3 | F9: 4 | G9: 5 | H9: 6 | I9: 7 | J9: 8 | K9: 9 | L9: 10 | M9: 11 | N9: 12 | O9: 13 | P9: 14 | Q9: 15 | R9: 16 | S9: 17 | T9: 18 | U9: 19 | V9: 20 | W9: 21 | X9: 22 | Y9: 23 | Z9: 24 | AA9: 25 | AB9: 26 | AC9: 27 | AD9: 28 | AE9: 29 | AF9: 30 | AG9: 31 | AH9: 32 | AI9: 33 | AJ9: 34 | AK9: 35 | AL9: 36 | AM9: 37 | AN9: 38 | AO9: 39 | AP9: 40 | AQ9: 41 | AR9: 42 | AS9: 43 | AT9: 44 | AU9: 45 | AV9: 46 | AW9: 47 | AX9: 48 | AY9: 49 | AZ9: 50 | BA9: 51 | BB9: 52 | BC9: 53 | BD9: 54 | BE9: 55 | BF9: 56 | BG9: 57 | BH9: 58 | BI9: 59 | BJ9: 60 | BK9: 61 | BL9: 62 | BM9: 63 | BN9: 64 | BO9: 65 | BP9: 66 | BQ9: 67 | BR9: 68 | BS9: 69 | BT9: 70 | BU9: 71 | BV9: 72 | BW9: 73 | BX9: 74 | BY9: 75 | BZ9: 76 | CA9: 77 | CB9: 78 | CC9: 79 | CD9: 80 | CE9: 81 | CF9: 82 | CG9: 83 | CH9: 84 | CI9: 85 | CJ9: 86 | CK9: 87 | CL9: 88 | CM9: 89 | CN9: 90 | CO9: 91 | CP9: 92 | CQ9: 93 | CR9: 94 | CS9: 95 | CT9: 96 | CU9: 97 | CV9: 98 | CW9: 99 | CX9: 100 | CY9: 101 | CZ9: 102 | DA9: 103 | DB9: 104 | DC9: 105 | DD9: 106 | DE9: 107 | DF9: 108 | DG9: 109 | DH9: 110 | DI9: 111 | DJ9: 112 | DK9: 113 | DL9: 114 | DM9: 115 | DN9: 116 | DO9: 117 | DP9: 118 | DQ9: 119 | DR9: 120 | DS9: 121 | DT9: 122 | DU9: 123 | DV9: 124 | DW9: 125 | DX9: 126 | DY9: 127 | DZ9: 128 | EA9: 129 | EB9: 130 | EC9: 131 | ED9: 132
A10: Months | B10: =EDATE(C10,-12) -> 45292 | C10: =EDATE('Torrance Inputs'!analysis_start,0) -> 45658 | D10: =EOMONTH(C10,1) -> 45716 | E10: =EOMONTH(D10,1) -> 45747 | F10: =EOMONTH(E10,1) -> 45777 | G10: =EOMONTH(F10,1) -> 45808 | H10: =EOMONTH(G10,1) -> 45838 | I10: =EOMONTH(H10,1) -> 45869 | J10: =EOMONTH(I10,1) -> 45900 | K10: =EOMONTH(J10,1) -> 45930 | ... ED10: =EOMONTH(EC10,1) -> 49674
A12: Rental Revenue
A13: Base Rent / SF / Year | C13: =(C$16/'Torrance Inputs'!$D$10)*12 -> 4 | D13: =(D$16/'Torrance Inputs'!$D$10)*12 -> 4 | E13: =(E$16/'Torrance Inputs'!$D$10)*12 -> 4 | F13: =(F$16/'Torrance Inputs'!$D$10)*12 -> 4 | G13: =(G$16/'Torrance Inputs'!$D$10)*12 -> 4 | H13: =(H$16/'Torrance Inputs'!$D$10)*12 -> 4 | I13: =(I$16/'Torrance Inputs'!$D$10)*12 -> 4 | J13: =(J$16/'Torrance Inputs'!$D$10)*12 -> 4 | ... ED13: =(ED$16/'Torrance Inputs'!$D$10)*12 -> 19.582963
A14: Tenant 1 | C14: =IF(AND(C$10>='Torrance Inputs'!$N$38,C$10<'Torrance Inputs'!$N$40),'Torrance Inputs'!$M$41*(1+'Torrance Inputs'!$S$39)^('Torrance Pro Forma'!C$8-1),IF(C$10>='Torrance Inputs'!$I$18,'Torrance Inputs'!$H$22*(1+'Torrance Inputs'!$I$23)^(C$8-'Torrance Inputs'!$H$18),IF(C$10>=EDATE('Torrance Inputs'!$D$31,'Torrance Inputs'!$D$30),'Torrance Inputs'!$C$27*(1+'Torrance Inputs'!$D$35)^(ROUNDDOWN((C$9-1)/12,0)),0))) -> 91666.667 | D14: =IF(AND(D$10>='Torrance Inputs'!$N$38,D$10<'Torrance Inputs'!$N$40),'Torrance Inputs'!$M$41*(1+'Torrance Inputs'!$S$39)^('Torrance Pro Forma'!D$8-1),IF(D$10>='Torrance Inputs'!$I$18,'Torrance Inputs'!$H$22*(1+'Torrance Inputs'!$I$23)^(D$8-'Torrance Inputs'!$H$18),IF(D$10>=EDATE('Torrance Inputs'!$D$31,'Torrance Inputs'!$D$30),'Torrance Inputs'!$C$27*(1+'Torrance Inputs'!$D$35)^(ROUNDDOWN((D$9-1)/12,0)),0))) -> 91666.667 | E14: =IF(AND(E$10>='Torrance Inputs'!$N$38,E$10<'Torrance Inputs'!$N$40),'Torrance Inputs'!$M$41*(1+'Torrance Inputs'!$S$39)^('Torrance Pro Forma'!E$8-1),IF(E$10>='Torrance Inputs'!$I$18,'Torrance Inputs'!$H$22*(1+'Torrance Inputs'!$I$23)^(E$8-'Torrance Inputs'!$H$18),IF(E$10>=EDATE('Torrance Inputs'!$D$31,'Torrance Inputs'!$D$30),'Torrance Inputs'!$C$27*(1+'Torrance Inputs'!$D$35)^(ROUNDDOWN((E$9-1)/12,0)),0))) -> 91666.667 | F14: =IF(AND(F$10>='Torrance Inputs'!$N$38,F$10<'Torrance Inputs'!$N$40),'Torrance Inputs'!$M$41*(1+'Torrance Inputs'!$S$39)^('Torrance Pro Forma'!F$8-1),IF(F$10>='Torrance Inputs'!$I$18,'Torrance Inputs'!$H$22*(1+'Torrance Inputs'!$I$23)^(F$8-'Torrance Inputs'!$H$18),IF(F$10>=EDATE('Torrance Inputs'!$D$31,'Torrance Inputs'!$D$30),'Torrance Inputs'!$C$27*(1+'Torrance Inputs'!$D$35)^(ROUNDDOWN((F$9-1)/12,0)),0))) -> 91666.667 | G14: =IF(AND(G$10>='Torrance Inputs'!$N$38,G$10<'Torrance Inputs'!$N$40),'Torrance Inputs'!$M$41*(1+'Torrance Inputs'!$S$39)^('Torrance Pro Forma'!G$8-1),IF(G$10>='Torrance Inputs'!$I$18,'Torrance Inputs'!$H$22*(1+'Torrance Inputs'!$I$23)^(G$8-'Torrance Inputs'!$H$18),IF(G$10>=EDATE('Torrance Inputs'!$D$31,'Torrance Inputs'!$D$30),'Torrance Inputs'!$C$27*(1+'Torrance Inputs'!$D$35)^(ROUNDDOWN((G$9-1)/12,0)),0))) -> 91666.667 | H14: =IF(AND(H$10>='Torrance Inputs'!$N$38,H$10<'Torrance Inputs'!$N$40),'Torrance Inputs'!$M$41*(1+'Torrance Inputs'!$S$39)^('Torrance Pro Forma'!H$8-1),IF(H$10>='Torrance Inputs'!$I$18,'Torrance Inputs'!$H$22*(1+'Torrance Inputs'!$I$23)^(H$8-'Torrance Inputs'!$H$18),IF(H$10>=EDATE('Torrance Inputs'!$D$31,'Torrance Inputs'!$D$30),'Torrance Inputs'!$C$27*(1+'Torrance Inputs'!$D$35)^(ROUNDDOWN((H$9-1)/12,0)),0))) -> 91666.667 | I14: =IF(AND(I$10>='Torrance Inputs'!$N$38,I$10<'Torrance Inputs'!$N$40),'Torrance Inputs'!$M$41*(1+'Torrance Inputs'!$S$39)^('Torrance Pro Forma'!I$8-1),IF(I$10>='Torrance Inputs'!$I$18,'Torrance Inputs'!$H$22*(1+'Torrance Inputs'!$I$23)^(I$8-'Torrance Inputs'!$H$18),IF(I$10>=EDATE('Torrance Inputs'!$D$31,'Torrance Inputs'!$D$30),'Torrance Inputs'!$C$27*(1+'Torrance Inputs'!$D$35)^(ROUNDDOWN((I$9-1)/12,0)),0))) -> 91666.667 | J14: =IF(AND(J$10>='Torrance Inputs'!$N$38,J$10<'Torrance Inputs'!$N$40),'Torrance Inputs'!$M$41*(1+'Torrance Inputs'!$S$39)^('Torrance Pro Forma'!J$8-1),IF(J$10>='Torrance Inputs'!$I$18,'Torrance Inputs'!$H$22*(1+'Torrance Inputs'!$I$23)^(J$8-'Torrance Inputs'!$H$18),IF(J$10>=EDATE('Torrance Inputs'!$D$31,'Torrance Inputs'!$D$30),'Torrance Inputs'!$C$27*(1+'Torrance Inputs'!$D$35)^(ROUNDDOWN((J$9-1)/12,0)),0))) -> 91666.667 | ... ED14: =IF(AND(ED$10>='Torrance Inputs'!$N$38,ED$10<'Torrance Inputs'!$N$40),'Torrance Inputs'!$M$41*(1+'Torrance Inputs'!$S$39)^('Torrance Pro Forma'!ED$8-1),IF(ED$10>='Torrance Inputs'!$I$18,'Torrance Inputs'!$H$22*(1+'Torrance Inputs'!$I$23)^(ED$8-'Torrance Inputs'!$H$18),IF(ED$10>=EDATE('Torrance Inputs'!$D$31,'Torrance Inputs'!$D$30),'Torrance Inputs'!$C$27*(1+'Torrance Inputs'!$D$35)^(ROUNDDOWN((ED$9-1)/12,0)),0))) -> 224388.12
A15: Tenant 2 | C15: =IF(C$10>='Torrance Inputs'!$I$18,'Torrance Inputs'!$H$22*(1+'Torrance Inputs'!$I$23)^(C8-'Torrance Inputs'!$M$18),IF(C$10>=EDATE('Torrance Inputs'!$D$31,'Torrance Inputs'!$D$30),'Torrance Inputs'!$C$27*(1+'Torrance Inputs'!$D$35)^(ROUNDDOWN((C$9-1)/12,0)),0)) -> 0 | D15: =IF(D$10>='Torrance Inputs'!$I$18,'Torrance Inputs'!$H$22*(1+'Torrance Inputs'!$I$23)^(D8-'Torrance Inputs'!$M$18),IF(D$10>=EDATE('Torrance Inputs'!$D$31,'Torrance Inputs'!$D$30),'Torrance Inputs'!$C$27*(1+'Torrance Inputs'!$D$35)^(ROUNDDOWN((D$9-1)/12,0)),0)) -> 0 | E15: =IF(E$10>='Torrance Inputs'!$I$18,'Torrance Inputs'!$H$22*(1+'Torrance Inputs'!$I$23)^(E8-'Torrance Inputs'!$M$18),IF(E$10>=EDATE('Torrance Inputs'!$D$31,'Torrance Inputs'!$D$30),'Torrance Inputs'!$C$27*(1+'Torrance Inputs'!$D$35)^(ROUNDDOWN((E$9-1)/12,0)),0)) -> 0 | F15: =IF(F$10>='Torrance Inputs'!$I$18,'Torrance Inputs'!$H$22*(1+'Torrance Inputs'!$I$23)^(F8-'Torrance Inputs'!$M$18),IF(F$10>=EDATE('Torrance Inputs'!$D$31,'Torrance Inputs'!$D$30),'Torrance Inputs'!$C$27*(1+'Torrance Inputs'!$D$35)^(ROUNDDOWN((F$9-1)/12,0)),0)) -> 0 | G15: =IF(G$10>='Torrance Inputs'!$I$18,'Torrance Inputs'!$H$22*(1+'Torrance Inputs'!$I$23)^(G8-'Torrance Inputs'!$M$18),IF(G$10>=EDATE('Torrance Inputs'!$D$31,'Torrance Inputs'!$D$30),'Torrance Inputs'!$C$27*(1+'Torrance Inputs'!$D$35)^(ROUNDDOWN((G$9-1)/12,0)),0)) -> 0 | H15: =IF(H$10>='Torrance Inputs'!$I$18,'Torrance Inputs'!$H$22*(1+'Torrance Inputs'!$I$23)^(H8-'Torrance Inputs'!$M$18),IF(H$10>=EDATE('Torrance Inputs'!$D$31,'Torrance Inputs'!$D$30),'Torrance Inputs'!$C$27*(1+'Torrance Inputs'!$D$35)^(ROUNDDOWN((H$9-1)/12,0)),0)) -> 0 | I15: =IF(I$10>='Torrance Inputs'!$I$18,'Torrance Inputs'!$H$22*(1+'Torrance Inputs'!$I$23)^(I8-'Torrance Inputs'!$M$18),IF(I$10>=EDATE('Torrance Inputs'!$D$31,'Torrance Inputs'!$D$30),'Torrance Inputs'!$C$27*(1+'Torrance Inputs'!$D$35)^(ROUNDDOWN((I$9-1)/12,0)),0)) -> 0 | J15: =IF(J$10>='Torrance Inputs'!$I$18,'Torrance Inputs'!$H$22*(1+'Torrance Inputs'!$I$23)^(J8-'Torrance Inputs'!$M$18),IF(J$10>=EDATE('Torrance Inputs'!$D$31,'Torrance Inputs'!$D$30),'Torrance Inputs'!$C$27*(1+'Torrance Inputs'!$D$35)^(ROUNDDOWN((J$9-1)/12,0)),0)) -> 0 | ... ED15: =IF(ED$10>='Torrance Inputs'!$I$18,'Torrance Inputs'!$H$22*(1+'Torrance Inputs'!$I$23)^(ED8-'Torrance Inputs'!$M$18),IF(ED$10>=EDATE('Torrance Inputs'!$D$31,'Torrance Inputs'!$D$30),'Torrance Inputs'!$C$27*(1+'Torrance Inputs'!$D$35)^(ROUNDDOWN((ED$9-1)/12,0)),0)) -> 224388.12
A16: Potential Base Rent | C16: =SUM(C14:C15) -> 91666.667 | D16: =SUM(D14:D15) -> 91666.667 | E16: =SUM(E14:E15) -> 91666.667 | F16: =SUM(F14:F15) -> 91666.667 | G16: =SUM(G14:G15) -> 91666.667 | H16: =SUM(H14:H15) -> 91666.667 | I16: =SUM(I14:I15) -> 91666.667 | J16: =SUM(J14:J15) -> 91666.667 | ... ED16: =SUM(ED14:ED15) -> 448776.25
A17: Vacancy / Turnover | C17: =IF(AND(C$10>='Torrance Inputs'!$I$18,C$10<='Torrance Inputs'!$R$18),0,IF(C$10>='Torrance Inputs'!$N$38,0,-C$16)) -> 0 | D17: =IF(AND(D$10>='Torrance Inputs'!$I$18,D$10<='Torrance Inputs'!$R$18),0,IF(D$10>='Torrance Inputs'!$N$38,0,-D$16)) -> 0 | E17: =IF(AND(E$10>='Torrance Inputs'!$I$18,E$10<='Torrance Inputs'!$R$18),0,IF(E$10>='Torrance Inputs'!$N$38,0,-E$16)) -> 0 | F17: =IF(AND(F$10>='Torrance Inputs'!$I$18,F$10<='Torrance Inputs'!$R$18),0,IF(F$10>='Torrance Inputs'!$N$38,0,-F$16)) -> 0 | G17: =IF(AND(G$10>='Torrance Inputs'!$I$18,G$10<='Torrance Inputs'!$R$18),0,IF(G$10>='Torrance Inputs'!$N$38,0,-G$16)) -> 0 | H17: =IF(AND(H$10>='Torrance Inputs'!$I$18,H$10<='Torrance Inputs'!$R$18),0,IF(H$10>='Torrance Inputs'!$N$38,0,-H$16)) -> 0 | I17: =IF(AND(I$10>='Torrance Inputs'!$I$18,I$10<='Torrance Inputs'!$R$18),0,IF(I$10>='Torrance Inputs'!$N$38,0,-I$16)) -> 0 | J17: =IF(AND(J$10>='Torrance Inputs'!$I$18,J$10<='Torrance Inputs'!$R$18),0,IF(J$10>='Torrance Inputs'!$N$38,0,-J$16)) -> 0 | ... ED17: =IF(AND(ED$10>='Torrance Inputs'!$I$18,ED$10<='Torrance Inputs'!$R$18),0,IF(ED$10>='Torrance Inputs'!$N$38,0,-ED$16)) -> 0
A18: Security Deposit | C18: =IF('Torrance Pro Forma'!C$9='Torrance Inputs'!$G$18,'Torrance Inputs'!$C$39,0) -> 0 | D18: =IF('Torrance Pro Forma'!D$9='Torrance Inputs'!$G$18,'Torrance Inputs'!$C$39,0) -> 0 | E18: =IF('Torrance Pro Forma'!E$9='Torrance Inputs'!$G$18,'Torrance Inputs'!$C$39,0) -> 0 | F18: =IF('Torrance Pro Forma'!F$9='Torrance Inputs'!$G$18,'Torrance Inputs'!$C$39,0) -> 0 | G18: =IF('Torrance Pro Forma'!G$9='Torrance Inputs'!$G$18,'Torrance Inputs'!$C$39,0) -> 0 | H18: =IF('Torrance Pro Forma'!H$9='Torrance Inputs'!$G$18,'Torrance Inputs'!$C$39,0) -> 0 | I18: =IF('Torrance Pro Forma'!I$9='Torrance Inputs'!$G$18,'Torrance Inputs'!$C$39,0) -> 0 | J18: =IF('Torrance Pro Forma'!J$9='Torrance Inputs'!$G$18,'Torrance Inputs'!$C$39,0) -> 0 | ... ED18: =IF('Torrance Pro Forma'!ED$9='Torrance Inputs'!$G$18,'Torrance Inputs'!$C$39,0) -> 0
A19: Free Rent / Concessions | C19: =-IF(AND(C$10>='Torrance Inputs'!$I$18,C$10<'Torrance Inputs'!$R$18),('Torrance Inputs'!$D$37*'Torrance Inputs'!$H$22)/DATEDIF('Torrance Inputs'!$I$18,'Torrance Inputs'!$R$18,"m"),0) -> 0 | D19: =-IF(AND(D$10>='Torrance Inputs'!$I$18,D$10<'Torrance Inputs'!$R$18),('Torrance Inputs'!$D$37*'Torrance Inputs'!$H$22)/DATEDIF('Torrance Inputs'!$I$18,'Torrance Inputs'!$R$18,"m"),0) -> 0 | E19: =-IF(AND(E$10>='Torrance Inputs'!$I$18,E$10<'Torrance Inputs'!$R$18),('Torrance Inputs'!$D$37*'Torrance Inputs'!$H$22)/DATEDIF('Torrance Inputs'!$I$18,'Torrance Inputs'!$R$18,"m"),0) -> 0 | F19: =-IF(AND(F$10>='Torrance Inputs'!$I$18,F$10<'Torrance Inputs'!$R$18),('Torrance Inputs'!$D$37*'Torrance Inputs'!$H$22)/DATEDIF('Torrance Inputs'!$I$18,'Torrance Inputs'!$R$18,"m"),0) -> 0 | G19: =-IF(AND(G$10>='Torrance Inputs'!$I$18,G$10<'Torrance Inputs'!$R$18),('Torrance Inputs'!$D$37*'Torrance Inputs'!$H$22)/DATEDIF('Torrance Inputs'!$I$18,'Torrance Inputs'!$R$18,"m"),0) -> 0 | H19: =-IF(AND(H$10>='Torrance Inputs'!$I$18,H$10<'Torrance Inputs'!$R$18),('Torrance Inputs'!$D$37*'Torrance Inputs'!$H$22)/DATEDIF('Torrance Inputs'!$I$18,'Torrance Inputs'!$R$18,"m"),0) -> 0 | I19: =-IF(AND(I$10>='Torrance Inputs'!$I$18,I$10<'Torrance Inputs'!$R$18),('Torrance Inputs'!$D$37*'Torrance Inputs'!$H$22)/DATEDIF('Torrance Inputs'!$I$18,'Torrance Inputs'!$R$18,"m"),0) -> 0 | J19: =-IF(AND(J$10>='Torrance Inputs'!$I$18,J$10<'Torrance Inputs'!$R$18),('Torrance Inputs'!$D$37*'Torrance Inputs'!$H$22)/DATEDIF('Torrance Inputs'!$I$18,'Torrance Inputs'!$R$18,"m"),0) -> 0 | ... ED19: =-IF(AND(ED$10>='Torrance Inputs'!$I$18,ED$10<'Torrance Inputs'!$R$18),('Torrance Inputs'!$D$37*'Torrance Inputs'!$H$22)/DATEDIF('Torrance Inputs'!$I$18,'Torrance Inputs'!$R$18,"m"),0) -> -4801.2104
A20: Total Base Rent | C20: =SUM(C16:C19) -> 91666.667 | D20: =SUM(D16:D19) -> 91666.667 | E20: =SUM(E16:E19) -> 91666.667 | F20: =SUM(F16:F19) -> 91666.667 | G20: =SUM(G16:G19) -> 91666.667 | H20: =SUM(H16:H19) -> 91666.667 | I20: =SUM(I16:I19) -> 91666.667 | J20: =SUM(J16:J19) -> 91666.667 | ... ED20: =SUM(ED16:ED19) -> 443975.04
A21: Total Rental Revenue | C21: =C20 -> 91666.667 | D21: =D20 -> 91666.667 | E21: =E20 -> 91666.667 | F21: =F20 -> 91666.667 | G21: =G20 -> 91666.667 | H21: =H20 -> 91666.667 | I21: =I20 -> 91666.667 | J21: =J20 -> 91666.667 | ... ED21: =ED20 -> 443975.04
A23: Other Tenant Revenue
A24: Utilities | C24: =IF(AND(C$10>='Torrance Inputs'!$N$38,C$10<'Torrance Inputs'!$N$40),'Torrance Inputs'!$Q3*'Torrance Pro Forma'!$C46,IF(C$10>='Torrance Inputs'!$I$18,'Torrance Inputs'!$M$3*'Torrance Pro Forma'!$C46,0)) -> 1250 | D24: =IF(AND(D$10>='Torrance Inputs'!$N$38,D$10<'Torrance Inputs'!$N$40),'Torrance Inputs'!$Q3*'Torrance Pro Forma'!$C46,IF(D$10>='Torrance Inputs'!$I$18,'Torrance Inputs'!$M$3*'Torrance Pro Forma'!$C46,0)) -> 1250 | E24: =IF(AND(E$10>='Torrance Inputs'!$N$38,E$10<'Torrance Inputs'!$N$40),'Torrance Inputs'!$Q3*'Torrance Pro Forma'!$C46,IF(E$10>='Torrance Inputs'!$I$18,'Torrance Inputs'!$M$3*'Torrance Pro Forma'!$C46,0)) -> 1250 | F24: =IF(AND(F$10>='Torrance Inputs'!$N$38,F$10<'Torrance Inputs'!$N$40),'Torrance Inputs'!$Q3*'Torrance Pro Forma'!$C46,IF(F$10>='Torrance Inputs'!$I$18,'Torrance Inputs'!$M$3*'Torrance Pro Forma'!$C46,0)) -> 1250 | G24: =IF(AND(G$10>='Torrance Inputs'!$N$38,G$10<'Torrance Inputs'!$N$40),'Torrance Inputs'!$Q3*'Torrance Pro Forma'!$C46,IF(G$10>='Torrance Inputs'!$I$18,'Torrance Inputs'!$M$3*'Torrance Pro Forma'!$C46,0)) -> 1250 | H24: =IF(AND(H$10>='Torrance Inputs'!$N$38,H$10<'Torrance Inputs'!$N$40),'Torrance Inputs'!$Q3*'Torrance Pro Forma'!$C46,IF(H$10>='Torrance Inputs'!$I$18,'Torrance Inputs'!$M$3*'Torrance Pro Forma'!$C46,0)) -> 1250 | I24: =IF(AND(I$10>='Torrance Inputs'!$N$38,I$10<'Torrance Inputs'!$N$40),'Torrance Inputs'!$Q3*'Torrance Pro Forma'!$C46,IF(I$10>='Torrance Inputs'!$I$18,'Torrance Inputs'!$M$3*'Torrance Pro Forma'!$C46,0)) -> 1250 | J24: =IF(AND(J$10>='Torrance Inputs'!$N$38,J$10<'Torrance Inputs'!$N$40),'Torrance Inputs'!$Q3*'Torrance Pro Forma'!$C46,IF(J$10>='Torrance Inputs'!$I$18,'Torrance Inputs'!$M$3*'Torrance Pro Forma'!$C46,0)) -> 1250 | ... ED24: =IF(AND(ED$10>='Torrance Inputs'!$N$38,ED$10<'Torrance Inputs'!$N$40),'Torrance Inputs'!$Q3*'Torrance Pro Forma'!$C46,IF(ED$10>='Torrance Inputs'!$I$18,'Torrance Inputs'!$M$3*'Torrance Pro Forma'!$C46,0)) -> 1250
A25: Repairs & Maintenance | C25: =IF(AND(C$10>='Torrance Inputs'!$N$38,C$10<'Torrance Inputs'!$N$40),'Torrance Inputs'!$Q4*'Torrance Pro Forma'!C$47,IF(C$10>='Torrance Inputs'!$I$18,'Torrance Inputs'!$M$3*'Torrance Pro Forma'!C$47,0)) -> 1250 | D25: =IF(AND(D$10>='Torrance Inputs'!$N$38,D$10<'Torrance Inputs'!$N$40),'Torrance Inputs'!$Q4*'Torrance Pro Forma'!D$47,IF(D$10>='Torrance Inputs'!$I$18,'Torrance Inputs'!$M$3*'Torrance Pro Forma'!D$47,0)) -> 1250 | E25: =IF(AND(E$10>='Torrance Inputs'!$N$38,E$10<'Torrance Inputs'!$N$40),'Torrance Inputs'!$Q4*'Torrance Pro Forma'!E$47,IF(E$10>='Torrance Inputs'!$I$18,'Torrance Inputs'!$M$3*'Torrance Pro Forma'!E$47,0)) -> 1250 | F25: =IF(AND(F$10>='Torrance Inputs'!$N$38,F$10<'Torrance Inputs'!$N$40),'Torrance Inputs'!$Q4*'Torrance Pro Forma'!F$47,IF(F$10>='Torrance Inputs'!$I$18,'Torrance Inputs'!$M$3*'Torrance Pro Forma'!F$47,0)) -> 1250 | G25: =IF(AND(G$10>='Torrance Inputs'!$N$38,G$10<'Torrance Inputs'!$N$40),'Torrance Inputs'!$Q4*'Torrance Pro Forma'!G$47,IF(G$10>='Torrance Inputs'!$I$18,'Torrance Inputs'!$M$3*'Torrance Pro Forma'!G$47,0)) -> 1250 | H25: =IF(AND(H$10>='Torrance Inputs'!$N$38,H$10<'Torrance Inputs'!$N$40),'Torrance Inputs'!$Q4*'Torrance Pro Forma'!H$47,IF(H$10>='Torrance Inputs'!$I$18,'Torrance Inputs'!$M$3*'Torrance Pro Forma'!H$47,0)) -> 1250 | I25: =IF(AND(I$10>='Torrance Inputs'!$N$38,I$10<'Torrance Inputs'!$N$40),'Torrance Inputs'!$Q4*'Torrance Pro Forma'!I$47,IF(I$10>='Torrance Inputs'!$I$18,'Torrance Inputs'!$M$3*'Torrance Pro Forma'!I$47,0)) -> 1250 | J25: =IF(AND(J$10>='Torrance Inputs'!$N$38,J$10<'Torrance Inputs'!$N$40),'Torrance Inputs'!$Q4*'Torrance Pro Forma'!J$47,IF(J$10>='Torrance Inputs'!$I$18,'Torrance Inputs'!$M$3*'Torrance Pro Forma'!J$47,0)) -> 1250 | ... ED25: =IF(AND(ED$10>='Torrance Inputs'!$N$38,ED$10<'Torrance Inputs'!$N$40),'Torrance Inputs'!$Q4*'Torrance Pro Forma'!ED$47,IF(ED$10>='Torrance Inputs'!$I$18,'Torrance Inputs'!$M$3*'Torrance Pro Forma'!ED$47,0)) -> 1679.8955
A26: Insurance | C26: =IF(AND(C$10>='Torrance Inputs'!$N$38,C$10<'Torrance Inputs'!$N$40),'Torrance Inputs'!$Q5*'Torrance Pro Forma'!C$48,IF(C$10>='Torrance Inputs'!$I$18,'Torrance Inputs'!$M$3*'Torrance Pro Forma'!C$48,0)) -> 416.66667 | D26: =IF(AND(D$10>='Torrance Inputs'!$N$38,D$10<'Torrance Inputs'!$N$40),'Torrance Inputs'!$Q5*'Torrance Pro Forma'!D$48,IF(D$10>='Torrance Inputs'!$I$18,'Torrance Inputs'!$M$3*'Torrance Pro Forma'!D$48,0)) -> 416.66667 | E26: =IF(AND(E$10>='Torrance Inputs'!$N$38,E$10<'Torrance Inputs'!$N$40),'Torrance Inputs'!$Q5*'Torrance Pro Forma'!E$48,IF(E$10>='Torrance Inputs'!$I$18,'Torrance Inputs'!$M$3*'Torrance Pro Forma'!E$48,0)) -> 416.66667 | F26: =IF(AND(F$10>='Torrance Inputs'!$N$38,F$10<'Torrance Inputs'!$N$40),'Torrance Inputs'!$Q5*'Torrance Pro Forma'!F$48,IF(F$10>='Torrance Inputs'!$I$18,'Torrance Inputs'!$M$3*'Torrance Pro Forma'!F$48,0)) -> 416.66667 | G26: =IF(AND(G$10>='Torrance Inputs'!$N$38,G$10<'Torrance Inputs'!$N$40),'Torrance Inputs'!$Q5*'Torrance Pro Forma'!G$48,IF(G$10>='Torrance Inputs'!$I$18,'Torrance Inputs'!$M$3*'Torrance Pro Forma'!G$48,0)) -> 416.66667 | H26: =IF(AND(H$10>='Torrance Inputs'!$N$38,H$10<'Torrance Inputs'!$N$40),'Torrance Inputs'!$Q5*'Torrance Pro Forma'!H$48,IF(H$10>='Torrance Inputs'!$I$18,'Torrance Inputs'!$M$3*'Torrance Pro Forma'!H$48,0)) -> 416.66667 | I26: =IF(AND(I$10>='Torrance Inputs'!$N$38,I$10<'Torrance Inputs'!$N$40),'Torrance Inputs'!$Q5*'Torrance Pro Forma'!I$48,IF(I$10>='Torrance Inputs'!$I$18,'Torrance Inputs'!$M$3*'Torrance Pro Forma'!I$48,0)) -> 416.66667 | J26: =IF(AND(J$10>='Torrance Inputs'!$N$38,J$10<'Torrance Inputs'!$N$40),'Torrance Inputs'!$Q5*'Torrance Pro Forma'!J$48,IF(J$10>='Torrance Inputs'!$I$18,'Torrance Inputs'!$M$3*'Torrance Pro Forma'!J$48,0)) -> 416.66667 | ... ED26: =IF(AND(ED$10>='Torrance Inputs'!$N$38,ED$10<'Torrance Inputs'!$N$40),'Torrance Inputs'!$Q5*'Torrance Pro Forma'!ED$48,IF(ED$10>='Torrance Inputs'!$I$18,'Torrance Inputs'!$M$3*'Torrance Pro Forma'!ED$48,0)) -> 559.96516
A27: Property Taxes | C27: =IF(AND(C$10>='Torrance Inputs'!$N$38,C$10<'Torrance Inputs'!$N$40),'Torrance Inputs'!$Q6*'Torrance Pro Forma'!C$49,IF(C$10>='Torrance Inputs'!$I$18,'Torrance Inputs'!$M$3*'Torrance Pro Forma'!C$49,0)) -> 0 | D27: =IF(AND(D$10>='Torrance Inputs'!$N$38,D$10<'Torrance Inputs'!$N$40),'Torrance Inputs'!$Q6*'Torrance Pro Forma'!D$49,IF(D$10>='Torrance Inputs'!$I$18,'Torrance Inputs'!$M$3*'Torrance Pro Forma'!D$49,0)) -> 0 | E27: =IF(AND(E$10>='Torrance Inputs'!$N$38,E$10<'Torrance Inputs'!$N$40),'Torrance Inputs'!$Q6*'Torrance Pro Forma'!E$49,IF(E$10>='Torrance Inputs'!$I$18,'Torrance Inputs'!$M$3*'Torrance Pro Forma'!E$49,0)) -> 0 | F27: =IF(AND(F$10>='Torrance Inputs'!$N$38,F$10<'Torrance Inputs'!$N$40),'Torrance Inputs'!$Q6*'Torrance Pro Forma'!F$49,IF(F$10>='Torrance Inputs'!$I$18,'Torrance Inputs'!$M$3*'Torrance Pro Forma'!F$49,0)) -> 0 | G27: =IF(AND(G$10>='Torrance Inputs'!$N$38,G$10<'Torrance Inputs'!$N$40),'Torrance Inputs'!$Q6*'Torrance Pro Forma'!G$49,IF(G$10>='Torrance Inputs'!$I$18,'Torrance Inputs'!$M$3*'Torrance Pro Forma'!G$49,0)) -> 0 | H27: =IF(AND(H$10>='Torrance Inputs'!$N$38,H$10<'Torrance Inputs'!$N$40),'Torrance Inputs'!$Q6*'Torrance Pro Forma'!H$49,IF(H$10>='Torrance Inputs'!$I$18,'Torrance Inputs'!$M$3*'Torrance Pro Forma'!H$49,0)) -> 0 | I27: =IF(AND(I$10>='Torrance Inputs'!$N$38,I$10<'Torrance Inputs'!$N$40),'Torrance Inputs'!$Q6*'Torrance Pro Forma'!I$49,IF(I$10>='Torrance Inputs'!$I$18,'Torrance Inputs'!$M$3*'Torrance Pro Forma'!I$49,0)) -> 0 | J27: =IF(AND(J$10>='Torrance Inputs'!$N$38,J$10<'Torrance Inputs'!$N$40),'Torrance Inputs'!$Q6*'Torrance Pro Forma'!J$49,IF(J$10>='Torrance Inputs'!$I$18,'Torrance Inputs'!$M$3*'Torrance Pro Forma'!J$49,0)) -> 0 | ... ED27: =IF(AND(ED$10>='Torrance Inputs'!$N$38,ED$10<'Torrance Inputs'!$N$40),'Torrance Inputs'!$Q6*'Torrance Pro Forma'!ED$49,IF(ED$10>='Torrance Inputs'!$I$18,'Torrance Inputs'!$M$3*'Torrance Pro Forma'!ED$49,0)) -> 19613.552
A28: Total Expense Recoveries | C28: =SUM(C24:C27) -> 2916.6667 | D28: =SUM(D24:D27) -> 2916.6667 | E28: =SUM(E24:E27) -> 2916.6667 | F28: =SUM(F24:F27) -> 2916.6667 | G28: =SUM(G24:G27) -> 2916.6667 | H28: =SUM(H24:H27) -> 2916.6667 | I28: =SUM(I24:I27) -> 2916.6667 | J28: =SUM(J24:J27) -> 2916.6667 | ... ED28: =SUM(ED24:ED27) -> 23103.413
A29: Total Other Tenant Revenue | C29: =SUM(C28) -> 2916.6667 | D29: =SUM(D28) -> 2916.6667 | E29: =SUM(E28) -> 2916.6667 | F29: =SUM(F28) -> 2916.6667 | G29: =SUM(G28) -> 2916.6667 | H29: =SUM(H28) -> 2916.6667 | I29: =SUM(I28) -> 2916.6667 | J29: =SUM(J28) -> 2916.6667 | ... ED29: =SUM(ED28) -> 23103.413
A31: Total Tenant Revenue | C31: =C21+C29 -> 94583.333 | D31: =D21+D29 -> 94583.333 | E31: =E21+E29 -> 94583.333 | F31: =F21+F29 -> 94583.333 | G31: =G21+G29 -> 94583.333 | H31: =H21+H29 -> 94583.333 | I31: =I21+I29 -> 94583.333 | J31: =J21+J29 -> 94583.333 | ... ED31: =ED21+ED29 -> 467078.45
A33: Other Income
A34: Parking Income | C34: =IF(AND(C$14=0,C$15=0),0,'Torrance Inputs'!$R$24*(1+'Torrance Inputs'!$T$22)^('Torrance Pro Forma'!C$8-1)) -> 15895 | D34: =IF(AND(D$14=0,D$15=0),0,'Torrance Inputs'!$R$24*(1+'Torrance Inputs'!$T$22)^('Torrance Pro Forma'!D$8-1)) -> 15895 | E34: =IF(AND(E$14=0,E$15=0),0,'Torrance Inputs'!$R$24*(1+'Torrance Inputs'!$T$22)^('Torrance Pro Forma'!E$8-1)) -> 15895 | F34: =IF(AND(F$14=0,F$15=0),0,'Torrance Inputs'!$R$24*(1+'Torrance Inputs'!$T$22)^('Torrance Pro Forma'!F$8-1)) -> 15895 | G34: =IF(AND(G$14=0,G$15=0),0,'Torrance Inputs'!$R$24*(1+'Torrance Inputs'!$T$22)^('Torrance Pro Forma'!G$8-1)) -> 15895 | H34: =IF(AND(H$14=0,H$15=0),0,'Torrance Inputs'!$R$24*(1+'Torrance Inputs'!$T$22)^('Torrance Pro Forma'!H$8-1)) -> 15895 | I34: =IF(AND(I$14=0,I$15=0),0,'Torrance Inputs'!$R$24*(1+'Torrance Inputs'!$T$22)^('Torrance Pro Forma'!I$8-1)) -> 15895 | J34: =IF(AND(J$14=0,J$15=0),0,'Torrance Inputs'!$R$24*(1+'Torrance Inputs'!$T$22)^('Torrance Pro Forma'!J$8-1)) -> 15895 | ... ED34: =IF(AND(ED$14=0,ED$15=0),0,'Torrance Inputs'!$R$24*(1+'Torrance Inputs'!$T$22)^('Torrance Pro Forma'!ED$8-1)) -> 19375.916
A35: Total Other Income | C35: =C34 -> 15895 | D35: =D34 -> 15895 | E35: =E34 -> 15895 | F35: =F34 -> 15895 | G35: =G34 -> 15895 | H35: =H34 -> 15895 | I35: =I34 -> 15895 | J35: =J34 -> 15895 | ... ED35: =ED34 -> 19375.916
A37: Potential Gross Revenue | C37: =C35+C31 -> 110478.33 | D37: =D35+D31 -> 110478.33 | E37: =E35+E31 -> 110478.33 | F37: =F35+F31 -> 110478.33 | G37: =G35+G31 -> 110478.33 | H37: =H35+H31 -> 110478.33 | I37: =I35+I31 -> 110478.33 | J37: =J35+J31 -> 110478.33 | ... ED37: =ED35+ED31 -> 486454.36
A39: General Vacancy & Credit Loss
A40: Vacancy & L2L
A41: Total Vacancy & Credit Loss | C41: =C40 -> 0 | D41: =D40 -> 0 | E41: =E40 -> 0 | F41: =F40 -> 0 | G41: =G40 -> 0 | H41: =H40 -> 0 | I41: =I40 -> 0 | J41: =J40 -> 0 | ... ED41: =ED40 -> 0
A43: Effective Gross Revenue | C43: =C37+C41 -> 110478.33 | D43: =D37+D41 -> 110478.33 | E43: =E37+E41 -> 110478.33 | F43: =F37+F41 -> 110478.33 | G43: =G37+G41 -> 110478.33 | H43: =H37+H41 -> 110478.33 | I43: =I37+I41 -> 110478.33 | J43: =J37+J41 -> 110478.33 | ... ED43: =ED37+ED41 -> 486454.36
A45: Operating Expenses
A46: Utilities | B46: 1250 | C46: =IF(OR(C$10<'Torrance Inputs'!$N$40,C$10>='Torrance Inputs'!$I$18),'Torrance Inputs'!$I3*(1+'Torrance Inputs'!$N$3)^(C$8-1),0) -> 1250 | D46: =IF(OR(D$10<'Torrance Inputs'!$N$40,D$10>='Torrance Inputs'!$I$18),'Torrance Inputs'!$I3*(1+'Torrance Inputs'!$N$3)^(D$8-1),0) -> 1250 | E46: =IF(OR(E$10<'Torrance Inputs'!$N$40,E$10>='Torrance Inputs'!$I$18),'Torrance Inputs'!$I3*(1+'Torrance Inputs'!$N$3)^(E$8-1),0) -> 1250 | F46: =IF(OR(F$10<'Torrance Inputs'!$N$40,F$10>='Torrance Inputs'!$I$18),'Torrance Inputs'!$I3*(1+'Torrance Inputs'!$N$3)^(F$8-1),0) -> 1250 | G46: =IF(OR(G$10<'Torrance Inputs'!$N$40,G$10>='Torrance Inputs'!$I$18),'Torrance Inputs'!$I3*(1+'Torrance Inputs'!$N$3)^(G$8-1),0) -> 1250 | H46: =IF(OR(H$10<'Torrance Inputs'!$N$40,H$10>='Torrance Inputs'!$I$18),'Torrance Inputs'!$I3*(1+'Torrance Inputs'!$N$3)^(H$8-1),0) -> 1250 | I46: =IF(OR(I$10<'Torrance Inputs'!$N$40,I$10>='Torrance Inputs'!$I$18),'Torrance Inputs'!$I3*(1+'Torrance Inputs'!$N$3)^(I$8-1),0) -> 1250 | J46: =IF(OR(J$10<'Torrance Inputs'!$N$40,J$10>='Torrance Inputs'!$I$18),'Torrance Inputs'!$I3*(1+'Torrance Inputs'!$N$3)^(J$8-1),0) -> 1250 | ... ED46: =IF(OR(ED$10<'Torrance Inputs'!$N$40,ED$10>='Torrance Inputs'!$I$18),'Torrance Inputs'!$I3*(1+'Torrance Inputs'!$N$3)^(ED$8-1),0) -> 1679.8955
A47: Repairs & Maintenance | B47: 1250 | C47: =IF(OR(C$10<'Torrance Inputs'!$N$40,C$10>='Torrance Inputs'!$I$18),'Torrance Inputs'!$I4*(1+'Torrance Inputs'!$N$3)^(C$8-1),0) -> 1250 | D47: =IF(OR(D$10<'Torrance Inputs'!$N$40,D$10>='Torrance Inputs'!$I$18),'Torrance Inputs'!$I4*(1+'Torrance Inputs'!$N$3)^(D$8-1),0) -> 1250 | E47: =IF(OR(E$10<'Torrance Inputs'!$N$40,E$10>='Torrance Inputs'!$I$18),'Torrance Inputs'!$I4*(1+'Torrance Inputs'!$N$3)^(E$8-1),0) -> 1250 | F47: =IF(OR(F$10<'Torrance Inputs'!$N$40,F$10>='Torrance Inputs'!$I$18),'Torrance Inputs'!$I4*(1+'Torrance Inputs'!$N$3)^(F$8-1),0) -> 1250 | G47: =IF(OR(G$10<'Torrance Inputs'!$N$40,G$10>='Torrance Inputs'!$I$18),'Torrance Inputs'!$I4*(1+'Torrance Inputs'!$N$3)^(G$8-1),0) -> 1250 | H47: =IF(OR(H$10<'Torrance Inputs'!$N$40,H$10>='Torrance Inputs'!$I$18),'Torrance Inputs'!$I4*(1+'Torrance Inputs'!$N$3)^(H$8-1),0) -> 1250 | I47: =IF(OR(I$10<'Torrance Inputs'!$N$40,I$10>='Torrance Inputs'!$I$18),'Torrance Inputs'!$I4*(1+'Torrance Inputs'!$N$3)^(I$8-1),0) -> 1250 | J47: =IF(OR(J$10<'Torrance Inputs'!$N$40,J$10>='Torrance Inputs'!$I$18),'Torrance Inputs'!$I4*(1+'Torrance Inputs'!$N$3)^(J$8-1),0) -> 1250 | ... ED47: =IF(OR(ED$10<'Torrance Inputs'!$N$40,ED$10>='Torrance Inputs'!$I$18),'Torrance Inputs'!$I4*(1+'Torrance Inputs'!$N$3)^(ED$8-1),0) -> 1679.8955
A48: Insurance | B48: 417 | C48: =IF(OR(C$10<'Torrance Inputs'!$N$40,C$10>='Torrance Inputs'!$I$18),'Torrance Inputs'!$I5*(1+'Torrance Inputs'!$N$3)^(C$8-1),0) -> 416.66667 | D48: =IF(OR(D$10<'Torrance Inputs'!$N$40,D$10>='Torrance Inputs'!$I$18),'Torrance Inputs'!$I5*(1+'Torrance Inputs'!$N$3)^(D$8-1),0) -> 416.66667 | E48: =IF(OR(E$10<'Torrance Inputs'!$N$40,E$10>='Torrance Inputs'!$I$18),'Torrance Inputs'!$I5*(1+'Torrance Inputs'!$N$3)^(E$8-1),0) -> 416.66667 | F48: =IF(OR(F$10<'Torrance Inputs'!$N$40,F$10>='Torrance Inputs'!$I$18),'Torrance Inputs'!$I5*(1+'Torrance Inputs'!$N$3)^(F$8-1),0) -> 416.66667 | G48: =IF(OR(G$10<'Torrance Inputs'!$N$40,G$10>='Torrance Inputs'!$I$18),'Torrance Inputs'!$I5*(1+'Torrance Inputs'!$N$3)^(G$8-1),0) -> 416.66667 | H48: =IF(OR(H$10<'Torrance Inputs'!$N$40,H$10>='Torrance Inputs'!$I$18),'Torrance Inputs'!$I5*(1+'Torrance Inputs'!$N$3)^(H$8-1),0) -> 416.66667 | I48: =IF(OR(I$10<'Torrance Inputs'!$N$40,I$10>='Torrance Inputs'!$I$18),'Torrance Inputs'!$I5*(1+'Torrance Inputs'!$N$3)^(I$8-1),0) -> 416.66667 | J48: =IF(OR(J$10<'Torrance Inputs'!$N$40,J$10>='Torrance Inputs'!$I$18),'Torrance Inputs'!$I5*(1+'Torrance Inputs'!$N$3)^(J$8-1),0) -> 416.66667 | ... ED48: =IF(OR(ED$10<'Torrance Inputs'!$N$40,ED$10>='Torrance Inputs'!$I$18),'Torrance Inputs'!$I5*(1+'Torrance Inputs'!$N$3)^(ED$8-1),0) -> 559.96516
A49: Property Taxes | B49: ='Torrance Inputs'!$I$6 -> 16089.944 | C49: ='Torrance Inputs'!$I6*(1+'Torrance Inputs'!$N6)^(C$8-1) -> 16089.944 | D49: ='Torrance Inputs'!$I6*(1+'Torrance Inputs'!$N6)^(D$8-1) -> 16089.944 | E49: ='Torrance Inputs'!$I6*(1+'Torrance Inputs'!$N6)^(E$8-1) -> 16089.944 | F49: ='Torrance Inputs'!$I6*(1+'Torrance Inputs'!$N6)^(F$8-1) -> 16089.944 | G49: ='Torrance Inputs'!$I6*(1+'Torrance Inputs'!$N6)^(G$8-1) -> 16089.944 | H49: ='Torrance Inputs'!$I6*(1+'Torrance Inputs'!$N6)^(H$8-1) -> 16089.944 | I49: ='Torrance Inputs'!$I6*(1+'Torrance Inputs'!$N6)^(I$8-1) -> 16089.944 | J49: ='Torrance Inputs'!$I6*(1+'Torrance Inputs'!$N6)^(J$8-1) -> 16089.944 | ... ED49: ='Torrance Inputs'!$I6*(1+'Torrance Inputs'!$N6)^(ED$8-1) -> 19613.552
A50: Management Fee | B50: =C$43*'Torrance Inputs'!$K$8 -> 3314.35 | C50: 0 | D50: =D$43*'Torrance Inputs'!$K$8 -> 3314.35 | E50: =E$43*'Torrance Inputs'!$K$8 -> 3314.35 | F50: =F$43*'Torrance Inputs'!$K$8 -> 3314.35 | G50: =G$43*'Torrance Inputs'!$K$8 -> 3314.35 | H50: =H$43*'Torrance Inputs'!$K$8 -> 3314.35 | I50: =I$43*'Torrance Inputs'!$K$8 -> 3314.35 | J50: =J$43*'Torrance Inputs'!$K$8 -> 3314.35 | K50: =K$43*'Torrance Inputs'!$K$8 -> 3314.35 | ... ED50: =ED$43*'Torrance Inputs'!$K$8 -> 14593.631
A51: Total Operating Expenses | C51: =SUM(C46:C50) -> 19006.611 | D51: =SUM(D46:D50) -> 22320.961 | E51: =SUM(E46:E50) -> 22320.961 | F51: =SUM(F46:F50) -> 22320.961 | G51: =SUM(G46:G50) -> 22320.961 | H51: =SUM(H46:H50) -> 22320.961 | I51: =SUM(I46:I50) -> 22320.961 | J51: =SUM(J46:J50) -> 22320.961 | ... ED51: =SUM(ED46:ED50) -> 38126.94
A53: Net Operating Income | C53: =C43-C51 -> 91471.722 | D53: =D43-D51 -> 88157.372 | E53: =E43-E51 -> 88157.372 | F53: =F43-F51 -> 88157.372 | G53: =G43-G51 -> 88157.372 | H53: =H43-H51 -> 88157.372 | I53: =I43-I51 -> 88157.372 | J53: =J43-J51 -> 88157.372 | ... ED53: =ED43-ED51 -> 448327.43
A55: Leasing Costs
A56: Tenant Improvements | C56: =IF(AND(C$10>EOMONTH('Torrance Inputs'!$H$35,'Torrance Inputs'!$L$28),C$10<=EOMONTH('Torrance Inputs'!$H$35,'Torrance Inputs'!$M$28)),'Torrance Inputs'!$Q$17/('Torrance Inputs'!$M$28-'Torrance Inputs'!$L$28),0) -> 0 | D56: =IF(AND(D$10>EOMONTH('Torrance Inputs'!$H$35,'Torrance Inputs'!$L$28),D$10<=EOMONTH('Torrance Inputs'!$H$35,'Torrance Inputs'!$M$28)),'Torrance Inputs'!$Q$17/('Torrance Inputs'!$M$28-'Torrance Inputs'!$L$28),0) -> 0 | E56: =IF(AND(E$10>EOMONTH('Torrance Inputs'!$H$35,'Torrance Inputs'!$L$28),E$10<=EOMONTH('Torrance Inputs'!$H$35,'Torrance Inputs'!$M$28)),'Torrance Inputs'!$Q$17/('Torrance Inputs'!$M$28-'Torrance Inputs'!$L$28),0) -> 0 | F56: =IF(AND(F$10>EOMONTH('Torrance Inputs'!$H$35,'Torrance Inputs'!$L$28),F$10<=EOMONTH('Torrance Inputs'!$H$35,'Torrance Inputs'!$M$28)),'Torrance Inputs'!$Q$17/('Torrance Inputs'!$M$28-'Torrance Inputs'!$L$28),0) -> 0 | G56: =IF(AND(G$10>EOMONTH('Torrance Inputs'!$H$35,'Torrance Inputs'!$L$28),G$10<=EOMONTH('Torrance Inputs'!$H$35,'Torrance Inputs'!$M$28)),'Torrance Inputs'!$Q$17/('Torrance Inputs'!$M$28-'Torrance Inputs'!$L$28),0) -> 0 | H56: =IF(AND(H$10>EOMONTH('Torrance Inputs'!$H$35,'Torrance Inputs'!$L$28),H$10<=EOMONTH('Torrance Inputs'!$H$35,'Torrance Inputs'!$M$28)),'Torrance Inputs'!$Q$17/('Torrance Inputs'!$M$28-'Torrance Inputs'!$L$28),0) -> 0 | I56: =IF(AND(I$10>EOMONTH('Torrance Inputs'!$H$35,'Torrance Inputs'!$L$28),I$10<=EOMONTH('Torrance Inputs'!$H$35,'Torrance Inputs'!$M$28)),'Torrance Inputs'!$Q$17/('Torrance Inputs'!$M$28-'Torrance Inputs'!$L$28),0) -> 0 | J56: =IF(AND(J$10>EOMONTH('Torrance Inputs'!$H$35,'Torrance Inputs'!$L$28),J$10<=EOMONTH('Torrance Inputs'!$H$35,'Torrance Inputs'!$M$28)),'Torrance Inputs'!$Q$17/('Torrance Inputs'!$M$28-'Torrance Inputs'!$L$28),0) -> 0 | ... ED56: =IF(AND(ED$10>EOMONTH('Torrance Inputs'!$H$35,'Torrance Inputs'!$L$28),ED$10<=EOMONTH('Torrance Inputs'!$H$35,'Torrance Inputs'!$M$28)),'Torrance Inputs'!$Q$17/('Torrance Inputs'!$M$28-'Torrance Inputs'!$L$28),0) -> 0
A57: Leasing Commissions | C57: =IF(AND(C$10>=EOMONTH('Torrance Inputs'!$H$35,'Torrance Inputs'!$L$29),C$10<=EOMONTH('Torrance Inputs'!$H$35,'Torrance Inputs'!$M$29)),'Torrance Inputs'!$Q$16/('Torrance Inputs'!$M$29-'Torrance Inputs'!$L$29),0) -> 0 | D57: =IF(AND(D$10>=EOMONTH('Torrance Inputs'!$H$35,'Torrance Inputs'!$L$29),D$10<=EOMONTH('Torrance Inputs'!$H$35,'Torrance Inputs'!$M$29)),'Torrance Inputs'!$Q$16/('Torrance Inputs'!$M$29-'Torrance Inputs'!$L$29),0) -> 0 | E57: =IF(AND(E$10>=EOMONTH('Torrance Inputs'!$H$35,'Torrance Inputs'!$L$29),E$10<=EOMONTH('Torrance Inputs'!$H$35,'Torrance Inputs'!$M$29)),'Torrance Inputs'!$Q$16/('Torrance Inputs'!$M$29-'Torrance Inputs'!$L$29),0) -> 0 | F57: =IF(AND(F$10>=EOMONTH('Torrance Inputs'!$H$35,'Torrance Inputs'!$L$29),F$10<=EOMONTH('Torrance Inputs'!$H$35,'Torrance Inputs'!$M$29)),'Torrance Inputs'!$Q$16/('Torrance Inputs'!$M$29-'Torrance Inputs'!$L$29),0) -> 0 | G57: =IF(AND(G$10>=EOMONTH('Torrance Inputs'!$H$35,'Torrance Inputs'!$L$29),G$10<=EOMONTH('Torrance Inputs'!$H$35,'Torrance Inputs'!$M$29)),'Torrance Inputs'!$Q$16/('Torrance Inputs'!$M$29-'Torrance Inputs'!$L$29),0) -> 0 | H57: =IF(AND(H$10>=EOMONTH('Torrance Inputs'!$H$35,'Torrance Inputs'!$L$29),H$10<=EOMONTH('Torrance Inputs'!$H$35,'Torrance Inputs'!$M$29)),'Torrance Inputs'!$Q$16/('Torrance Inputs'!$M$29-'Torrance Inputs'!$L$29),0) -> 0 | I57: =IF(AND(I$10>=EOMONTH('Torrance Inputs'!$H$35,'Torrance Inputs'!$L$29),I$10<=EOMONTH('Torrance Inputs'!$H$35,'Torrance Inputs'!$M$29)),'Torrance Inputs'!$Q$16/('Torrance Inputs'!$M$29-'Torrance Inputs'!$L$29),0) -> 0 | J57: =IF(AND(J$10>=EOMONTH('Torrance Inputs'!$H$35,'Torrance Inputs'!$L$29),J$10<=EOMONTH('Torrance Inputs'!$H$35,'Torrance Inputs'!$M$29)),'Torrance Inputs'!$Q$16/('Torrance Inputs'!$M$29-'Torrance Inputs'!$L$29),0) -> 0 | ... ED57: =IF(AND(ED$10>=EOMONTH('Torrance Inputs'!$H$35,'Torrance Inputs'!$L$29),ED$10<=EOMONTH('Torrance Inputs'!$H$35,'Torrance Inputs'!$M$29)),'Torrance Inputs'!$Q$16/('Torrance Inputs'!$M$29-'Torrance Inputs'!$L$29),0) -> 0
A58: Total Leasing Costs | C58: =SUM(C56:C57) -> 0 | D58: =SUM(D56:D57) -> 0 | E58: =SUM(E56:E57) -> 0 | F58: =SUM(F56:F57) -> 0 | G58: =SUM(G56:G57) -> 0 | H58: =SUM(H56:H57) -> 0 | I58: =SUM(I56:I57) -> 0 | J58: =SUM(J56:J57) -> 0 | ... ED58: =SUM(ED56:ED57) -> 0
C59: =C58 -> 0 | D59: =D58 -> 0 | E59: =E58 -> 0 | F59: =F58 -> 0 | G59: =G58 -> 0 | H59: =H58 -> 0 | I59: =I58 -> 0 | J59: =J58 -> 0 | ... ED59: =ED58 -> 0
A60: Capital Expenditures
A61: Replacement Reserve | C61: ='Torrance Inputs'!$I$10*(1+'Torrance Inputs'!$N$10)^(C$8-1) -> 11458.333 | D61: ='Torrance Inputs'!$I$10*(1+'Torrance Inputs'!$N$10)^(D$8-1) -> 11458.333 | E61: ='Torrance Inputs'!$I$10*(1+'Torrance Inputs'!$N$10)^(E$8-1) -> 11458.333 | F61: ='Torrance Inputs'!$I$10*(1+'Torrance Inputs'!$N$10)^(F$8-1) -> 11458.333 | G61: ='Torrance Inputs'!$I$10*(1+'Torrance Inputs'!$N$10)^(G$8-1) -> 11458.333 | H61: ='Torrance Inputs'!$I$10*(1+'Torrance Inputs'!$N$10)^(H$8-1) -> 11458.333 | I61: ='Torrance Inputs'!$I$10*(1+'Torrance Inputs'!$N$10)^(I$8-1) -> 11458.333 | J61: ='Torrance Inputs'!$I$10*(1+'Torrance Inputs'!$N$10)^(J$8-1) -> 11458.333 | ... ED61: ='Torrance Inputs'!$I$10*(1+'Torrance Inputs'!$N$10)^(ED$8-1) -> 13967.644
A62: Tenant Buyout Expense | C62: =IF(C$8='Torrance Inputs'!$M$40,'Torrance Inputs'!$S$40/12,0) -> 0 | D62: =IF(D$8='Torrance Inputs'!$M$40,'Torrance Inputs'!$S$40/12,0) -> 0 | E62: =IF(E$8='Torrance Inputs'!$M$40,'Torrance Inputs'!$S$40/12,0) -> 0 | F62: =IF(F$8='Torrance Inputs'!$M$40,'Torrance Inputs'!$S$40/12,0) -> 0 | G62: =IF(G$8='Torrance Inputs'!$M$40,'Torrance Inputs'!$S$40/12,0) -> 0 | H62: =IF(H$8='Torrance Inputs'!$M$40,'Torrance Inputs'!$S$40/12,0) -> 0 | I62: =IF(I$8='Torrance Inputs'!$M$40,'Torrance Inputs'!$S$40/12,0) -> 0 | J62: =IF(J$8='Torrance Inputs'!$M$40,'Torrance Inputs'!$S$40/12,0) -> 0 | ... ED62: =IF(ED$8='Torrance Inputs'!$M$40,'Torrance Inputs'!$S$40/12,0) -> 0
A63: Total Capital Expenditures | C63: =SUM(C61:C62) -> 11458.333 | D63: =SUM(D61:D62) -> 11458.333 | E63: =SUM(E61:E62) -> 11458.333 | F63: =SUM(F61:F62) -> 11458.333 | G63: =SUM(G61:G62) -> 11458.333 | H63: =SUM(H61:H62) -> 11458.333 | I63: =SUM(I61:I62) -> 11458.333 | J63: =SUM(J61:J62) -> 11458.333 | ... ED63: =SUM(ED61:ED62) -> 13967.644
A65: Total Leasing & Capital Costs | C65: =C63+C58 -> 11458.333 | D65: =D63+D58 -> 11458.333 | E65: =E63+E58 -> 11458.333 | F65: =F63+F58 -> 11458.333 | G65: =G63+G58 -> 11458.333 | H65: =H63+H58 -> 11458.333 | I65: =I63+I58 -> 11458.333 | J65: =J63+J58 -> 11458.333 | ... ED65: =ED63+ED58 -> 13967.644
A67: Construction Cost
A68: Soft Costs | C68: =IF(AND(C$10>='Torrance Inputs'!$H44,C$10<'Torrance Inputs'!$I44),'Torrance Inputs'!$I36/DATEDIF('Torrance Inputs'!$H44,'Torrance Inputs'!$I44,"m"),0) -> 0 | D68: =IF(AND(D$10>='Torrance Inputs'!$H44,D$10<'Torrance Inputs'!$I44),'Torrance Inputs'!$I36/DATEDIF('Torrance Inputs'!$H44,'Torrance Inputs'!$I44,"m"),0) -> 0 | E68: =IF(AND(E$10>='Torrance Inputs'!$H44,E$10<'Torrance Inputs'!$I44),'Torrance Inputs'!$I36/DATEDIF('Torrance Inputs'!$H44,'Torrance Inputs'!$I44,"m"),0) -> 0 | F68: =IF(AND(F$10>='Torrance Inputs'!$H44,F$10<'Torrance Inputs'!$I44),'Torrance Inputs'!$I36/DATEDIF('Torrance Inputs'!$H44,'Torrance Inputs'!$I44,"m"),0) -> 0 | G68: =IF(AND(G$10>='Torrance Inputs'!$H44,G$10<'Torrance Inputs'!$I44),'Torrance Inputs'!$I36/DATEDIF('Torrance Inputs'!$H44,'Torrance Inputs'!$I44,"m"),0) -> 0 | H68: =IF(AND(H$10>='Torrance Inputs'!$H44,H$10<'Torrance Inputs'!$I44),'Torrance Inputs'!$I36/DATEDIF('Torrance Inputs'!$H44,'Torrance Inputs'!$I44,"m"),0) -> 0 | I68: =IF(AND(I$10>='Torrance Inputs'!$H44,I$10<'Torrance Inputs'!$I44),'Torrance Inputs'!$I36/DATEDIF('Torrance Inputs'!$H44,'Torrance Inputs'!$I44,"m"),0) -> 0 | J68: =IF(AND(J$10>='Torrance Inputs'!$H44,J$10<'Torrance Inputs'!$I44),'Torrance Inputs'!$I36/DATEDIF('Torrance Inputs'!$H44,'Torrance Inputs'!$I44,"m"),0) -> 0 | ... ED68: =IF(AND(ED$10>='Torrance Inputs'!$H44,ED$10<'Torrance Inputs'!$I44),'Torrance Inputs'!$I36/DATEDIF('Torrance Inputs'!$H44,'Torrance Inputs'!$I44,"m"),0) -> 0
A69: Demolition | C69: =IF(AND(C$10>='Torrance Inputs'!$H45,C$10<'Torrance Inputs'!$I45),'Torrance Inputs'!$I37/DATEDIF('Torrance Inputs'!$H45,'Torrance Inputs'!$I45,"m"),0) -> 0 | D69: =IF(AND(D$10>='Torrance Inputs'!$H45,D$10<'Torrance Inputs'!$I45),'Torrance Inputs'!$I37/DATEDIF('Torrance Inputs'!$H45,'Torrance Inputs'!$I45,"m"),0) -> 0 | E69: =IF(AND(E$10>='Torrance Inputs'!$H45,E$10<'Torrance Inputs'!$I45),'Torrance Inputs'!$I37/DATEDIF('Torrance Inputs'!$H45,'Torrance Inputs'!$I45,"m"),0) -> 0 | F69: =IF(AND(F$10>='Torrance Inputs'!$H45,F$10<'Torrance Inputs'!$I45),'Torrance Inputs'!$I37/DATEDIF('Torrance Inputs'!$H45,'Torrance Inputs'!$I45,"m"),0) -> 0 | G69: =IF(AND(G$10>='Torrance Inputs'!$H45,G$10<'Torrance Inputs'!$I45),'Torrance Inputs'!$I37/DATEDIF('Torrance Inputs'!$H45,'Torrance Inputs'!$I45,"m"),0) -> 0 | H69: =IF(AND(H$10>='Torrance Inputs'!$H45,H$10<'Torrance Inputs'!$I45),'Torrance Inputs'!$I37/DATEDIF('Torrance Inputs'!$H45,'Torrance Inputs'!$I45,"m"),0) -> 0 | I69: =IF(AND(I$10>='Torrance Inputs'!$H45,I$10<'Torrance Inputs'!$I45),'Torrance Inputs'!$I37/DATEDIF('Torrance Inputs'!$H45,'Torrance Inputs'!$I45,"m"),0) -> 0 | J69: =IF(AND(J$10>='Torrance Inputs'!$H45,J$10<'Torrance Inputs'!$I45),'Torrance Inputs'!$I37/DATEDIF('Torrance Inputs'!$H45,'Torrance Inputs'!$I45,"m"),0) -> 0 | ... ED69: =IF(AND(ED$10>='Torrance Inputs'!$H45,ED$10<'Torrance Inputs'!$I45),'Torrance Inputs'!$I37/DATEDIF('Torrance Inputs'!$H45,'Torrance Inputs'!$I45,"m"),0) -> 0
A70: Building Const. | C70: =IF(AND(C$10>='Torrance Inputs'!$H46,C$10<'Torrance Inputs'!$I46),'Torrance Inputs'!$I38/DATEDIF('Torrance Inputs'!$H46,'Torrance Inputs'!$I46,"m"),0) -> 0 | D70: =IF(AND(D$10>='Torrance Inputs'!$H46,D$10<'Torrance Inputs'!$I46),'Torrance Inputs'!$I38/DATEDIF('Torrance Inputs'!$H46,'Torrance Inputs'!$I46,"m"),0) -> 0 | E70: =IF(AND(E$10>='Torrance Inputs'!$H46,E$10<'Torrance Inputs'!$I46),'Torrance Inputs'!$I38/DATEDIF('Torrance Inputs'!$H46,'Torrance Inputs'!$I46,"m"),0) -> 0 | F70: =IF(AND(F$10>='Torrance Inputs'!$H46,F$10<'Torrance Inputs'!$I46),'Torrance Inputs'!$I38/DATEDIF('Torrance Inputs'!$H46,'Torrance Inputs'!$I46,"m"),0) -> 0 | G70: =IF(AND(G$10>='Torrance Inputs'!$H46,G$10<'Torrance Inputs'!$I46),'Torrance Inputs'!$I38/DATEDIF('Torrance Inputs'!$H46,'Torrance Inputs'!$I46,"m"),0) -> 0 | H70: =IF(AND(H$10>='Torrance Inputs'!$H46,H$10<'Torrance Inputs'!$I46),'Torrance Inputs'!$I38/DATEDIF('Torrance Inputs'!$H46,'Torrance Inputs'!$I46,"m"),0) -> 0 | I70: =IF(AND(I$10>='Torrance Inputs'!$H46,I$10<'Torrance Inputs'!$I46),'Torrance Inputs'!$I38/DATEDIF('Torrance Inputs'!$H46,'Torrance Inputs'!$I46,"m"),0) -> 0 | J70: =IF(AND(J$10>='Torrance Inputs'!$H46,J$10<'Torrance Inputs'!$I46),'Torrance Inputs'!$I38/DATEDIF('Torrance Inputs'!$H46,'Torrance Inputs'!$I46,"m"),0) -> 0 | ... ED70: =IF(AND(ED$10>='Torrance Inputs'!$H46,ED$10<'Torrance Inputs'!$I46),'Torrance Inputs'!$I38/DATEDIF('Torrance Inputs'!$H46,'Torrance Inputs'!$I46,"m"),0) -> 0
A71: Site Work | C71: =IF(AND(C$10>='Torrance Inputs'!$H47,C$10<'Torrance Inputs'!$I47),'Torrance Inputs'!$I39/DATEDIF('Torrance Inputs'!$H47,'Torrance Inputs'!$I47,"m"),0) -> 0 | D71: =IF(AND(D$10>='Torrance Inputs'!$H47,D$10<'Torrance Inputs'!$I47),'Torrance Inputs'!$I39/DATEDIF('Torrance Inputs'!$H47,'Torrance Inputs'!$I47,"m"),0) -> 0 | E71: =IF(AND(E$10>='Torrance Inputs'!$H47,E$10<'Torrance Inputs'!$I47),'Torrance Inputs'!$I39/DATEDIF('Torrance Inputs'!$H47,'Torrance Inputs'!$I47,"m"),0) -> 0 | F71: =IF(AND(F$10>='Torrance Inputs'!$H47,F$10<'Torrance Inputs'!$I47),'Torrance Inputs'!$I39/DATEDIF('Torrance Inputs'!$H47,'Torrance Inputs'!$I47,"m"),0) -> 0 | G71: =IF(AND(G$10>='Torrance Inputs'!$H47,G$10<'Torrance Inputs'!$I47),'Torrance Inputs'!$I39/DATEDIF('Torrance Inputs'!$H47,'Torrance Inputs'!$I47,"m"),0) -> 0 | H71: =IF(AND(H$10>='Torrance Inputs'!$H47,H$10<'Torrance Inputs'!$I47),'Torrance Inputs'!$I39/DATEDIF('Torrance Inputs'!$H47,'Torrance Inputs'!$I47,"m"),0) -> 0 | I71: =IF(AND(I$10>='Torrance Inputs'!$H47,I$10<'Torrance Inputs'!$I47),'Torrance Inputs'!$I39/DATEDIF('Torrance Inputs'!$H47,'Torrance Inputs'!$I47,"m"),0) -> 0 | J71: =IF(AND(J$10>='Torrance Inputs'!$H47,J$10<'Torrance Inputs'!$I47),'Torrance Inputs'!$I39/DATEDIF('Torrance Inputs'!$H47,'Torrance Inputs'!$I47,"m"),0) -> 0 | ... ED71: =IF(AND(ED$10>='Torrance Inputs'!$H47,ED$10<'Torrance Inputs'!$I47),'Torrance Inputs'!$I39/DATEDIF('Torrance Inputs'!$H47,'Torrance Inputs'!$I47,"m"),0) -> 0
A72: Lease Up - Broker Fee | C72: =IF(AND(C$10>='Torrance Inputs'!$H48,C$10<'Torrance Inputs'!$I48),'Torrance Inputs'!$I40/DATEDIF('Torrance Inputs'!$H48,'Torrance Inputs'!$I48,"m"),0) -> 0 | D72: =IF(AND(D$10>='Torrance Inputs'!$H48,D$10<'Torrance Inputs'!$I48),'Torrance Inputs'!$I40/DATEDIF('Torrance Inputs'!$H48,'Torrance Inputs'!$I48,"m"),0) -> 0 | E72: =IF(AND(E$10>='Torrance Inputs'!$H48,E$10<'Torrance Inputs'!$I48),'Torrance Inputs'!$I40/DATEDIF('Torrance Inputs'!$H48,'Torrance Inputs'!$I48,"m"),0) -> 0 | F72: =IF(AND(F$10>='Torrance Inputs'!$H48,F$10<'Torrance Inputs'!$I48),'Torrance Inputs'!$I40/DATEDIF('Torrance Inputs'!$H48,'Torrance Inputs'!$I48,"m"),0) -> 0 | G72: =IF(AND(G$10>='Torrance Inputs'!$H48,G$10<'Torrance Inputs'!$I48),'Torrance Inputs'!$I40/DATEDIF('Torrance Inputs'!$H48,'Torrance Inputs'!$I48,"m"),0) -> 0 | H72: =IF(AND(H$10>='Torrance Inputs'!$H48,H$10<'Torrance Inputs'!$I48),'Torrance Inputs'!$I40/DATEDIF('Torrance Inputs'!$H48,'Torrance Inputs'!$I48,"m"),0) -> 0 | I72: =IF(AND(I$10>='Torrance Inputs'!$H48,I$10<'Torrance Inputs'!$I48),'Torrance Inputs'!$I40/DATEDIF('Torrance Inputs'!$H48,'Torrance Inputs'!$I48,"m"),0) -> 0 | J72: =IF(AND(J$10>='Torrance Inputs'!$H48,J$10<'Torrance Inputs'!$I48),'Torrance Inputs'!$I40/DATEDIF('Torrance Inputs'!$H48,'Torrance Inputs'!$I48,"m"),0) -> 0 | ... ED72: =IF(AND(ED$10>='Torrance Inputs'!$H48,ED$10<'Torrance Inputs'!$I48),'Torrance Inputs'!$I40/DATEDIF('Torrance Inputs'!$H48,'Torrance Inputs'!$I48,"m"),0) -> 0
A73: Total Construction Cost | C73: =SUM(C68:C72) -> 0 | D73: =SUM(D68:D72) -> 0 | E73: =SUM(E68:E72) -> 0 | F73: =SUM(F68:F72) -> 0 | G73: =SUM(G68:G72) -> 0 | H73: =SUM(H68:H72) -> 0 | I73: =SUM(I68:I72) -> 0 | J73: =SUM(J68:J72) -> 0 | ... ED73: =SUM(ED68:ED72) -> 0
A75: Cash Flow Before Debt Service | C75: =C53-C65-C73 -> 80013.389 | D75: =D53-D65-D73 -> 76699.039 | E75: =E53-E65-E73 -> 76699.039 | F75: =F53-F65-F73 -> 76699.039 | G75: =G53-G65-G73 -> 76699.039 | H75: =H53-H65-H73 -> 76699.039 | I75: =I53-I65-I73 -> 76699.039 | J75: =J53-J65-J73 -> 76699.039 | ... ED75: =ED53-ED65-ED73 -> 434359.78
A77: Acquisition
A78: Purchase Price | B78: =-'Torrance Inputs'!$D$11 -> -17552667
A79: Cost of Sales | B79: =-B78*'Torrance Inputs'!$D$12 -> 351053.33
A80: Total Acquisition Cost | B80: =SUM(B78:B79) -> -17201613
A82: Disposition
A83: Sale Price | C83: =IF(C$9='Torrance Inputs'!$D$20*12,SUMIF(_xlfn.ANCHORARRAY('Torrance Pro Forma'!$C$9),">120",'Torrance Pro Forma'!$C$53:$ED$53)/'Torrance Inputs'!$D$16,0) -> 0 | D83: =IF(D$9='Torrance Inputs'!$D$20*12,SUMIF(_xlfn.ANCHORARRAY('Torrance Pro Forma'!$C$9),">120",'Torrance Pro Forma'!$C$53:$ED$53)/'Torrance Inputs'!$D$16,0) -> 0 | E83: =IF(E$9='Torrance Inputs'!$D$20*12,SUMIF(_xlfn.ANCHORARRAY('Torrance Pro Forma'!$C$9),">120",'Torrance Pro Forma'!$C$53:$ED$53)/'Torrance Inputs'!$D$16,0) -> 0 | F83: =IF(F$9='Torrance Inputs'!$D$20*12,SUMIF(_xlfn.ANCHORARRAY('Torrance Pro Forma'!$C$9),">120",'Torrance Pro Forma'!$C$53:$ED$53)/'Torrance Inputs'!$D$16,0) -> 0 | G83: =IF(G$9='Torrance Inputs'!$D$20*12,SUMIF(_xlfn.ANCHORARRAY('Torrance Pro Forma'!$C$9),">120",'Torrance Pro Forma'!$C$53:$ED$53)/'Torrance Inputs'!$D$16,0) -> 0 | H83: =IF(H$9='Torrance Inputs'!$D$20*12,SUMIF(_xlfn.ANCHORARRAY('Torrance Pro Forma'!$C$9),">120",'Torrance Pro Forma'!$C$53:$ED$53)/'Torrance Inputs'!$D$16,0) -> 0 | I83: =IF(I$9='Torrance Inputs'!$D$20*12,SUMIF(_xlfn.ANCHORARRAY('Torrance Pro Forma'!$C$9),">120",'Torrance Pro Forma'!$C$53:$ED$53)/'Torrance Inputs'!$D$16,0) -> 0 | J83: =IF(J$9='Torrance Inputs'!$D$20*12,SUMIF(_xlfn.ANCHORARRAY('Torrance Pro Forma'!$C$9),">120",'Torrance Pro Forma'!$C$53:$ED$53)/'Torrance Inputs'!$D$16,0) -> 0 | ... ED83: =IF(ED$9='Torrance Inputs'!$D$20*12,SUMIF(_xlfn.ANCHORARRAY('Torrance Pro Forma'!$C$9),">120",'Torrance Pro Forma'!$C$53:$ED$53)/'Torrance Inputs'!$D$16,0) -> 0
A84: Cost of Sales | C84: =-C$83*'Torrance Inputs'!$D$17 -> 0 | D84: =-D$83*'Torrance Inputs'!$D$17 -> 0 | E84: =-E$83*'Torrance Inputs'!$D$17 -> 0 | F84: =-F$83*'Torrance Inputs'!$D$17 -> 0 | G84: =-G$83*'Torrance Inputs'!$D$17 -> 0 | H84: =-H$83*'Torrance Inputs'!$D$17 -> 0 | I84: =-I$83*'Torrance Inputs'!$D$17 -> 0 | J84: =-J$83*'Torrance Inputs'!$D$17 -> 0 | ... ED84: =-ED$83*'Torrance Inputs'!$D$17 -> 0
A85: Total Sale Proceeds | C85: =SUM(C83:C84) -> 0 | D85: =SUM(D83:D84) -> 0 | E85: =SUM(E83:E84) -> 0 | F85: =SUM(F83:F84) -> 0 | G85: =SUM(G83:G84) -> 0 | H85: =SUM(H83:H84) -> 0 | I85: =SUM(I83:I84) -> 0 | J85: =SUM(J83:J84) -> 0 | ... ED85: =SUM(ED83:ED84) -> 0
A87: Asset Cash Flow | B87: =IF(B$9<='Torrance Inputs'!$D$20*12,B75+B85+B80,0) -> -17201613 | C87: =IF(C$9<='Torrance Inputs'!$D$20*12,C75+C85+C80,0) -> 80013.389 | D87: =IF(D$9<='Torrance Inputs'!$D$20*12,D75+D85+D80,0) -> 76699.039 | E87: =IF(E$9<='Torrance Inputs'!$D$20*12,E75+E85+E80,0) -> 76699.039 | F87: =IF(F$9<='Torrance Inputs'!$D$20*12,F75+F85+F80,0) -> 76699.039 | G87: =IF(G$9<='Torrance Inputs'!$D$20*12,G75+G85+G80,0) -> 76699.039 | H87: =IF(H$9<='Torrance Inputs'!$D$20*12,H75+H85+H80,0) -> 76699.039 | I87: =IF(I$9<='Torrance Inputs'!$D$20*12,I75+I85+I80,0) -> 76699.039 | ... ED87: =IF(ED$9<='Torrance Inputs'!$D$20*12,ED75+ED85+ED80,0) -> 0
A89: Asset IRR | B89: =XIRR(B87:ED87,B10:ED10) -> 0.17199615
A90: Asset MOIC | B90: =SUMIF(B87:ED87,">0")/-SUMIF(B87:ED87,"<0") -> 3.5062031

Sheet Torrance Inputs
B2: Property | F2: Expenses - Operating | H2: Year 1 | I2: Month 1 | K2: Inputs | L2: Fixed | M2: Recoverable | N2: Inflation (%) | P2: Existing Tenant Recoveries | Q2: Recoverable | V2: Buyout Cost Analysis
B3: Address | D3: 20000 S. Western Avenue | F3: Utilities | G3: =$H3/$D$9 -> 0.024663559 | H3: =I3*12 -> 15000 | I3: =K3/12 -> 1250 | K3: 15000 | L3: 0.25 | M3: 1 | N3: 0.03 | Q3: 1
B4: City | D4: Torrance | F4: Repairs & Maintenance | G4: =$H4/$D$9 -> 0.024663559 | H4: =I4*12 -> 15000 | I4: =K4/12 -> 1250 | K4: 15000 | L4: 0.25 | M4: 1 | N4: 0.03 | Q4: 1 | W4: Year | X4: Buyout Cost
B5: Year Built | D5: 2013 | F5: Insurance | G5: =$H5/$D$9 -> 0.0082211865 | H5: =I5*12 -> 5000 | I5: =K5/12 -> 416.66667 | K5: 5000 | L5: 1 | M5: 1 | N5: 0.03 | Q5: 1 | W5: {=_xlfn.SEQUENCE(10,1,1,1)} -> 1 | X5: =IFERROR(DATEDIF(EDATE(analysis_start,$W5*12),$N$39,"m")*$M$41,0) -> 5500000
B6: State | D6: California | F6: Property Taxes | G6: =$H6/$D$9 -> 0.31746824 | H6: =K6*D11 -> 193079.33 | I6: =H6/12 -> 16089.944 | K6: 0.011 | L6: 1 | M6: 1 | N6: 0.02 | Q6: 0 | W6: 2 | X6: =IFERROR(DATEDIF(EDATE(analysis_start,$W6*12),$N$39,"m")*$M$41,0) -> 4400000
B7: Building Class | D7: Manufacturing / Distribution | F7: Previous RE Tax | H7: =I7*12 -> 100000 | I7: =K7/12 -> 8333.3333 | K7: 100000 | W7: 3 | X7: =IFERROR(DATEDIF(EDATE(analysis_start,$W7*12),$N$39,"m")*$M$41,0) -> 3300000
B8: Occupancy Type | D8: Multitenant | F8: Management Fee | K8: 3.0% | M8: 0 | W8: 4 | X8: =IFERROR(DATEDIF(EDATE(analysis_start,$W8*12),$N$39,"m")*$M$41,0) -> 2200000
B9: Lot Size (SF) | C9: 13.962 | D9: =C9*43560 -> 608184.72 | F9: Expenses - Capital | W9: 5 | X9: =IFERROR(DATEDIF(EDATE(analysis_start,$W9*12),$N$39,"m")*$M$41,0) -> 1100000
B10: Building (SF) | D10: 275000 | F10: Replacement Reserve | H10: =I10*12 -> 137500 | I10: =(K10*D10)/12 -> 11458.333 | K10: 0.5 | N10: 0.02 | W10: 6 | X10: =IFERROR(DATEDIF(EDATE(analysis_start,$W10*12),$N$39,"m")*$M$41,0) -> 0
B11: Purchase Price | D11: =1316450/D13 -> 17552667 | W11: 7 | X11: =IFERROR(DATEDIF(EDATE(analysis_start,$W11*12),$N$39,"m")*$M$41,0) -> 0
B12: Closing Costs | C12: =D11*D12 -> 351053.33 | D12: 0.02 | F12: Tenant Rating | H12: Credit | K12: Asset Management Fee | W12: 8 | X12: =IFERROR(DATEDIF(EDATE(analysis_start,$W12*12),$N$39,"m")*$M$41,0) -> 0
B13: Entry Cap | D13: 0.075 | W13: 9 | X13: =IFERROR(DATEDIF(EDATE(analysis_start,$W13*12),$N$39,"m")*$M$41,0) -> 0
B14: Vacancy (Y1-5) | D14: 0.1 | F14: Rent Roll - New Tenant 1 | K14: Rent Roll - New Tenant 2 | P14: Recoveries | W14: 10 | X14: =IFERROR(DATEDIF(EDATE(analysis_start,$W14*12),$N$39,"m")*$M$41,0) -> 0
B15: Vacancy (Y6-10) | C15: 6 | D15: 0.1 | F15: Name | I15: =_xlfn.CONCAT(H12," Tenant") -> Credit Tenant | K15: Name | N15: =_xlfn.CONCAT(H12," Tenant") -> Credit Tenant | P15: Recovery Structure | R15: NNN
B16: Exit Cap | C16: =SUMIF(_xlfn.ANCHORARRAY('Torrance Pro Forma'!C9),">120",'Torrance Pro Forma'!$C$53:$ED$53)/'Torrance Inputs'!$D$16 -> 89665485 | D16: =D13-(10*0.0015) -> 0.06 | F16: Suite | I16: Space 1 | K16: Suite | N16: Space 2 | P16: Leasing Commission | Q16: =(market_rent*D26*D28)*R16 -> 635250 | R16: 0.06
B17: Cost of Sales | C17: =C16*D17 -> 1793309.7 | D17: 0.02 | F17: Area | I17: =D10/2 -> 137500 | K17: Area | N17: =D10/2 -> 137500 | P17: Tenant Improvements | Q17: =R17*D26 -> 550000 | R17: 4
B18: Analysis Start | D18: 45658 | F18: Lease Start | G18: {=INDEX('Torrance Pro Forma'!A9:EC9,,MATCH($I$18,'Torrance Pro Forma'!A10:EC10),1)+1} -> 61 | H18: {=INDEX('Torrance Pro Forma'!B8:ED8,,MATCH('Torrance Inputs'!N18,'Torrance Pro Forma'!B10:ED10),1)} -> 5 | I18: =H35+1 -> 47485 | K18: Lease Start | L18: {=INDEX('Torrance Pro Forma'!F9:EH9,,MATCH($I$18,'Torrance Pro Forma'!F10:EH10),1)+1} -> 61 | M18: =H18 -> 5 | N18: =I18 -> 47485 | P18: Lease Expiry | R18: =EOMONTH(I18,(I19*12)-1) -> 50040
B19: Analsis End | D19: =EDATE(analysis_start,D20*12) -> 49310 | F19: Term | I19: 7 | K19: Term | N19: 7
B20: Holding Period | D20: 10 | F20: Lease End | I20: =EDATE(I18,I19*12) -> 50042 | K20: Lease End | N20: =EDATE(N18,N19*12) -> 50042 | P20: Other Income | Q20: Amount | R20: Mo/ | S20: Amount | T20: Inflation
B21: Parking | D21: 170 | F21: Base Rent | I21: 15 | K21: Base Rent | N21: 15 | P21: Parking
B22: Year 0 NOI | D22: 1045000 | F22: Projected Base Rent | H22: =(I22*I17)/12 -> 199250.23 | I22: =I21*(1+3%)^(YEAR(I18)-YEAR(analysis_start)) -> 17.389111 | K22: Projected Base Rent | M22: =(N22*N17)/12 -> 199250.23 | N22: =N21*(1+3%)^(YEAR(N18)-YEAR(analysis_start)) -> 17.389111 | P22: Trailer | Q22: =$D$21*30% -> 51 | R22: =S22*Q22 -> 15300 | S22: 300 | T22: 0.02
F23: Rent Increase | I23: 0.02 | K23: Rent Increase | N23: 0.02 | P23: Car | Q23: =$D$21-Q22 -> 119 | R23: =S23*Q23 -> 595 | S23: 5 | T23: 0.02
F24: Type | I24: Fixed Steps | K24: Type | N24: Fixed Steps | Q24: =D21 -> 170 | R24: =SUM(R22:R23) -> 15895 | S24: =SUM(S22:S23) -> 305
B25: Market Assumptions | P25: Rooftop Solar Leasing | R25: =S25*D10 -> 220000 | S25: 0.8 | T25: 0.02
B26: Size / Space | C26: Mo | D26: =I17 -> 137500
B27: Market Base Rent | C27: =D27/12 -> 126041.67 | D27: =market_rent*D26 -> 1512500 | F27: Recoverable Expenses - NNN | I27: Month 1 | K27: Timing | L27: Start | M27: End
B28: Term Length | D28: 7 | F28: Utilities | I28: 0 | K28: Tenant Improvemts | L28: -1 | M28: 2
B29: Renewal Probability | D29: 0.7 | F29: Repairs & Maintenance | I29: 0 | K29: Leasing Commission | L29: -1 | M29: 1
B30: Months Vacant | D30: =ROUND(D15*12,0)*$D$28 -> 7 | F30: Insurance | I30: 0 | K30: Free Rent | L30: Whole Lease
B31: Available | C31: Space 1 | D31: =EDATE(I18,I19*12)+1 -> 50043 | F31: Property Taxes | I31: 0 | K31: Security Deposit | L31: 0
B32: Market Base Rent (/sf) | D32: 11
B33: Available | C33: Space 2 | D33: =EDATE(N18,N19*12)+1 -> 50043 | F33: Construction Costs | K33: Rent Roll - Existing Tenant | P33: Rent Roll - Existing Tenant Continued
B34: Rent Increase Type | D34: Fixed Steps | F34: Start Date | H34: =N40 -> 47119 | I34: 3 | K34: Name | N34: Big Baller brand | P34: Lease Type | S34: Gross
B35: Rent Increase (%) | D35: 0.02 | F35: End Date | H35: =EDATE(H34,SUM(H37:H40)) -> 47484 | K35: Suite | N35: 1 & 2 | P35: Recoveries:
B36: Leasing Costs | F36: Soft Costs | G36: =I36/$D$9 -> 4.9327119 | H36: 24 | I36: 3000000 | K36: Area | N36: =D10 -> 275000 | P36: Utilities
B37: Free Rent | D37: 2 | F37: Demolition | G37: =I37/$D$9 -> 2.4663559 | H37: 1 | I37: 1500000 | K37: Lease Length | N37: 7 | P37: Repairs & Maintenance
B38: Tenant Improvemnts | D38: 2 | F38: Building Const. | G38: =I38/$D$9 -> 20.552966 | H38: 6 | I38: 12500000 | K38: Lease Start | N38: =EDATE(analysis_start,-1*12) -> 45292 | P38: Insurance
B39: Security Deposit | C39: =D39*C27 -> 504166.67 | D39: 4 | F39: Site Work | G39: =I39/$D$9 -> 0.65769492 | H39: 2 | I39: 400000 | K39: Lease End | N39: =EDATE(N38,N37*12) -> 47849 | P39: Rent Increase | R39: Fixed Step | S39: 0.02
F40: Lease Up - Broker Fee | G40: =I40/$D$9 -> 0.16442373 | H40: 3 | I40: 100000 | K40: Expected Default | M40: 4 | N40: =EDATE(analysis_start,M40*12) -> 47119 | P40: Tenant Buyout Cost | S40: =DATEDIF(N40,N39,"m")*M41*70% -> 1540000
F41: Total Timeline and Costs | G41: =I41/$D$9 -> 28.774153 | H41: =SUM(H36:H40) -> 36 | I41: =SUM(I36:I40) -> 17500000 | K41: Base Rent / mo | M41: =(N41*N36)/12 -> 91666.667 | N41: 4
F43: Timeline | H43: Start | I43: End | K43: Duration
F44: Soft Costs | H44: =EDATE(H34,0) -> 47119 | I44: =EDATE(H44,H36) -> 47849 | K44: =ROUND((I44-H44)/30,0) -> 24
F45: Demolition | H45: =I44+1 -> 47850 | I45: =EDATE(H45,H37) -> 47881 | K45: =ROUND((I45-H45)/30,0) -> 1
F46: Building Const. | H46: =I45+1 -> 47882 | I46: =EDATE(H46,H38) -> 48063 | K46: =ROUND((I46-H46)/30,0) -> 6
F47: Site Work | H47: =I46+1 -> 48064 | I47: =EDATE(H47,H39) -> 48125 | K47: =ROUND((I47-H47)/30,0) -> 2
F48: Lease Up - Broker Fee | H48: =I47+1 -> 48126 | I48: =EDATE(H48,H40) -> 48218 | K48: =ROUND((I48-H48)/30,0) -> 3

Sheet Debt & Equity Assumptions
B2: Equity Assumptions
B3: Holding Period | D3: 10
B4: Structure
B5: Limited Partner | D5: 0.9
B6: General Partner | D6: =1-D5 -> 0.1
B7: Distribution Fee | D7: 0.03
B9: Tier 1
B10: Parispasu | D10: 0.1
B12: Tier 2
B13: Limited Partner | D13: 0.8
B14: General Partner | D14: =1-D13 -> 0.2
B16: Debt Assumptions | C16: Preconstruction | F16: Debt Assumptions | G16: Construction | J16: Debt Assumptions | K16: Permenant
C17: 0 | D17: 1 | G17: 0 | H17: 1 | K17: 0 | L17: =ROUND((H25+D26)/12,0) -> 7
B18: NOI | D18: ='Annual Pro Forma'!$C$53 -> 1061202.8 | F18: Leading NOI | H18: ='Annual Pro Forma'!$C$53 -> 1061202.8 | J18: Leading NOI | L18: {=INDEX('Annual Pro Forma'!$C$53:$M$53,,MATCH('Debt & Equity Assumptions'!L17,'Annual Pro Forma'!$C$8:$M$8,0),1)} -> 4967816.3
B19: Purchase Price | D19: ='Torrance Inputs'!D11 -> 17552667 | F19: Purchase Price | H19: ='Torrance Inputs'!D11 -> 17552667 | J19: Purchase Price | L19: =L18/5% -> 99356325
B20: Terms | F20: Terms | J20: Terms
B21: Start Date | D21: =EDATE('Torrance Inputs'!analysis_start,-12) -> 45292 | F21: Start Date | H21: =EDATE(D21,12) -> 45658 | J21: Start Date | L21: =H22 -> 46753
B22: End Date | D22: =H22 -> 46753 | F22: End Date | H22: =EDATE(H21,H25) -> 46753 | J22: End Date | L22: 49310
B23: Rate | D23: 0.06 | F23: Rate | H23: 0.08 | J23: Rate | L23: 0.055
B24: Amortization | D24: 360 | F24: Amortization | H24: 0 | J24: Amortization | L24: 360
B25: Loan Length | D25: =D24 -> 360 | F25: Loan Length | H25: =SUM('Torrance Inputs'!H36:H40) -> 36 | J25: Loan Length | L25: =L24 -> 360
B26: Loan Payoff Months | D26: =DATEDIF(D21,D22,"m") -> 48 | F26: Origination Fee | H26: 0.0075 | J26: Origination Fee | L26: 0.0075
B27: Origination Fee | D27: 0.0025 | F27: Loan Type | H27: Interest Only | J27: Loan Type | L27: Fixed
B28: Loan Type | D28: Fixed | F28: Annual PMT | H28: =H23*H30 -> 912738.67 | J28: Constraints
B29: Constraints | F29: LTV | G29: =H29*H19 -> 11409233 | H29: 0.65 | J29: DY | K29: =L18/L29 -> 66237550 | L29: 0.075
B30: DY | C30: =D18/D30 -> 14149371 | D30: 0.075 | F30: Loan Amount | H30: =MIN(G27:G29) -> 11409233 | J30: DSCR | K30: =PV(L23/12,L24,-(L18/L30/12)) -> 54008676 | L30: 1.35
B31: DSCR | C31: =PV(D23/12,D24,-(D18/D31/12)) -> 11799982 | D31: 1.25 | J31: LTV | K31: =L31*L19 -> 64581611 | L31: 0.65
B32: LTV | C32: =D32*D19 -> 12286867 | D32: 0.7 | J32: Loan Amount | L32: =MIN(K29:K31) -> 54008676
B33: Loan Amount | D33: =MIN(C30:C32) -> 11799982

Sheet Debt Returns
D2: {=_xlfn.SEQUENCE(1,11,0,1)} -> 0 | E2: 1 | F2: 2 | G2: 3 | H2: 4 | I2: 5 | J2: 6 | K2: 7 | L2: 8 | M2: 9 | N2: 10
B3: Preconstruction CF | D3: {=IFERROR(INDEX($D$19:$N$19,,MATCH(D$2,_xlfn.ANCHORARRAY($D$13),0),1),0)} -> 11770482 | E3: {=INDEX($D$19:$N$19,,MATCH(E$2,_xlfn.ANCHORARRAY($D$13),0),1)} -> -848962.25 | F3: {=INDEX($D$19:$N$19,,MATCH(F$2,_xlfn.ANCHORARRAY($D$13),0),1)} -> -848962.25 | G3: {=INDEX($D$19:$N$19,,MATCH(G$2,_xlfn.ANCHORARRAY($D$13),0),1)} -> -848962.25 | H3: {=INDEX($D$19:$N$19,,MATCH(H$2,_xlfn.ANCHORARRAY($D$13),0),1)} -> -10723863 | I3: {=INDEX($D$19:$N$19,,MATCH(I$2,_xlfn.ANCHORARRAY($D$13),0),1)} -> 0 | J3: {=INDEX($D$19:$N$19,,MATCH(J$2,_xlfn.ANCHORARRAY($D$13),0),1)} -> 0 | K3: {=INDEX($D$19:$N$19,,MATCH(K$2,_xlfn.ANCHORARRAY($D$13),0),1)} -> 0 | L3: {=INDEX($D$19:$N$19,,MATCH(L$2,_xlfn.ANCHORARRAY($D$13),0),1)} -> 0 | ... N3: {=INDEX($D$19:$N$19,,MATCH(N$2,_xlfn.ANCHORARRAY($D$13),0),1)} -> 0
B4: Construction Debt CF | D4: {=IFERROR(INDEX($D$33:$N$33,,MATCH(D$2,_xlfn.ANCHORARRAY($D$27),0),1),0)} -> 0 | E4: {=IFERROR(INDEX($D$33:$N$33,,MATCH(E$2,_xlfn.ANCHORARRAY($D$27),0),1),0)} -> 0 | F4: {=IFERROR(INDEX($D$33:$N$33,,MATCH(F$2,_xlfn.ANCHORARRAY($D$27),0),1),0)} -> 0 | G4: {=IFERROR(INDEX($D$33:$N$33,,MATCH(G$2,_xlfn.ANCHORARRAY($D$27),0),1),0)} -> 0 | H4: {=IFERROR(INDEX($D$33:$N$33,,MATCH(H$2,_xlfn.ANCHORARRAY($D$27),0),1),0)} -> 11323664 | I4: {=IFERROR(INDEX($D$33:$N$33,,MATCH(I$2,_xlfn.ANCHORARRAY($D$27),0),1),0)} -> -912738.67 | J4: {=IFERROR(INDEX($D$33:$N$33,,MATCH(J$2,_xlfn.ANCHORARRAY($D$27),0),1),0)} -> -12321972 | K4: {=IFERROR(INDEX($D$33:$N$33,,MATCH(K$2,_xlfn.ANCHORARRAY($D$27),0),1),0)} -> 0 | ... N4: {=IFERROR(INDEX($D$33:$N$33,,MATCH(N$2,_xlfn.ANCHORARRAY($D$27),0),1),0)} -> 0
B5: Perm Debt CF | D5: {=IFERROR(INDEX($D$47:$N$47,,MATCH(D$2,$D$41:$N$41,0),1),0)} -> 0 | E5: {=IFERROR(INDEX($D$47:$N$47,,MATCH(E$2,$D$41:$N$41,0),1),0)} -> 0 | F5: {=IFERROR(INDEX($D$47:$N$47,,MATCH(F$2,$D$41:$N$41,0),1),0)} -> 0 | G5: {=IFERROR(INDEX($D$47:$N$47,,MATCH(G$2,$D$41:$N$41,0),1),0)} -> 0 | H5: {=IFERROR(INDEX($D$47:$N$47,,MATCH(H$2,$D$41:$N$41,0),1),0)} -> 0 | I5: {=IFERROR(INDEX($D$47:$N$47,,MATCH(I$2,$D$41:$N$41,0),1),0)} -> 0 | J5: {=IFERROR(INDEX($D$47:$N$47,,MATCH(J$2,$D$41:$N$41,0),1),0)} -> 53603611 | K5: {=IFERROR(INDEX($D$47:$N$47,,MATCH(K$2,$D$41:$N$41,0),1),0)} -> -3679863.9 | ... N5: {=IFERROR(INDEX($D$47:$N$47,,MATCH(N$2,$D$41:$N$41,0),1),0)} -> -3679863.9
B6: Total Debt CF | D6: =SUM(D3:D5) -> 11770482 | E6: =SUM(E3:E5) -> -848962.25 | F6: =SUM(F3:F5) -> -848962.25 | G6: =SUM(G3:G5) -> -848962.25 | H6: =SUM(H3:H5) -> 599801.29 | I6: =SUM(I3:I5) -> -912738.67 | J6: =SUM(J3:J5) -> 41281639 | K6: =SUM(K3:K5) -> -3679863.9 | ... N6: =SUM(N3:N5) -> -3679863.9
B10: Pre-Construction
D12: =EDATE('Debt & Equity Assumptions'!$D$21,0) -> 45292 | E12: =EDATE(D12,12) -> 45658 | F12: =EDATE(E12,12) -> 46023 | G12: =EDATE(F12,12) -> 46388 | H12: =EDATE(G12,12) -> 46753 | I12: =EDATE(H12,12) -> 47119 | J12: =EDATE(I12,12) -> 47484 | K12: =EDATE(J12,12) -> 47849 | L12: =EDATE(K12,12) -> 48214 | ... N12: =EDATE(M12,12) -> 48945
D13: {=_xlfn.SEQUENCE(1,11,0,1)} -> 0 | E13: 1 | F13: 2 | G13: 3 | H13: 4 | I13: 5 | J13: 6 | K13: 7 | L13: 8 | M13: 9 | N13: 10
B14: Debt
B15: Origination Fee | D15: =-D16*'Debt & Equity Assumptions'!$D$27 -> -29499.955
B16: Loan Proceeds | D16: ='Debt & Equity Assumptions'!D33 -> 11799982
B17: Debt Service | E17: =IF(E12<'Debt & Equity Assumptions'!$D$22,PMT('Debt & Equity Assumptions'!$D$23/12,'Debt & Equity Assumptions'!$D$24,$D$16)*12,0) -> -848962.25 | F17: =IF(F12<='Debt & Equity Assumptions'!$D$22,PMT('Debt & Equity Assumptions'!$D$23/12,'Debt & Equity Assumptions'!$D$24,$D$16)*12,0) -> -848962.25 | G17: =IF(G12<='Debt & Equity Assumptions'!$D$22,PMT('Debt & Equity Assumptions'!$D$23/12,'Debt & Equity Assumptions'!$D$24,$D$16)*12,0) -> -848962.25 | H17: =IF(H12<='Debt & Equity Assumptions'!$D$22,PMT('Debt & Equity Assumptions'!$D$23/12,'Debt & Equity Assumptions'!$D$24,$D$16)*12,0) -> -848962.25 | I17: =IF(I12<='Debt & Equity Assumptions'!$D$22,PMT('Debt & Equity Assumptions'!$D$23/12,'Debt & Equity Assumptions'!$D$24,$D$16)*12,0) -> 0 | J17: =IF(J12<='Debt & Equity Assumptions'!$D$22,PMT('Debt & Equity Assumptions'!$D$23/12,'Debt & Equity Assumptions'!$D$24,$D$16)*12,0) -> 0 | K17: =IF(K12<='Debt & Equity Assumptions'!$D$22,PMT('Debt & Equity Assumptions'!$D$23/12,'Debt & Equity Assumptions'!$D$24,$D$16)*12,0) -> 0 | L17: =IF(L12<='Debt & Equity Assumptions'!$D$22,PMT('Debt & Equity Assumptions'!$D$23/12,'Debt & Equity Assumptions'!$D$24,$D$16)*12,0) -> 0 | M17: =IF(M12<='Debt & Equity Assumptions'!$D$22,PMT('Debt & Equity Assumptions'!$D$23/12,'Debt & Equity Assumptions'!$D$24,$D$16)*12,0) -> 0 | N17: =IF(N12<='Debt & Equity Assumptions'!$D$22,PMT('Debt & Equity Assumptions'!$D$23/12,'Debt & Equity Assumptions'!$D$24,$D$16)*12,0) -> 0
B18: Loan Repayment | E18: =-IF(E$12='Debt & Equity Assumptions'!$D$22,'Debt & Equity Assumptions'!$D$33+CUMPRINC('Debt & Equity Assumptions'!$D$23/12,'Debt & Equity Assumptions'!$D$24,'Debt & Equity Assumptions'!$D$33,1,120,0),0) -> 0 | F18: =-IF(F$12='Debt & Equity Assumptions'!$D$22,'Debt & Equity Assumptions'!$D$33+CUMPRINC('Debt & Equity Assumptions'!$D$23/12,'Debt & Equity Assumptions'!$D$24,'Debt & Equity Assumptions'!$D$33,1,120,0),0) -> 0 | G18: =-IF(G$12='Debt & Equity Assumptions'!$D$22,'Debt & Equity Assumptions'!$D$33+CUMPRINC('Debt & Equity Assumptions'!$D$23/12,'Debt & Equity Assumptions'!$D$24,'Debt & Equity Assumptions'!$D$33,1,120,0),0) -> 0 | H18: =-IF(H$12='Debt & Equity Assumptions'!$D$22,'Debt & Equity Assumptions'!$D$33+CUMPRINC('Debt & Equity Assumptions'!$D$23/12,'Debt & Equity Assumptions'!$D$24,'Debt & Equity Assumptions'!$D$33,1,120,0),0) -> -9874900.5 | I18: =-IF(I$12='Debt & Equity Assumptions'!$D$22,'Debt & Equity Assumptions'!$D$33+CUMPRINC('Debt & Equity Assumptions'!$D$23/12,'Debt & Equity Assumptions'!$D$24,'Debt & Equity Assumptions'!$D$33,1,120,0),0) -> 0 | J18: =-IF(J$12='Debt & Equity Assumptions'!$D$22,'Debt & Equity Assumptions'!$D$33+CUMPRINC('Debt & Equity Assumptions'!$D$23/12,'Debt & Equity Assumptions'!$D$24,'Debt & Equity Assumptions'!$D$33,1,120,0),0) -> 0 | K18: =-IF(K$12='Debt & Equity Assumptions'!$D$22,'Debt & Equity Assumptions'!$D$33+CUMPRINC('Debt & Equity Assumptions'!$D$23/12,'Debt & Equity Assumptions'!$D$24,'Debt & Equity Assumptions'!$D$33,1,120,0),0) -> 0 | L18: =-IF(L$12='Debt & Equity Assumptions'!$D$22,'Debt & Equity Assumptions'!$D$33+CUMPRINC('Debt & Equity Assumptions'!$D$23/12,'Debt & Equity Assumptions'!$D$24,'Debt & Equity Assumptions'!$D$33,1,120,0),0) -> 0 | ... N18: =-IF(N$12='Debt & Equity Assumptions'!$D$22,'Debt & Equity Assumptions'!$D$33+CUMPRINC('Debt & Equity Assumptions'!$D$23/12,'Debt & Equity Assumptions'!$D$24,'Debt & Equity Assumptions'!$D$33,1,120,0),0) -> 0
B19: Debt CF | D19: =SUM(D15:D18) -> 11770482 | E19: =SUM(E15:E18) -> -848962.25 | F19: =SUM(F15:F18) -> -848962.25 | G19: =SUM(G15:G18) -> -848962.25 | H19: =SUM(H15:H18) -> -10723863 | I19: =SUM(I15:I18) -> 0 | J19: =SUM(J15:J18) -> 0 | K19: =SUM(K15:K18) -> 0 | ... N19: =SUM(N15:N18) -> 0
B21: IRR | D21: =XIRR(D19:N19,D12:N12) -> 0.033826527
B22: EM | D22: =-SUMIF(D19:N19,"<0")/SUMIF(D19:N19,">0") -> 1.1274602
B24: Construction
D26: =EDATE('Debt & Equity Assumptions'!$H$21,0) -> 45658 | E26: =EDATE(D26,12) -> 46023 | F26: =EDATE(E26,12) -> 46388 | G26: =EDATE(F26,12) -> 46753 | H26: =EDATE(G26,12) -> 47119 | I26: =EDATE(H26,12) -> 47484 | J26: =EDATE(I26,12) -> 47849 | K26: =EDATE(J26,12) -> 48214 | L26: =EDATE(K26,12) -> 48580 | ... N26: =EDATE(M26,12) -> 49310
D27: {=_xlfn.SEQUENCE(1,11,ROUNDDOWN('Debt & Equity Assumptions'!D26/12,0),1)} -> 4 | E27: 5 | F27: 6 | G27: 7 | H27: 8 | I27: 9 | J27: 10 | K27: 11 | L27: 12 | M27: 13 | N27: 14
B28: Debt
B29: Origination Fee | D29: =-D30*'Debt & Equity Assumptions'!H$26 -> -85569.25
B30: Loan Proceeds | D30: ='Debt & Equity Assumptions'!H30 -> 11409233
B31: Debt Service | E31: =IF(E26<'Debt & Equity Assumptions'!$H$22,-'Debt & Equity Assumptions'!$H$28,IF(E26>='Debt & Equity Assumptions'!$H$21,0)) -> -912738.67 | F31: =IF(F26<'Debt & Equity Assumptions'!$H$22,-'Debt & Equity Assumptions'!$H$28,IF(F26>='Debt & Equity Assumptions'!$H$21,0)) -> -912738.67 | G31: =IF(G26<'Debt & Equity Assumptions'!$H$22,-'Debt & Equity Assumptions'!$H$28,IF(G26>='Debt & Equity Assumptions'!$H$21,0)) -> 0 | H31: =IF(H26<'Debt & Equity Assumptions'!$H$22,-'Debt & Equity Assumptions'!$H$28,IF(H26>='Debt & Equity Assumptions'!$H$21,0)) -> 0 | I31: =IF(I26<'Debt & Equity Assumptions'!$H$22,-'Debt & Equity Assumptions'!$H$28,IF(I26>='Debt & Equity Assumptions'!$H$21,0)) -> 0 | J31: =IF(J26<'Debt & Equity Assumptions'!$H$22,-'Debt & Equity Assumptions'!$H$28,IF(J26>='Debt & Equity Assumptions'!$H$21,0)) -> 0 | K31: =IF(K26<'Debt & Equity Assumptions'!$H$22,-'Debt & Equity Assumptions'!$H$28,IF(K26>='Debt & Equity Assumptions'!$H$21,0)) -> 0 | L31: =IF(L26<'Debt & Equity Assumptions'!$H$22,-'Debt & Equity Assumptions'!$H$28,IF(L26>='Debt & Equity Assumptions'!$H$21,0)) -> 0 | ... N31: =IF(N26<'Debt & Equity Assumptions'!$H$22,-'Debt & Equity Assumptions'!$H$28,IF(N26>='Debt & Equity Assumptions'!$H$21,0)) -> 0
B32: Loan Repayment | E32: =-IF(YEAR(E26)=YEAR('Debt & Equity Assumptions'!$H$22-1),'Debt & Equity Assumptions'!$H$30,0) -> 0 | F32: =-IF(YEAR(F26)=YEAR('Debt & Equity Assumptions'!$H$22-1),'Debt & Equity Assumptions'!$H$30,0) -> -11409233 | G32: =-IF(YEAR(G26)=YEAR('Debt & Equity Assumptions'!$H$22-1),'Debt & Equity Assumptions'!$H$30,0) -> 0 | H32: =-IF(YEAR(H26)=YEAR('Debt & Equity Assumptions'!$H$22-1),'Debt & Equity Assumptions'!$H$30,0) -> 0 | I32: =-IF(YEAR(I26)=YEAR('Debt & Equity Assumptions'!$H$22-1),'Debt & Equity Assumptions'!$H$30,0) -> 0 | J32: =-IF(YEAR(J26)=YEAR('Debt & Equity Assumptions'!$H$22-1),'Debt & Equity Assumptions'!$H$30,0) -> 0 | K32: =-IF(YEAR(K26)=YEAR('Debt & Equity Assumptions'!$H$22-1),'Debt & Equity Assumptions'!$H$30,0) -> 0 | L32: =-IF(YEAR(L26)=YEAR('Debt & Equity Assumptions'!$H$22-1),'Debt & Equity Assumptions'!$H$30,0) -> 0 | ... N32: =-IF(YEAR(N26)=YEAR('Debt & Equity Assumptions'!$H$22-1),'Debt & Equity Assumptions'!$H$30,0) -> 0
B33: Debt CF | D33: =SUM(D29:D32) -> 11323664 | E33: =SUM(E29:E32) -> -912738.67 | F33: =SUM(F29:F32) -> -12321972 | G33: =SUM(G29:G32) -> 0 | H33: =SUM(H29:H32) -> 0 | I33: =SUM(I29:I32) -> 0 | J33: =SUM(J29:J32) -> 0 | K33: =SUM(K29:K32) -> 0 | ... N33: =SUM(N29:N32) -> 0
B35: IRR | D35: =XIRR(D33:N33,D26:N26) -> 0.084230176
B36: EM | D36: =-SUMIF(D33:N33,"<0")/SUMIF(D33:N33,">0") -> 1.1687657
B38: Perm Loan
D40: =EDATE('Debt & Equity Assumptions'!H21,'Debt & Equity Assumptions'!H25) -> 46753 | E40: =EDATE(D40,12) -> 47119 | F40: =EOMONTH(E40,12) -> 47514 | G40: =EOMONTH(F40,12) -> 47879 | H40: =EOMONTH(G40,12) -> 48244 | I40: =EOMONTH(H40,12) -> 48610 | J40: =EOMONTH(I40,12) -> 48975 | K40: =EOMONTH(J40,12) -> 49340 | L40: =EOMONTH(K40,12) -> 49705 | M40: =EOMONTH(L40,12) -> 50071 | N40: =EOMONTH(M40,12) -> 50436
D41: {=_xlfn.SEQUENCE(1,11,(('Debt & Equity Assumptions'!$H$25+'Debt & Equity Assumptions'!$D$26)/12)-1,1)} -> 6 | E41: 7 | F41: 8 | G41: 9 | H41: 10 | I41: 11 | J41: 12 | K41: 13 | L41: 14 | M41: 15 | N41: 16
B42: Debt
B43: Origination Fee | D43: =-D44*'Debt & Equity Assumptions'!$L$26 -> -405065.07
B44: Loan Proceeds | D44: ='Debt & Equity Assumptions'!L32 -> 54008676
B45: Debt Service | E45: =IF(YEAR(E$40)<=YEAR('Torrance Inputs'!$D$19),PMT('Debt & Equity Assumptions'!$L$23/12,'Debt & Equity Assumptions'!$L$24,'Debt & Equity Assumptions'!$L$32)*12,0) -> -3679863.9 | F45: =IF(YEAR(F$40)<=YEAR('Debt & Equity Assumptions'!$L$22)-1,PMT('Debt & Equity Assumptions'!$L$23/12,'Debt & Equity Assumptions'!$L$24,'Debt & Equity Assumptions'!$L$32)*12,0) -> -3679863.9 | G45: =IF(YEAR(G$40)<=YEAR('Debt & Equity Assumptions'!$L$22)-1,PMT('Debt & Equity Assumptions'!$L$23/12,'Debt & Equity Assumptions'!$L$24,'Debt & Equity Assumptions'!$L$32)*12,0) -> -3679863.9 | H45: =IF(YEAR(H$40)<=YEAR('Debt & Equity Assumptions'!$L$22)-1,PMT('Debt & Equity Assumptions'!$L$23/12,'Debt & Equity Assumptions'!$L$24,'Debt & Equity Assumptions'!$L$32)*12,0) -> -3679863.9 | I45: =IF(YEAR(I$40)<=YEAR('Debt & Equity Assumptions'!$L$22)-1,PMT('Debt & Equity Assumptions'!$L$23/12,'Debt & Equity Assumptions'!$L$24,'Debt & Equity Assumptions'!$L$32)*12,0) -> -3679863.9 | J45: =IF(YEAR(J$40)<=YEAR('Debt & Equity Assumptions'!$L$22)-1,PMT('Debt & Equity Assumptions'!$L$23/12,'Debt & Equity Assumptions'!$L$24,'Debt & Equity Assumptions'!$L$32)*12,0) -> -3679863.9 | K45: =IF(YEAR(K$40)<=YEAR('Debt & Equity Assumptions'!$L$22)-1,PMT('Debt & Equity Assumptions'!$L$23/12,'Debt & Equity Assumptions'!$L$24,'Debt & Equity Assumptions'!$L$32)*12,0) -> 0 | L45: =IF(YEAR(L$40)<=YEAR('Debt & Equity Assumptions'!$L$22)-1,PMT('Debt & Equity Assumptions'!$L$23/12,'Debt & Equity Assumptions'!$L$24,'Debt & Equity Assumptions'!$L$32)*12,0) -> 0 | M45: =IF(YEAR(M$40)<=YEAR('Debt & Equity Assumptions'!$L$22)-1,PMT('Debt & Equity Assumptions'!$L$23/12,'Debt & Equity Assumptions'!$L$24,'Debt & Equity Assumptions'!$L$32)*12,0) -> 0 | N45: =IF(YEAR(N$40)<=YEAR('Debt & Equity Assumptions'!$L$22)-1,PMT('Debt & Equity Assumptions'!$L$23/12,'Debt & Equity Assumptions'!$L$24,'Debt & Equity Assumptions'!$L$32)*12,0) -> 0
B46: Loan Repayment | E46: =-IF(YEAR(E$40)=YEAR('Debt & Equity Assumptions'!$L$22)-1,('Debt & Equity Assumptions'!$L$32+CUMPRINC('Debt & Equity Assumptions'!$L$23/12,'Debt & Equity Assumptions'!$L$24,'Debt & Equity Assumptions'!$L$32,1,(E$41*12),0))) -> 0 | F46: =-IF(YEAR(F$40)=YEAR('Debt & Equity Assumptions'!$L$22)-1,('Debt & Equity Assumptions'!$L$32+CUMPRINC('Debt & Equity Assumptions'!$L$23/12,'Debt & Equity Assumptions'!$L$24,'Debt & Equity Assumptions'!$L$32,1,(F$41*12),0))) -> 0 | G46: =-IF(YEAR(G$40)=YEAR('Debt & Equity Assumptions'!$L$22)-1,('Debt & Equity Assumptions'!$L$32+CUMPRINC('Debt & Equity Assumptions'!$L$23/12,'Debt & Equity Assumptions'!$L$24,'Debt & Equity Assumptions'!$L$32,1,(G$41*12),0))) -> 0 | H46: =-IF(YEAR(H$40)=YEAR('Debt & Equity Assumptions'!$L$22)-1,('Debt & Equity Assumptions'!$L$32+CUMPRINC('Debt & Equity Assumptions'!$L$23/12,'Debt & Equity Assumptions'!$L$24,'Debt & Equity Assumptions'!$L$32,1,(H$41*12),0))) -> 0 | I46: =-IF(YEAR(I$40)=YEAR('Debt & Equity Assumptions'!$L$22)-1,('Debt & Equity Assumptions'!$L$32+CUMPRINC('Debt & Equity Assumptions'!$L$23/12,'Debt & Equity Assumptions'!$L$24,'Debt & Equity Assumptions'!$L$32,1,(I$41*12),0))) -> 0 | J46: =-IF(YEAR(J$40)=YEAR('Debt & Equity Assumptions'!$L$22)-1,('Debt & Equity Assumptions'!$L$32+CUMPRINC('Debt & Equity Assumptions'!$L$23/12,'Debt & Equity Assumptions'!$L$24,'Debt & Equity Assumptions'!$L$32,1,(J$41*12),0))) -> -41989382 | K46: =-IF(YEAR(K$40)=YEAR('Debt & Equity Assumptions'!$L$22)-1,('Debt & Equity Assumptions'!$L$32+CUMPRINC('Debt & Equity Assumptions'!$L$23/12,'Debt & Equity Assumptions'!$L$24,'Debt & Equity Assumptions'!$L$32,1,(K$41*12),0))) -> 0 | L46: =-IF(YEAR(L$40)=YEAR('Debt & Equity Assumptions'!$L$22)-1,('Debt & Equity Assumptions'!$L$32+CUMPRINC('Debt & Equity Assumptions'!$L$23/12,'Debt & Equity Assumptions'!$L$24,'Debt & Equity Assumptions'!$L$32,1,(L$41*12),0))) -> 0 | ... N46: =-IF(YEAR(N$40)=YEAR('Debt & Equity Assumptions'!$L$22)-1,('Debt & Equity Assumptions'!$L$32+CUMPRINC('Debt & Equity Assumptions'!$L$23/12,'Debt & Equity Assumptions'!$L$24,'Debt & Equity Assumptions'!$L$32,1,(N$41*12),0))) -> 0
B47: Debt CF | D47: =SUM(D43:D46) -> 53603611 | E47: =SUM(E43:E46) -> -3679863.9 | F47: =SUM(F43:F46) -> -3679863.9 | G47: =SUM(G43:G46) -> -3679863.9 | H47: =SUM(H43:H46) -> -3679863.9 | I47: =SUM(I43:I46) -> -3679863.9 | J47: =SUM(J43:J46) -> -45669246 | K47: =SUM(K43:K46) -> 0 | ... N47: =SUM(N43:N46) -> 0
B49: IRR | D49: =XIRR(D47:N47,D40:N40) -> 0.035047093
B50: EM | D50: =-SUMIF(D47:N47,"<0")/SUMIF(D47:N47,">0") -> 1.1952285

Sheet Equity Returns
D2: 0 | E2: {=_xlfn.SEQUENCE(1,10,1,1)} -> 1 | F2: 2 | G2: 3 | H2: 4 | I2: 5 | J2: 6 | K2: 7 | L2: 8 | M2: 9 | N2: 10 | O2: 11
B3: Asset CF | D3: -13580221 | E3: 964351.1 | F3: 979810.48 | G3: 998955.01 | H3: 1018477.6 | I3: -61614.301 | J3: -15236774 | K3: -1395236.8 | L3: 5823525.9 | M3: 5940895 | N3: 1.3707766e+08
B4: Debt CF | D4: ='Debt Returns'!D6 -> 11770482 | E4: ='Debt Returns'!E6 -> -848962.25 | F4: ='Debt Returns'!F6 -> -848962.25 | G4: ='Debt Returns'!G6 -> -848962.25 | H4: ='Debt Returns'!H6 -> 599801.29 | I4: ='Debt Returns'!I6 -> -912738.67 | J4: ='Debt Returns'!J6 -> 41281639 | K4: ='Debt Returns'!K6 -> -3679863.9 | ... O4: ='Debt Returns'!O6 -> 0
B6: Equity Levered CF | D6: =SUM(D3:D4) -> -1809738.9 | E6: =SUM(E3:E4) -> 115388.84 | F6: =SUM(F3:F4) -> 130848.23 | G6: =SUM(G3:G4) -> 149992.76 | H6: =SUM(H3:H4) -> 1618278.9 | I6: =SUM(I3:I4) -> -974352.97 | J6: =SUM(J3:J4) -> 26044865 | K6: =SUM(K3:K4) -> -5075100.7 | ... N6: =SUM(N3:N4) -> 1.333978e+08
B7: IRR | C7: =IRR(D6:N6) -> 0.71676993
B8: Tier 1 - Preferred Return
B9: Beginning Balance | D9: =C20 -> 0 | E9: =D20 -> 1809738.9 | F9: =E20 -> 1875324 | G9: =F20 -> 1932008.2 | H9: =G20 -> 1975216.2 | I9: =H20 -> 719936.22 | J9: =I20 -> 1766282.8 | K9: =J20 -> -23864483 | ... O9: =N20 -> -1.5084448e+08
B11: Contribution | D11: =-IF(D$6<0,D$6,0) -> 1809738.9 | E11: =-IF(E$6<0,E$6,0) -> 0 | F11: =-IF(F$6<0,F$6,0) -> 0 | G11: =-IF(G$6<0,G$6,0) -> 0 | H11: =-IF(H$6<0,H$6,0) -> 0 | I11: =-IF(I$6<0,I$6,0) -> 974352.97 | J11: =-IF(J$6<0,J$6,0) -> 0 | K11: =-IF(K$6<0,K$6,0) -> 5075100.7 | ... O11: =-IF(O$6<0,O$6,0) -> 0
B12: Pref Earned | D12: =IF(AND(D2>0,D2<='Debt & Equity Assumptions'!$D$3),D$9*'Debt & Equity Assumptions'!$D$10,0) -> 0 | E12: =IF(AND(E2>0,E2<='Debt & Equity Assumptions'!$D$3),E$9*'Debt & Equity Assumptions'!$D$10,0) -> 180973.89 | F12: =IF(AND(F2>0,F2<='Debt & Equity Assumptions'!$D$3),F$9*'Debt & Equity Assumptions'!$D$10,0) -> 187532.4 | G12: =IF(AND(G2>0,G2<='Debt & Equity Assumptions'!$D$3),G$9*'Debt & Equity Assumptions'!$D$10,0) -> 193200.82 | H12: =IF(AND(H2>0,H2<='Debt & Equity Assumptions'!$D$3),H$9*'Debt & Equity Assumptions'!$D$10,0) -> 197521.62 | I12: =IF(AND(I2>0,I2<='Debt & Equity Assumptions'!$D$3),I$9*'Debt & Equity Assumptions'!$D$10,0) -> 71993.622 | J12: =IF(AND(J2>0,J2<='Debt & Equity Assumptions'!$D$3),J$9*'Debt & Equity Assumptions'!$D$10,0) -> 176628.28 | K12: =IF(AND(K2>0,K2<='Debt & Equity Assumptions'!$D$3),K$9*'Debt & Equity Assumptions'!$D$10,0) -> -2386448.3 | ... O12: =IF(AND(O2>0,O2<='Debt & Equity Assumptions'!$D$3),O$9*'Debt & Equity Assumptions'!$D$10,0) -> 0
B13: Pref Paid | D13: =-IF(D6>0,MIN(D12,D6,SUM(C17,D12)),0) -> 0 | E13: =-IF(E6>0,MIN(E12,E6,SUM(D17,E12)),0) -> -115388.84 | F13: =-IF(F6>0,MIN(F12,F6,SUM(E17,F12)),0) -> -130848.23 | G13: =-IF(G6>0,MIN(G12,G6,SUM(F17,G12)),0) -> -149992.76 | H13: =-IF(H6>0,MIN(H12,H6,SUM(G17,H12)),0) -> -197521.62 | I13: =-IF(I6>0,MIN(I12,I6,SUM(H17,I12)),0) -> 0 | J13: =-IF(J6>0,MIN(J12,J6,SUM(I17,J12)),0) -> -176628.28 | K13: =-IF(K6>0,MIN(K12,K6,SUM(J17,K12)),0) -> 0 | ... O13: =-IF(O6>0,MIN(O12,O6,SUM(N17,O12)),0) -> 0
B14: Pref Unpaid | D14: =SUM(D12:D13) -> 0 | E14: =SUM(E12:E13) -> 65585.05 | F14: =SUM(F12:F13) -> 56684.17 | G14: =SUM(G12:G13) -> 43208.058 | H14: =SUM(H12:H13) -> 0 | I14: =SUM(I12:I13) -> 71993.622 | J14: =SUM(J12:J13) -> 0 | K14: =SUM(K12:K13) -> -2386448.3 | ... O14: =SUM(O12:O13) -> 0
B15: Equity Repaid | D15: =IF(D6>0,MAX(MIN(D6-D13,SUM(D6,-C17,-D12)),0),0) -> 0 | E15: =IF(E6>0,MAX(MIN(E6-E13,SUM(E6,-D17,-E12)),0),0) -> 0 | F15: =IF(F6>0,MAX(MIN(F6-F13,SUM(F6,-E17,-F12)),0),0) -> 0 | G15: =IF(G6>0,MAX(MIN(G6-G13,SUM(G6,-F17,-G12)),0),0) -> 0 | H15: =IF(H6>0,MAX(MIN(H6-H13,SUM(H6,-G17,-H12)),0),0) -> 1255280 | I15: =IF(I6>0,MAX(MIN(I6-I13,SUM(I6,-H17,-I12)),0),0) -> 0 | J15: =IF(J6>0,MAX(MIN(J6-J13,SUM(J6,-I17,-J12)),0),0) -> 25630766 | K15: =IF(K6>0,MAX(MIN(K6-K13,SUM(K6,-J17,-K12)),0),0) -> 0 | ... O15: =IF(O6>0,MAX(MIN(O6-O13,SUM(O6,-N17,-O12)),0),0) -> 0
B17: Ending Balance - Cumulative Unpaid Pref | D17: =C17+D14 -> 0 | E17: =D17+E14 -> 65585.05 | F17: =E17+F14 -> 122269.22 | G17: =F17+G14 -> 165477.28 | H17: =G17+H14 -> 165477.28 | I17: =H17+I14 -> 237470.9 | J17: =I17+J14 -> 237470.9 | K17: =J17+K14 -> -2148977.4 | ... N17: =M17+N14 -> 0 | O17: =N17+O14-O13 -> 0
B18: Ending Balance - Equity Contribution | D18: =C18-D15+D11 -> 1809738.9 | E18: =D18-E15+E11 -> 1809738.9 | F18: =E18-F15+F11 -> 1809738.9 | G18: =F18-G15+G11 -> 1809738.9 | H18: =G18-H15+H11 -> 554458.94 | I18: =H18-I15+I11 -> 1528811.9 | J18: =I18-J15+J11 -> -24101954 | K18: =J18-K15+K11 -> -19026854 | ... O18: =N18-O15+O11 -> -1.5084448e+08
B20: Total Ending Balance | C20: 0 | D20: =SUM(D17:D18) -> 1809738.9 | E20: =SUM(E17:E18) -> 1875324 | F20: =SUM(F17:F18) -> 1932008.2 | G20: =SUM(G17:G18) -> 1975216.2 | H20: =SUM(H17:H18) -> 719936.22 | I20: =SUM(I17:I18) -> 1766282.8 | J20: =SUM(J17:J18) -> -23864483 | K20: =SUM(K17:K18) -> -21175831 | ... O20: =SUM(O17:O18) -> -1.5084448e+08
